Workbook
Name LISTAPARCEIROS: #REF!

Sheet Ago.25
A1: Dia | B1: Quarto | Nome | C1: Empresa | D1: Voucher | Res. | E1: Hora | F1: Direcções | Observações | G1: Nº Pax | H1: Valor | I1: Comissão | J1: Por Quem | K1: Pago Hósp? | L1: Pago | N1: Parceiros | O1: Valor Total | P1: Comissão | Q1: Tips | R1: Envelope | S1: Comissões 7Roads | W1: Pago | X1: Dia | Y1: Por Quem
A2: 1 | B2: 214 | C2: 7Roads | D2: 2805 | E2: 06h20 | F2: Hotel-Aero | G2: 1 | H2: 25 | I2: 8 | J2: Nicole | K2: Sim | L2: Sim | N2: Where To | O2: =SUMIFS(H2:H197,C2:C197,N2,L2:L197,"Sim") -> 1108 | P2: =O2*0.3 -> 332.4 | Q2: =SUMIFS(I2:I197,C2:C197,N2,K2:K197,"Sim") -> 332.4 | S2: Hotel - Aero | T2: Valor | U2: Comissão | V2: Nº Malas | W2: Sim | X2: 1 | Y2: Ricardo
A3: 1 | B3: 601 | C3: 7Roads | D3: 2804 | E3: 12h00 | F3: Hotel-Oriente Comboios | G3: 2 | H3: 25 | I3: 8 | J3: Nicole | K3: Sim | L3: Não | N3: 7Roads | O3: =SUMIFS(H2:H197,C2:C197,N3,L2:L197,"Não") -> 3965 | P3: =SUMIFS(I2:I197,C2:C197,N3,L2:L197,"Não") -> 1180 | Q3: =SUMIFS(I2:I197,C2:C197,N3,K2:K197,"Sim") -> 1196 | R3: =SUMIFS(H2:H197,C2:C197,N3,K2:K197,"Sim")-Q3-Q5 -> 2819 | S3: 1 a 2 Pax | T3: 25 | U3: 8 | V3: 3 Malas | W3: Não | X3: 2 | Y3: Adriana
A4: 1 | B4: Francesca Ferraro | C4: 7Roads | D4: 2808 | E4: 20h35 | F4: Aero-Hotel (W46219) | G4: 2 | H4: 35 | I4: 10 | J4: Adriana | K4: Sim | L4: Não | N4: CitySightSeeing | O4: =SUMIFS(H2:H197,C2:C197,N4,L2:L197,"Não") -> 0 | P4: =O4*0.25 -> 0 | Q4: =SUMIFS(I2:I196,C2:C196,N4,K2:K196,"Sim") -> 103.5 | R4: =O4-P4 -> 0 | S4: 3 a 4 Pax | T4: 35 | U4: 10 | V4: 4 Malas | W4: De: | X4: 3 | Y4: Helder
A5: 1 | B5: Berkan Kaplam | C5: 7Roads | D5: 2623 | E5: 21h45 | F5: Aero-Hotel (TP244) | G5: 2 | H5: 35 | I5: 10 | J5: Adriana | K5: Sim | L5: Não | N5: 7Roads Driver | O5: =SUMIFS(H2:H197,C2:C197,N5,L2:L197,"Não") -> 0 | P5: =SUMIFS(I2:I197,C2:C197,N5,L2:L197,"Não") -> 0 | Q5: =SUMIFS(I2:I197,C2:C197,N5,K2:K197,"Sim") -> 0 | S5: 3 a 4 Pax | T5: 40 | U5: 12 | V5: 5/6 Malas | W5: Aero | X5: 4 | Y5: Erica
A6: 2 | B6: Veronica Bachetti | C6: 7Roads | D6: 2811 | E6: 13h00 | F6: Aero-Hotel (FR9903) | G6: 2 | H6: 35 | I6: 10 | J6: Nicole | K6: Sim | L6: Não | N6: Website | O6: =SUMIFS(H2:H197,C2:C197,N6,L2:L197,"Não") -> 683 | P6: =O6*0.15 -> 102.45 | S6: 5 a 8 Pax | T6: 55 | U6: 15 | V6: 12 Malas | W6: Hotel | X6: 5 | Y6: Nicole
A7: 2 | B7: Joel Pereira | C7: 7Roads | D7: 2806 | E7: 16h50 | F7: Aero-Hotel (QR343) | G7: 4 | H7: 45 | I7: 10 | J7: Nicole | K7: Sim | L7: Não | N7: Outra | O7: =SUMIFS(H2:H197,C2:C197,N7,L2:L197,"Não") -> 0 | P7: =SUMIFS(I2:I197,C2:C197,N7,L2:L197,"Não") -> 0 | S7: Aero - Hotel | T7: 35€ a 45€ | U7: 10 | V7: N/A | W7: Tour | X7: 6 | Y7: Francisco
A8: 3 | B8: 310 | C8: CitySightSeeing | D8: 173108 | E8: - | F8: Pack Iconic | G8: 2 | H8: 66 | I8: 16.5 | J8: Sara | K8: Sim | L8: Sim | N8: Total | O8: =SUM(O2:O3) -> 5073 | P8: =SUM(P2:P3) -> 1512.4 | R8: =R4 -> 0 | T8: 55 | U8: 15 | V8: N/A | W8: Para: | X8: 7 | Y8: Diogo
A9: 3 | B9: 507 | C9: Where To | D9: 2593 | E9: 08h20 | F9: Tour Sintra/Cascais | G9: 2 | H9: 138 | I9: 41.4 | J9: Sara | K9: Sim | L9: Sim | W9: Aero | X9: 8 | Y9: Erike
A10: 3 | B10: Berkan Kaplam | C10: 7Roads | D10: 2624 | E10: 11h30 | F10: Hotel-Aero Rental | G10: 2 | H10: 25 | I10: 8 | J10: Adriana | K10: Sim | L10: Não | N10: Contagem MAPA TOURS | Q10: Contagem CAIXA TURNO | W10: Hotel | X10: 9 | Y10: Thomas
A11: 3 | B11: Ermenegilda Manganaro | C11: 7Roads | D11: 379 | E11: 13h55 | F11: Aero-Hotel (TP861) | G11: 2 | H11: 35 | I11: 10 | J11: Nicole | K11: Sim | L11: Não | N11: Notas | Q11: Notas | T11: Facturas | U11: Valor | W11: Outro | X11: 10 | Y11: Maycon
A12: 3 | B12: 216 | C12: 7Roads | D12: 2815 | E12: 14h30 | F12: Hotel-Aero | G12: 2 | H12: 25 | I12: 8 | J12: Sara | K12: Sim | L12: Não | N12: 500 | O12: 0 | P12: =N12*O12 -> 0 | Q12: 500 | R12: 0 | S12: =Q12*R12 -> 0 | T12: Fundo Maneio | U12: 18.77 | W12: Sintra/Cascais | X12: 11
A13: 3 | B13: Brat Sybille | C13: 7Roads | D13: 2801 | E13: 18h00 | F13: Aero-Hotel (U27606) | G13: 3 | H13: 35 | I13: 10 | J13: Erica | K13: Sim | L13: Não | N13: 200 | O13: 1 | P13: =N13*O13 -> 200 | Q13: 200 | R13: 0 | S13: =Q13*R13 -> 0 | W13: Fátima/Óbidos | X13: 12
A14: 4 | B14: 430 | C14: Where To | D14: 2594 | E14: 08h25 | F14: Tour Sintra/Cascais | G14: 2 | H14: 138 | I14: 41.4 | J14: Sara | K14: Sim | L14: Sim | N14: 100 | O14: 12 | P14: =N14*O14 -> 1200 | Q14: 100 | R14: 0 | S14: =Q14*R14 -> 0 | X14: 13
A15: 4 | B15: 305 | C15: 7Roads | D15: 2814 | E15: 08h30 | F15: Hotel-Aero | G15: 1 | H15: 25 | I15: 8 | J15: Sara | K15: Sim | L15: Não | N15: 50 | O15: 29 | P15: =N15*O15 -> 1450 | Q15: 50 | R15: 0 | S15: =Q15*R15 -> 0 | X15: 14
A16: 4 | B16: 427 | C16: 7Roads | D16: 2819 | E16: 09h30 | F16: Hotel-Aero | G16: 2 | H16: 25 | I16: 8 | J16: Helder | K16: Sim | L16: Não | N16: 20 | O16: 11 | P16: =N16*O16 -> 220 | Q16: 20 | R16: 0 | S16: =Q16*R16 -> 0 | X16: 15
A17: 4 | B17: 219 | C17: 7Roads | D17: 2820 | E17: 17h30 | F17: Hotel-Aero | G17: 2 | H17: 25 | I17: 8 | J17: Erica | K17: Sim | L17: Não | N17: 10 | O17: 0 | P17: =N17*O17 -> 0 | Q17: 10 | R17: 6 | S17: =Q17*R17 -> 60 | X17: 16
A18: 4 | B18: Juan Carlos Yepes Cano | C18: Website | D18: 172839 | E18: 19h15 | F18: Aero-Hotel (UX1157) | G18: 2 | H18: 39 | I18: - | J18: Nicole | K18: Sim | L18: Não | N18: 5 | O18: 0 | P18: =N18*O18 -> 0 | Q18: 5 | R18: 1 | S18: =Q18*R18 -> 5 | X18: 17
A19: 5 | B19: 316 | C19: 7Roads | D19: 2822 | E19: 05h20 | F19: Hotel-Aero | G19: 4 | H19: 40 | I19: 12 | J19: Adriana | K19: Sim | L19: Não | P19: =SUM(P12:P18) -> 3070 | S19: =SUM(S12:S18) -> 65 | X19: 18
A20: 5 | B20: Amanda Fuller | C20: 7Roads | D20: 2641 | E20: 06h55 | F20: Aero-Hotel (QR343) | G20: 2 | H20: 35 | I20: 10 | J20: Maycon | K20: Sim | L20: Não | N20: Moedas | Q20: Moedas | X20: 19
A21: 5 | B21: 325 | C21: Where To | D21: 2597 | E21: 08h15 | F21: COMBO Tour Sintra | G21: 2 | H21: 140 | I21: 42 | J21: Adriana | K21: Sim | L21: Sim | N21: 2 | O21: 0 | P21: =N21*O21 -> 0 | Q21: 2 | R21: 1 | S21: =Q21*R21 -> 2 | X21: 20
A22: 5 | B22: 406/408 | C22: Where To | D22: 2595 | E22: 08h20 | F22: Tour Sintra/Cascais | G22: 2 | H22: 138 | I22: 41.4 | J22: Helder | K22: Sim | L22: Sim | N22: 1 | O22: 0 | P22: =N22*O22 -> 0 | Q22: 1 | R22: 8 | S22: =Q22*R22 -> 8 | X22: 21
A23: 5 | B23: 112 | C23: 7Roads | D23: 2821 | E23: 10h30 | F23: Hotel-Aero | G23: 2 | H23: 25 | I23: 8 | J23: Nicole | K23: Sim | L23: Não | N23: 0.5 | O23: 0 | P23: =N23*O23 -> 0 | Q23: 0.5 | R23: 11 | S23: =Q23*R23 -> 5.5 | X23: 22
A24: 5 | B24: Shaldeen Somers | C24: 7Roads | D24: 2809 | E24: 11h20 | F24: Aero-Hotel (SN3815) | G24: 4 | H24: 45 | I24: 10 | J24: Helder | K24: Sim | L24: Não | N24: 0.2 | O24: 2 | P24: =N24*O24 -> 0.4 | Q24: 0.2 | R24: 8 | S24: =Q24*R24 -> 1.6 | X24: 23
A25: 5 | B25: Loes Klarenbeek #323 | C25: Website | D25: 172416 | E25: 15h45 | F25: Hotel-Aero | G25: 2 | H25: 22 | I25: - | J25: Ricardo | K25: Sim | L25: Não | N25: 0.1 | O25: 1 | P25: =N25*O25 -> 0.1 | Q25: 0.1 | R25: 17 | S25: =Q25*R25 -> 1.7 | T25: Total Facturas | U25: =SUM(U12:U24) -> 18.77 | X25: 24
A26: 6 | B26: 517 | C26: 7Roads | D26: 2824 | E26: 06h15 | F26: Hotel-Aero | G26: 2 | H26: 25 | I26: 8 | J26: Ricardo | K26: Sim | L26: Não | N26: 0.05 | O26: 0 | P26: =N26*O26 -> 0 | Q26: 0.05 | R26: 17 | S26: =Q26*R26 -> 0.85 | T26: Fundo de Caixa | U26: 103.72 | X26: 25
A27: 6 | B27: 325 | C27: Where To | D27: 2598 | E27: 08h15 | F27: COMBO Tour Fátima | G27: 2 | H27: 140 | I27: 42 | J27: Adriana | K27: Sim | L27: Sim | N27: 0.02 | O27: 0 | P27: =N27*O27 -> 0 | Q27: 0.02 | R27: 5 | S27: =Q27*R27 -> 0.1 | T27: Diferença de Caixa | X27: 26
A28: 6 | B28: 528 | C28: 7Roads | D28: 2825 | E28: 09h25 | F28: Hotel-Aero | G28: 1 | H28: 25 | I28: 8 | J28: Ricardo | K28: Sim | L28: Não | N28: 0.01 | O28: 0 | P28: =N28*O28 -> 0 | Q28: 0.01 | R28: 20 | S28: =Q28*R28 -> 0.2 | T28: =S19+S29+U25-U26 -> 0 | X28: 27 | AB28: -
A29: 7 | B29: 423 | C29: 7Roads | D29: 2813 | E29: 07h00 | F29: Hotel-Aero | G29: 1 | H29: 25 | I29: 8 | J29: Sara | K29: Sim | L29: Não | P29: =SUM(P21:P28) -> 0.5 | S29: =SUM(S21:S28) -> 19.95 | X29: 28
A30: 7 | B30: 111 | C30: 7Roads | D30: 2826 | E30: 09h00 | F30: Hotel-Aero | G30: 2 | H30: 25 | I30: 8 | J30: Erica | K30: Sim | L30: Não | N30: Total | P30: =SUM(P19+P29-R8) -> 3070.5 | X30: 29
A31: 7 | B31: Beatriz Bielsa #225 | C31: Website | D31: 172709 | E31: 11h30 | F31: Hotel-Aero | G31: 2 | H31: 22 | I31: - | J31: Ricardo | K31: Sim | L31: Não | X31: 30
A32: 7 | B32: Erna Ruthers & Inge te Paske | C32: 7Roads | D32: 834 | E32: 12h15 | F32: Aero-Hotel (EW9603) | G32: 2 | H32: 35 | I32: 10 | J32: Vanessa | K32: Sim | L32: Não | N32: Contagem TIPS | S32: Lançamentos TIPS | X32: 31
A33: 7 | B33: 325 | C33: 7Roads | D33: 2830 | E33: 13h30 | F33: Hotel-Aero | G33: 2 | H33: 25 | I33: 8 | J33: Sara | K33: Sim | L33: Não | N33: Notas | Q33: Descrição | R33: Valor | S33: Dia | T33: Descrição | U33: Valor | V33: Por Quem
A34: 7 | B34: Zara Gold | C34: 7Roads | D34: 487 | E34: 20h55 | F34: Aero-Hotel (LY375) | G34: 4 | H34: 45 | I34: 10 | J34: Nicole | K34: Sim | L34: Não | N34: 500 | O34: 0 | P34: =N34*O34 -> 0 | T34: Where To | U34: =Q2-208.2 -> 124.2
A35: 7 | B35: German Rodriguez Soucase | C35: Website | D35: 173047 | E35: 22h50 | F35: Aero-Hotel (FR1769) | G35: 2 | H35: 39 | I35: - | J35: Adriana | K35: Sim | L35: Não | N35: 200 | O35: 0 | P35: =N35*O35 -> 0 | T35: 7Roads | U35: =Q3-502 -> 694
A36: 8 | B36: 413 | C36: Outra | D36: Go2Lisbon | E36: 08h30 | F36: Tour Sintra/Cascais | G36: 2 | H36: 156 | I36: 46.8 | J36: Adriana | K36: Sim | L36: Sim | N36: 100 | O36: 0 | P36: =N36*O36 -> 0 | T36: CitySightSeeing | U36: =Q4-52.5 -> 51
A37: 8 | B37: Ermenegilda 406 /408 | C37: 7Roads | D37: 380 | E37: 11h15 | F37: Hotel-Aero | G37: 2 | H37: 25 | I37: 8 | J37: Nicole | K37: Sim | L37: Não | N37: 50 | O37: 0 | P37: =N37*O37 -> 0 | S37: 12 | T37: Sobras TIPS | U37: 20.69 | V37: Ricardo
A38: 8 | B38: Alessio Carnevale | C38: 7Roads | D38: 2823 | E38: 13h10 | F38: Aero-Hotel (EJU3871) | G38: 4 | H38: 45 | I38: 10 | J38: Erica | K38: Sim | L38: Não | N38: 20 | O38: 0 | P38: =N38*O38 -> 0 | S38: 14 | T38: a mais | U38: 2 | V38: Ricardo
A39: 8 | B39: April Campbell | C39: 7Roads | D39: 2833 | E39: 13h25 | F39: Aero-Hotel (TP1453) | G39: 1 | H39: 35 | I39: 10 | J39: Nicole | K39: Sim | L39: Não | N39: 10 | O39: 0 | P39: =N39*O39 -> 0 | S39: 14 | T39: TIPS SARA | U39: -25 | V39: Ricardo
A40: 8 | B40: Ramon Spekking & Kate Soeter | C40: 7Roads | D40: 835 | E40: 17h10 | F40: Aero-Hotel (EW9602) | G40: 2 | H40: 35 | I40: 10 | J40: Vanessa | K40: Sim | L40: Não | N40: 5 | O40: 0 | P40: =N40*O40 -> 0 | S40: 15 | T40: Tips Alcobia | U40: 10 | V40: Erica
A41: 8 | B41: 430 | C41: 7Roads | D41: 2832 | E41: 19h30 | F41: Hotel-Aero | G41: 2 | H41: 25 | I41: 8 | J41: Erica | K41: Sim | L41: Não | P41: =SUM(P34:P40) -> 0 | S41: 16 | T41: Trovas Antigas | U41: 25 | V41: Adriana
A42: 9 | B42: 116 | C42: 7Roads | D42: 2837 | E42: 07h30 | F42: Hotel-Aero | G42: 2 | H42: 25 | I42: 8 | J42: Adriana | K42: Sim | L42: Não | N42: Moedas | S42: 18 | T42: A menos | U42: -0.45 | V42: Helder
A43: 9 | B43: 530 | C43: 7Roads | D43: 2839 | E43: 09h00 | F43: Hotel-Aero | G43: 2 | H43: 25 | I43: 8 | J43: Erica | K43: Sim | L43: Não | N43: 2 | O43: 0 | P43: =N43*O43 -> 0 | S43: 18 | T43: A MAIS | U43: 0.51 | V43: Adriana
A44: 9 | B44: Shaldeen Somers 501|502 | C44: 7Roads | D44: 2810 | E44: 09h15 | F44: Hotel-Aero | G44: 4 | H44: 40 | I44: 12 | J44: Helder | K44: Sim | L44: Não | N44: 1 | O44: 1 | P44: =N44*O44 -> 1 | S44: 19 | T44: Fado Night | U44: 30 | V44: Erica
A45: 9 | B45: Lawrence Annamarie | C45: 7Roads | D45: 2637 | E45: 18h05 | F45: Aero-Hotel (BA502) | G45: 2 | H45: 35 | I45: 10 | J45: Sara | K45: Sim | L45: Não | N45: 0.5 | O45: 2 | P45: =N45*O45 -> 1 | S45: 19 | T45: O POÇO | U45: 8 | V45: Francisco
A46: 10 | B46: 223 | C46: 7Roads | D46: 2838 | E46: 06h00 | F46: Hotel-Aero | G46: 1 | H46: 25 | I46: 8 | J46: Diogo | K46: Sim | L46: Não | N46: 0.2 | O46: 6 | P46: =N46*O46 -> 1.2 | Q46: Total | R46: =SUM(R34:R45) -> 0 | S46: 21 | T46: TIP | U46: 2 | V46: Helder
A47: 10 | B47: 316 | C47: 7Roads | D47: 2840 | E47: 09h15 | F47: Hotel-Aero | G47: 2 | H47: 25 | I47: 8 | J47: Erica | K47: Sim | L47: Não | N47: 0.1 | O47: 1 | P47: =N47*O47 -> 0.1 | S47: 22 | T47: A MAIS | U47: 24.08 | V47: Nicole
A48: 10 | B48: 411 | C48: 7Roads | D48: 2845 | E48: 10h00 | F48: Hotel-Aero | G48: 4 | H48: 40 | I48: 12 | J48: Nicole | K48: Sim | L48: Não | N48: 0.05 | O48: 1 | P48: =N48*O48 -> 0.05 | Q48: Lançamentos | R48: =SUM(U34:U51) -> 29.4 | S48: 26 | T48: TukTuk Tejo | U48: 21.37 | V48: Adriana
A49: 10 | B49: Melany Veloso #416 | C49: Website | D49: 173481 | E49: 10h30 | F49: Hotel-Aero | G49: 3 | H49: 22 | I49: - | J49: Adriana | K49: Sim | L49: Não | N49: 0.02 | O49: 1 | P49: =N49*O49 -> 0.02 | Q49: Cash | R49: =P41+P51+R46 -> 3.4 | S49: 26 | T49: Tip | U49: 2 | V49: Nicole
A50: 10 | B50: Mattia Oddone | C50: 7Roads | D50: 2836 | E50: 11h55 | F50: Aero-Hotel (EJU6732) | G50: 2 | H50: 35 | I50: 10 | J50: Erica | K50: Sim | L50: Não | N50: 0.01 | O50: 3 | P50: =N50*O50 -> 0.03 | Q50: Diferença | R50: =R49-R48 -> -26 | S50: 28 | T50: Divisão tips 8 pax | U50: -960 | V50: Ricardo
A51: 10 | B51: Ruthers & Spekking | C51: 7Roads | D51: 836 | E51: 15h30 | F51: Hotel-Aero | G51: 2 | H51: 40 | I51: 12 | J51: Vanessa | K51: Sim | L51: Não | P51: =SUM(P43:P50) -> 3.4 | Q51: Valor por pax | R51: =R49/8 -> 0.425
A52: 10 | B52: Davide Solaeri | C52: 7Roads | D52: 2842 | E52: 16h15 | F52: Aero-Hotel (FR 2622) | G52: 2 | H52: 35 | I52: 10 | J52: Nicole | K52: Sim | L52: Não
A53: 10 | B53: Petra Lindner | C53: 7Roads | D53: 2834 | E53: 21h20 | F53: Aero-Hotel (S40152) | G53: 2 | H53: 35 | I53: 10 | J53: Erica | K53: Sim | L53: Não | N53: CONTAR EM SETEMBRO
A54: 11 | B54: 510 | C54: 7Roads | D54: 2849 | E54: 07h30 | F54: Hotel-Aero | G54: 2 | H54: 25 | I54: 8 | J54: Ricardo | K54: Sim | L54: Não
A55: 11 | B55: 205 | C55: 7Roads | D55: 2850 | E55: 14h00 | F55: Hotel-Aero | G55: 3 | H55: 25 | I55: 8 | J55: Sara | K55: Sim | L55: Não
A56: 11 | B56: Katelyn Moorley | C56: 7Roads | D56: 2831 | E56: 20h55 | F56: Aero-Hotel (EZY2465) | G56: 1 | H56: 35 | I56: 10 | J56: Erica | K56: Sim | L56: Não
A57: 11 | B57: Kathleen Martini | C57: Website | D57: 173312 | E57: 22h05 | F57: Aero-Hotel (LH1170) | G57: 2 | H57: 39 | I57: - | J57: Ricardo | K57: Sim | L57: Não
A58: 12 | B58: 101/102 | C58: CitySightSeeing | D58: 168778 | E58: - | F58: Pack Essential | G58: 4 | H58: 144 | I58: 36 | J58: Adriana | K58: Sim | L58: Sim
A59: 12 | B59: 507 | C59: 7Roads | D59: 2753 | E59: 03h40 | F59: Hotel-Aero | G59: 2 | H59: 25 | I59: 8 | J59: Adriana | K59: Sim | L59: Não
A60: 12 | B60: 407 | C60: 7Roads | D60: 2754 | E60: 04h30 | F60: Hotel-Aero | G60: 1 | H60: 25 | I60: 8 | J60: Ricardo | K60: Sim | L60: Não
A61: 12 | B61: Justine Schlegel | C61: 7Roads | D61: 2848 | E61: 09h35 | F61: Aero-Hotel (TSC480) | G61: 1 | H61: 35 | I61: 10 | J61: Ricardo | K61: Sim | L61: Não
A62: 12 | B62: Filomena Menichino | C62: 7Roads | D62: 2841 | E62: 13h10 | F62: Aero-Hotel (FR9903) | G62: 2 | H62: 35 | I62: 10 | J62: Adriana | K62: Sim | L62: Não
A63: 12 | B63: Maria Sirera | C63: 7Roads | D63: 2843 | E63: 13h55 | F63: Aero-Hotel (S4150) | G63: 2 | H63: 35 | I63: 10 | J63: Nicole | K63: Sim | L63: Não
A64: 12 | B64: Marianne Misund | C64: Website | D64: 166697 | E64: 22h05 | F64: Aero-Hotel (TP765) | G64: 2 | H64: 39 | I64: - | J64: Beatriz | K64: Sim | L64: Não
A65: 12 | B65: Akiko Shiozawa | C65: 7Roads | D65: 2827 | E65: 23h20 | F65: Aero-Hotel (LX 2082) | G65: 2 | H65: 35 | I65: 10 | J65: Erica | K65: Sim | L65: Não
A66: 13 | B66: 312 | C66: CitySightSeeing | D66: 171849 | E66: - | F66: Pack Iconic | G66: 2 | H66: 66 | I66: 16.5 | J66: Nicole | K66: Sim | L66: Sim
A67: 13 | B67: 214 | C67: 7Roads | D67: 2757 | E67: 05h45 | F67: Hotel-Aero | G67: 2 | H67: 25 | I67: 8 | J67: Nicole | K67: Sim | L67: Não
A68: 13 | B68: Priscila Castro | C68: 7Roads | D68: 2846 | E68: 06h20 | F68: Aero-Hotel (TP58) | G68: 2 | H68: 35 | I68: 10 | J68: Ricardo | K68: Sim | L68: Não
A69: 13 | B69: 109 | Petra Lindner | C69: 7Roads | D69: 2835 | E69: 07h30 | F69: Hotel-Aero | G69: 2 | H69: 25 | I69: 8 | J69: Erica | K69: Sim | L69: Não
A70: 13 | B70: 502 | C70: 7Roads | D70: 2755 | E70: 09h30 | F70: Hotel-Aero | G70: 2 | H70: 25 | I70: 8 | J70: Francisco | K70: Sim | L70: Não
A71: 13 | B71: 321 | C71: 7Roads | D71: 2556 | E71: 10h30 | F71: Hotel-Centauro, Olivais | G71: 3+1 | H71: 35 | I71: 10 | J71: Francisco | K71: Sim | L71: Não
A72: 13 | B72: 406 | C72: 7Roads | D72: 2758 | E72: 11h00 | F72: Hotel-Aero | G72: 2 | H72: 25 | I72: 8 | J72: Ricardo | K72: Sim | L72: Não
A73: 13 | B73: 416 | C73: 7Roads | D73: 2759 | E73: 11h00 | F73: Hotel-Aero | G73: 3 | H73: 35 | I73: 10 | J73: Nicole | K73: Sim | L73: Não
A74: 13 | B74: Andrei Măjeri | C74: 7Roads | D74: 2760 | E74: 17h35 | F74: Aero-Hotel (W43197) | G74: 3 | H74: 35 | I74: 10 | J74: Adriana | K74: Sim | L74: Não
A75: 13 | B75: Rage Ben | C75: 7Roads | D75: 2751 | E75: 22h45 | F75: Aero-Hotel (FR8619) | G75: 2 | H75: 35 | I75: 10 | J75: Sara | K75: Sim | L75: Não
A76: 14 | B76: 428 | C76: 7Roads | D76: 428 | E76: 05h15 | F76: Hotel-Aero | G76: 2 | H76: 25 | I76: 8 | J76: Erica | K76: Sim | L76: Não
A77: 14 | B77: 417 | C77: Where To | D77: 2599 | E77: 08h20 | F77: Tour Sintra/Cascais | G77: 1 | H77: 69 | I77: 20.7 | J77: Erica | K77: Sim | L77: Sim
A78: 14 | B78: Maria Sirera #410 | C78: 7Roads | D78: 2844 | E78: 12h15 | F78: Hotel-Aero | G78: 2 | H78: 25 | I78: 8 | J78: Nicole | K78: Sim | L78: Não
A79: 15 | B79: 429/430 | C79: 7Roads | D79: 2768 | E79: 07h40 | F79: Hotel-Aero | G79: 4 | H79: 55 | I79: 15 | J79: Ricardo | K79: Sim | L79: Não
A80: 15 | B80: 208/214 | C80: Where To | D80: 2600 | E80: 08h15 | F80: Tour Sintra/Cascais | G80: 3 | H80: 207 | I80: 62.1 | J80: Ricardo | K80: Sim | L80: Sim
A81: 16 | B81: Fábio Galdini | C81: 7Roads | D81: 2765 | E81: 08h00 | F81: Aero-Hotel (AD8750) | G81: 2 | H81: 35 | I81: 10 | J81: Erica | K81: Sim | L81: Não
A82: 16 | B82: 404 | C82: 7Roads | D82: 2767 | E82: 08h45 | F82: Hotel-Aero | G82: 2 | H82: 25 | I82: 8 | J82: Ricardo | K82: Sim | L82: Não
A83: 16 | B83: 304 - Christopher | C83: 7Roads | D83: 2769 | E83: 09h15 | F83: Hotel-Santa Apolonia | G83: 2 | H83: 25 | I83: 8 | J83: Francisco | K83: Sim | L83: Não
A84: 16 | B84: Petros Mandalis | C84: 7Roads | D84: 2761 | E84: 23h45 | F84: Aero-Hotel (A3722) | G84: 2 | H84: 35 | I84: 10 | J84: Adriana | K84: Sim | L84: Não
A85: 17 | B85: 303 | C85: 7Roads | D85: 2766 | E85: 04h30 | F85: Hotel-Aero | G85: 2 | H85: 25 | I85: 8 | J85: Sara | K85: Sim | L85: Não
A86: 17 | B86: 401/402 | C86: 7Roads | D86: 2764 | E86: 14h30 | F86: Hotel-Aero | G86: 5 | H86: 55 | I86: 15 | J86: Nicole | K86: Sim | L86: Não
A87: 18 | B87: Yi Tong | C87: 7Roads | D87: 227 | E87: 04h40 | F87: Hotel-Aero | G87: 2 | H87: 25 | I87: 8 | J87: Diogo | K87: Sim | L87: Não
A88: 18 | B88: Krzysztof Kondracki | C88: Website | D88: 171046 | E88: 05h40 | F88: Hotel-Aero | G88: 2 | H88: 22 | I88: - | J88: Nicole | K88: Sim | L88: Não
A89: 18 | B89: 414 | C89: 7Roads | D89: 2773 | E89: 12h30 | F89: Hotel-Aero | G89: 2 | H89: 25 | I89: 8 | J89: Helder | K89: Sim | L89: Não
A90: 18 | B90: 205 / 215 / 216 | C90: 7Roads | D90: 2771 | E90: 12h45 | F90: Hotel-Aero | G90: 6 | H90: 55 | I90: 15 | J90: Adriana | K90: Sim | L90: Não
A91: 18 | B91: 208/214 | C91: 7Roads | D91: 2763 | E91: 14h00 | F91: Hotel-Aero | G91: 3 | H91: 35 | I91: 10 | J91: Nicole | K91: Sim | L91: Não
A92: 18 | B92: Gregory Sheets | C92: 7Roads | D92: 459 | E92: 14h50 | F92: Aero-Hotel (DL8296) | G92: 2 | H92: 35 | I92: 10 | J92: Ricardo | K92: Sim | L92: Não
A93: 18 | B93: 421 | C93: 7Roads | D93: 2752 | E93: 18h00 | F93: Hotel-Aero | G93: 2 | H93: 25 | I93: 8 | J93: Sara | K93: Sim | L93: Não
A94: 18 | B94: Stefano Grossi | C94: 7Roads | D94: 2772 | E94: 18h15 | F94: Aero-Hotel (S4124) | G94: 2 | H94: 35 | I94: 10 | J94: Helder | K94: Sim | L94: Não
A95: 19 | B95: Akiko Shiozawa | C95: 7Roads | D95: 2828 | E95: 03h30 | F95: Hotel-Aero | G95: 2 | H95: 25 | I95: 8 | J95: Erica | K95: Sim | L95: Não
A96: 19 | B96: Sanna, Giovannino/ 310 | C96: 7Roads | D96: 2776 | E96: 04h00 | F96: Hotel-Aero | G96: 2 | H96: 25 | I96: 8 | J96: Erike | K96: Sim
A97: 19 | B97: Curtis Levy | C97: 7Roads | D97: 2829 | E97: 08h05 | F97: Aero-Hotel (TP244) | G97: 2 | H97: 35 | I97: 10 | J97: Erica | K97: Sim | L97: Não
A98: 19 | B98: 224 | C98: 7Roads | D98: 2778 | E98: 08h30 | F98: Hotel-Aero | G98: 2 | H98: 25 | I98: 8 | J98: Francisco | K98: Sim | L98: Não
A99: 19 | B99: Lucas Borchenko | C99: Website | D99: 168072 | E99: 09h35 | F99: Aero-Hotel (TS480) | G99: 2 | H99: 39 | I99: - | J99: Ricardo | K99: Sim | L99: Não
A100: 19 | B100: Thomas DeClercq | C100: Website | D100: 165244 | E100: 10h55 | F100: Aero-Hotel (DL9349) | G100: 2 | H100: 39 | I100: - | J100: Vanessa | K100: Sim | L100: Não
...

Sheet Set.25
A1: Dia | B1: Quarto | Nome | C1: Empresa | D1: Voucher | Res. | E1: Hora | F1: Direcções | Observações | G1: Nº Pax | H1: Valor | I1: Comissão | J1: Por Quem | K1: Pago Hósp? | L1: Pago | N1: Parceiros | O1: Valor Total | P1: Comissão | Q1: Tips | R1: Envelope | S1: Comissões 7Roads | W1: Pago | X1: Dia | Y1: Por Quem
A2: 1 | B2: Thalia Fernandes | C2: Where To | D2: 2569 | E2: 08h20 | F2: Tour Sintra/Cascais | G2: 3 | H2: 207 | I2: 62.1 | J2: Nicole | K2: Sim | L2: Sim | N2: Where To | O2: =SUMIFS(H2:H235,C2:C235,N2,L2:L235,"Sim") -> 1193 | P2: =O2*0.3 -> 357.9 | Q2: =SUMIFS(I2:I235,C2:C235,N2,K2:K235,"Sim") -> 399.3 | S2: Hotel - Aero | T2: Valor | U2: Comissão | V2: Nº Malas | W2: Sim | X2: 1 | Y2: Ricardo
A3: 1 | B3: Franklin Zbaraschuk | C3: 7Roads | D3: 169 | E3: 09h35 | F3: Aero-Hotel (TS480) | G3: 2 | H3: 35 | I3: 10 | J3: Adriana | K3: Sim | L3: Não | N3: 7Roads | O3: =SUMIFS(H2:H235,C2:C235,N3,L2:L235,"Não") -> 4786 | P3: =SUMIFS(I2:I235,C2:C235,N3,L2:L235,"Não") -> 1437.3 | Q3: =SUMIFS(I2:I235,C2:C235,N3,K2:K235,"Sim") -> 1452.3 | R3: =SUMIFS(H2:H235,C2:C235,N3,K2:K235,"Sim")-Q3-Q5 -> 3287.7 | S3: 1 a 2 Pax | T3: 25 | U3: 8 | V3: 3 Malas | W3: Não | X3: 2 | Y3: Adriana
A4: 1 | B4: Leslie Fall | C4: Website | D4: 170688 | E4: 09h50 | F4: Aero-Hotel (TAP216) | G4: 2 | H4: 39 | I4: - | J4: Vanessa | K4: Sim | L4: Não | N4: CitySightSeeing | O4: =SUMIFS(H2:H235,C2:C235,N4,L2:L235,"Não") -> 915 | P4: =O4*0.25 -> 228.75 | Q4: =SUMIFS(I2:I234,C2:C234,N4,K2:K234,"Sim") -> 228.75 | R4: =O4-P4 -> 686.25 | S4: 3 a 4 Pax | T4: 35 | U4: 10 | V4: 4 Malas | X4: 3 | Y4: Thomas
A5: 2 | B5: 106 | C5: 7Roads | D5: 435 | E5: 02h00 | F5: Hotel-Aero | G5: 1 | H5: 25 | I5: 8 | J5: Francisco | K5: Sim | L5: Não | N5: 7Roads Driver | O5: =SUMIFS(H2:H235,C2:C235,N5,L2:L235,"Não") -> 0 | P5: =SUMIFS(I2:I235,C2:C235,N5,L2:L235,"Não") -> 0 | Q5: =SUMIFS(I2:I235,C2:C235,N5,K2:K235,"Sim") -> 36 | S5: 3 a 4 Pax | T5: 40 | U5: 12 | V5: 5/6 Malas | X5: 4 | Y5: Maycon
A6: 2 | B6: 209 | C6: 7Roads | D6: 429 | E6: 02h20 | F6: Hotel-Aero | G6: 2 | H6: 25 | I6: 8 | J6: Nicole | K6: Sim | L6: Não | N6: Website | O6: =SUMIFS(H2:H235,C2:C235,N6,L2:L235,"Não") -> 1555 | P6: =O6*0.15 -> 233.25 | S6: 5 a 8 Pax | T6: 55 | U6: 15 | V6: 12 Malas | X6: 5 | Y6: Helder
A7: 2 | B7: 102 | C7: 7Roads | D7: 432 | E7: 05h30 | F7: Hotel-Aero | G7: 1 | H7: 25 | I7: 8 | J7: Helder | K7: Sim | L7: Não | N7: Outra | O7: =SUMIFS(H2:H235,C2:C235,N7,L2:L235,"Não") -> 0 | P7: =SUMIFS(I2:I235,C2:C235,N7,L2:L235,"Não") -> 0 | S7: Aero - Hotel | T7: 35€ a 45€ | U7: 10 | V7: N/A | X7: 6 | Y7: Erica
A8: 2 | B8: 511 | C8: 7Roads | D8: 436 | E8: 07h40 | F8: Hotel-Oriente | G8: 2 | H8: 25 | I8: 8 | J8: Francisco | K8: Sim | L8: Não | N8: Total | O8: =SUM(O2:O3) -> 5979 | P8: =SUM(P2:P3) -> 1795.2 | R8: =SUM(R3+R4)+Ago.25!R8 -> 3973.95 | T8: 55 | U8: 15 | V8: N/A | X8: 7 | Y8: Nicole
A9: 2 | B9: James Anderson | C9: Website | D9: 165895 | E9: 08h20 | F9: Aero-Hotel (UA64) | G9: 2 | H9: 39 | I9: - | J9: Nicole | K9: Sim | L9: Não | S9: WhereTo | T9: 0.3 | U9: CitySightSeeing | V9: 0.25 | X9: 8 | Y9: Francisco
A10: 2 | B10: 229 | C10: Where To | D10: 3253 | E10: 08h20 | F10: Sintra-Cascais | G10: 2 | H10: 138 | I10: 41.4 | J10: Erica | K10: Sim | L10: Sim | N10: Contagem MAPA TOURS | Q10: Contagem CAIXA TURNO | X10: 9 | Y10: Diogo
A11: 2 | B11: Robert Coulthurst | C11: Website | D11: 162865 | E11: 09h20 | F11: Aero-Hotel (LH6547) | G11: 2 | H11: 39 | I11: - | J11: Vanessa | K11: Sim | L11: Não | N11: Notas | Q11: Notas | T11: Facturas | U11: Valor | X11: 10 | Y11: Erike
A12: 2 | B12: 212 | C12: 7Roads | D12: 428 | E12: 09h30 | F12: Hotel-Aero | G12: 2 | H12: 40 | I12: 12 | J12: Erike | K12: Sim | L12: Não | N12: ALCOBIA | O12: 0 | P12: 0 | Q12: 500 | R12: 0 | S12: =Q12*R12 -> 0 | T12: Fundo Maneio | U12: 18.77 | X12: 11 | Y12: Alexandre
A13: 2 | B13: 102 | C13: 7Roads | D13: 433 | E13: 14h30 | F13: Hotel - Aero | G13: 1 | H13: 25 | I13: 8 | J13: Helder | K13: Sim | L13: Não | N13: 200 | O13: 0 | P13: =N13*O13 -> 0 | Q13: 200 | R13: 0 | S13: =Q13*R13 -> 0 | T13: Wash Station | U13: 13.8 | X13: 12 | Y13: Marcus
A14: 2 | B14: Markus Schick | C14: 7Roads | D14: 430 | E14: 22h35 | F14: Aero-Hotel (TP1273) | G14: 2 | H14: 55 | I14: 15 | J14: Maycon | K14: Sim | L14: Não | N14: 100 | O14: 0 | P14: =N14*O14 -> 0 | Q14: 100 | R14: 0 | S14: =Q14*R14 -> 0 | X14: 13 | Y14: Denise
A15: 3 | B15: 321 | C15: CitySightSeeing | D15: 166938 | E15: - | F15: Essencial Pack | G15: 2 | H15: 72 | I15: 18 | J15: Nicole | K15: Sim | L15: Não | N15: 50 | O15: 0 | P15: =N15*O15 -> 0 | Q15: 50 | R15: 0 | S15: =Q15*R15 -> 0 | X15: 14
A16: 3 | B16: 320 - MCLane Gregory | C16: 7Roads | D16: 438 | E16: 06h30 | F16: Hotel-Aero | G16: 2 | H16: 25 | I16: 8 | J16: Erike | K16: Sim | L16: Não | N16: 20 | O16: 34 | P16: =N16*O16 -> 680 | Q16: 20 | R16: 1 | S16: =Q16*R16 -> 20 | X16: 15
A17: 3 | B17: 107/112 | C17: 7Roads | D17: 440 | E17: 09h00 | F17: Hotel-Oriente | G17: 4 | H17: 40 | I17: 12 | J17: Erica | K17: Sim | L17: Não | N17: 10 | O17: 0 | P17: =N17*O17 -> 0 | Q17: 10 | R17: 0 | S17: =Q17*R17 -> 0 | X17: 16
A18: 3 | B18: 518 | C18: 7Roads | D18: 439 | E18: 09h20 | F18: Hotel-Aero | G18: 1 | H18: 25 | I18: 8 | J18: Erica | K18: Sim | L18: Não | N18: 5 | O18: 1 | P18: =N18*O18 -> 5 | Q18: 5 | R18: 1 | S18: =Q18*R18 -> 5 | X18: 17
A19: 3 | B19: Marie Pierre Locatelli | C19: Website | D19: 172263 | E19: 12h10 | F19: Aero-Hotel (EJU7642) | G19: 2 | H19: 39 | I19: - | J19: Nicole | K19: Sim | L19: Não | P19: =SUM(P12:P18) -> 685 | S19: =SUM(S12:S18) -> 25 | X19: 18
A20: 3 | B20: 218/219 | C20: 7Roads | D20: 441 | E20: 15h45 | F20: Hotel-Aero | G20: 4 | H20: 40 | I20: 12 | J20: Francisco | K20: Sim | L20: Não | N20: Moedas | Q20: Moedas | X20: 19
A21: 3 | B21: Jutta Zawodny | C21: 7Roads | D21: 427 | E21: 17h05 | F21: Aero-Hotel (EW7602) | G21: 2 | H21: 35 | I21: 10 | J21: Helder | K21: Sim | L21: Não | N21: 2 | O21: 0 | P21: =N21*O21 -> 0 | Q21: 2 | R21: 8 | S21: =Q21*R21 -> 16 | X21: 20
A22: 4 | B22: 412 | C22: CitySightSeeing | D22: 171128 | E22: - | F22: Iconic Pack | G22: 2 | H22: 66 | I22: 16.5 | J22: Nicole | K22: Sim | L22: Não | N22: 1 | O22: 0 | P22: =N22*O22 -> 0 | Q22: 1 | R22: 15 | S22: =Q22*R22 -> 15 | X22: 21
A23: 4 | B23: Caitlin Faeth #501 | C23: Website | D23: 173413 | E23: 08h00 | F23: Hotel-Aero | G23: 2 | H23: 22 | I23: - | J23: Thomas | K23: Sim | L23: Não | N23: 0.5 | O23: 0 | P23: =N23*O23 -> 0 | Q23: 0.5 | R23: 20 | S23: =Q23*R23 -> 10 | X23: 22
A24: 4 | B24: Diana Pond #507 | C24: Website | D24: 173414 | E24: 08h00 | F24: Hotel-Aero | G24: 2 | H24: 22 | I24: - | J24: Thomas | K24: Sim | L24: Não | N24: 0.2 | O24: 0 | P24: =N24*O24 -> 0 | Q24: 0.2 | R24: 10 | S24: =Q24*R24 -> 2 | X24: 23
A25: 4 | B25: Ken Frankish | C25: 7Roads | D25: 1897 | E25: 23h00 | F25: Aero-Hotel (A3722) | G25: 2 | H25: 35 | I25: 10 | J25: Adriana | K25: Sim | L25: Não | N25: 0.1 | O25: 0 | P25: =N25*O25 -> 0 | Q25: 0.1 | R25: 22 | S25: =Q25*R25 -> 2.2 | T25: Total Facturas | U25: =SUM(U12:U24) -> 32.57 | X25: 24
A26: 5 | B26: 218 | C26: 7Roads | D26: 443 | E26: 04h00 | F26: Hotel-Aero | G26: 4 | H26: 55 | I26: 15 | J26: Erike | K26: Sim | L26: Não | N26: 0.05 | O26: 0 | P26: =N26*O26 -> 0 | Q26: 0.05 | R26: 16 | S26: =Q26*R26 -> 0.8 | T26: Fundo de Caixa | U26: 103.72 | X26: 25
A27: 5 | B27: Franklin Zbaraschuk | C27: 7Roads | D27: 170 | E27: 05h30 | F27: Hotel-Aero | G27: 2 | H27: 25 | I27: 8 | J27: Adriana | K27: Sim | L27: Não | N27: 0.02 | O27: 0 | P27: =N27*O27 -> 0 | Q27: 0.02 | R27: 1 | S27: =Q27*R27 -> 0.02 | T27: Diferença de Caixa | X27: 26
A28: 5 | B28: 511 | C28: 7Roads | D28: 442 | E28: 06h00 | F28: Hotel-Aero | G28: 2 | H28: 25 | I28: 8 | J28: Nicole | K28: Sim | L28: Não | N28: 0.01 | O28: 0 | P28: =N28*O28 -> 0 | Q28: 0.01 | R28: 13 | S28: =Q28*R28 -> 0.13 | T28: =S19+S29+U25-U26 -> 0 | X28: 27 | AB28: -
A29: 5 | B29: Michael Green | C29: 7Roads | D29: 1946 | E29: 08h00 | F29: Aero-Hotel (DL0272) | G29: 2 | H29: 35 | I29: 10 | J29: Beatriz | K29: Sim | L29: Não | P29: =SUM(P21:P28) -> 0 | S29: =SUM(S21:S28) -> 46.15 | X29: 28
A30: 5 | B30: Guillermo Alfonso Osuna Paez | C30: Website | D30: 171835 | E30: 08h00 | F30: Aero-Hotel (AM6898) Reservou 4 mas chega 5 | G30: 2 | H30: 39 | I30: _ | J30: Erica | K30: Sim | L30: Não | N30: Total | P30: =SUM(P19+P29-R8) -> -3288.95 | X30: 29
A31: 5 | B31: 306 | C31: 7Roads | D31: 445 | E31: 11h00 | F31: Hotel-Aero | G31: 2 | H31: 25 | I31: 8 | J31: Erica | K31: Sim | L31: Não | X31: 30
A32: 5 | B32: Dubois | C32: 7Roads | D32: 446 | E32: 18h20 | F32: Aero-Hotel (EJU7606) | G32: 3 | H32: 35 | I32: 10 | J32: Erica | K32: Sim | L32: Não | N32: Contagem TIPS | S32: Lançamentos TIPS | X32: 31 | AI32: 605
A33: 6 | B33: 408 | C33: 7Roads | D33: 449 | E33: 01h30 | F33: Hotel-Aero | G33: 2 | H33: 25 | I33: 8 | J33: Helder | K33: Sim | L33: Não | N33: Notas | Q33: Descrição | R33: Valor | S33: Dia | T33: Descrição | U33: Valor | V33: Por Quem
A34: 6 | B34: 303 | C34: 7Roads | D34: 450 | E34: 08h00 | F34: Hotel - Aero | G34: 1 | H34: 25 | I34: 8 | J34: Helder | K34: Sim | L34: Não | N34: 500 | O34: 0 | P34: =N34*O34 -> 0 | T34: Where To | U34: =Q2-357.9 -> 41.4
A35: 6 | B35: 401_402 | C35: 7Roads | D35: 444 | E35: 10h00 | F35: Hotel-Aero | G35: 4 | H35: 40 | I35: 12 | J35: Erica | K35: Sim | L35: Não | N35: 200 | O35: 0 | P35: =N35*O35 -> 0 | T35: 7Roads | U35: =Q3-965.3 -> 487
A36: 6 | B36: Cathy Fallon | C36: 7Roads | D36: 434 | E36: 10h45 | F36: Aero-Hotel (TP1351) | G36: 1 | H36: 35 | I36: 10 | J36: Erica | K36: Sim | L36: Não | N36: 100 | O36: 0 | P36: =N36*O36 -> 0 | T36: CitySightSeeing | U36: =Q4-194.25 -> 34.5
A37: 6 | B37: 320 | C37: Outra | D37: Tuktuk | E37: 11h05 | F37: Lisbon of neighborhoods 2 | G37: 4 | H37: 142.5 | I37: 21.37 | J37: Francisco | K37: Sim | L37: Sim | N37: 50 | O37: 1 | P37: =N37*O37 -> 50 | S37: 10 | T37: Sobras TIPS | U37: 66.69 | V37: Ricardo
A38: 6 | B38: Deborah Warren | C38: Website | D38: 160361 | E38: 18h40 | F38: Aero-Hotel (DL9446) Reservou 7 mas chega 6 | G38: 2 | H38: 39 | I38: - | J38: Ricardo | K38: Sim | L38: Não | N38: 20 | O38: 16 | P38: =N38*O38 -> 320 | S38: 22 | T38: TIP A SERIO | U38: 6.5 | V38: Nicole
A39: 6 | B39: Jose Francisco Martha González | C39: Website | D39: 168955 | E39: 19h50 | F39: Aero-Hotel (TP835) | G39: 2 | H39: 39 | I39: - | J39: Nicole | K39: Sim | L39: Não | N39: 10 | O39: 5 | P39: =N39*O39 -> 50 | S39: 22 | T39: A MENOS | U39: -26 | V39: Nicole
A40: 7 | B40: 210 | C40: 7Roads | D40: 2852 | E40: 07h15 | F40: Hotel-Lisboa Oriente | G40: 2 | H40: 25 | I40: 8 | J40: Helder | K40: Sim | L40: Não | N40: 5 | O40: 28 | P40: =N40*O40 -> 140 | S40: 22 | T40: TIP A SERIO | U40: 4 | V40: Erica
A41: 7 | B41: Norene Pease | C41: Website | D41: 167208 | E41: 10h45 | F41: Aero-Hotel (DL124) (NoShow) | G41: 2 | H41: 39 | I41: - | J41: Vanessa | K41: Sim | L41: Não | P41: =SUM(P34:P40) -> 560 | S41: 22 | T41: A mais | U41: 20 | V41: Ricardo
A42: 7 | B42: Brenda Young | C42: Website | D42: 167142 | E42: 15h25 | F42: Aero-Hotel (AC9364) | G42: 2 | H42: 39 | I42: - | J42: Ricardo | K42: Sim | L42: Não | N42: Moedas | S42: 23 | T42: a mais | U42: 1 | V42: Erica
A43: 7 | B43: Julie Ekelund | C43: 7Roads | D43: 431 | E43: 16h00 | F43: Aero-Hotel (SK8913) | G43: 2 | H43: 35 | I43: 10 | J43: Helder | K43: Sim | L43: Não | N43: 2 | O43: 2 | P43: =N43*O43 -> 4 | S43: 27 | T43: A mais | U43: 10 | V43: Ricardo
A44: 7 | B44: 410 | C44: 7Roads | D44: 2857 | E44: 17h00 | F44: Hotel-Aero | G44: 2 | H44: 25 | I44: 8 | J44: Erica | K44: Sim | L44: Não | N44: 1 | O44: 110 | P44: =N44*O44 -> 110 | S44: 27 | T44: 7Roads Driver | U44: 8 | V44: Ricardo
A45: 7 | B45: 415 | C45: 7Roads | D45: 2853 | E45: 17h00 | F45: Hotel-Aero | G45: 2 | H45: 25 | I45: 8 | J45: Helder | K45: Sim | L45: Não | N45: 0.5 | O45: 30 | P45: =N45*O45 -> 15 | S45: 28 | T45: TIP A SERIO | U45: 20 | V45: Helder
A46: 8 | B46: 418 | C46: 7Roads | D46: 2851 | E46: 06h00 | F46: Hotel-Aero | G46: 2 | H46: 25 | I46: 8 | J46: Helder | K46: Sim | L46: Não | N46: 0.2 | O46: 0 | P46: =N46*O46 -> 0 | Q46: Total | R46: =SUM(R34:R45) -> 0 | S46: 28 | T46: TIP A SERIO | U46: 10 | V46: Nicole
A47: 8 | B47: Jacques Barriere | C47: Website | D47: 167198 | E47: 08h10 | F47: Aero-Hotel (TP495) | G47: 2 | H47: 39 | I47: - | J47: Adriana | K47: Sim | L47: Não | N47: 0.1 | O47: 0 | P47: =N47*O47 -> 0 | S47: 28 | T47: 7Roads Driver | U47: 10 | V47: Ricardo
A48: 8 | B48: Georgi Ginev | C48: Where To | D48: 3254 | E48: 08h20 | F48: Sintra-Cascais | G48: 4 | H48: 276 | I48: 82.8 | J48: Nicole | K48: Sim | L48: Sim | N48: 0.05 | O48: 1 | P48: =N48*O48 -> 0.05 | Q48: Lançamentos | R48: =SUM(U34:U51) -> 701.09 | S48: 28 | T48: 7Roads Driver | U48: 8 | V48: Ricardo
A49: 8 | B49: 603_604 | Hans Georg | C49: 7Roads | D49: 2860 | E49: 11h30 | F49: Hotel-Aero | G49: 4 | H49: 55 | I49: 15 | J49: Erike | K49: Sim | L49: Não | N49: 0.02 | O49: 2 | P49: =N49*O49 -> 0.04 | Q49: Cash | R49: =P41+P51+R46 -> 689.09
A50: 8 | B50: Inbal Levi | C50: 7Roads | D50: 2854 | E50: 20h55 | F50: Aero-Hotel (LY375) | G50: 2 | H50: 35 | I50: 10 | J50: Erica | K50: Sim | L50: Não | N50: 0.01 | O50: 0 | P50: =N50*O50 -> 0 | Q50: Diferença | R50: =R49-R48 -> -12
A51: 9 | B51: 208 | C51: CitySightSeeing | D51: 166538 | E51: - | F51: Iconic Pack | G51: 2 | H51: 66 | I51: 16.5 | J51: Nicole | K51: Sim | L51: Não | P51: =SUM(P43:P50) -> 129.09 | Q51: Valor por pax | R51: =R49/9 -> 76.565556
A52: 9 | B52: 501 | C52: 7Roads | D52: 2855 | E52: 04h30 | F52: Hotel-Aero | G52: 1 | H52: 25 | I52: 8 | J52: Erica | K52: Sim | L52: Não
A53: 9 | B53: 429 | C53: 7Roads | D53: 2856 | E53: 08h00 | F53: Hotel-Aero | G53: 2 | H53: 25 | I53: 8 | J53: Erica | K53: Sim | L53: Não | O53: CONTAR EM OUTUBRO
A54: 9 | B54: Jose Francisco Martha González | C54: Website | D54: 168955 | E54: 08h30 | F54: Hotel-Aero | G54: 2 | H54: 22 | I54: - | J54: Nicole | K54: Sim | L54: Não
A55: 9 | B55: 518 | Jutta | C55: 7Roads | D55: 2859 | E55: 09h00 | F55: Hotel-Aero | G55: 2 | H55: 25 | I55: 8 | J55: Erike | K55: Sim | L55: Não
A56: 9 | B56: 210/222 | C56: 7Roads | D56: 2864 | E56: 09h00 | F56: Hotel-Oriente | G56: 4 | H56: 40 | I56: 12 | J56: Helder | K56: Sim | L56: Não
A57: 9 | B57: 206 | C57: 7Roads | D57: 2861 | E57: 10h00 | F57: Hotel-Aero | G57: 2 | H57: 25 | I57: 8 | J57: Helder | K57: Sim | L57: Não
A58: 9 | B58: 424 | C58: 7Roads | D58: 2867 | E58: 14h00 | F58: Hotel-Aero | G58: 2 | H58: 25 | I58: 8 | J58: Helder | K58: Sim | L58: Não
A59: 9 | B59: Christiane Lemberg | C59: 7Roads | D59: 2869 | E59: 20h15 | F59: Aero-Hotel (TP563) | G59: 2 | H59: 35 | I59: 10 | J59: Helder | K59: Sim | L59: Não
A60: 10 | B60: 109 | C60: CitySightSeeing | D60: N/A | E60: - | F60: Essencial Pack | G60: 1 | H60: 36 | I60: 9 | J60: Ricardo | K60: Sim | L60: Não
A61: 10 | B61: 220 | C61: 7Roads | D61: 2871 | E61: 06h30 | F61: Hotel-Aero | G61: 2 | H61: 25 | I61: 8 | J61: Ricardo | K61: Sim | L61: Não
A62: 10 | B62: Norene Pease | C62: Website | D62: 167208 | E62: 09h00 | F62: Hotel-Aero (NoShow) | G62: 2 | H62: 22 | I62: - | J62: Vanessa | K62: Sim | L62: Não
A63: 10 | B63: 430 | C63: 7Roads | D63: 2872 | E63: 13h30 | F63: Hotel - Aero | G63: 2 | H63: 25 | I63: 8 | J63: Nicole | K63: Sim | L63: Não
A64: 10 | B64: 503 | C64: 7Roads | D64: 2863 | E64: 16h00 | F64: Hotel-Aero | G64: 2 | H64: 25 | I64: 8 | J64: Helder | K64: Sim | L64: Não
A65: 11 | B65: 226 | C65: CitySightSeeing | D65: 167508 | E65: - | F65: Iconic Pack | G65: 2 | H65: 66 | I65: 16.5 | J65: Francisco | K65: Sim | L65: Não
A66: 11 | B66: 214 | C66: CitySightSeeing | D66: 173682 | E66: - | F66: Value Pack | G66: 2 | H66: 102 | I66: 25.5 | J66: Francisco | K66: Sim | L66: Não
A67: 11 | B67: 202 | C67: 7Roads | D67: 2876 | E67: 06h30 | F67: Hotel-Aero | G67: 4 | H67: 40 | I67: 12 | J67: Ricardo | K67: Sim | L67: Não
A68: 11 | B68: Mark Fisher #501/502 | C68: Website | D68: 170337 | E68: 08h00 | F68: Hotel-Aero (VAN) - Matheus! | G68: 4 | H68: 39 | I68: - | J68: Maycon | K68: Sim | L68: Não
A69: 11 | B69: Ken Konzen | C69: Website | D69: 167313 | E69: 10h45 | F69: Aero-Hotel (TP1351) | G69: 2 | H69: 39 | I69: - | J69: Ricardo | K69: Sim | L69: Não
A70: 11 | B70: 210 | C70: 7Roads | D70: 2873 | E70: 11h15 | F70: Hotel-Aero | G70: 2 | H70: 25 | I70: 8 | J70: Nicole | K70: Sim | L70: Não
A71: 11 | B71: Consuelo Garelli | C71: 7Roads | D71: 2870 | E71: 11h45 | F71: Aero-Hotel (FR2087) | G71: 2 | H71: 35 | I71: 10 | J71: Erica | K71: Sim | L71: Não
A72: 11 | B72: 510 | C72: 7Roads | D72: 2879 | E72: 15h15 | F72: Hotel-Rossio comboios | G72: 2 | H72: 20 | I72: 5 | J72: Francisco | K72: Sim | L72: Não
A73: 11 | B73: Mark Fisher #501/502 | C73: 7Roads | D73: 170337 | F73: Não é serviço - é o valor cobrado extra pela VAN | G73: 4 | H73: 16 | I73: 3.3 | J73: Maycon | K73: Sim | L73: Não
A74: 12 | B74: 405 | C74: 7Roads | D74: 170317 | E74: 04h04 | F74: Hotel- Aero | G74: 1 | H74: 25 | I74: 8 | J74: Erike | K74: Sim | L74: Não
A75: 12 | B75: 530 | C75: 7Roads | D75: 2878 | E75: 05h45 | F75: Hotel - Aero | G75: 2 | H75: 25 | I75: 8 | J75: Nicole | K75: Sim | L75: Não
A76: 12 | B76: Lisa Porter | C76: 7Roads | D76: 2882 | E76: 10h30 | F76: Aero-Hotel | G76: 2 | H76: 35 | I76: 10 | J76: Helder | K76: Sim | L76: Não
A77: 12 | B77: Benjamin Stalder | C77: 7Roads | D77: 447 | E77: 12h40 | F77: Aero-Hotel (EJU7642) | G77: 2 | H77: 35 | I77: 10 | J77: Erica | K77: Sim | L77: Não
A78: 12 | B78: 529 | C78: 7Roads | D78: 2880 | E78: 17h00 | F78: Hotel-Aero | G78: 2 | H78: 25 | I78: 8 | J78: Erica | K78: Sim | L78: Não
A79: 13 | B79: 509 | C79: 7Roads | D79: 2884 | E79: 07h30 | F79: Hotel-Aero | G79: 2 | H79: 25 | I79: 8 | J79: Ricardo | K79: Sim | L79: Não
A80: 13 | B80: 319 | C80: 7Roads | D80: 2883 | E80: 09h00 | F80: Hotel-Aero | G80: 2 | H80: 25 | I80: 8 | J80: Helder | K80: Sim | L80: Não
A81: 13 | B81: SUYOUN LEE | C81: 7Roads | D81: 169834 | E81: 22h50 | F81: Aero-Hotel (KL1587) | G81: 2 | H81: 35 | I81: 10 | J81: Maycon | K81: Sim | L81: Não
A82: 14 | B82: André Meyer | C82: Website | D82: 171914 | E82: 08h10 | F82: Aero-Hotel (TP935) | G82: 4 | H82: 50 | I82: - | J82: Ricardo | K82: Sim | L82: Não
A83: 14 | B83: 203 | C83: Where To | D83: 3256 | E83: 08h20 | F83: Tour Sintra-Cascais | G83: 2 | H83: 138 | I83: 41.4 | J83: Helder | K83: Sim | L83: Sim
A84: 14 | B84: 321 | C84: 7Roads | D84: 2886 | E84: 09h00 | F84: Hotel-Aero | G84: 2 | H84: 25 | I84: 8 | J84: Helder | K84: Sim | L84: Não
A85: 14 | B85: André Meyer | C85: 7Roads | D85: 2890 | E85: 15h15 | F85: Aero-Hotel (TP931) | G85: 2 | H85: 35 | I85: 10 | J85: Erica | K85: Sim | L85: Não
A86: 15 | B86: 112 | C86: 7Roads | D86: 2887 | E86: 05h00 | F86: Hotel-Aero | G86: 2 | H86: 25 | I86: 8 | J86: Helder | K86: Sim | L86: Não
A87: 15 | B87: 219 | C87: 7Roads | D87: 2892 | E87: 07h00 | F87: Hotel-Aero | G87: 2 | H87: 25 | I87: 8 | J87: Erica | K87: Sim | L87: Não
A88: 15 | B88: 403 | C88: 7Roads | D88: 2895 | E88: 07h00 | F88: Hotel-Aero | G88: 2 | H88: 25 | I88: 8 | J88: Helder | K88: Sim | L88: Não
A89: 15 | B89: 321 | C89: 7Roads | D89: 2891 | E89: 07h15 | F89: Hotel-Aero | G89: 2 | H89: 25 | I89: 8 | J89: Erica | K89: Sim | L89: Não
A90: 15 | B90: 312 | C90: Website | D90: 173959 | E90: 07h30 | F90: Hotel-Aero | G90: 1 | H90: 22 | I90: - | J90: Helder | K90: Sim | L90: Não
A91: 15 | B91: Theresa Breidigan | C91: 7Roads | D91: 2640 | E91: 08h20 | F91: Aero-Hotel (UA145) | G91: 2 | H91: 35 | I91: 10 | J91: Thomas | K91: Sim | L91: Não
A92: 15 | B92: 216 | C92: Where To | D92: 3255 | E92: 08h20 | F92: Tour Sintra-Cascais | G92: 2 | H92: 138 | I92: 41.4 | J92: Nicole | K92: Sim | L92: Sim
A93: 15 | B93: Maria Cuestas | C93: 7Roads | D93: 2897 | E93: 09h05 | F93: Aero - Hotel (TP1020) (Não foi feito, mas pagou) | G93: 2 | H93: 35 | I93: 10 | J93: Nicole | K93: Sim | L93: Não
A94: 15 | B94: Scott Weaver | C94: Website | D94: 158550 | E94: 17h55 | F94: Aero-Hotel (BA502) | G94: 2 | H94: 39 | I94: - | J94: Ricardo | K94: Sim | L94: Não
A95: 16 | B95: 429 | C95: 7Roads | D95: 2894 | E95: 07h20 | F95: Hotel-Oriente Comboios | G95: 2 | H95: 25 | I95: 8 | J95: Helder | K95: Sim | L95: Não
A96: 16 | B96: Theresa Breidigan #504 | C96: Where To | D96: 2592 | E96: 08h25 | F96: Tour Sintra/Cascais | G96: 2 | H96: 138 | I96: 41.4 | J96: Sara | K96: Sim | L96: Sim
A97: 16 | B97: Mary Hlavinka | C97: 7Roads | D97: 437 | E97: 10h30 | F97: Aero-Hotel (UA942) | G97: 2 | H97: 35 | I97: 10 | J97: Maycon | K97: Sim | L97: Não
A98: 16 | B98: 607 | C98: 7Roads | D98: 2900 | E98: 15h00 | F98: Hotel-Aero | G98: 2 | H98: 25 | I98: 8 | J98: Erica | K98: Sim | L98: Não
A99: 17 | B99: 309 | C99: CitySightSeeing | D99: 153269 | E99: - | F99: Pack Iconic | G99: 2 | H99: 66 | I99: 16.5 | J99: Helder | K99: Sim | L99: Não
A100: 17 | B100: Ken Konzen #216 | C100: Website | D100: 167313 | E100: 05h00 | F100: Hotel-Aero | G100: 2 | H100: 22 | I100: - | J100: Ricardo | K100: Sim | L100: Não
...

Sheet Out.25
A1: Dia | B1: Quarto | Nome | C1: Empresa | D1: Voucher | Res. | E1: Hora | F1: Direcções | Observações | G1: Nº Pax | H1: Valor | I1: Comissão | J1: Por Quem | K1: Pago Hósp? | L1: Pago | N1: Parceiros | O1: Valor Total | P1: Comissão | Q1: Tips | R1: Envelope | S1: Comissões 7Roads | W1: Pago | X1: Dia | Y1: Por Quem
A2: 1 | B2: 605 | C2: 7Roads | D2: 1544 | E2: 05h00 | F2: Hotel-Aero | G2: 1 | H2: 25 | I2: 8 | J2: Ricardo | K2: Sim | L2: Sim | N2: Where To | O2: =SUMIFS(H2:H231,C2:C231,N2,L2:L231,"Sim") -> 948 | P2: =O2*0.3 -> 284.4 | Q2: =SUMIFS(I2:I231,C2:C231,N2,K2:K231,"Sim") -> 408.6 | S2: Hotel - Aero | T2: Valor | U2: Comissão | V2: Nº Malas | W2: Sim | X2: 1
A3: 1 | B3: 308 | C3: 7Roads | D3: 1546 | E3: 06h00 | F3: Hotel-Aero | G3: 1 | H3: 25 | I3: 8 | J3: Denise | K3: Sim | L3: Sim | N3: 7Roads | O3: =SUMIFS(H2:H231,C2:C231,N3,L2:L231,"Não") -> 50 | P3: =SUMIFS(I2:I231,C2:C231,N3,L2:L231,"Não") -> 16 | Q3: =SUMIFS(I2:I231,C2:C231,N3,K2:K231,"Sim") -> 1251 | R3: =SUMIFS(H2:H231,C2:C231,N3,K2:K231,"Sim")-Q3-Q5 -> 2911 | S3: 1 a 2 Pax | T3: 25 | U3: 8 | V3: 3 Malas | W3: Não | X3: 2 | Y3: Adriana
A4: 1 | B4: #309 Katelyn Cafaro | C4: Website | D4: 174496 | E4: 07h00 | F4: Hotel-Aero | G4: 2 | H4: 22 | I4: - | J4: Ricardo | K4: Sim | L4: Não | N4: CitySightSeeing | O4: =SUMIFS(H2:H231,C2:C231,N4,L2:L231,"Não") -> 36 | P4: =O4*0.25 -> 9 | Q4: =SUMIFS(I2:I230,C2:C230,N4,K2:K230,"Sim") -> 212.25 | R4: =O4-P4 -> 27 | S4: 3 a 4 Pax | T4: 35 | U4: 10 | V4: 4 Malas | X4: 3 | Y4: Thomas
A5: 1 | B5: 416 | C5: 7Roads | D5: 1547 | E5: 07h15 | F5: Hotel-Oriente Comboios | G5: 4 | H5: 35 | I5: 10 | J5: Ricardo | K5: Sim | L5: Sim | N5: 7Roads Driver | O5: =SUMIFS(H2:H231,C2:C231,N5,L2:L231,"Não") -> 25 | P5: =SUMIFS(I2:I231,C2:C231,N5,L2:L231,"Não") -> 8 | Q5: =SUMIFS(I2:I231,C2:C231,N5,K2:K231,"Sim") -> 8 | S5: 3 a 4 Pax | T5: 40 | U5: 12 | V5: 5/6 Malas | X5: 4 | Y5: Maycon
A6: 1 | B6: #401 Steve Korman | C6: 7Roads | D6: 2128 | E6: 09h00 | F6: Hotel-Oriente | G6: 2 | H6: 25 | I6: 8 | J6: Ricardo | K6: Sim | L6: Sim | N6: Website | O6: =SUMIFS(H2:H231,C2:C231,N6,L2:L231,"Não") -> 1148 | P6: =O6*0.15 -> 172.2 | S6: 5 a 8 Pax | T6: 55 | U6: 15 | V6: 12 Malas | X6: 5 | Y6: Helder
A7: 1 | B7: 509 | C7: 7Roads | D7: 1550 | E7: 15h00 | F7: Hotel-Aero | G7: 2 | H7: 25 | I7: 8 | J7: Erica | K7: Sim | L7: Sim | N7: Outra | O7: =SUMIFS(H2:H231,C2:C231,N7,L2:L231,"Não") -> 0 | P7: =SUMIFS(I2:I231,C2:C231,N7,L2:L231,"Não") -> 0 | S7: Aero - Hotel | T7: 35€ a 45€ | U7: 10 | V7: N/A | X7: 6 | Y7: Erica
A8: 1 | B8: Ana Rojas | C8: 7Roads | D8: 1508 | E8: 15h30 | F8: Aero-Hotel (BA6844) | G8: 2 | H8: 35 | I8: 10 | J8: Erica | K8: Sim | L8: Sim | N8: Total | O8: =SUM(O2:O3) -> 998 | P8: =SUM(P2:P3) -> 300.4 | R8: =SUM(R3+R4) -> 2938 | T8: 55 | U8: 15 | V8: N/A | X8: 7 | Y8: Nicole
A9: 1 | B9: 422 | C9: 7Roads | D9: 1538 | E9: 18h30 | F9: Hotel-Aero | G9: 1 | H9: 25 | I9: 8 | J9: Marcus | K9: Sim | L9: Sim | S9: WhereTo | T9: 0.3 | U9: CitySightSeeing | V9: 0.25 | X9: 8 | Y9: Francisco
A10: 2 | B10: 608 | C10: 7Roads | D10: 1545 | E10: 06h00 | F10: Hotel-Aero | G10: 2 | H10: 25 | I10: 8 | J10: Erica | K10: Sim | L10: Sim | N10: Contagem MAPA TOURS | Q10: Contagem CAIXA TURNO | X10: 9 | Y10: Diogo
A11: 2 | B11: 507 | C11: 7Roads | D11: 1551 | E11: 18h30 | F11: Hotel-Aero | G11: 2 | H11: 25 | I11: 8 | J11: Ricardo | K11: Sim | L11: Sim | N11: Notas | Q11: Notas | T11: Facturas | U11: Valor | X11: 10 | Y11: Erike
A12: 2 | B12: 416 | C12: 7Roads | D12: 1548 | E12: 19h45 | F12: Oriente Comboios-Hotel | G12: 4 | H12: 35 | I12: 10 | J12: Ricardo | K12: Sim | L12: Sim | N12: FundoManeio 14.10 | O12: 0 | P12: 220.06 | Q12: 500 | R12: 0 | S12: =Q12*R12 -> 0 | T12: Papelaria | U12: 7.99 | X12: 11 | Y12: Alexandre
A13: 3 | B13: 601 | C13: 7Roads | D13: 1552 | E13: 05h30 | F13: Hotel-Aero | G13: 2 | H13: 25 | I13: 8 | J13: Denise | K13: Sim | L13: Sim | N13: 200 | O13: 0 | P13: =N13*O13 -> 0 | Q13: 200 | R13: 0 | S13: =Q13*R13 -> 0 | T13: TIPS | U13: 0.03 | Y13: Arselia
A14: 3 | B14: 208 | C14: 7Roads | D14: 1542 | E14: 14h30 | F14: Hotel-Aero | G14: 2 | H14: 25 | I14: 8 | J14: Nicole | K14: Sim | L14: Sim | N14: 100 | O14: 11 | P14: =N14*O14 -> 1100 | Q14: 100 | R14: 0 | S14: =Q14*R14 -> 0 | X14: 12 | Y14: Marcus
A15: 3 | B15: 329 | C15: 7Roads | D15: 1553 | E15: 15h00 | F15: Hotel-Aero | G15: 2 | H15: 25 | I15: 8 | J15: Nicole | K15: Sim | L15: Sim | N15: 50 | O15: 31 | P15: =N15*O15 -> 1550 | Q15: 50 | R15: 0 | S15: =Q15*R15 -> 0 | X15: 13
A16: 4 | B16: 501 | C16: CitySightSeeing | D16: 167038 | E16: - | F16: Essencial Pack | G16: 2 | H16: 72 | I16: 18 | J16: Nicole | K16: Sim | L16: Sim | N16: 20 | O16: 0 | P16: =N16*O16 -> 0 | Q16: 20 | R16: 1 | S16: =Q16*R16 -> 20 | X16: 14
A17: 4 | B17: 416/428 - Tomera | C17: 7Roads | D17: 1555 | E17: 08h00 | F17: Hotel-Aero | G17: 4 | H17: 40 | I17: 12 | J17: Erike | K17: Sim | L17: Sim | N17: 10 | O17: 1 | P17: =N17*O17 -> 10 | Q17: 10 | R17: 3 | S17: =Q17*R17 -> 30 | X17: 15
A18: 4 | B18: Connie Kleier Mcglynn | C18: Website | D18: 163126 | E18: 08h34 | F18: Aero-Hotel (Delta 272) | G18: 2 | H18: 39 | I18: - | J18: Beatriz | K18: Sim | L18: Não | N18: 5 | O18: 0 | P18: =N18*O18 -> 0 | Q18: 5 | R18: 3 | S18: =Q18*R18 -> 15 | X18: 16
A19: 4 | B19: Yohanna Sullivan | C19: Website | D19: 174103 | E19: 13h35 | F19: Aero-Hotel (UA8938) | G19: 2 | H19: 39 | I19: - | J19: Erike | K19: Sim | L19: Não | P19: =SUM(P12:P18) -> 2880.06 | S19: =SUM(S12:S18) -> 65 | X19: 17
A20: 4 | B20: Pieter Bjil | C20: Website | D20: 174077 | E20: 15h50 | F20: Hotel-Aero | G20: 2 | H20: 22 | I20: - | J20: Helder | K20: Sim | L20: Não | N20: Moedas | Q20: Moedas | X20: 18
A21: 5 | B21: 402 | C21: 7Roads | D21: 1557 | E21: 03h00 | F21: Hotel-Aero | G21: 2 | H21: 25 | I21: 8 | J21: Francisco | K21: Sim | L21: Sim | N21: 2 | O21: 0 | P21: =N21*O21 -> 0 | Q21: 2 | R21: 2 | S21: =Q21*R21 -> 4 | X21: 19
A22: 5 | B22: 519 | C22: 7Roads | D22: 1556 | E22: 04h00 | F22: Hotel-Aero | G22: 2 | H22: 25 | I22: 8 | J22: Francisco | K22: Sim | L22: Sim | N22: 1 | O22: 4 | P22: =N22*O22 -> 4 | Q22: 1 | R22: 13 | S22: =Q22*R22 -> 13 | X22: 20
A23: 5 | B23: #326 - Donna Laura Barbey | C23: Website | D23: 168590 | E23: 04h30 | F23: Hotel-Aero | G23: 2 | H23: 22 | I23: - | J23: Vanessa | K23: Sim | L23: Não | N23: 0.5 | O23: 5 | P23: =N23*O23 -> 2.5 | Q23: 0.5 | R23: 32 | S23: =Q23*R23 -> 16 | X23: 21
A24: 5 | B24: #313 Thomas Atkins | C24: 7Roads | D24: 167221 | E24: 07h00 | F24: Hotel-Aero | G24: 5 | H24: 55 | I24: 15 | J24: Denise | K24: Sim | L24: Sim | N24: 0.2 | O24: 2 | P24: =N24*O24 -> 0.4 | Q24: 0.2 | R24: 4 | S24: =Q24*R24 -> 0.8 | X24: 22
A25: 5 | B25: Keith Simila | C25: Website | D25: 166087 | E25: 14h50 | F25: Aero-Hotel (AF1624) | G25: 2 | H25: 39 | I25: - | J25: Thomas | K25: Sim | L25: Não | N25: 0.1 | O25: 0 | P25: =N25*O25 -> 0 | Q25: 0.1 | R25: 0 | S25: =Q25*R25 -> 0 | T25: Total Facturas | U25: =SUM(U12:U24) -> 8.02 | X25: 23
A26: 5 | B26: Shannon Daly | C26: Website | D26: 166880 | E26: 14h50 | F26: Aero-Hotel (WS5149) | G26: 2 | H26: 39 | I26: - | J26: Mera | K26: Sim | L26: Não | N26: 0.05 | O26: 0 | P26: =N26*O26 -> 0 | Q26: 0.05 | R26: 3 | S26: =Q26*R26 -> 0.15 | T26: Fundo de Caixa | U26: 103.72 | X26: 24
A27: 5 | B27: Elisa Alvarez Torres | C27: Website | D27: 174668 | E27: 21h50 | F27: Aero-Hotel (V73594) | G27: 2 | H27: 39 | I27: - | J27: Erica | K27: Sim | L27: Não | N27: 0.02 | O27: 0 | P27: =N27*O27 -> 0 | Q27: 0.02 | R27: 0 | S27: =Q27*R27 -> 0 | T27: Diferença de Caixa | X27: 25
A28: 6 | B28: 324 | C28: 7Roads | D28: 1564 | E28: 03h30 | F28: Hotel-Aero | G28: 2 | H28: 25 | I28: 8 | J28: Francisco | K28: Sim | L28: Sim | N28: 0.01 | O28: 4 | P28: =N28*O28 -> 0.04 | Q28: 0.01 | R28: 0 | S28: =Q28*R28 -> 0 | T28: =S19+S29+U25-U26 -> 3.25 | X28: 26
A29: 6 | B29: 501 | C29: 7Roads | D29: 1563 | E29: 07h20 | F29: Hotel-Oriente | G29: 2 | H29: 25 | I29: 8 | J29: Maycon | K29: Sim | L29: Sim | P29: =SUM(P21:P28) -> 6.94 | S29: =SUM(S21:S28) -> 33.95 | X29: 27 | AB29: -
A30: 6 | B30: Mark Schmitz | C30: Website | D30: 171383 | E30: 08h20 | F30: Aero-Hotel (UA64) | G30: 2 | H30: 39 | I30: - | J30: Nicole | K30: Sim | L30: Não | N30: Total | P30: =SUM(P19+P29-R8) -> -51 | X30: 28
A31: 6 | B31: Marry Henny | C31: Where To | D31: 3258 | E31: 08h20 | F31: Tour Sintra/Cascais (Pack) | G31: 1 | H31: 70 | I31: 21 | J31: Erica | K31: Sim | L31: Sim | X31: 29
A32: 6 | B32: 205 | C32: Where To | D32: 3263 | E32: 08h20 | F32: Tour Sintra/Cascais | G32: 1 | H32: 69 | I32: 20.7 | J32: Helder | K32: Sim | L32: Sim | N32: Contagem TIPS | S32: Lançamentos TIPS | X32: 30
A33: 6 | B33: 227 | C33: 7Roads | D33: 1562 | E33: 08h30 | F33: Hotel-Oriente | G33: 2 | H33: 25 | I33: 8 | J33: Francisco | K33: Sim | L33: Sim | N33: Notas | Q33: Descrição | R33: Valor | S33: Dia | T33: Descrição | U33: Valor | V33: Por Quem | X33: 31
A34: 6 | B34: 505 | C34: 7Roads | D34: 1560 | E34: 10h30 | F34: Hotel-Sete Rios | G34: 2 | H34: 30 | I34: 10 | J34: Nicole | K34: Sim | L34: Sim | N34: 500 | O34: 0 | P34: =N34*O34 -> 0 | Q34: CAIXA | R34: 0.03 | T34: Where To | U34: =Q2-180.9 -> 227.7
A35: 6 | B35: Deborah Doherty | C35: Website | D35: 164960 | E35: 10h45 | F35: Aero-Hotel (DL124) | G35: 2 | H35: 39 | I35: - | J35: Vanessa | K35: Sim | L35: Não | N35: 200 | O35: 0 | P35: =N35*O35 -> 0 | T35: 7Roads | U35: =Q3-326 -> 925
A36: 7 | B36: Kevin Kirby | C36: Website | D36: 165426 | E36: 05h40 | F36: Aero-Hotel (TP218) | G36: 3 | H36: 39 | I36: - | J36: Ricardo | K36: Sim | L36: Não | N36: 100 | O36: 3 | P36: =N36*O36 -> 300 | T36: CitySightSeeing | U36: =Q4-72 -> 140.25
A37: 7 | B37: 529 | C37: 7Roads | D37: 1567 | E37: 08h30 | F37: Hotel-Aero | G37: 2 | H37: 25 | I37: 8 | J37: Ricardo | K37: Sim | L37: Sim | N37: 50 | O37: 10 | P37: =N37*O37 -> 500 | S37: 10 | T37: Sobras TIPS | U37: 73.01 | V37: Ricardo
A38: 7 | B38: 214 | C38: 7Roads | D38: 1568 | E38: 08h45 | F38: Hotel-Aero | G38: 2 | H38: 25 | I38: 8 | J38: Erica | K38: Sim | L38: Sim | N38: 20 | O38: 3 | P38: =N38*O38 -> 60 | S38: 10 | T38: TIP A SERIO | U38: 41.43 | V38: Nicole
A39: 7 | B39: Ana Rojas | C39: 7Roads | D39: 1509 | E39: 09h30 | F39: Hotel-Aero | G39: 2 | H39: 25 | I39: 8 | J39: Erica | K39: Sim | L39: Sim | N39: 10 | O39: 3 | P39: =N39*O39 -> 30 | S39: 11 | T39: Tuktuk Tejo | U39: 28.5 | V39: Francisco
A40: 7 | B40: John Stephens | C40: Website | D40: 174935 | E40: 12h45 | F40: Aero-Hotel (BA528) | G40: 2 | H40: 39 | I40: - | J40: Erike | K40: Sim | L40: Não | N40: 5 | O40: 10 | P40: =N40*O40 -> 50 | S40: 14 | T40: 7Roads Driver | U40: 8 | V40: Ricardo
A41: 7 | B41: 312 | C41: 7Roads | D41: 173850 | E41: 13h15 | F41: Hotel-Aero | G41: 2 | H41: 25 | I41: 8 | J41: Denise | K41: Sim | L41: Sim | P41: =SUM(P34:P40) -> 940 | S41: 14 | T41: Tips | U41: -51 | V41: Ricardo
A42: 7 | B42: #222 Aurea Julieta Nieva | C42: 7Roads | D42: 171902 | E42: 14h30 | F42: Aero-Hotel (TP861) | G42: 2 | H42: 35 | I42: 10 | J42: Diogo | K42: Sim | L42: Sim | N42: Moedas | S42: 16 | T42: Tips | U42: 7 | V42: Arselia
A43: 8 | B43: #408 Connie Kleier Mcglynn | C43: Website | D43: 163126 | E43: 04h30 | F43: Hotel-Aero | G43: 2 | H43: 22 | I43: - | J43: Beatriz | K43: Sim | L43: Não | N43: 2 | O43: 5 | P43: =N43*O43 -> 10 | S43: 16 | T43: Trovas Antigas | U43: 40 | V43: Francisco
A44: 8 | B44: 401 | C44: 7Roads | D44: 1569 | E44: 06h00 | F44: Hotel-Aero | G44: 2 | H44: 25 | I44: 8 | J44: Ricardo | K44: Sim | L44: Sim | N44: 1 | O44: 41 | P44: =N44*O44 -> 41 | S44: 17 | T44: Parreirinha | U44: 55 | V44: Nicole
A45: 8 | B45: Marry Henny | C45: Where To | D45: 3259 | E45: 08h20 | F45: Tour Fátima/Óbidos (Pack) | G45: 1 | H45: 70 | I45: 21 | J45: Erica | K45: Sim | L45: Sim | N45: 0.5 | O45: 3 | P45: =N45*O45 -> 1.5 | S45: 18 | T45: A MAIS | U45: 34.38 | V45: Erica
A46: 8 | B46: Bernard Leprohon | C46: Website | D46: 172377 | E46: 09h20 | F46: Aero-Hotel (AC812) | G46: 2 | H46: 39 | I46: - | J46: Ricardo | K46: Sim | L46: Não | N46: 0.2 | O46: 4 | P46: =N46*O46 -> 0.8 | Q46: Total | R46: =SUM(R34:R45) -> 0.03 | S46: 18 | T46: tip | U46: 10 | V46: Erica
A47: 8 | B47: 517 | C47: 7Roads | D47: 173907 | E47: 10h00 | F47: Hotel-Aero | G47: 1 | H47: 25 | I47: 8 | J47: Denise | K47: Sim | L47: Sim | N47: 0.1 | O47: 0 | P47: =N47*O47 -> 0 | S47: 21 | T47: DEVOLUÇÃO | U47: -10 | V47: Francisco
A48: 8 | B48: 515 | C48: 7Roads | D48: 1575 | E48: 11h00 | F48: Hotel - Aero | G48: 2 | H48: 25 | I48: 8 | J48: Diogo | K48: Sim | L48: Sim | N48: 0.05 | O48: 2 | P48: =N48*O48 -> 0.1 | Q48: Lançamentos | R48: =SUM(U34:U61) -> 415.33 | S48: 21 | T48: A mais | U48: 6.01 | V48: Erica
A49: 8 | B49: 307 | C49: Outra | D49: Tuktuk Tejo | E49: 12h30 | F49: Lisbon of Hills II | G49: 2 | H49: 212.5 | I49: 31.87 | J49: Nicole | K49: Sim | L49: Sim | N49: 0.02 | O49: 0 | P49: =N49*O49 -> 0 | Q49: Cash | R49: =P41+P51+R46 -> 993.44 | S49: 22 | T49: A menos | U49: -2 | V49: Francisco
A50: 8 | B50: 205 | C50: 7Roads | D50: 1578 | E50: 17h00 | F50: Hotel-Aero | G50: 2 | H50: 25 | I50: 8 | J50: Nicole | K50: Sim | L50: Sim | N50: 0.01 | O50: 1 | P50: =N50*O50 -> 0.01 | Q50: Diferença | R50: =R49-R48 -> 578.11 | S50: 23 | T50: tip | U50: 4 | V50: Nicole
A51: 9 | B51: #507 Carol DeMarco | C51: Website | D51: 165392 | E51: 07h00 | F51: Hotel-Aero | G51: 2 | H51: 22 | I51: - | J51: Ricardo | K51: Sim | L51: Não | P51: =SUM(P43:P50) -> 53.41 | Q51: Valor por pax | R51: =R49/8 -> 124.18 | S51: 24 | T51: Tips Dividas | U51: -1120 | V51: Maycon
A52: 9 | B52: #225/506 Wallbank | Abela | C52: Where To | D52: 174611 | E52: 08h20 | F52: Tour Sintra/Cascais | G52: 4 | H52: 256 | I52: 76.8 | J52: Denise | K52: Sim | L52: Sim | S52: 25 | T52: TIP A SERIO | U52: 9 | V52: Nicole
A53: 9 | B53: 324 | C53: 7Roads | D53: 1580 | E53: 10h30 | F53: Hotel-Aero | G53: 2 | H53: 35 | I53: 10 | J53: Erica | K53: Sim | L53: Sim | S53: 28 | T53: erro deposito 17/10 | U53: -10
A54: 9 | B54: 605 | C54: 7Roads | D54: 1572 | E54: 18h00 | F54: Hotel-Aero | G54: 2 | H54: 25 | I54: 8 | J54: Francisco | K54: Sim | L54: Sim | S54: 30 | T54: A MENOS | U54: -0.95 | V54: Nicole
A55: 9 | B55: 224 | C55: 7Roads | D55: 1579 | E55: 18h00 | F55: Hotel-Aero | G55: 1 | H55: 25 | I55: 8 | J55: Erica | K55: Sim | L55: Sim
A56: 10 | B56: 508 | C56: CitySightSeeing | D56: 174345 | E56: - | F56: Essencial Pack | G56: 1 | H56: 36 | I56: 9 | J56: Nicole | K56: Sim | L56: Sim
A57: 10 | B57: 212 | C57: CitySightSeeing | D57: 174310 | E57: - | F57: Essencial Pack | G57: 5 | H57: 180 | I57: 45 | J57: Ricardo | K57: Sim | L57: Sim
A58: 10 | B58: 317 | C58: 7Roads | D58: 1582 | E58: 04h30 | F58: Hotel-Aero | G58: 2 | H58: 25 | I58: 8 | J58: Diogo | K58: Sim | L58: Sim
A59: 10 | B59: Matthew Obreza | C59: Website | D59: 173571 | E59: 11h05 | F59: Aero-Hotel (AC810) | G59: 2 | H59: 39 | I59: - | J59: Ricardo | K59: Sim | L59: Não
A60: 10 | B60: Sue Wardropper | C60: 7Roads | D60: 2816 | E60: 18h00 | F60: Aero-Hotel (FR1882) | G60: 2 | H60: 35 | I60: 10 | J60: Nicole | K60: Sim | L60: Sim
A61: 10 | B61: #519 Elisa Alvarez Torres | C61: Website | D61: 174668 | E61: 19h45 | F61: Hotel-Aero | G61: 2 | H61: 22 | I61: - | J61: Ricardo | K61: Sim | L61: Não
A62: 10 | B62: Julie Ee | C62: 7Roads | D62: 2349 | E62: 21h30 | F62: Aero-Hotel (WS5149) | G62: 2 | H62: 35 | I62: 10 | J62: Beatriz | K62: Sim | L62: Sim | U62: =U38+U39+U41+U42+U47+U44+U48+U50+U53+U54 -> 69.99
A63: 10 | B63: Francesco Carofiglio | C63: 7Roads | D63: 1576 | E63: 22h55 | F63: Aero-Hotel (EJU7674) | G63: 2 | H63: 35 | I63: 10 | J63: Nicole | K63: Sim | L63: Sim
A64: 11 | B64: 607 / Leprohon Bernard | C64: 7Roads | D64: 172377 | E64: 08h:00 | F64: Hotel - Aeroporto Rent a car Portela | G64: 2 | H64: 25 | I64: 8 | J64: Erike | K64: Sim | L64: Sim
A65: 11 | B65: Artur 112 | C65: 7Roads | D65: 1587 | E65: 16h50 | F65: Hotel-Aero | G65: 1 | H65: 25 | I65: 8 | J65: Erike | K65: Sim | L65: Sim
A66: 11 | B66: 202/207 | C66: Outra | D66: Tuktuk Tejo | E66: 17h20 | F66: Lisbon of Hills I | G66: 4 | H66: 190 | I66: 28.5 | J66: Francisco | K66: Sim | L66: Sim
A67: 12 | B67: 319 | C67: 7Roads | D67: 1586 | E67: 08H00 | F67: Hotel - Aero | G67: 2 | H67: 25 | I67: 8 | J67: Nicole | K67: Sim | L67: Sim
A68: 12 | B68: David Hanks | C68: Where To | D68: 3266 | E68: 08h40 | F68: Tour Sintra/Cascais | G68: 1 | H68: 69 | I68: 20.7 | J68: Erike | K68: Sim | L68: Sim
A69: 12 | B69: #419 Matthew Obreza | C69: Website | D69: 173571 | E69: 12h00 | F69: Hotel-Aero | G69: 2 | H69: 22 | I69: - | J69: Ricardo | K69: Sim | L69: Não
A70: 12 | B70: 314/315 | C70: 7Roads | D70: 1583 | E70: 13h30 | F70: Hotel-Cruzeiros | G70: 6 | H70: 55 | I70: 15 | J70: Ricardo | K70: Sim | L70: Sim
A71: 13 | B71: 504 | C71: CitySightSeeing | D71: 173967 | E71: - | F71: Iconic Pack | G71: 2 | H71: 66 | I71: 16.5 | J71: Erica | K71: Sim | L71: Sim
A72: 13 | B72: 526 | C72: CitySightSeeing | D72: 174177 | E72: - | F72: Essencial Pack | G72: 2 | H72: 72 | I72: 18 | J72: Nicole | K72: Sim | L72: Sim
A73: 13 | B73: Sue Wardropper | C73: 7Roads | D73: 2817 | E73: 04h15 | F73: Hotel-Aero | G73: 2 | H73: 25 | I73: 8 | J73: Nicole | K73: Sim | L73: Sim
A74: 13 | B74: 407 / Stav Assi | C74: 7Roads | D74: 175270 | E74: 06h30 | F74: Hotel-Santa Apolonia | G74: 1 | H74: 25 | I74: 8 | J74: Erike | K74: Sim | L74: Sim
A75: 13 | B75: 416 | C75: 7Roads | D75: 1588 | E75: 08h00 | F75: Hotel-Aero | G75: 2 | H75: 25 | I75: 8 | J75: Erica | K75: Sim | L75: Sim
A76: 13 | B76: 607 / Bernard Leprohon | C76: Where To | D76: 172377 | E76: 08h20 | F76: Tour Sintra/Cascais | G76: 2 | H76: 138 | I76: 41.4 | J76: Erica | K76: Sim | L76: Sim
A77: 13 | B77: #107 Kate Gunn | C77: Website | D77: 172132 | E77: 11h00 | F77: Hotel-Aero | G77: 2 | H77: 22 | I77: - | J77: Ricardo | K77: Sim | L77: Não
A78: 13 | B78: Aj Alles | C78: Website | D78: 175318 | E78: 17h50 | F78: Aero-Hotel (BA502) | G78: 1 | H78: 39 | I78: - | J78: Erica | K78: Sim | L78: Não
A79: 13 | B79: Adelman | C79: 7Roads | D79: 171577 | E79: 17h55 | F79: Aero-Hotel (BA502) | G79: 2 | H79: 35 | I79: 10 | J79: Denise | K79: Sim | L79: Sim
A80: 14 | B80: 201 | C80: 7Roads | D80: 1591 | E80: 05h00 | F80: Hotel-Aero | G80: 2 | H80: 25 | I80: 8 | J80: Francisco | K80: Sim | L80: Sim
A81: 14 | B81: 112 | C81: 7Roads | D81: 1599 | E81: 05H20 | F81: Hotel - Aero | G81: 2 | H81: 25 | I81: 8 | J81: Erike | K81: Sim | L81: Sim
A82: 14 | B82: Alan Adelman | C82: Where To | D82: 3264 | E82: 08h20 | F82: Tour Sintra/Cascais | G82: 2 | H82: 138 | I82: 41.4 | J82: Helder | K82: Sim | L82: Não
A83: 14 | B83: 530 / Maria Lourdes | C83: Where To | D83: 3267 | E83: 08h20 | F83: Tour Sintra/Cascais | G83: 2 | H83: 138 | I83: 41.4 | J83: Erike | K83: Sim | L83: Sim
A84: 14 | B84: 416 | C84: 7Roads | D84: 1596 | E84: 09h00 | F84: Hotel - Aero | G84: 2 | H84: 25 | I84: 8 | J84: Francisco | K84: Sim | L84: Sim
A85: 14 | B85: Keenan Cluskey | C85: 7Roads | D85: - | E85: 11h30 | F85: Aero-Hotel (TO124) | G85: 2 | H85: 35 | I85: 10 | J85: Erica | K85: Sim | L85: Sim
A86: 14 | B86: Fernanda da Silva Bockstaller | C86: 7Roads | D86: 451 | E86: 12h40 | F86: Aero-Hotel (EJU7648) | G86: 8 | H86: 55 | I86: 15 | J86: Ricardo | K86: Sim | L86: Sim
A87: 14 | B87: Yen Vo | C87: Website | D87: 169822 | E87: 14h35 | F87: Aero-Hotel (KL1583) | G87: 1 | H87: 39 | I87: - | J87: Ricardo | K87: Sim | L87: Não
A88: 14 | B88: Mariana Perdomo Barros | C88: 7Roads | D88: 1590 | E88: 16h45 | F88: Aero-Hotel(TP1015 ) | G88: 2 | H88: 35 | I88: 10 | J88: Francisco | K88: Sim | L88: Sim
A89: 14 | B89: 509 | C89: 7Roads | D89: 1593 | E89: 18h00 | F89: Hotel-Aero | G89: 2 | H89: 25 | I89: 8 | J89: Erica | K89: Sim | L89: Sim
A90: 15 | B90: 608 | C90: 7Roads | D90: 2608 | E90: 04h30 | F90: Hotel-Aero | G90: 1 | H90: 25 | I90: 8 | J90: Erike | K90: Sim | L90: Sim
A91: 15 | B91: 518 | C91: 7Roads | D91: 2603 | E91: 05h00 | F91: Hotel-Aero | G91: 2 | H91: 25 | I91: 8 | J91: Francisco | K91: Sim | L91: Sim
A92: 15 | B92: 215 | C92: 7Roads | D92: 2604 | E92: 06H15 | F92: Hotel - Aero | G92: 2 | H92: 25 | I92: 8 | J92: Nicole | K92: Sim | L92: Sim
A93: 15 | B93: #607 Bernard Leprohon | C93: Website | D93: 172377 | E93: 07h30 | F93: Hotel-Aero | G93: 2 | H93: 22 | I93: - | J93: Ricardo | K93: Sim | L93: Não
A94: 15 | B94: 308 | C94: 7Roads Driver | D94: - | E94: 07h30 | F94: Hotel-Aero (PAGO AO DRIVER) | G94: 2 | H94: 25 | I94: 8 | J94: Erica | K94: Sim | L94: Não
A95: 15 | B95: 604 | C95: 7Roads | D95: 1600 | E95: 09h15 | F95: Hotel-Aero | G95: 2 | H95: 25 | I95: 8 | J95: Erica | K95: Sim | L95: Sim
A96: 15 | B96: 526 | C96: 7Roads | D96: 2605 | E96: 09h30 | F96: Hotel-Aero | G96: 2 | H96: 25 | I96: 8 | J96: Francisco | K96: Sim | L96: Sim
A97: 15 | B97: 507 | C97: 7Roads | D97: 2609 | E97: 09h30 | F97: Hotel-Aero | G97: 2 | H97: 25 | I97: 8 | J97: Francisco | K97: Sim | L97: Sim
A98: 15 | B98: Francesco Carofiglio | C98: 7Roads | D98: 1577 | E98: 11h30 | F98: Hotel-Aero | G98: 2 | H98: 25 | I98: 8 | J98: Nicole | K98: Sim | L98: Sim
A99: 15 | B99: 423 | C99: 7Roads | D99: 1598 | E99: 14h30 | F99: Hotel-Santa Apolónia | G99: 2 | H99: 25 | I99: 8 | J99: Francisco | K99: Sim | L99: Sim
A100: 15 | B100: Harris, Emma Jean | C100: 7Roads | D100: 2614 | E100: 17h30 | F100: Hotel-Aero | G100: 1 | H100: 25 | I100: 8 | J100: Erica | K100: Sim | L100: Sim | N100: Falha Carla, cliente pegou UBER, vai pagar comissao
...

Sheet Nov.25
A1: Dia | B1: Quarto | Nome | C1: Empresa | D1: Voucher | Res. | E1: Hora | F1: Direcções | Observações | G1: Nº Pax | H1: Valor | I1: Comissão | J1: Por Quem | K1: Pago Hósp? | L1: Pago | N1: Parceiros | O1: Valor Total | P1: Comissão | Q1: Tips | R1: Envelope | S1: Comissões 7Roads | W1: Pago | X1: Dia | Y1: Por Quem
A2: 1 | B2: 510 | C2: 7Roads | D2: 2581 | E2: 05h00 | F2: Hotel - Aero | G2: 2 | H2: 25 | I2: 8 | J2: Nicole | K2: Sim | L2: Não | N2: Where To | O2: =SUMIFS(H2:H199,C2:C199,N2,L2:L199,"Sim") -> 138 | P2: =O2*0.3 -> 41.4 | Q2: =SUMIFS(I2:I199,C2:C199,N2,K2:K199,"Sim") -> 124.2 | S2: Hotel - Aero | T2: Valor | U2: Comissão | V2: Nº Malas | W2: Sim | X2: 1 | Y2: André
A3: 1 | B3: 114 / 116 | C3: 7Roads | D3: 2583 | E3: 12h36 | F3: Aero - Hotel | G3: 4 | H3: 45 | I3: 12 | J3: Helder | K3: Sim | L3: Não | N3: 7Roads | O3: =SUMIFS(H2:H199,C2:C199,N3,L2:L199,"Não") -> 1335 | P3: =SUMIFS(I2:I199,C2:C199,N3,L2:L199,"Não") -> 388 | Q3: =SUMIFS(I2:I199,C2:C199,N3,K2:K199,"Sim") -> 310 | R3: =SUMIFS(H2:H199,C2:C199,N3,K2:K199,"Sim")-Q3 -> 745 | S3: 1 a 2 Pax | T3: 25 | U3: 8 | V3: 3 Malas | W3: Não | X3: 2 | Y3: Adriana
A4: 1 | B4: Carla Alpendre | C4: Where To | D4: 3261 | E4: 08H20 | F4: Sintra/Cascais | G4: 1 | H4: 69 | I4: 20.7 | J4: Nicole | K4: Sim | L4: Não | N4: CitySightSeeing | O4: =SUMIFS(H2:H199,C2:C199,N4,L2:L199,"Não") -> 204 | P4: =O4*0.25 -> 51 | Q4: =SUMIFS(I2:I198,C2:C198,N4,K2:K198,"Sim") -> 51 | R4: =O4-P4 -> 153 | S4: 3 a 4 Pax | T4: 35 | U4: 10 | V4: 4 Malas | W4: De: | X4: 3 | Y4: Helder
A5: 1 | B5: Dawn Carpenter | C5: Website | D5: 175137 | E5: 12h05 | F5: Aero-Hotel British Airways flight 505 | G5: 1 | H5: 39 | I5: - | J5: Ricardo | K5: Sim | L5: Não | N5: Website | O5: =SUMIFS(H2:H199,C2:C199,N5,L2:L199,"Não") -> 482 | P5: =O5*0.15 -> 72.3 | S5: 5 a 8 Pax | T5: 55 | U5: 15 | V5: 12 Malas | W5: Hotel | X5: 5 | Y5: Erica
A6: 2 | B6: 605 | C6: 7Roads | D6: 2582 | E6: 05h30 | F6: Hotel-Aero | G6: 2 | H6: 25 | I6: 8 | J6: Francisco | K6: Sim | L6: Não | N6: Outra | O6: =SUMIFS(H2:H199,C2:C199,N6,L2:L199,"Não") -> 170 | P6: =SUMIFS(I2:I199,C2:C199,N6,L2:L199,"Não") -> 25.5 | S6: Aero - Hotel | T6: 35€ a 45€ | U6: 10 | V6: N/A | W6: Tour | X6: 6 | Y6: Francisco
A7: 2 | B7: 502 | C7: 7Roads | D7: 2584 | E7: 09H00 | F7: Hotel - Aero | G7: 2 | H7: 25 | I7: 8 | J7: Helder | K7: Sim | L7: Não | N7: Total | O7: =SUM(O2:O3) -> 1473 | P7: =SUM(P2:P3) -> 429.4 | R7: =SUM(R3+R4) -> 898 | T7: 55 | U7: 15 | V7: N/A | W7: Para: | X7: 7 | Y7: Diogo
A8: 2 | B8: 312 | C8: 7Roads | D8: 2585 | E8: 07H00 | F8: Hotel - Aero | G8: 1 | H8: 25 | I8: 8 | J8: Erike | K8: Sim | L8: Não | W8: Aero | X8: 8 | Y8: Erike
A9: 2 | B9: 321 | C9: 7Roads | D9: 2586 | E9: 10H30 | F9: Hotel-Aero | G9: 4 | H9: 40 | I9: 12 | J9: Francisco | K9: Sim | L9: Não | N9: Contagem MAPA TOURS | Q9: Contagem CAIXA TURNO | W9: Hotel | X9: 9 | Y9: Thomas
A10: 2 | B10: 603/604 | C10: 7Roads | D10: 2587 | E10: 05h30 | F10: Hotel - Aero | G10: 4 | H10: 45 | I10: 12 | J10: Erike | K10: Sim | L10: Não | N10: Notas | Q10: Notas | T10: Facturas | U10: Valor | W10: Outro | X10: 10 | Y10: Arsélia
A11: 2 | B11: Rosalina Oo | C11: Website | D11: 172583 | E11: 07H00 | F11: Hotel-Aero | G11: 1 | H11: 22 | I11: - | J11: Vanessa | K11: Sim | L11: Não | N11: 500 | O11: 0 | P11: =N11*O11 -> 0 | Q11: 500 | R11: 0 | S11: =Q11*R11 -> 0 | T11: Fundo Maneio | U11: 18.77 | W11: Sintra/Cascais | X11: 11 | Y11: Maycon
A12: 2 | B12: Marissa Alonzo-Ejanda | C12: 7Roads | D12: 172591 | E12: 07H00 | F12: Hotel-Aero(Carla) | G12: 6 | H12: 55 | I12: 15 | J12: Helder | K12: Sim | L12: Não | N12: 200 | O12: 0 | P12: =N12*O12 -> 0 | Q12: 200 | R12: 0 | S12: =Q12*R12 -> 0 | T12: Silvia | U12: 14.95 | W12: Fátima/Óbidos | X12: 12
A13: 3 | B13: 324 | C13: 7Roads | D13: 2588 | E13: 05h30 | F13: Hotel- Aero | G13: 8 | H13: 55 | I13: 15 | J13: Arsélia | K13: Sim | L13: Não | N13: 100 | O13: 1 | P13: =N13*O13 -> 100 | Q13: 100 | R13: 0 | S13: =Q13*R13 -> 0 | X13: 13
A14: 3 | B14: 422 | C14: 7Roads | D14: 2589 | E14: 12h30 | F14: Hotel-aero | G14: 2 | H14: 35 | I14: 10 | J14: Arsélia | K14: Sim | L14: Não | N14: 50 | O14: 12 | P14: =N14*O14 -> 600 | Q14: 50 | R14: 0 | S14: =Q14*R14 -> 0 | X14: 14
A15: 3 | B15: 412 | C15: 7Roads | D15: 2590 | E15: 12h30 | F15: Hotel-Aero | G15: 1 | H15: 25 | I15: 8 | J15: Erica | K15: Sim | L15: Não | N15: 20 | O15: 9 | P15: =N15*O15 -> 180 | Q15: 20 | R15: 2 | S15: =Q15*R15 -> 40 | X15: 15
A16: 3 | B16: 604/605 | C16: 7Roads | D16: 2592 | E16: 13h30 | F16: Hotel-Aero | G16: 4 | H16: 40 | I16: 12 | J16: Helder | K16: Sim | L16: Não | N16: 10 | O16: 1 | P16: =N16*O16 -> 10 | Q16: 10 | R16: 1 | S16: =Q16*R16 -> 10 | X16: 13
A17: 3 | B17: 508 | C17: 7Roads | D17: 2594 | E17: 17h30 | F17: Hotel-Aero | G17: 2 | H17: 25 | I17: 8 | J17: Helder | K17: Sim | L17: Não | N17: 5 | O17: 1 | P17: =N17*O17 -> 5 | Q17: 5 | R17: 1 | S17: =Q17*R17 -> 5 | X17: 13
A18: 3 | B18: 406/Mariana Ferreira | C18: Where To | D18: 3271 | E18: 08h20 | F18: Sintra/Cascais | G18: 2 | H18: 138 | I18: 41.4 | J18: Francisco | K18: Sim | L18: Sim | P18: =SUM(P11:P17) -> 895 | S18: =SUM(S11:S17) -> 55 | X18: 18
A19: 3 | B19: Moncarz Avraham-Gezel | C19: Website | D19: 172062 | E19: 17h50 | F19: Aero-Hotel (LY375) | G19: 4 | H19: 50 | I19: _ | J19: Ricardo | K19: Sim | L19: Não | N19: Moedas | Q19: Moedas | X19: 19
A20: 3 | B20: - | C20: CitySightSeeing | D20: - | E20: - | F20: Pack Essencial | G20: 2 | H20: 72 | I20: 18 | J20: Helder | K20: Sim | L20: Não | N20: 2 | O20: 0 | P20: =N20*O20 -> 0 | Q20: 2 | R20: 1 | S20: =Q20*R20 -> 2 | X20: 20
A21: 3 | B21: - | C21: CitySightSeeing | D21: - | E21: - | F21: Pack iconic | G21: 2 | H21: 66 | I21: 16.5 | J21: Helder | K21: Sim | L21: Não | N21: 1 | O21: 2 | P21: =N21*O21 -> 2 | Q21: 1 | R21: 6 | S21: =Q21*R21 -> 6 | X21: 21
A22: 4 | B22: 401 | C22: 7Roads | D22: 2585 | E22: 06h00 | F22: Hotel-Aero | G22: 2 | H22: 25 | I22: 8 | J22: Helder | K22: Sim | L22: Não | N22: 0.5 | O22: 2 | P22: =N22*O22 -> 1 | Q22: 0.5 | R22: 13 | S22: =Q22*R22 -> 6.5 | X22: 22
A23: 4 | B23: 104 | C23: 7Roads | D23: 2597 | E23: 09h00 | F23: Hotel-Aero | G23: 2 | H23: 25 | I23: 8 | J23: Erike | K23: Sim | L23: Não | N23: 0.2 | O23: 0 | P23: =N23*O23 -> 0 | Q23: 0.2 | R23: 2 | S23: =Q23*R23 -> 0.4 | X23: 23
A24: 4 | B24: 601 | C24: 7Roads | D24: 2649 | E24: 08h00 | F24: Hotel-Aero | G24: 2 | H24: 25 | I24: 8 | J24: Arsélia | K24: Sim | L24: Não | N24: 0.1 | O24: 0 | P24: =N24*O24 -> 0 | Q24: 0.1 | R24: 0 | S24: =Q24*R24 -> 0 | T24: Total Facturas | U24: =SUM(U11:U23) -> 33.72 | X24: 24
A25: 4 | B25: 407 | C25: 7Roads | D25: 175802 | E25: 6H | F25: Hotel- Aero | G25: 2 | H25: 25 | I25: 8 | J25: Arsélia | K25: Sim | L25: Não | N25: 0.05 | O25: 0 | P25: =N25*O25 -> 0 | Q25: 0.05 | R25: 2 | S25: =Q25*R25 -> 0.1 | T25: Fundo de Caixa | U25: 103.72 | X25: 25
A26: 5 | B26: Marguife Layos | C26: 7Roads | D26: 2598 | E26: 15h00 | F26: Aero-Hotel (TP 1929) | G26: 1 | H26: 35 | I26: 10 | J26: André | K26: Sim | L26: Não | N26: 0.02 | O26: 0 | P26: =N26*O26 -> 0 | Q26: 0.02 | R26: 0 | S26: =Q26*R26 -> 0 | T26: Diferença de Caixa | X26: 26
A27: 5 | B27: 212 | C27: 7Roads | D27: 2599 | E27: 04h30 | F27: Hotel-Aero | G27: 1 | H27: 25 | I27: 8 | J27: Francisco | K27: Sim | L27: Não | N27: 0.01 | O27: 0 | P27: =N27*O27 -> 0 | Q27: 0.01 | R27: 0 | S27: =Q27*R27 -> 0 | T27: =S18+S28+U24-U25 -> 0 | X27: 27 | AB27: -
A28: 5 | B28: 212 | C28: 7Roads | D28: 2600 | E28: 07h30 | F28: Hotel-Aero | G28: 1 | H28: 25 | I28: 8 | J28: Francisco | K28: Sim | L28: Não | P28: =SUM(P20:P27) -> 3 | S28: =SUM(S20:S27) -> 15 | X28: 28
A29: 6 | B29: 414/415 | C29: 7Roads | D29: 2551 | E29: 11h20 | F29: Hotel-Aero | G29: 3 | H29: 35 | I29: 10 | J29: Erica | K29: Sim | L29: Não | N29: Total | P29: =SUM(P18+P28-R7) -> 0 | X29: 29
A30: 6 | B30: 101_102 | C30: 7Roads | D30: 2653 | E30: 14h45 | F30: Hotel-Aero | G30: 3 | H30: 35 | J30: Helder | K30: Sim | L30: Não | X30: 30
A31: 6 | B31: Ralf Zaich | C31: Website | D31: 168101 | E31: ? | F31: Hotel-Aero | G31: 2 | H31: 22 | I31: - | J31: Vanessa | K31: Sim | L31: Não | N31: Contagem TIPS | S31: Lançamentos TIPS | X31: 31
A32: 7 | B32: 218 | C32: 7Roads | D32: 2652 | E32: 07H45 | F32: Hotel-Aero | G32: 2 | H32: 25 | I32: 8 | J32: Helder | K32: Sim | L32: Não | N32: Notas | Q32: Descrição | R32: Valor | S32: Dia | T32: Descrição | U32: Valor | V32: Por Quem
A33: 7 | B33: 230 | C33: 7Roads | D33: 2654 | E33: 06H30 | F33: Hotel- Aero | G33: 2 | H33: 25 | I33: 8 | J33: Arsélia | K33: Sim | L33: Não | N33: 500 | O33: 0 | P33: =N33*O33 -> 0 | Q33: Ricardo | R33: 1.7 | T33: Where To | U33: =Q2 -> 124.2
A34: 7 | B34: 319 | C34: 7Roads | D34: 2655 | E34: 06H30 | F34: hotel-aero | G34: 1 | H34: 25 | I34: 8 | J34: Arsélia | K34: Sim | L34: Não | N34: 200 | O34: 0 | P34: =N34*O34 -> 0 | T34: 7Roads | U34: =Q3 -> 310
A35: 7 | B35: 216 | C35: 7Roads | D35: 2656 | E35: 06H30 | F35: hotel-aero | G35: 1 | H35: 25 | I35: 8 | J35: Francisco | K35: Sim | L35: Não | N35: 100 | O35: 0 | P35: =N35*O35 -> 0 | T35: CitySightSeeing | U35: =Q4 -> 51
A36: 7 | B36: Alfred Miller | C36: 7Roads | D36: 2888 | E36: 14H20 | F36: Aero-Hotel (TP861) | G36: 2 | H36: 35 | I36: 10 | J36: Ricardo | K36: Sim | L36: Não | N36: 50 | O36: 2 | P36: =N36*O36 -> 100 | T36: Sobras TIPS | U36: 237.6
A37: 7 | B37: 328 | C37: 7Roads | D37: 2657 | E37: 16h00 | F37: Hotel- Aero | G37: 1 | H37: 25 | I37: 8 | J37: Maycon | K37: Sim | L37: Não | N37: 20 | O37: 5 | P37: =N37*O37 -> 100 | S37: 1 | T37: tip | U37: 1 | V37: Francisco
A38: 8 | B38: Frederick Randolph | C38: 7Roads | D38: 171227 | E38: 07h00 | F38: Hotel - Aero | G38: 1 | H38: 25 | I38: 8 | J38: Diogo | K38: Sim | L38: Não | N38: 10 | O38: 11 | P38: =N38*O38 -> 110 | S38: 3 | T38: A mais | U38: 25 | V38: Erica
A39: 8 | B39: 110 | C39: 7Roads | D39: 2659 | E39: 12h00 | F39: Hotel-Aero | G39: 2 | H39: 25 | I39: 8 | J39: Helder | K39: Sim | L39: Não | N39: 5 | O39: 9 | P39: =N39*O39 -> 45 | S39: 5 | T39: A menos | U39: -10 | V39: Erica
A40: 8 | B40: 216 | C40: CitySightSeeing | D40: 173879 | E40: - | F40: Pack iconic | G40: 2 | H40: 66 | I40: 16.5 | J40: Helder | K40: Sim | L40: Não | P40: =SUM(P33:P39) -> 355 | S40: 6 | T40: City Tax | U40: -21 | V40: Helder
A41: 9 | B41: 514 | C41: Website | D41: 175812 | E41: 06H30 | F41: Hotel-Aero | G41: 1 | H41: 22 | I41: - | J41: Francisco | K41: Sim | L41: Não | N41: Moedas | S41: 7 | T41: rosas | U41: -360 | V41: Francisco
A42: 9 | B42: 404 | C42: 7Roads | D42: 2658 | E42: 07H30 | F42: Hotel - Aero | G42: 2 | H42: 25 | I42: 8 | J42: Erike | K42: Sim | L42: Não | N42: 2 | O42: 0 | P42: =N42*O42 -> 0
A43: 9 | B43: 216 | C43: 7Roads | D43: 2889 | E43: 08H30 | F43: Hotel-Aero | G43: 2 | H43: 25 | I43: 8 | J43: Ricardo | K43: Sim | L43: Não | N43: 1 | O43: 0 | P43: =N43*O43 -> 0
A44: 9 | B44: Haris Raonic | C44: 7Roads | D44: 2618 | E44: 15H10 | F44: Aero - Hotel (Os8151) | G44: 2 | H44: 35 | I44: 10 | J44: Nicole | K44: Não | L44: Não | N44: 0.5 | O44: 1 | P44: =N44*O44 -> 0.5
A45: 9 | B45: 402 | C45: 7Roads | D45: 2660 | E45: 16h30 | F45: Hotel-Aero | G45: 2 | H45: 25 | I45: 8 | J45: Helder | K45: Sim | L45: Não | N45: 0.2 | O45: 3 | P45: =N45*O45 -> 0.6 | Q45: Total | R45: =SUM(R33:R44) -> 1.7
A46: 9 | B46: 509 | C46: 7Roads | D46: 2661 | E46: 6h00 | F46: Hotel-Aero | G46: 2 | H46: 25 | I46: 8 | J46: Helder | K46: Sim | L46: Não | N46: 0.1 | O46: 0 | P46: =N46*O46 -> 0
A47: 9 | B47: 206 | C47: Where To | D47: 3272 | E47: 8h20 | F47: Sintra/Cascais | G47: 3 | H47: 207 | I47: 62.1 | J47: Helder | K47: Sim | L47: Não | N47: 0.05 | O47: 0 | P47: =N47*O47 -> 0 | Q47: Lançamentos | R47: =SUM(U33:U50) -> 357.8
A48: 10 | B48: Marguife Layos | C48: 7Roads | D48: 2598 | E48: 08h30 | F48: Hotel-Aero | G48: 1 | H48: 25 | I48: 8 | J48: André | K48: Sim | L48: Não | N48: 0.02 | O48: 0 | P48: =N48*O48 -> 0 | Q48: Cash | R48: =P40+P50+R45 -> 357.8
A49: 11 | B49: Marla Sparks | C49: Website | D49: 171758 | E49: 11h30 | F49: Aero (Rent-a-Car)-Hotel | G49: 4 | H49: 50 | I49: - | J49: Nicole | K49: Não | L49: Não | N49: 0.01 | O49: 0 | P49: =N49*O49 -> 0 | Q49: Diferença | R49: =R48-R47 -> 0
A50: 11 | B50: Peter Curtin | C50: Website | D50: 174294 | E50: 07h45 | F50: Aero-Hotel (TS680) | G50: 4 | H50: 50 | I50: - | J50: Erica | K50: Não | L50: Não | P50: =SUM(P42:P49) -> 1.1 | Q50: Valor por pax | R50: =R48/10 -> 35.78
A51: 13 | B51: Timothy Mooney | C51: Website | D51: 174071 | E51: ? | F51: Hotel-Aero | G51: 2 | H51: 22 | I51: - | J51: Nicole | K51: Não | L51: Não
A52: 14 | B52: Haris Raonic | C52: 7Roads | D52: 2619 | E52: ? | F52: Hotel - Aero | G52: 2 | H52: 25 | I52: 8 | J52: Nicole | K52: Não | L52: Não
A53: 15 | B53: Aki Toivonen | C53: Website | D53: 176045 | E53: 15h25 | F53: Aero-Hotel (AY1739) | G53: 2 | H53: 39 | I53: - | J53: Erica | K53: Não | L53: Não
A54: 18 | B54: Alicia Goncalves | C54: Website | D54: 168820 | E54: ? | F54: Hotel-Aero | G54: 2 | H54: 22 | I54: - | J54: Ricardo | K54: Não | L54: Não
A55: 19 | B55: Aki Toivonen | C55: Website | D55: 176045 | E55: ? | F55: Hotel-Aero | G55: 2 | H55: 22 | I55: - | J55: Erica | K55: Não | L55: Não
A56: 20 | B56: Group Vallaster Steuerberatung | C56: 7Roads | D56: 2574 | E56: 19H55 | F56: Aero - Hotel (TP933) | G56: 12 | H56: 110 | I56: 30 | J56: Helder | K56: Não | L56: Não
A57: 20 | B57: Tonya Scardina | C57: Website | D57: 173651 | E57: 09h05 | F57: Aero-Hotel (TP244) | G57: 2 | H57: 39 | I57: - | J57: Francisco | K57: Não | L57: Não
A58: 23 | B58: Group Vallaster Steuerberatung | C58: 7Roads | D58: 2575 | E58: ? | F58: Hotel-Aero | G58: 12 | H58: 110 | I58: 30 | J58: Helder | K58: Não | L58: Não
A59: 23 | B59: Sally Lopez | C59: Website | D59: 172158 | E59: ? | F59: Hotel-Aero | G59: 2 | H59: 22 | I59: - | J59: Ricardo | K59: Não | L59: Não
A60: 23 | B60: Tonya Scardina | C60: Website | D60: 173651 | E60: ? | F60: Hotel-Aero | G60: 2 | H60: 22 | I60: - | J60: Francisco | K60: Não | L60: Não
A61: 28 | B61: Liliane Bruggman | C61: Outra | D61: 170369 | E61: 09h3 | F61: Tuktuk Tejo (Lisbon by the River) | G61: 1 | H61: 170 | I61: 25.5 | J61: Helder | K61: Não | L61: Não
A62: 29 | B62: Aida Lucia Capote | C62: Website | D62: 176114 | E62: ? | F62: Aero-Hotel | G62: 2 | H62: 39 | I62: - | J62: Erica | K62: Sim | L62: Não

Sheet Dez.25
A1: Dia | B1: Quarto | Nome | C1: Empresa | D1: Voucher | Res. | E1: Hora | F1: Direcções | Observações | G1: Nº Pax | H1: Valor | I1: Comissão | J1: Por Quem | K1: Pago Hósp? | L1: Pago | N1: Parceiros | O1: Valor Total | P1: Comissão | Q1: Tips | R1: Envelope | S1: Comissões 7Roads | W1: Pago | X1: Dia | Y1: Por Quem
A2: 1 | B2: Stefano Frezza | C2: Website | D2: 172537 | E2: 14h30 | F2: Aero-Hotel (FR820) | G2: 2 | H2: 39 | I2: - | J2: Ricardo | K2: Não | L2: Não | N2: Where To | O2: =SUMIFS(H2:H200,C2:C200,N2,L2:L200,"Sim") -> 0 | P2: =O2*0.3 -> 0 | Q2: =SUMIFS(I2:I200,C2:C200,N2,K2:K200,"Sim") -> 0 | S2: Hotel - Aero | T2: Valor | U2: Comissão | V2: Nº Malas | W2: Sim | X2: 1 | Y2: Ricardo
A3: 2 | B3: Aviram Cohen | C3: 7Roads | D3: 2626 | E3: 17h50 | F3: Aero-Hotel (LY375) | G3: 1 | H3: 35 | I3: 10 | J3: Adriana | K3: Não | L3: Não | N3: 7Roads | O3: =SUMIFS(H2:H200,C2:C200,N3,L2:L200,"Não") -> 95 | P3: =SUMIFS(I2:I200,C2:C200,N3,L2:L200,"Não") -> 28 | Q3: =SUMIFS(I2:I200,C2:C200,N3,K2:K200,"Sim") -> 0 | R3: =SUMIFS(H2:H200,C2:C200,N3,K2:K200,"Sim")-Q3-Q5 -> 0 | S3: 1 a 2 Pax | T3: 25 | U3: 8 | V3: 3 Malas | W3: Não | X3: 2 | Y3: Adriana
A4: 5 | B4: Stefano Frezza | C4: Website | D4: 172537 | E4: 18h30 | F4: Hotel-Aero | G4: 2 | H4: 22 | I4: - | J4: Ricardo | K4: Não | L4: Não | N4: CitySightSeeing | O4: =SUMIFS(H2:H200,C2:C200,N4,L2:L200,"Não") -> 0 | P4: =O4*0.25 -> 0 | Q4: =SUMIFS(I2:I199,C2:C199,N4,K2:K199,"Sim") -> 0 | R4: =O4-P4 -> 0 | S4: 3 a 4 Pax | T4: 35 | U4: 10 | V4: 4 Malas | W4: De: | X4: 3 | Y4: Helder
A5: 7 | B5: Aviram Cohen | C5: 7Roads | D5: 2627 | E5: ? | F5: Hotel-Aero | G5: 1 | H5: 25 | I5: 8 | J5: Adriana | K5: Não | L5: Não | N5: 7Roads Driver | O5: =SUMIFS(H2:H200,C2:C200,N5,L2:L200,"Não") -> 0 | P5: =SUMIFS(I2:I200,C2:C200,N5,L2:L200,"Não") -> 0 | Q5: =SUMIFS(I2:I200,C2:C200,N5,K2:K200,"Sim") -> 0 | S5: 3 a 4 Pax | T5: 40 | U5: 12 | V5: 5/6 Malas | W5: Aero | X5: 4 | Y5: Erica
A6: 11 | B6: Benjamin Wade Davis | C6: Website | D6: 170607 | E6: 15h40 | F6: Aero-Hotel (EJU7394) | G6: 2 | H6: 39 | I6: - | J6: Nicole | K6: Não | L6: Não | N6: Website | O6: =SUMIFS(H2:H200,C2:C200,N6,L2:L200,"Não") -> 310 | P6: =O6*0.15 -> 46.5 | S6: 5 a 8 Pax | T6: 55 | U6: 15 | V6: 12 Malas | W6: Hotel | X6: 5 | Y6: Nicole
A7: 27 | B7: Lisa Nakamura | C7: 7Roads | D7: 423 | E7: 14h10 | F7: Aero-Hotel (TP238) | G7: 2 | H7: 35 | I7: 10 | J7: Helder | K7: Não | L7: Não | N7: Outra | O7: =SUMIFS(H2:H200,C2:C200,N7,L2:L200,"Não") -> 0 | P7: =SUMIFS(I2:I200,C2:C200,N7,L2:L200,"Não") -> 0 | S7: Aero - Hotel | T7: 35€ a 45€ | U7: 10 | V7: N/A | W7: Tour | X7: 6 | Y7: Francisco
A8: 22 | B8: Corinne CAMIADE | C8: Website | D8: 174400 | E8: 15h40 | F8: Aero-Hotel (FR486) | G8: 2 | H8: 39 | I8: - | J8: Francisco | K8: Não | L8: Não | N8: Total | O8: =SUM(O2:O3) -> 95 | P8: =SUM(P2:P3) -> 28 | R8: =SUM(R3+R4)+Nov.25!R7 -> 898 | T8: 55 | U8: 15 | V8: N/A | W8: Para: | X8: 7 | Y8: Diogo
A9: 27 | B9: Corinne CAMIADE | C9: Website | D9: 174400 | E9: ? | F9: Hotel-Aero | G9: 2 | H9: 22 | I9: - | J9: Francisco | K9: Não | L9: Não | W9: Aero | X9: 8 | Y9: Erike
A10: 3 | B10: Tim Savage | C10: Website | D10: 1573 | E10: 14h55 | F10: Aero - Hotel (BA0506) | G10: 6 | H10: 55 | I10: 15 | J10: Diogo | K10: Não | L10: Não | N10: Contagem MAPA TOURS | Q10: Contagem CAIXA TURNO | W10: Hotel | X10: 9 | Y10: Thomas
A11: 3 | B11: Tim Savage | C11: Website | D11: 1574 | E11: 14h55 | F11: Aero - Hotel (BA0506) | G11: 6 | H11: 55 | I11: 15 | J11: Diogo | K11: Não | L11: Não | N11: Notas | Q11: Notas | T11: Facturas | U11: Valor | W11: Outro | X11: 10 | Y11: Maycon
A12: 28 | B12: Sinuk Kang | C12: Website | D12: - | E12: ? | F12: Hotel-Aero | G12: 3 | H12: 39 | I12: - | J12: Erike | K12: Não | L12: Não | N12: 500 | O12: 0 | P12: =N12*O12 -> 0 | Q12: 500 | R12: 0 | S12: =Q12*R12 -> 0 | T12: Fundo Maneio | U12: 18.77 | W12: Sintra/Cascais | X12: 11
N13: 200 | O13: 1 | P13: =N13*O13 -> 200 | Q13: 200 | R13: 0 | S13: =Q13*R13 -> 0 | W13: Fátima/Óbidos | X13: 12
N14: 100 | O14: 8 | P14: =N14*O14 -> 800 | Q14: 100 | R14: 0 | S14: =Q14*R14 -> 0 | X14: 13
N15: 50 | O15: 31 | P15: =N15*O15 -> 1550 | Q15: 50 | R15: 0 | S15: =Q15*R15 -> 0 | X15: 14
N16: 20 | O16: 24 | P16: =N16*O16 -> 480 | Q16: 20 | R16: 0 | S16: =Q16*R16 -> 0 | X16: 15
N17: 10 | O17: 1 | P17: =N17*O17 -> 10 | Q17: 10 | R17: 7 | S17: =Q17*R17 -> 70 | X17: 16
N18: 5 | O18: 1 | P18: =N18*O18 -> 5 | Q18: 5 | R18: 1 | S18: =Q18*R18 -> 5 | X18: 17
P19: =SUM(P12:P18) -> 3045 | S19: =SUM(S12:S18) -> 75 | X19: 18
N20: Moedas | Q20: Moedas | X20: 19
N21: 2 | O21: 0 | P21: =N21*O21 -> 0 | Q21: 2 | R21: 1 | S21: =Q21*R21 -> 2 | X21: 20
N22: 1 | O22: 0 | P22: =N22*O22 -> 0 | Q22: 1 | R22: 2 | S22: =Q22*R22 -> 2 | X22: 21
N23: 0.5 | O23: 0 | P23: =N23*O23 -> 0 | Q23: 0.5 | R23: 3 | S23: =Q23*R23 -> 1.5 | X23: 22
N24: 0.2 | O24: 2 | P24: =N24*O24 -> 0.4 | Q24: 0.2 | R24: 8 | S24: =Q24*R24 -> 1.6 | X24: 23
N25: 0.1 | O25: 1 | P25: =N25*O25 -> 0.1 | Q25: 0.1 | R25: 17 | S25: =Q25*R25 -> 1.7 | T25: Total Facturas | U25: =SUM(U12:U24) -> 18.77 | X25: 24
N26: 0.05 | O26: 0 | P26: =N26*O26 -> 0 | Q26: 0.05 | R26: 17 | S26: =Q26*R26 -> 0.85 | T26: Fundo de Caixa | U26: 103.72 | X26: 25
N27: 0.02 | O27: 0 | P27: =N27*O27 -> 0 | Q27: 0.02 | R27: 5 | S27: =Q27*R27 -> 0.1 | T27: Diferença de Caixa | X27: 26
N28: 0.01 | O28: 0 | P28: =N28*O28 -> 0 | Q28: 0.01 | R28: 20 | S28: =Q28*R28 -> 0.2 | T28: =S19+S29+U25-U26 -> 0 | X28: 27 | AB28: -
P29: =SUM(P21:P28) -> 0.5 | S29: =SUM(S21:S28) -> 9.95 | X29: 28
N30: Total | P30: =SUM(P19+P29-R8) -> 2147.5 | X30: 29
X31: 30
N32: Contagem TIPS | S32: Lançamentos TIPS | X32: 31
N33: Notas | Q33: Descrição | R33: Valor | S33: Dia | T33: Descrição | U33: Valor | V33: Por Quem
N34: 500 | O34: 0 | P34: =N34*O34 -> 0 | Q34: Ricardo | R34: 1.7 | T34: Where To | U34: =Q2 -> 0
N35: 200 | O35: 0 | P35: =N35*O35 -> 0 | T35: 7Roads | U35: =Q3 -> 0
N36: 100 | O36: 4 | P36: =N36*O36 -> 400 | T36: CitySightSeeing | U36: =Q4 -> 0
N37: 50 | O37: 5 | P37: =N37*O37 -> 250 | S37: 12 | T37: Sobras TIPS | U37: 20.69 | V37: Ricardo
N38: 20 | O38: 12 | P38: =N38*O38 -> 240
N39: 10 | O39: 6 | P39: =N39*O39 -> 60
N40: 5 | O40: 0 | P40: =N40*O40 -> 0
P41: =SUM(P34:P40) -> 950
N42: Moedas
N43: 2 | O43: 0 | P43: =N43*O43 -> 0
N44: 1 | O44: 3 | P44: =N44*O44 -> 3
N45: 0.5 | O45: 0 | P45: =N45*O45 -> 0
N46: 0.2 | O46: 1 | P46: =N46*O46 -> 0.2 | Q46: Total | R46: =SUM(R34:R45) -> 1.7
N47: 0.1 | O47: 1 | P47: =N47*O47 -> 0.1
N48: 0.05 | O48: 1 | P48: =N48*O48 -> 0.05 | Q48: Lançamentos | R48: =SUM(U34:U51) -> 20.69
N49: 0.02 | O49: 0 | P49: =N49*O49 -> 0 | Q49: Cash | R49: =P41+P51+R46 -> 955.06
N50: 0.01 | O50: 1 | P50: =N50*O50 -> 0.01 | Q50: Diferença | R50: =R49-R48 -> 934.37
P51: =SUM(P43:P50) -> 3.36 | Q51: Valor por pax | R51: =R49/9 -> 106.11778

Sheet Jan.26
A1: Dia | B1: Quarto | Nome | C1: Empresa | D1: Voucher | Res. | E1: Hora | F1: Direcções | Observações | G1: Nº Pax | H1: Valor | I1: Comissão | J1: Por Quem | K1: Pago Hósp? | L1: Pago | N1: Parceiros | O1: Valor Total | P1: Comissão | Q1: Tips | R1: Envelope | S1: Comissões 7Roads | W1: Pago | X1: Dia | Y1: Por Quem
N2: Where To | O2: =SUMIFS(H2:H200,C2:C200,N2,L2:L200,"Sim") -> 0 | P2: =O2*0.3 -> 0 | Q2: =SUMIFS(I2:I200,C2:C200,N2,K2:K200,"Sim") -> 0 | S2: Hotel - Aero | T2: Valor | U2: Comissão | V2: Nº Malas | W2: Sim | X2: 1 | Y2: Ricardo
N3: 7Roads | O3: =SUMIFS(H2:H200,C2:C200,N3,L2:L200,"Não") -> 0 | P3: =SUMIFS(I2:I200,C2:C200,N3,L2:L200,"Não") -> 0 | Q3: =SUMIFS(I2:I200,C2:C200,N3,K2:K200,"Sim") -> 0 | R3: =SUMIFS(H2:H200,C2:C200,N3,K2:K200,"Sim")-Q3-Q5 -> 0 | S3: 1 a 2 Pax | T3: 25 | U3: 8 | V3: 3 Malas | W3: Não | X3: 2 | Y3: Adriana
N4: CitySightSeeing | O4: =SUMIFS(H2:H200,C2:C200,N4,L2:L200,"Não") -> 0 | P4: =O4*0.25 -> 0 | Q4: =SUMIFS(I2:I199,C2:C199,N4,K2:K199,"Sim") -> 0 | R4: =O4-P4 -> 0 | S4: 3 a 4 Pax | T4: 35 | U4: 10 | V4: 4 Malas | W4: De: | X4: 3 | Y4: Helder
N5: 7Roads Driver | O5: =SUMIFS(H2:H200,C2:C200,N5,L2:L200,"Não") -> 0 | P5: =SUMIFS(I2:I200,C2:C200,N5,L2:L200,"Não") -> 0 | Q5: =SUMIFS(I2:I200,C2:C200,N5,K2:K200,"Sim") -> 0 | S5: 3 a 4 Pax | T5: 40 | U5: 12 | V5: 5/6 Malas | W5: Aero | X5: 4 | Y5: Erica
N6: Website | O6: =SUMIFS(H2:H200,C2:C200,N6,L2:L200,"Não") -> 0 | P6: =O6*0.15 -> 0 | S6: 5 a 8 Pax | T6: 55 | U6: 15 | V6: 12 Malas | W6: Hotel | X6: 5 | Y6: Nicole
N7: Outra | O7: =SUMIFS(H2:H200,C2:C200,N7,L2:L200,"Não") -> 0 | P7: =SUMIFS(I2:I200,C2:C200,N7,L2:L200,"Não") -> 0 | S7: Aero - Hotel | T7: 35€ a 45€ | U7: 10 | V7: N/A | W7: Tour | X7: 6 | Y7: Francisco
N8: Total | O8: =SUM(O2:O3) -> 0 | P8: =SUM(P2:P3) -> 0 | R8: =SUM(R3+R4)+Nov.25!R7 -> 898 | T8: 55 | U8: 15 | V8: N/A | W8: Para: | X8: 7 | Y8: Diogo
W9: Aero | X9: 8 | Y9: Erike
N10: Contagem MAPA TOURS | Q10: Contagem CAIXA TURNO | W10: Hotel | X10: 9 | Y10: Thomas
N11: Notas | Q11: Notas | T11: Facturas | U11: Valor | W11: Outro | X11: 10 | Y11: Maycon
N12: 500 | O12: 0 | P12: =N12*O12 -> 0 | Q12: 500 | R12: 0 | S12: =Q12*R12 -> 0 | T12: Fundo Maneio | U12: 18.77 | W12: Sintra/Cascais | X12: 11
N13: 200 | O13: 1 | P13: =N13*O13 -> 200 | Q13: 200 | R13: 0 | S13: =Q13*R13 -> 0 | W13: Fátima/Óbidos | X13: 12
N14: 100 | O14: 8 | P14: =N14*O14 -> 800 | Q14: 100 | R14: 0 | S14: =Q14*R14 -> 0 | X14: 13
N15: 50 | O15: 31 | P15: =N15*O15 -> 1550 | Q15: 50 | R15: 0 | S15: =Q15*R15 -> 0 | X15: 14
N16: 20 | O16: 24 | P16: =N16*O16 -> 480 | Q16: 20 | R16: 0 | S16: =Q16*R16 -> 0 | X16: 15
N17: 10 | O17: 1 | P17: =N17*O17 -> 10 | Q17: 10 | R17: 7 | S17: =Q17*R17 -> 70 | X17: 16
N18: 5 | O18: 1 | P18: =N18*O18 -> 5 | Q18: 5 | R18: 1 | S18: =Q18*R18 -> 5 | X18: 17
P19: =SUM(P12:P18) -> 3045 | S19: =SUM(S12:S18) -> 75 | X19: 18
N20: Moedas | Q20: Moedas | X20: 19
N21: 2 | O21: 0 | P21: =N21*O21 -> 0 | Q21: 2 | R21: 1 | S21: =Q21*R21 -> 2 | X21: 20
N22: 1 | O22: 0 | P22: =N22*O22 -> 0 | Q22: 1 | R22: 2 | S22: =Q22*R22 -> 2 | X22: 21
N23: 0.5 | O23: 0 | P23: =N23*O23 -> 0 | Q23: 0.5 | R23: 3 | S23: =Q23*R23 -> 1.5 | X23: 22
N24: 0.2 | O24: 2 | P24: =N24*O24 -> 0.4 | Q24: 0.2 | R24: 8 | S24: =Q24*R24 -> 1.6 | X24: 23
N25: 0.1 | O25: 1 | P25: =N25*O25 -> 0.1 | Q25: 0.1 | R25: 17 | S25: =Q25*R25 -> 1.7 | T25: Total Facturas | U25: =SUM(U12:U24) -> 18.77 | X25: 24
N26: 0.05 | O26: 0 | P26: =N26*O26 -> 0 | Q26: 0.05 | R26: 17 | S26: =Q26*R26 -> 0.85 | T26: Fundo de Caixa | U26: 103.72 | X26: 25
N27: 0.02 | O27: 0 | P27: =N27*O27 -> 0 | Q27: 0.02 | R27: 5 | S27: =Q27*R27 -> 0.1 | T27: Diferença de Caixa | X27: 26
N28: 0.01 | O28: 0 | P28: =N28*O28 -> 0 | Q28: 0.01 | R28: 20 | S28: =Q28*R28 -> 0.2 | T28: =S19+S29+U25-U26 -> 0 | X28: 27 | AB28: -
P29: =SUM(P21:P28) -> 0.5 | S29: =SUM(S21:S28) -> 9.95 | X29: 28
N30: Total | P30: =SUM(P19+P29-R8) -> 2147.5 | X30: 29
X31: 30
N32: Contagem TIPS | S32: Lançamentos TIPS | X32: 31
N33: Notas | Q33: Descrição | R33: Valor | S33: Dia | T33: Descrição | U33: Valor | V33: Por Quem
N34: 500 | O34: 0 | P34: =N34*O34 -> 0 | Q34: Ricardo | R34: 1.7 | T34: Where To | U34: =Q2 -> 0
N35: 200 | O35: 0 | P35: =N35*O35 -> 0 | T35: 7Roads | U35: =Q3 -> 0
N36: 100 | O36: 4 | P36: =N36*O36 -> 400 | T36: CitySightSeeing | U36: =Q4 -> 0
N37: 50 | O37: 5 | P37: =N37*O37 -> 250 | S37: 12 | T37: Sobras TIPS | U37: 20.69 | V37: Ricardo
N38: 20 | O38: 12 | P38: =N38*O38 -> 240
N39: 10 | O39: 6 | P39: =N39*O39 -> 60
N40: 5 | O40: 0 | P40: =N40*O40 -> 0
P41: =SUM(P34:P40) -> 950
N42: Moedas
N43: 2 | O43: 0 | P43: =N43*O43 -> 0
N44: 1 | O44: 3 | P44: =N44*O44 -> 3
N45: 0.5 | O45: 0 | P45: =N45*O45 -> 0
N46: 0.2 | O46: 1 | P46: =N46*O46 -> 0.2 | Q46: Total | R46: =SUM(R34:R45) -> 1.7
N47: 0.1 | O47: 1 | P47: =N47*O47 -> 0.1
N48: 0.05 | O48: 1 | P48: =N48*O48 -> 0.05 | Q48: Lançamentos | R48: =SUM(U34:U51) -> 20.69
N49: 0.02 | O49: 0 | P49: =N49*O49 -> 0 | Q49: Cash | R49: =P41+P51+R46 -> 955.06
N50: 0.01 | O50: 1 | P50: =N50*O50 -> 0.01 | Q50: Diferença | R50: =R49-R48 -> 934.37
P51: =SUM(P43:P50) -> 3.36 | Q51: Valor por pax | R51: =R49/9 -> 106.11778

Sheet Fev. 26
A1: Dia | B1: Quarto | Nome | C1: Empresa | D1: Voucher | Res. | E1: Hora | F1: Direcções | Observações | G1: Nº Pax | H1: Valor | I1: Comissão | J1: Por Quem | K1: Pago Hósp? | L1: Pago | N1: Parceiros | O1: Valor Total | P1: Comissão | Q1: Tips | R1: Envelope | S1: Comissões 7Roads | W1: Pago | X1: Dia | Y1: Por Quem
N2: Where To | O2: =SUMIFS(H2:H200,C2:C200,N2,L2:L200,"Sim") -> 0 | P2: =O2*0.3 -> 0 | Q2: =SUMIFS(I2:I200,C2:C200,N2,K2:K200,"Sim") -> 0 | S2: Hotel - Aero | T2: Valor | U2: Comissão | V2: Nº Malas | W2: Sim | X2: 1 | Y2: Ricardo
N3: 7Roads | O3: =SUMIFS(H2:H200,C2:C200,N3,L2:L200,"Não") -> 0 | P3: =SUMIFS(I2:I200,C2:C200,N3,L2:L200,"Não") -> 0 | Q3: =SUMIFS(I2:I200,C2:C200,N3,K2:K200,"Sim") -> 0 | R3: =SUMIFS(H2:H200,C2:C200,N3,K2:K200,"Sim")-Q3-Q5 -> 0 | S3: 1 a 2 Pax | T3: 25 | U3: 8 | V3: 3 Malas | W3: Não | X3: 2 | Y3: Adriana
N4: CitySightSeeing | O4: =SUMIFS(H2:H200,C2:C200,N4,L2:L200,"Não") -> 0 | P4: =O4*0.25 -> 0 | Q4: =SUMIFS(I2:I199,C2:C199,N4,K2:K199,"Sim") -> 0 | R4: =O4-P4 -> 0 | S4: 3 a 4 Pax | T4: 35 | U4: 10 | V4: 4 Malas | W4: De: | X4: 3 | Y4: Helder
N5: 7Roads Driver | O5: =SUMIFS(H2:H200,C2:C200,N5,L2:L200,"Não") -> 0 | P5: =SUMIFS(I2:I200,C2:C200,N5,L2:L200,"Não") -> 0 | Q5: =SUMIFS(I2:I200,C2:C200,N5,K2:K200,"Sim") -> 0 | S5: 3 a 4 Pax | T5: 40 | U5: 12 | V5: 5/6 Malas | W5: Aero | X5: 4 | Y5: Erica
N6: Website | O6: =SUMIFS(H2:H200,C2:C200,N6,L2:L200,"Não") -> 0 | P6: =O6*0.15 -> 0 | S6: 5 a 8 Pax | T6: 55 | U6: 15 | V6: 12 Malas | W6: Hotel | X6: 5 | Y6: Nicole
N7: Outra | O7: =SUMIFS(H2:H200,C2:C200,N7,L2:L200,"Não") -> 0 | P7: =SUMIFS(I2:I200,C2:C200,N7,L2:L200,"Não") -> 0 | S7: Aero - Hotel | T7: 35€ a 45€ | U7: 10 | V7: N/A | W7: Tour | X7: 6 | Y7: Francisco
N8: Total | O8: =SUM(O2:O3) -> 0 | P8: =SUM(P2:P3) -> 0 | R8: =SUM(R3+R4)+Nov.25!R7 -> 898 | T8: 55 | U8: 15 | V8: N/A | W8: Para: | X8: 7 | Y8: Diogo
W9: Aero | X9: 8 | Y9: Erike
N10: Contagem MAPA TOURS | Q10: Contagem CAIXA TURNO | W10: Hotel | X10: 9 | Y10: Thomas
N11: Notas | Q11: Notas | T11: Facturas | U11: Valor | W11: Outro | X11: 10 | Y11: Maycon
N12: 500 | O12: 0 | P12: =N12*O12 -> 0 | Q12: 500 | R12: 0 | S12: =Q12*R12 -> 0 | T12: Fundo Maneio | U12: 18.77 | W12: Sintra/Cascais | X12: 11
N13: 200 | O13: 1 | P13: =N13*O13 -> 200 | Q13: 200 | R13: 0 | S13: =Q13*R13 -> 0 | W13: Fátima/Óbidos | X13: 12
N14: 100 | O14: 8 | P14: =N14*O14 -> 800 | Q14: 100 | R14: 0 | S14: =Q14*R14 -> 0 | X14: 13
N15: 50 | O15: 31 | P15: =N15*O15 -> 1550 | Q15: 50 | R15: 0 | S15: =Q15*R15 -> 0 | X15: 14
N16: 20 | O16: 24 | P16: =N16*O16 -> 480 | Q16: 20 | R16: 0 | S16: =Q16*R16 -> 0 | X16: 15
N17: 10 | O17: 1 | P17: =N17*O17 -> 10 | Q17: 10 | R17: 7 | S17: =Q17*R17 -> 70 | X17: 16
N18: 5 | O18: 1 | P18: =N18*O18 -> 5 | Q18: 5 | R18: 1 | S18: =Q18*R18 -> 5 | X18: 17
P19: =SUM(P12:P18) -> 3045 | S19: =SUM(S12:S18) -> 75 | X19: 18
N20: Moedas | Q20: Moedas | X20: 19
N21: 2 | O21: 0 | P21: =N21*O21 -> 0 | Q21: 2 | R21: 1 | S21: =Q21*R21 -> 2 | X21: 20
N22: 1 | O22: 0 | P22: =N22*O22 -> 0 | Q22: 1 | R22: 2 | S22: =Q22*R22 -> 2 | X22: 21
N23: 0.5 | O23: 0 | P23: =N23*O23 -> 0 | Q23: 0.5 | R23: 3 | S23: =Q23*R23 -> 1.5 | X23: 22
N24: 0.2 | O24: 2 | P24: =N24*O24 -> 0.4 | Q24: 0.2 | R24: 8 | S24: =Q24*R24 -> 1.6 | X24: 23
N25: 0.1 | O25: 1 | P25: =N25*O25 -> 0.1 | Q25: 0.1 | R25: 17 | S25: =Q25*R25 -> 1.7 | T25: Total Facturas | U25: =SUM(U12:U24) -> 18.77 | X25: 24
N26: 0.05 | O26: 0 | P26: =N26*O26 -> 0 | Q26: 0.05 | R26: 17 | S26: =Q26*R26 -> 0.85 | T26: Fundo de Caixa | U26: 103.72 | X26: 25
N27: 0.02 | O27: 0 | P27: =N27*O27 -> 0 | Q27: 0.02 | R27: 5 | S27: =Q27*R27 -> 0.1 | T27: Diferença de Caixa | X27: 26
N28: 0.01 | O28: 0 | P28: =N28*O28 -> 0 | Q28: 0.01 | R28: 20 | S28: =Q28*R28 -> 0.2 | T28: =S19+S29+U25-U26 -> 0 | X28: 27 | AB28: -
P29: =SUM(P21:P28) -> 0.5 | S29: =SUM(S21:S28) -> 9.95 | X29: 28
N30: Total | P30: =SUM(P19+P29-R8) -> 2147.5 | X30: 29
X31: 30
N32: Contagem TIPS | S32: Lançamentos TIPS | X32: 31
N33: Notas | Q33: Descrição | R33: Valor | S33: Dia | T33: Descrição | U33: Valor | V33: Por Quem
N34: 500 | O34: 0 | P34: =N34*O34 -> 0 | Q34: Ricardo | R34: 1.7 | T34: Where To | U34: =Q2 -> 0
N35: 200 | O35: 0 | P35: =N35*O35 -> 0 | T35: 7Roads | U35: =Q3 -> 0
N36: 100 | O36: 4 | P36: =N36*O36 -> 400 | T36: CitySightSeeing | U36: =Q4 -> 0
N37: 50 | O37: 5 | P37: =N37*O37 -> 250 | S37: 12 | T37: Sobras TIPS | U37: 20.69 | V37: Ricardo
N38: 20 | O38: 12 | P38: =N38*O38 -> 240
N39: 10 | O39: 6 | P39: =N39*O39 -> 60
N40: 5 | O40: 0 | P40: =N40*O40 -> 0
P41: =SUM(P34:P40) -> 950
N42: Moedas
N43: 2 | O43: 0 | P43: =N43*O43 -> 0
N44: 1 | O44: 3 | P44: =N44*O44 -> 3
N45: 0.5 | O45: 0 | P45: =N45*O45 -> 0
N46: 0.2 | O46: 1 | P46: =N46*O46 -> 0.2 | Q46: Total | R46: =SUM(R34:R45) -> 1.7
N47: 0.1 | O47: 1 | P47: =N47*O47 -> 0.1
N48: 0.05 | O48: 1 | P48: =N48*O48 -> 0.05 | Q48: Lançamentos | R48: =SUM(U34:U51) -> 20.69
N49: 0.02 | O49: 0 | P49: =N49*O49 -> 0 | Q49: Cash | R49: =P41+P51+R46 -> 955.06
N50: 0.01 | O50: 1 | P50: =N50*O50 -> 0.01 | Q50: Diferença | R50: =R49-R48 -> 934.37
P51: =SUM(P43:P50) -> 3.36 | Q51: Valor por pax | R51: =R49/9 -> 106.11778

Sheet Mar.26
A1: Dia | B1: Quarto | Nome | C1: Empresa | D1: Voucher | Res. | E1: Hora | F1: Direcções | Observações | G1: Nº Pax | H1: Valor | I1: Comissão | J1: Por Quem | K1: Pago Hósp? | L1: Pago | N1: Parceiros | O1: Valor Total | P1: Comissão | Q1: Tips | R1: Envelope | S1: Comissões 7Roads | W1: Pago | X1: Dia | Y1: Por Quem
A2: 26 | B2: Frances Cook | C2: Website | D2: 176209 | E2: 9h20 | F2: Aero-Hotel (AC810) | G2: 2 | H2: 39 | I2: - | J2: Erica | K2: Sim | L2: Não | N2: Where To | O2: =SUMIFS(H2:H200,C2:C200,N2,L2:L200,"Sim") -> 0 | P2: =O2*0.3 -> 0 | Q2: =SUMIFS(I2:I200,C2:C200,N2,K2:K200,"Sim") -> 0 | S2: Hotel - Aero | T2: Valor | U2: Comissão | V2: Nº Malas | W2: Sim | X2: 1 | Y2: Ricardo
N3: 7Roads | O3: =SUMIFS(H2:H200,C2:C200,N3,L2:L200,"Não") -> 0 | P3: =SUMIFS(I2:I200,C2:C200,N3,L2:L200,"Não") -> 0 | Q3: =SUMIFS(I2:I200,C2:C200,N3,K2:K200,"Sim") -> 0 | R3: =SUMIFS(H2:H200,C2:C200,N3,K2:K200,"Sim")-Q3-Q5 -> 0 | S3: 1 a 2 Pax | T3: 25 | U3: 8 | V3: 3 Malas | W3: Não | X3: 2 | Y3: Adriana
N4: CitySightSeeing | O4: =SUMIFS(H2:H200,C2:C200,N4,L2:L200,"Não") -> 0 | P4: =O4*0.25 -> 0 | Q4: =SUMIFS(I2:I199,C2:C199,N4,K2:K199,"Sim") -> 0 | R4: =O4-P4 -> 0 | S4: 3 a 4 Pax | T4: 35 | U4: 10 | V4: 4 Malas | W4: De: | X4: 3 | Y4: Helder
N5: 7Roads Driver | O5: =SUMIFS(H2:H200,C2:C200,N5,L2:L200,"Não") -> 0 | P5: =SUMIFS(I2:I200,C2:C200,N5,L2:L200,"Não") -> 0 | Q5: =SUMIFS(I2:I200,C2:C200,N5,K2:K200,"Sim") -> 0 | S5: 3 a 4 Pax | T5: 40 | U5: 12 | V5: 5/6 Malas | W5: Aero | X5: 4 | Y5: Erica
N6: Website | O6: =SUMIFS(H2:H200,C2:C200,N6,L2:L200,"Não") -> 39 | P6: =O6*0.15 -> 5.85 | S6: 5 a 8 Pax | T6: 55 | U6: 15 | V6: 12 Malas | W6: Hotel | X6: 5 | Y6: Nicole
N7: Outra | O7: =SUMIFS(H2:H200,C2:C200,N7,L2:L200,"Não") -> 0 | P7: =SUMIFS(I2:I200,C2:C200,N7,L2:L200,"Não") -> 0 | S7: Aero - Hotel | T7: 35€ a 45€ | U7: 10 | V7: N/A | W7: Tour | X7: 6 | Y7: Francisco
N8: Total | O8: =SUM(O2:O3) -> 0 | P8: =SUM(P2:P3) -> 0 | R8: =SUM(R3+R4)+Nov.25!R7 -> 898 | T8: 55 | U8: 15 | V8: N/A | W8: Para: | X8: 7 | Y8: Diogo
W9: Aero | X9: 8 | Y9: Erike
N10: Contagem MAPA TOURS | Q10: Contagem CAIXA TURNO | W10: Hotel | X10: 9 | Y10: Thomas
N11: Notas | Q11: Notas | T11: Facturas | U11: Valor | W11: Outro | X11: 10 | Y11: Maycon
N12: 500 | O12: 0 | P12: =N12*O12 -> 0 | Q12: 500 | R12: 0 | S12: =Q12*R12 -> 0 | T12: Fundo Maneio | U12: 18.77 | W12: Sintra/Cascais | X12: 11
N13: 200 | O13: 1 | P13: =N13*O13 -> 200 | Q13: 200 | R13: 0 | S13: =Q13*R13 -> 0 | W13: Fátima/Óbidos | X13: 12
N14: 100 | O14: 8 | P14: =N14*O14 -> 800 | Q14: 100 | R14: 0 | S14: =Q14*R14 -> 0 | X14: 13
N15: 50 | O15: 31 | P15: =N15*O15 -> 1550 | Q15: 50 | R15: 0 | S15: =Q15*R15 -> 0 | X15: 14
N16: 20 | O16: 24 | P16: =N16*O16 -> 480 | Q16: 20 | R16: 0 | S16: =Q16*R16 -> 0 | X16: 15
N17: 10 | O17: 1 | P17: =N17*O17 -> 10 | Q17: 10 | R17: 7 | S17: =Q17*R17 -> 70 | X17: 16
N18: 5 | O18: 1 | P18: =N18*O18 -> 5 | Q18: 5 | R18: 1 | S18: =Q18*R18 -> 5 | X18: 17
P19: =SUM(P12:P18) -> 3045 | S19: =SUM(S12:S18) -> 75 | X19: 18
N20: Moedas | Q20: Moedas | X20: 19
N21: 2 | O21: 0 | P21: =N21*O21 -> 0 | Q21: 2 | R21: 1 | S21: =Q21*R21 -> 2 | X21: 20
N22: 1 | O22: 0 | P22: =N22*O22 -> 0 | Q22: 1 | R22: 2 | S22: =Q22*R22 -> 2 | X22: 21
N23: 0.5 | O23: 0 | P23: =N23*O23 -> 0 | Q23: 0.5 | R23: 3 | S23: =Q23*R23 -> 1.5 | X23: 22
N24: 0.2 | O24: 2 | P24: =N24*O24 -> 0.4 | Q24: 0.2 | R24: 8 | S24: =Q24*R24 -> 1.6 | X24: 23
N25: 0.1 | O25: 1 | P25: =N25*O25 -> 0.1 | Q25: 0.1 | R25: 17 | S25: =Q25*R25 -> 1.7 | T25: Total Facturas | U25: =SUM(U12:U24) -> 18.77 | X25: 24
N26: 0.05 | O26: 0 | P26: =N26*O26 -> 0 | Q26: 0.05 | R26: 17 | S26: =Q26*R26 -> 0.85 | T26: Fundo de Caixa | U26: 103.72 | X26: 25
N27: 0.02 | O27: 0 | P27: =N27*O27 -> 0 | Q27: 0.02 | R27: 5 | S27: =Q27*R27 -> 0.1 | T27: Diferença de Caixa | X27: 26
N28: 0.01 | O28: 0 | P28: =N28*O28 -> 0 | Q28: 0.01 | R28: 20 | S28: =Q28*R28 -> 0.2 | T28: =S19+S29+U25-U26 -> 0 | X28: 27 | AB28: -
P29: =SUM(P21:P28) -> 0.5 | S29: =SUM(S21:S28) -> 9.95 | X29: 28
N30: Total | P30: =SUM(P19+P29-R8) -> 2147.5 | X30: 29
X31: 30
N32: Contagem TIPS | S32: Lançamentos TIPS | X32: 31
N33: Notas | Q33: Descrição | R33: Valor | S33: Dia | T33: Descrição | U33: Valor | V33: Por Quem
N34: 500 | O34: 0 | P34: =N34*O34 -> 0 | Q34: Ricardo | R34: 1.7 | T34: Where To | U34: =Q2 -> 0
N35: 200 | O35: 0 | P35: =N35*O35 -> 0 | T35: 7Roads | U35: =Q3 -> 0
N36: 100 | O36: 4 | P36: =N36*O36 -> 400 | T36: CitySightSeeing | U36: =Q4 -> 0
N37: 50 | O37: 5 | P37: =N37*O37 -> 250 | S37: 12 | T37: Sobras TIPS | U37: 20.69 | V37: Ricardo
N38: 20 | O38: 12 | P38: =N38*O38 -> 240
N39: 10 | O39: 6 | P39: =N39*O39 -> 60
N40: 5 | O40: 0 | P40: =N40*O40 -> 0
P41: =SUM(P34:P40) -> 950
N42: Moedas
N43: 2 | O43: 0 | P43: =N43*O43 -> 0
N44: 1 | O44: 3 | P44: =N44*O44 -> 3
N45: 0.5 | O45: 0 | P45: =N45*O45 -> 0
N46: 0.2 | O46: 1 | P46: =N46*O46 -> 0.2 | Q46: Total | R46: =SUM(R34:R45) -> 1.7
N47: 0.1 | O47: 1 | P47: =N47*O47 -> 0.1
N48: 0.05 | O48: 1 | P48: =N48*O48 -> 0.05 | Q48: Lançamentos | R48: =SUM(U34:U51) -> 20.69
N49: 0.02 | O49: 0 | P49: =N49*O49 -> 0 | Q49: Cash | R49: =P41+P51+R46 -> 955.06
N50: 0.01 | O50: 1 | P50: =N50*O50 -> 0.01 | Q50: Diferença | R50: =R49-R48 -> 934.37
P51: =SUM(P43:P50) -> 3.36 | Q51: Valor por pax | R51: =R49/9 -> 106.11778

Sheet Abr. 26
A1: Dia | B1: Quarto | Nome | C1: Empresa | D1: Voucher | Res. | E1: Hora | F1: Direcções | Observações | G1: Nº Pax | H1: Valor | I1: Comissão | J1: Por Quem | K1: Pago Hósp? | L1: Pago | N1: Parceiros | O1: Valor Total | P1: Comissão | Q1: Tips | R1: Envelope | S1: Comissões 7Roads | W1: Pago | X1: Dia | Y1: Por Quem
A2: 28 | B2: WELLS VANITA | C2: Website | D2: - | E2: - | F2: AERO-HOTEL | G2: 2 | H2: 39 | I2: - | J2: Thomas | K2: Não | L2: Não | N2: Where To | O2: =SUMIFS(H2:H200,C2:C200,N2,L2:L200,"Sim") -> 0 | P2: =O2*0.3 -> 0 | Q2: =SUMIFS(I2:I200,C2:C200,N2,K2:K200,"Sim") -> 0 | S2: Hotel - Aero | T2: Valor | U2: Comissão | V2: Nº Malas | W2: Sim | X2: 1 | Y2: Ricardo
N3: 7Roads | O3: =SUMIFS(H2:H200,C2:C200,N3,L2:L200,"Não") -> 0 | P3: =SUMIFS(I2:I200,C2:C200,N3,L2:L200,"Não") -> 0 | Q3: =SUMIFS(I2:I200,C2:C200,N3,K2:K200,"Sim") -> 0 | R3: =SUMIFS(H2:H200,C2:C200,N3,K2:K200,"Sim")-Q3-Q5 -> 0 | S3: 1 a 2 Pax | T3: 25 | U3: 8 | V3: 3 Malas | W3: Não | X3: 2 | Y3: Adriana
N4: CitySightSeeing | O4: =SUMIFS(H2:H200,C2:C200,N4,L2:L200,"Não") -> 0 | P4: =O4*0.25 -> 0 | Q4: =SUMIFS(I2:I199,C2:C199,N4,K2:K199,"Sim") -> 0 | R4: =O4-P4 -> 0 | S4: 3 a 4 Pax | T4: 35 | U4: 10 | V4: 4 Malas | W4: De: | X4: 3 | Y4: Helder
N5: 7Roads Driver | O5: =SUMIFS(H2:H200,C2:C200,N5,L2:L200,"Não") -> 0 | P5: =SUMIFS(I2:I200,C2:C200,N5,L2:L200,"Não") -> 0 | Q5: =SUMIFS(I2:I200,C2:C200,N5,K2:K200,"Sim") -> 0 | S5: 3 a 4 Pax | T5: 40 | U5: 12 | V5: 5/6 Malas | W5: Aero | X5: 4 | Y5: Erica
N6: Website | O6: =SUMIFS(H2:H200,C2:C200,N6,L2:L200,"Não") -> 39 | P6: =O6*0.15 -> 5.85 | S6: 5 a 8 Pax | T6: 55 | U6: 15 | V6: 12 Malas | W6: Hotel | X6: 5 | Y6: Nicole
N7: Outra | O7: =SUMIFS(H2:H200,C2:C200,N7,L2:L200,"Não") -> 0 | P7: =SUMIFS(I2:I200,C2:C200,N7,L2:L200,"Não") -> 0 | S7: Aero - Hotel | T7: 35€ a 45€ | U7: 10 | V7: N/A | W7: Tour | X7: 6 | Y7: Francisco
N8: Total | O8: =SUM(O2:O3) -> 0 | P8: =SUM(P2:P3) -> 0 | R8: =SUM(R3+R4)+Nov.25!R7 -> 898 | T8: 55 | U8: 15 | V8: N/A | W8: Para: | X8: 7 | Y8: Diogo
W9: Aero | X9: 8 | Y9: Erike
N10: Contagem MAPA TOURS | Q10: Contagem CAIXA TURNO | W10: Hotel | X10: 9 | Y10: Thomas
N11: Notas | Q11: Notas | T11: Facturas | U11: Valor | W11: Outro | X11: 10 | Y11: Maycon
N12: 500 | O12: 0 | P12: =N12*O12 -> 0 | Q12: 500 | R12: 0 | S12: =Q12*R12 -> 0 | T12: Fundo Maneio | U12: 18.77 | W12: Sintra/Cascais | X12: 11
N13: 200 | O13: 1 | P13: =N13*O13 -> 200 | Q13: 200 | R13: 0 | S13: =Q13*R13 -> 0 | W13: Fátima/Óbidos | X13: 12
N14: 100 | O14: 8 | P14: =N14*O14 -> 800 | Q14: 100 | R14: 0 | S14: =Q14*R14 -> 0 | X14: 13
N15: 50 | O15: 31 | P15: =N15*O15 -> 1550 | Q15: 50 | R15: 0 | S15: =Q15*R15 -> 0 | X15: 14
N16: 20 | O16: 24 | P16: =N16*O16 -> 480 | Q16: 20 | R16: 0 | S16: =Q16*R16 -> 0 | X16: 15
N17: 10 | O17: 1 | P17: =N17*O17 -> 10 | Q17: 10 | R17: 7 | S17: =Q17*R17 -> 70 | X17: 16
N18: 5 | O18: 1 | P18: =N18*O18 -> 5 | Q18: 5 | R18: 1 | S18: =Q18*R18 -> 5 | X18: 17
P19: =SUM(P12:P18) -> 3045 | S19: =SUM(S12:S18) -> 75 | X19: 18
N20: Moedas | Q20: Moedas | X20: 19
N21: 2 | O21: 0 | P21: =N21*O21 -> 0 | Q21: 2 | R21: 1 | S21: =Q21*R21 -> 2 | X21: 20
N22: 1 | O22: 0 | P22: =N22*O22 -> 0 | Q22: 1 | R22: 2 | S22: =Q22*R22 -> 2 | X22: 21
N23: 0.5 | O23: 0 | P23: =N23*O23 -> 0 | Q23: 0.5 | R23: 3 | S23: =Q23*R23 -> 1.5 | X23: 22
N24: 0.2 | O24: 2 | P24: =N24*O24 -> 0.4 | Q24: 0.2 | R24: 8 | S24: =Q24*R24 -> 1.6 | X24: 23
N25: 0.1 | O25: 1 | P25: =N25*O25 -> 0.1 | Q25: 0.1 | R25: 17 | S25: =Q25*R25 -> 1.7 | T25: Total Facturas | U25: =SUM(U12:U24) -> 18.77 | X25: 24
N26: 0.05 | O26: 0 | P26: =N26*O26 -> 0 | Q26: 0.05 | R26: 17 | S26: =Q26*R26 -> 0.85 | T26: Fundo de Caixa | U26: 103.72 | X26: 25
N27: 0.02 | O27: 0 | P27: =N27*O27 -> 0 | Q27: 0.02 | R27: 5 | S27: =Q27*R27 -> 0.1 | T27: Diferença de Caixa | X27: 26
N28: 0.01 | O28: 0 | P28: =N28*O28 -> 0 | Q28: 0.01 | R28: 20 | S28: =Q28*R28 -> 0.2 | T28: =S19+S29+U25-U26 -> 0 | X28: 27 | AB28: -
P29: =SUM(P21:P28) -> 0.5 | S29: =SUM(S21:S28) -> 9.95 | X29: 28
N30: Total | P30: =SUM(P19+P29-R8) -> 2147.5 | X30: 29
X31: 30
N32: Contagem TIPS | S32: Lançamentos TIPS | X32: 31
N33: Notas | Q33: Descrição | R33: Valor | S33: Dia | T33: Descrição | U33: Valor | V33: Por Quem
N34: 500 | O34: 0 | P34: =N34*O34 -> 0 | Q34: Ricardo | R34: 1.7 | T34: Where To | U34: =Q2 -> 0
N35: 200 | O35: 0 | P35: =N35*O35 -> 0 | T35: 7Roads | U35: =Q3 -> 0
N36: 100 | O36: 4 | P36: =N36*O36 -> 400 | T36: CitySightSeeing | U36: =Q4 -> 0
N37: 50 | O37: 5 | P37: =N37*O37 -> 250 | S37: 12 | T37: Sobras TIPS | U37: 20.69 | V37: Ricardo
N38: 20 | O38: 12 | P38: =N38*O38 -> 240
N39: 10 | O39: 6 | P39: =N39*O39 -> 60
N40: 5 | O40: 0 | P40: =N40*O40 -> 0
P41: =SUM(P34:P40) -> 950
N42: Moedas
N43: 2 | O43: 0 | P43: =N43*O43 -> 0
N44: 1 | O44: 3 | P44: =N44*O44 -> 3
N45: 0.5 | O45: 0 | P45: =N45*O45 -> 0
N46: 0.2 | O46: 1 | P46: =N46*O46 -> 0.2 | Q46: Total | R46: =SUM(R34:R45) -> 1.7
N47: 0.1 | O47: 1 | P47: =N47*O47 -> 0.1
N48: 0.05 | O48: 1 | P48: =N48*O48 -> 0.05 | Q48: Lançamentos | R48: =SUM(U34:U51) -> 20.69
N49: 0.02 | O49: 0 | P49: =N49*O49 -> 0 | Q49: Cash | R49: =P41+P51+R46 -> 955.06
N50: 0.01 | O50: 1 | P50: =N50*O50 -> 0.01 | Q50: Diferença | R50: =R49-R48 -> 934.37
P51: =SUM(P43:P50) -> 3.36 | Q51: Valor por pax | R51: =R49/9 -> 106.11778

Sheet Mai.26
A1: Dia | B1: Quarto | Nome | C1: Empresa | D1: Voucher | Res. | E1: Hora | F1: Direcções | Observações | G1: Nº Pax | H1: Valor | I1: Comissão | J1: Por Quem | K1: Pago Hósp? | L1: Pago | N1: Parceiros | O1: Valor Total | P1: Comissão | Q1: Tips | R1: Envelope | S1: Comissões 7Roads | W1: Pago | X1: Dia | Y1: Por Quem
A2: 18 | B2: Monique Stine | C2: Website | D2: 174135 | E2: 18H40 | F2: Aero - Hotel (DL9446) | G2: 2 | H2: 39 | I2: - | J2: Nicole | K2: Não | L2: Não | N2: Where To | O2: =SUMIFS(H2:H200,C2:C200,N2,L2:L200,"Sim") -> 0 | P2: =O2*0.3 -> 0 | Q2: =SUMIFS(I2:I200,C2:C200,N2,K2:K200,"Sim") -> 0 | S2: Hotel - Aero | T2: Valor | U2: Comissão | V2: Nº Malas | W2: Sim | X2: 1 | Y2: Ricardo
A3: 28 | B3: WELLS VANITA | C3: Website | D3: - | E3: - | F3: HOTEL-AERO | G3: 2 | H3: 22 | I3: - | J3: Thomas | K3: Não | L3: Não | N3: 7Roads | O3: =SUMIFS(H2:H200,C2:C200,N3,L2:L200,"Não") -> 0 | P3: =SUMIFS(I2:I200,C2:C200,N3,L2:L200,"Não") -> 0 | Q3: =SUMIFS(I2:I200,C2:C200,N3,K2:K200,"Sim") -> 0 | R3: =SUMIFS(H2:H200,C2:C200,N3,K2:K200,"Sim")-Q3-Q5 -> 0 | S3: 1 a 2 Pax | T3: 25 | U3: 8 | V3: 3 Malas | W3: Não | X3: 2 | Y3: Adriana
N4: CitySightSeeing | O4: =SUMIFS(H2:H200,C2:C200,N4,L2:L200,"Não") -> 0 | P4: =O4*0.25 -> 0 | Q4: =SUMIFS(I2:I199,C2:C199,N4,K2:K199,"Sim") -> 0 | R4: =O4-P4 -> 0 | S4: 3 a 4 Pax | T4: 35 | U4: 10 | V4: 4 Malas | W4: De: | X4: 3 | Y4: Helder
N5: 7Roads Driver | O5: =SUMIFS(H2:H200,C2:C200,N5,L2:L200,"Não") -> 0 | P5: =SUMIFS(I2:I200,C2:C200,N5,L2:L200,"Não") -> 0 | Q5: =SUMIFS(I2:I200,C2:C200,N5,K2:K200,"Sim") -> 0 | S5: 3 a 4 Pax | T5: 40 | U5: 12 | V5: 5/6 Malas | W5: Aero | X5: 4 | Y5: Erica
N6: Website | O6: =SUMIFS(H2:H200,C2:C200,N6,L2:L200,"Não") -> 61 | P6: =O6*0.15 -> 9.15 | S6: 5 a 8 Pax | T6: 55 | U6: 15 | V6: 12 Malas | W6: Hotel | X6: 5 | Y6: Nicole
N7: Outra | O7: =SUMIFS(H2:H200,C2:C200,N7,L2:L200,"Não") -> 0 | P7: =SUMIFS(I2:I200,C2:C200,N7,L2:L200,"Não") -> 0 | S7: Aero - Hotel | T7: 35€ a 45€ | U7: 10 | V7: N/A | W7: Tour | X7: 6 | Y7: Francisco
N8: Total | O8: =SUM(O2:O3) -> 0 | P8: =SUM(P2:P3) -> 0 | R8: =SUM(R3+R4)+Nov.25!R7 -> 898 | T8: 55 | U8: 15 | V8: N/A | W8: Para: | X8: 7 | Y8: Diogo
W9: Aero | X9: 8 | Y9: Erike
N10: Contagem MAPA TOURS | Q10: Contagem CAIXA TURNO | W10: Hotel | X10: 9 | Y10: Thomas
N11: Notas | Q11: Notas | T11: Facturas | U11: Valor | W11: Outro | X11: 10 | Y11: Maycon
N12: 500 | O12: 0 | P12: =N12*O12 -> 0 | Q12: 500 | R12: 0 | S12: =Q12*R12 -> 0 | T12: Fundo Maneio | U12: 18.77 | W12: Sintra/Cascais | X12: 11
N13: 200 | O13: 1 | P13: =N13*O13 -> 200 | Q13: 200 | R13: 0 | S13: =Q13*R13 -> 0 | W13: Fátima/Óbidos | X13: 12
N14: 100 | O14: 8 | P14: =N14*O14 -> 800 | Q14: 100 | R14: 0 | S14: =Q14*R14 -> 0 | X14: 13
N15: 50 | O15: 31 | P15: =N15*O15 -> 1550 | Q15: 50 | R15: 0 | S15: =Q15*R15 -> 0 | X15: 14
N16: 20 | O16: 24 | P16: =N16*O16 -> 480 | Q16: 20 | R16: 0 | S16: =Q16*R16 -> 0 | X16: 15
N17: 10 | O17: 1 | P17: =N17*O17 -> 10 | Q17: 10 | R17: 7 | S17: =Q17*R17 -> 70 | X17: 16
N18: 5 | O18: 1 | P18: =N18*O18 -> 5 | Q18: 5 | R18: 1 | S18: =Q18*R18 -> 5 | X18: 17
P19: =SUM(P12:P18) -> 3045 | S19: =SUM(S12:S18) -> 75 | X19: 18
N20: Moedas | Q20: Moedas | X20: 19
N21: 2 | O21: 0 | P21: =N21*O21 -> 0 | Q21: 2 | R21: 1 | S21: =Q21*R21 -> 2 | X21: 20
N22: 1 | O22: 0 | P22: =N22*O22 -> 0 | Q22: 1 | R22: 2 | S22: =Q22*R22 -> 2 | X22: 21
N23: 0.5 | O23: 0 | P23: =N23*O23 -> 0 | Q23: 0.5 | R23: 3 | S23: =Q23*R23 -> 1.5 | X23: 22
N24: 0.2 | O24: 2 | P24: =N24*O24 -> 0.4 | Q24: 0.2 | R24: 8 | S24: =Q24*R24 -> 1.6 | X24: 23
N25: 0.1 | O25: 1 | P25: =N25*O25 -> 0.1 | Q25: 0.1 | R25: 17 | S25: =Q25*R25 -> 1.7 | T25: Total Facturas | U25: =SUM(U12:U24) -> 18.77 | X25: 24
N26: 0.05 | O26: 0 | P26: =N26*O26 -> 0 | Q26: 0.05 | R26: 17 | S26: =Q26*R26 -> 0.85 | T26: Fundo de Caixa | U26: 103.72 | X26: 25
N27: 0.02 | O27: 0 | P27: =N27*O27 -> 0 | Q27: 0.02 | R27: 5 | S27: =Q27*R27 -> 0.1 | T27: Diferença de Caixa | X27: 26
N28: 0.01 | O28: 0 | P28: =N28*O28 -> 0 | Q28: 0.01 | R28: 20 | S28: =Q28*R28 -> 0.2 | T28: =S19+S29+U25-U26 -> 0 | X28: 27 | AB28: -
P29: =SUM(P21:P28) -> 0.5 | S29: =SUM(S21:S28) -> 9.95 | X29: 28
N30: Total | P30: =SUM(P19+P29-R8) -> 2147.5 | X30: 29
X31: 30
N32: Contagem TIPS | S32: Lançamentos TIPS | X32: 31
N33: Notas | Q33: Descrição | R33: Valor | S33: Dia | T33: Descrição | U33: Valor | V33: Por Quem
N34: 500 | O34: 0 | P34: =N34*O34 -> 0 | Q34: Ricardo | R34: 1.7 | T34: Where To | U34: =Q2 -> 0
N35: 200 | O35: 0 | P35: =N35*O35 -> 0 | T35: 7Roads | U35: =Q3 -> 0
N36: 100 | O36: 4 | P36: =N36*O36 -> 400 | T36: CitySightSeeing | U36: =Q4 -> 0
N37: 50 | O37: 5 | P37: =N37*O37 -> 250 | S37: 12 | T37: Sobras TIPS | U37: 20.69 | V37: Ricardo
N38: 20 | O38: 12 | P38: =N38*O38 -> 240
N39: 10 | O39: 6 | P39: =N39*O39 -> 60
N40: 5 | O40: 0 | P40: =N40*O40 -> 0
P41: =SUM(P34:P40) -> 950
N42: Moedas
N43: 2 | O43: 0 | P43: =N43*O43 -> 0
N44: 1 | O44: 3 | P44: =N44*O44 -> 3
N45: 0.5 | O45: 0 | P45: =N45*O45 -> 0
N46: 0.2 | O46: 1 | P46: =N46*O46 -> 0.2 | Q46: Total | R46: =SUM(R34:R45) -> 1.7
N47: 0.1 | O47: 1 | P47: =N47*O47 -> 0.1
N48: 0.05 | O48: 1 | P48: =N48*O48 -> 0.05 | Q48: Lançamentos | R48: =SUM(U34:U51) -> 20.69
N49: 0.02 | O49: 0 | P49: =N49*O49 -> 0 | Q49: Cash | R49: =P41+P51+R46 -> 955.06
N50: 0.01 | O50: 1 | P50: =N50*O50 -> 0.01 | Q50: Diferença | R50: =R49-R48 -> 934.37
P51: =SUM(P43:P50) -> 3.36 | Q51: Valor por pax | R51: =R49/9 -> 106.11778
