Workbook
Name FromArray_1: _xlfn.ANCHORARRAY(db!$B$2)

Sheet Restaurantesssssssssssssss
B2: 913699996 | H2: 218868209 | N2: 213428314 | T2: 961717778 | Z2: Restaurantes Olivier (Guilty, KOB, Yakuza, XXL)
B3: Trovas Antigas (5€) | H3: Parreirinha de Alfama (5€) | N3: A SEVERA (5€) | T3: Fado In Chiado (3€) | AF3: Hard Rock Café
B4: FADO | H4: FADO | N4: FADO | T4: FADO | Z4: Data | AA4: Hóspede | AB4: Quarto | AC4: Hora | AD4: Pax | AF4: FAST FOOD AMERICANA
B5: Data | C5: Hóspede | D5: Quarto | E5: Hora | F5: Pax | H5: Data | I5: Hóspede | J5: Quarto | K5: Hora | L5: Pax | N5: Data | O5: Hóspede | P5: Quarto | Q5: Hora | R5: Pax | T5: Data | U5: Hóspede | V5: Quarto | W5: Hora | X5: Pax | AF5: Data | AG5: Hóspede | AH5: Quarto | AI5: Hora | AJ5: Pax
B6: 45365 | C6: Marion Hebestreit | D6: 307 | E6: 19h00 | F6: 2 | H6: 45113 | I6: Liat Miller | K6: 20h00 | L6: 5
H7: 45156 | I7: Daniela Oliveira | K7: 20h30 | L7: 4
B23: Total: | E23: =+SUM(F6:F22)*5 -> 10 | H23: Total: | L23: =+SUM(L6:L22)*5 -> 45 | N23: Total: | Q23: =+SUM(R6:R22)*5 -> 0 | T23: Total: | W23: =+SUM(X6:X22)*3 -> 0 | Z23: Total: | AC23: =+SUM(AD6:AD21)*4 -> 0 | AF23: Total: | AI23: =+SUM(AJ7:AJ21)*4 -> 0
B25: Condições Trovas Antigas: | H25: Condições Parreirinha: | N25: Condições A Severa: | T25: Condições Fado In Chiado: | Z25: Condições Restaurantes Olivier: | AF25: Condições Hard Rock:
B26: Entregar Voucher aos hóspedes | H26: Pagamento em dinheiro | N26: Consumo mínimo de 45€ pax | T26: Entregas de comissão mensalmente- Ligar se não entregar até dia 05 | Z26: 4€ pax - Guilty (Pizzas, Pastas, Hamburgers, etc); KOB (Carnes Maturadas); Yakuza (Sushi) | AF26: 1€ pax até 20 pessoas | 2€ pax de 21 a 30 pessoas | 3€ pax de 31 a 60 pessoas | 4€ pax mais de 60 pessoas
B27: Pagamento efetuado no restaurante | H27: 55€ pax: menu + espetáculo - bebidas à parte | N27: Entregas de comissão mensalmente- Ligar se não entregar até dia 10
B28: 45€ pax: 1 prato principal + 1 sobremesa + 1 bebida + espetáculo | H28: Entrega comissões mensalmente (temos de marcar com regularidade) | Z28: 5€ pax - XXL (Comida típica Portuguesa)
H31: 213460088 | N31: 213421305 | T31: 210523906 | Z31: 911777388 | AF31: 213460501
B32: 213420572 | H32: Carmo Restaurant & Bar (2€) | N32: Mar ao Carmo (2€) | T32: Mar ao Largo (2€) | Z32: Lisboa em Fado (4€) | AF32: Café in Chiado (4€)
B33: Sacramento do Chiado (3€) | H33: TRADICIONAL PORTUGUESA | N33: MARISQUEIRA | T33: MARISQUEIRA + TRADICIONAL | Z33: FADO | AF33: Comida tipica portuguesa
B34: TRADICIONAL PORTUGUESA | H34: Data | I34: Hóspede | J34: Quarto | K34: Hora | L34: Pax | N34: Data | O34: Hóspede | P34: Quarto | Q34: Hora | R34: Pax | T34: Data | U34: Hóspede | V34: Quarto | W34: Hora | X34: Pax | Z34: Data | AA34: Hóspede | AB34: Quarto | AC34: Hora | AD34: Pax | AF34: Data | AG34: Hóspede | AH34: Quarto | AI34: Hora | AJ34: Pax
B35: Data | C35: Hóspede | D35: Quarto | E35: Hora | F35: Pax | T35: 45331 | U35: Enrique Carlos | W35: 12h00 | X35: 14 | Z35: 45356 | AA35: Tsvika Nir | AB35: 203 + 303 | AC35: 18h | AD35: 4
B36: 45353 | C36: STOJANOVIC | D36: 315 | E36: 21h | F36: 7
H52: Total: | L52: =+SUM(L35:L50)*2 -> 0 | N52: Total: | R52: =+SUM(R35:R50)*2 -> 0 | T52: Total: | X52: =+SUM(X35:X50)*2 -> 28 | Z52: Total: | AC52: =+SUM(AD35:AD50)*4 -> 16
B53: Total: | F53: =+SUM(F36:F51)*3 -> 21 | AF53: Total: | AI53: =+SUM(AJ35:AJ51)*4 -> 0
Z54: Condições Lisboa em Fado:
B55: Condições de pagamento Sacramento do Chiado; Mar ao Carmo; Carmo; Mar ao largo | Z55: Temos de ir lá todos os meses para recebermos as comissões | AF55: Condições Hard Rock:
B56: Enviar email no final do mês com todas reservas destes restaurantes para inesdamasceno@tablegroup.pt e marcar um dia para ela nos dar as comissões. | AF56: Mandar clientes com voucher
O58: 963342983
B59: Seisan | I59: Figus | O59: Monte Mar (5€)
B60: Japonês | I60: TRADICIONAL PORTUGUESA | O60: Marisqueira
B61: Data | C61: Hóspede | D61: Quarto | E61: Hora | F61: Pax | I61: Data | J61: Hóspede | K61: Quarto | L61: Hora | M61: Pax | O61: Data | P61: Hóspede | Q61: Quarto | R61: Hora | S61: Pax
B62: 45291 | C62: Olivier Marie | E62: 20h00 | F62: 2 | I62: 45291 | J62: Lars-anders Callenberg | L62: 19h00 | M62: 2
B79: Total: | I79: Total: | O79: Total:
O80: Condições Monte Mar:
O81: Entregam mensalmente, Por cada 40 pessoas oferecem um voucher para o hotel

Sheet Transfers Janeiro
B1: MSH ROSSIO - TRANSFERS JANEIRO 2023
C2: * Por favor conferir comissões de transfers pagos ao hotel e modificar cor para
B3: SUNDESTINY | F3: Rita & Pedro Lobo | G3: 962930401 | H3: 962522529 | M3: 7 Roads | Q3: Carla | R3: 939660691
B5: Data | C5: Horas | D5: Cliente | E5: Quarto | F5: Serviço | G5: Empresa | H5: Valor | I5: Comissão | J5: Nº pax | M5: Data | N5: Horas | O5: Cliente | P5: Quarto | Q5: Serviço | R5: Empresa | S5: Valor | T5: Comissão | U5: Nº pax
B6: 44562 | C6: 06h15 | D6: Edward Gaballa | F6: Aeroporto-Hotel | G6: SunDestiny | H6: 70 | I6: 6.25 | J6: 2 | K6: AR | M6: 44930 | N6: 14h35 | O6: Lisa Parks | Q6: Aeroporto-Hotel | R6: 7 Roads | S6: 39 | U6: 2
B7: 44562 | C7: 08h10 | D7: Alexandra Kelly | F7: Aeroporto-Hotel | G7: SunDestiny | H7: 70 | I7: 6.25 | J7: 2 | K7: CB | M7: 44935 | N7: 06h00 | O7: Mark Snoozy | Q7: Aeroporto-Hotel | R7: 7 Roads | S7: 39 | U7: 2
B8: 44562 | C8: 15h25 | D8: Debbie Fernandes | F8: Aeroporto-Hotel | G8: SunDestiny | H8: 140 | I8: 20 | J8: 8 | K8: AR | M8: 44941 | N8: 07h00 | O8: Erinn Meehan | Q8: Hotel-Aeroporto | R8: 7 Roads | S8: 22 | U8: 2
B9: 44928 | C9: 12h00 | D9: Muriel Quaderno | E9: 201 + 207 | F9: Hotel-Aeroporto | G9: SunDestiny | H9: 30 | I9: 7.5 | J9: 4 | K9: AR | M9: 44942 | N9: 11h40 | O9: Djenne Grant | Q9: Aeroporto-Hotel | R9: 7 Roads | S9: 39 | U9: 2
B10: 44928 | C10: 08h30 | D10: Debbie Fernandes | E10: 404 | F10: Hotel-Aeroporto | G10: SunDestiny | H10: 50 | I10: 10 | J10: 8 | K10: CB | M10: 44951 | N10: 22h20 | O10: Eric Lecat | Q10: Aeroporto-Hotel | R10: 7 Roads | S10: 39 | U10: 2
B11: 44928 | C11: 17h15 | D11: Samuel Anacito | F11: Aeroporto-Hotel | G11: SunDestiny | H11: 35 | I11: 5 | J11: 2 | K11: AR | M11: 44954 | N11: 15h00 | O11: Eric Lecat | Q11: Hotel-Aeroporto | R11: 7 Roads | S11: 22 | U11: 2
B12: 44564 | C12: 12h30 | D12: Taylor Wallace | F12: Aeroporto-Hotel | G12: SunDestiny | H12: 35 | I12: 5 | J12: 2 | K12: DO
B13: 44931 | C13: 19h50 | D13: Dominik Honegger | F13: Aeroporto-Hotel | G13: SunDestiny | H13: 35 | I13: 5 | J13: 2 | K13: AR
B14: 44932 | C14: 05h30 | D14: Rainer Fronlick | E14: 210 | F14: Hotel-Aeroporto | G14: SunDestiny | H14: 25 | I14: 7 | J14: 2 | K14: DO
B15: 44932 | C15: 06h20 | D15: Gebauer | E15: 204 + 216 | F15: Hotel-Aeroporto | G15: SunDestiny | H15: 30 | I15: 7.5 | J15: 3 | K15: AS
B16: 44934 | C16: 17h00 | D16: Dominik Honegger | E16: 401 | F16: Hotel-Aeroporto | G16: SunDestiny | H16: 25 | I16: 7 | J16: 2 | K16: AR
B17: 44571 | C17: 12h45 | D17: James Perone | F17: Aeroporto-Hotel | G17: SunDestiny | H17: 35 | I17: 5 | J17: 1 | K17: CB
B18: 44937 | C18: 15h20 | D18: Terje Nepper | F18: Aeroporto-Hotel | G18: SunDestiny | H18: 35 | I18: 5 | J18: 2 | K18: AG
B19: 44572 | C19: 15h35 | D19: Sarah Robertson | F19: Aeroporto-Hotel | G19: SunDestiny | H19: 35 | I19: 5 | J19: 1 | K19: AG
B20: 44937 | C20: 07h30 | D20: James Perone | E20: 308 | F20: Hotel-Aeroporto | G20: SunDestiny | H20: 25 | I20: 7 | J20: 1 | K20: SD
B21: 44937 | C21: 09h40 | D21: Shmuel Roizman | F21: Aeroporto-Hotel | G21: SunDestiny | H21: 35 | I21: 5 | J21: 2 | K21: AR
B22: 44938 | C22: 02h30 | D22: Marcia Machado | E22: 311 + 211 | F22: Hotel-Aeroporto | G22: SunDestiny | H22: 40 | I22: 10 | J22: 5 | K22: AS
B23: 44573 | C23: 05h15 | D23: Fanny Wong Lam | F23: Hotel-Aeroporto | G23: SunDestiny | H23: 30 | I23: 7.5 | J23: 3 | K23: AS
B24: 44938 | C24: 12h30 | D24: Nilson Filho | F24: Aeroporto-Hotel | G24: SunDestiny | H24: 35 | I24: 5 | J24: 2 | K24: FP
B25: 44574 | C25: 17h15 | D25: Stephanie Ripzaad | F25: Aeroporto-Hotel | G25: SunDestiny | H25: 35 | I25: 5 | J25: 2 | K25: AR
B26: 44939 | C26: 09h50 | D26: Michael Shepherd | F26: Aeroporto-Hotel | G26: SunDestiny | H26: 35 | I26: 5 | J26: 2 | K26: AR
B27: 44940 | C27: 08h30 | D27: Sarah Robertson | E27: 408 | F27: Hotel-Aeroporto | G27: SunDestiny | H27: 25 | I27: 7 | J27: 1 | K27: AS
B28: 44940 | C28: 13H55 | D28: Nepper, Terje | E28: 415 | F28: Hotel-Aeroporto | G28: SunDestiny | H28: 25 | I28: 7 | J28: 2 | K28: AS
B29: 44940 | C29: 11h30 | D29: Shmuel Roizman | E29: 204 | F29: Hotel-Aeroporto | G29: SunDestiny | H29: 25 | I29: 7 | J29: 2 | K29: CB
B30: 44941 | C30: 04h00 | D30: Jose Alcantara | E30: 201 | F30: Hotel-Aeroporto | G30: SunDestiny | H30: 25 | I30: 7 | J30: 1 | K30: DO
B31: 44941 | C31: 13H00 | D31: Nilson Filho | E31: 304 | F31: Hotel-Aeroporto | G31: SunDestiny | H31: 25 | I31: 7 | J31: 2 | K31: CB
B32: 44576 | C32: 23h10 | D32: Susan Knowler | F32: Aeroporto-Hotel | G32: SunDestiny | H32: 35 | I32: 5 | J32: 2 | K32: AR
B33: 44942 | C33: 05h30 | D33: Maria Gomez | E33: 315 | F33: Aeroporto-Hotel | G33: SunDestiny | H33: 35 | I33: 5 | J33: 2 | K33: AR
B34: 44943 | C34: 05h00 | D34: Maria Gomez | E34: 315 | F34: Hotel-Aeroporto | G34: SunDestiny | H34: 25 | I34: 7 | J34: 2 | K34: DO
B35: 44943 | C35: 07h15 | D35: Magaly Bouteraon | E35: 406 | F35: Hotel-Aeroporto | G35: SunDestiny | H35: 25 | I35: 7 | J35: 2 | K35: DO
B36: 44943 | C36: 09h20 | D36: Marcelo Yeh | F36: Aeroporto-Hotel | G36: SunDestiny | H36: 70 | I36: 15 | J36: 4 | K36: AR
B37: 44578 | C37: 12h40 | D37: Afreen Alam | F37: Aeroporto-Hotel | G37: SunDestiny | H37: 35 | I37: 5 | J37: 2 | K37: AS
B38: 44579 | C38: 07h00 | D38: Afreen Alam | F38: Hotel-Aeroporto | G38: SunDestiny | H38: 25 | I38: 7 | J38: 2 | K38: AS
B39: 44945 | C39: 13h10 | D39: Mrs Hinley | F39: Aeroporto-Hotel | G39: SunDestiny | H39: 35 | I39: 5 | J39: 2 | K39: AR
B40: 44946 | C40: 19h30 | D40: Jasmin klink | F40: Aeroporto-Hotel | G40: SunDestiny | H40: 35 | I40: 5 | J40: 2 | K40: AG
B41: 44948 | C41: 10H00 | D41: Jasmin klink | F41: Hotel-Aeroporto | G41: SunDestiny | H41: 25 | I41: 7 | J41: 2 | K41: CB
B42: 44948 | C42: 4h00 | D42: John Fenner | F42: Hotel-Aeroporto | G42: SunDestiny | H42: 25 | I42: 7 | J42: 2 | K42: AS
B43: 44948 | C43: 5h20 | D43: Marcelo Yeh | E43: 315 | F43: Hotel-Aeroporto | G43: SunDestiny | H43: 40 | I43: 10 | J43: 4 | K43: AS
B44: 44948 | C44: 14h10/25 | D44: Adriane Velasquez | F44: Aeroporto-Hotel | G44: SunDestiny | H44: 35 | I44: 5 | J44: 2 | K44: AG
B45: 44949 | C45: 7h30 | D45: Sonya Hinley | F45: Hotel-Aeroporto | G45: SunDestiny | H45: 25 | I45: 7 | J45: 2 | K45: AS
B46: 44949 | C46: 15h15 | D46: Pamela Runciman | F46: Aeroporto-Hotel | G46: SunDestiny | H46: 35 | I46: 5 | J46: 2 | K46: CB
B47: 44949 | C47: 17h50 | D47: Hen Levi | F47: Aeroporto-Hotel | G47: SunDestiny | H47: 35 | I47: 5 | J47: 2 | K47: DO
B48: 44951 | C48: 05h35 | D48: Kelly Handzo | F48: Aeroporto-Hotel | G48: SunDestiny | H48: 40 | I48: 5 | J48: 3 | K48: DO
B49: 44951 | C49: 08h00 | D49: Anne Rohaiem | F49: Aeroporto-Hotel | G49: SunDestiny | H49: 35 | I49: 5 | J49: 2 | K49: AS
B50: 44952 | C50: 04h30 | D50: Leigh Fedorouk | F50: Hotel-Aeroporto | G50: SunDestiny | H50: 25 | I50: 7 | J50: 2 | K50: DO
B51: 44952 | C51: 7h20 | D51: Grohn, Susan | E51: 307 | F51: Hotel-Aeroporto | G51: SunDestiny | H51: 25 | I51: 7 | J51: 2 | K51: AS
B52: 44953 | C52: 05h00 | D52: Gruvander | E52: 306 | F52: Hotel-Aeroporto | G52: SunDestiny | H52: 25 | I52: 7 | J52: 1 | K52: AG
B53: 44954 | C53: 5H45 | D53: Mario Runge | E53: 201 | F53: Hotel-Aeroporto | G53: SunDestiny | H53: 25 | I53: 7 | J53: 2 | K53: CB
B54: 44954 | C54: 23h10 | D54: Marlene Doloir | F54: Aeroporto-Hotel | G54: SunDestiny | H54: 35 | I54: 5 | J54: 2 | K54: DO
B55: 44954 | C55: 07h15 | D55: Susan Cook | E55: 212 | F55: Hotel-Aeroporto | G55: SunDestiny | H55: 26.5 | I55: 7 | J55: 2 | K55: AG
B56: 44955 | C56: 04h30 | D56: Leticia Morales | E56: 411 | F56: Hotel-Aeroporto | G56: SunDestiny | H56: 25 | I56: 7 | J56: 2 | K56: CB
B57: 44955 | C57: 07h30 | D57: Ricardo Marto | E57: 209 | F57: Hotel-Aeroporto | G57: SunDestiny | H57: 25 | I57: 7 | J57: 2 | K57: DO
B58: 44956 | C58: 15h30 | D58: Louise Elkær-Hansen | F58: Aeroporto-Hotel | G58: SunDestiny | H58: 35 | I58: 5 | J58: 2 | K58: AS
H60: =SUM(H6:H58) -> 1871.5 | I60: =SUM(I6:I58) -> 357
S61: =SUM(S57:S59) -> 0 | T61: =SUM(T57:T59) -> 0
B63: ÉPOCA FESTIVA ( 24 e 25 Dezembro ; 31 Dezembro e 1 Janeiro 2022)
B65: - Relembramos que está previsto nas tabelas de preços os serviços a efetuar nestas datas, terão um acréscimo de 50% do valor a cobrar ao cliente;
B67: (Sendo que as V/ vossas comissões serão também beneficiadas nestas datas em mais 25% sobre a comissão já estabelecida)
B69: Exemplos :
B71: Comissão de 5,00€ – passa para 6,25€
B73: Comissão de 7,00€ – passa para 8,75€

Sheet Transfers Fevereiro
B1: MSH ROSSIO - TRANSFERS FEVEREIRO 2023
C2: * Por favor conferir comissões de transfers pagos ao hotel e modificar cor para
B3: SUNDESTINY | F3: Rita & Pedro Lobo | G3: 962930401 | H3: 962522529 | M3: 7 Roads | Q3: Carla | R3: 939660691
B5: Data | C5: Horas | D5: Cliente | E5: Quarto | F5: Serviço | G5: Empresa | H5: Valor | I5: Comissão | J5: Nº pax | M5: Data | N5: Horas | O5: Cliente | P5: Quarto | Q5: Serviço | R5: Empresa | S5: Valor | T5: Comissao | U5: Nº pax
B6: 44960 | C6: 14h55 | D6: Kevin Cassidy | F6: Aeroporto-Hotel | G6: SunDestiny | H6: 35 | I6: 5 | J6: 2 | K6: FP | M6: 44959 | N6: 17h50 | O6: Gina Gentry | Q6: Aeroporto-Hotel | R6: 7 Roads | S6: 39 | U6: 2
B7: 44961 | C7: 15h10 | D7: Ingo Eppmann | F7: Aeroporto-Hotel | G7: SunDestiny | H7: 35 | I7: 5 | J7: 2 | K7: CB | M7: 44961 | N7: 10h30 | O7: Donna Perfine | Q7: Aeroporto-Hotel | R7: 7 Roads | S7: 39 | U7: 2
B8: 44961 | C8: 05h00 | D8: Elkær-hansen | E8: 207 | F8: Hotel-Aeroporto | G8: SunDestiny | H8: 25 | I8: 7 | J8: 2 | K8: DO | M8: 44981 | N8: 22h25 | O8: Virginie Sauquillo | Q8: Aeroporto-Hotel | R8: 7 Roads | S8: 39 | U8: 2
B9: 44962 | C9: 14h35 | D9: Steve Ross | F9: Aeroporto-Hotel | G9: SunDestiny | H9: 35 | I9: 5 | J9: 2 | K9: AR | M9: 44984 | N9: 02h30 | O9: James Roberts | Q9: Hotel-Aeroporto | R9: 7 Roads | S9: 22 | U9: 2
B10: 44963 | C10: 08h00 | D10: Heather Raposa | E10: 303 | F10: Hotel-Aeroporto | G10: SunDestiny | H10: 25 | I10: 7 | J10: 2 | K10: AR | M10: 44985 | N10: 18h45 | O10: Pascal Lefebvre | Q10: Aeroporto-Hotel | R10: 7 Roads | S10: 39 | U10: 2
B11: 44963 | C11: 09h40 | D11: Tzvi Bar Heim | F11: Aeroporto-Hotel | G11: SunDestiny | H11: 35 | I11: 5 | J11: 2 | K11: AR
B12: 44964 | C12: 14h35 | D12: Deborah Hemmeter | F12: Aeroporto-Hotel | G12: SunDestiny | H12: 35 | I12: 5 | J12: 2 | K12: AR
B13: 44964 | C13: 17h20 | D13: Marco Pergola | F13: Aeroporto-Hotel | G13: SunDestiny | H13: 35 | I13: 5 | J13: 2 | K13: AS
B14: 44965 | C14: 14h10 | D14: Isabella Valletta | F14: Aeroporto-Hotel | G14: SunDestiny | H14: 35 | I14: 5 | J14: 2 | K14: AR
B15: 44967 | C15: 07h30 | D15: Mary Burke | E15: 305+307 | F15: Hotel-Aeroporto | G15: SunDestiny | H15: 40 | I15: 10 | J15: 4 | K15: CB
B16: 44602 | C16: 14h10 | D16: Niccolò Narni | F16: Aeroporto-Hotel | G16: SunDestiny | H16: 35 | I16: 5 | J16: 2 | K16: Bárbara
B17: 44968 | C17: 08h45 | D17: Elisa Milani | F17: Aeroporto-Hotel | G17: SunDestiny | H17: 35 | I17: 5 | J17: 2 | K17: DO
B18: 44968 | C18: 12h35 | D18: Juan Cengotitabengoa | F18: Aeroporto-Hotel | G18: SunDestiny | H18: 35 | I18: 5 | J18: 2 | K18: AS
B19: 44968 | C19: 06h00 | D19: Philomena Mary Dooley | E19: 407 | F19: Hotel-Aeroporto | G19: SunDestiny | H19: 25 | I19: 7 | J19: 2 | K19: CB
B20: 44969 | C20: 11h20 | D20: Sophia Ciurleo | F20: Aeroporto-Hotel | G20: SunDestiny | H20: 35 | I20: 5 | J20: 2 | K20: FP
B21: 44970 | C21: 08h55 | D21: Pascale Charland | F21: Aeroporto-Hotel | G21: SunDestiny | H21: 35 | I21: 5 | J21: 1 | K21: AR
B22: 44972 | C22: 23h10 | D22: Keisuke Kuroda | F22: Aeroporto-Hotel | G22: SunDestiny | H22: 35 | I22: 5 | J22: 1 | K22: AG
B23: 44972 | C23: 15h10 | D23: Clayton Liston Halliday | F23: Aeroporto-Hotel | G23: SunDestiny | H23: 35 | I23: 5.001 | J23: 1 | K23: AR
B24: 44972 | C24: 07h00 | D24: Jill Praisner | F24: Hotel-Aeroporto | G24: SunDestiny | H24: 25 | I24: 7 | J24: 2 | K24: AR
B25: 44973 | C25: 06h30 | D25: Sevil Kutay | E25: 304 | F25: Hotel-Aeroporto | G25: SunDestiny | H25: 25 | I25: 7 | J25: 2 | K25: DO
B26: 44973 | C26: 06h30 | D26: Claire Haselint | E26: 402 | F26: Hotel-Aeroporto | G26: SunDestiny | H26: 25 | I26: 7 | J26: 2 | K26: DO
B27: 44973 | C27: 10h35 | D27: Hannah Press | F27: Aeroporto-Hotel | G27: SunDestiny | H27: 35 | I27: 5 | J27: 2 | K27: AS
B28: 44973 | C28: 12h55 | D28: Cornelia Ziegler | F28: Aeroporto-Hotel | G28: SunDestiny | H28: 35 | I28: 5 | J28: 2 | K28: AR
B29: 44973 | C29: 15h50 | D29: OLATI GIORGIO | F29: Aeroporto-Hotel | G29: SunDestiny | H29: 80 | I29: 15 | J29: 8 | K29: CB
B30: 44974 | C30: 02h00 | D30: William Hodges | E30: 303 | F30: Hotel-Aeroporto | G30: SunDestiny | H30: 25 | I30: 7 | J30: 3 | K30: CB
B31: 44974 | C31: 04h30 | D31: Keisuke Kuroda | E31: 310 | F31: Hotel-Aeroporto | G31: SunDestiny | H31: 25 | I31: 7 | J31: 1 | K31: AG
B32: 44974 | C32: 05h25 | D32: Bruce Stanforth | E32: 206 | F32: Aeroporto-Hotel | G32: SunDestiny | H32: 35 | I32: 5 | J32: 2 | K32: AR
B33: 44974 | C33: 06h15 | D33: Edward Smith | E33: 204 | F33: Hotel-Aeroporto | G33: SunDestiny | H33: 25 | I33: 7 | J33: 2 | K33: DO
B34: 44974 | C34: 12h00 | D34: John Spataro | E34: 204 | F34: Aeroporto-Hotel | G34: SunDestiny | H34: 35 | I34: 5 | J34: 2 | K34: FP
B35: 44974 | C35: 13h00 | D35: Lidia Santos | E35: 102 | F35: Hotel-Aeroporto | G35: SunDestiny | H35: 25 | I35: 7 | J35: 2 | K35: DO
B36: 44975 | C36: 08h15 | D36: Michael Chapiro | E36: 302 | F36: Hotel-Aeroporto | G36: SunDestiny | H36: 25 | I36: 7 | J36: 2 | K36: DO
B37: 44975 | C37: 16h50 | D37: Patricia Bernard | F37: Aeroporto-Hotel | G37: SunDestiny | H37: 35 | I37: 5 | J37: 3 | K37: AS
B38: 44976 | C38: 05h00 | D38: Aurelie Marie | E38: 311 | F38: Hotel-Aeroporto | G38: SunDestiny | H38: 25 | I38: 7 | J38: 2 | K38: AG
B39: 44976 | C39: 04h15 | D39: Beth Brennan | E39: 101 | F39: Hotel-Aeroporto | G39: SunDestiny | H39: 25 | I39: 7 | J39: 2 | K39: DO
B40: 44976 | C40: 11h50 | D40: Marco Meichtry | F40: Aeroporto-Hotel | G40: SunDestiny | H40: 35 | I40: 5 | J40: 2 | K40: DO
B41: 44977 | C41: 04h40 | D41: Karen | E41: 215 | F41: Hotel-Aeroporto | G41: SunDestiny | H41: 25 | I41: 7 | J41: 2 | K41: AS
B42: 44978 | C42: 16h35 | D42: Cecile de Launay | F42: Aeroporto-Hotel | G42: SunDestiny | H42: 35 | I42: 5 | J42: 2 | K42: AR
B43: 44978 | C43: 08h00 | D43: Samina Kashif | E43: 306 | F43: Hotel-Aeroporto | G43: SunDestiny | H43: 25 | I43: 7 | J43: 2 | K43: Ana
B44: 44978 | C44: 06h30 | D44: John Spataro | E44: 204 | F44: Hotel-Aeroporto | G44: SunDestiny | H44: 25 | I44: 7 | J44: 2 | K44: AG
B45: 44979 | C45: 08h00 | D45: João Paulo Ferreira | E45: 312 | F45: Hotel-Aeroporto | G45: SunDestiny | H45: 25 | I45: 7 | J45: 1 | K45: AR
B46: 44979 | C46: 17h50 | D46: Netta Shani | F46: Aeroporto-Hotel | G46: SunDestiny | H46: 35 | I46: 5 | J46: 2 | K46: FP
B47: 44981 | C47: 10h00 | D47: virginie giraud-moine | E47: 407 | F47: Hotel-Aeroporto | G47: SunDestiny | H47: 25 | I47: 7 | J47: 2 | K47: CB
B48: 44981 | C48: 16h40 | D48: Leyre Idirin | F48: Aeroporto-Hotel | G48: SunDestiny | H48: 35 | I48: 5 | J48: 2 | K48: AR
B49: 44981 | C49: 18h30 | D49: Pauline Cécile | E49: 203 | F49: Hotel-Aeroporto | G49: SunDestiny | H49: 25 | I49: 7 | J49: 2 | K49: RL
B50: 44982 | C50: 03h30 | D50: Mat | E50: 211 | F50: Hotel-Aeroporto | G50: SunDestiny | H50: 25 | I50: 7 | J50: 2 | K50: CB
B51: 44983 | C51: 09h45 | D51: Vicente | E51: 415 | F51: Hotel-Aeroporto | G51: SunDestiny | H51: 25 | I51: 7 | J51: 2 | K51: CB
B52: 57 | C52: 05h00 | D52: Heloisa Giamberardino | E52: 416 | F52: Hotel-Aeroporto | G52: SunDestiny | H52: 25 | I52: 7 | J52: 2 | K52: CB
B53: 44983 | C53: 09h40 | D53: Sally Simmonds | F53: Aeroporto-Hotel | G53: SunDestiny | H53: 35 | I53: 5 | J53: 2 | K53: AR
B54: 44983 | C54: 15h15 | D54: Fernando Affonso | E54: 311 | F54: Hotel-Aeroporto | G54: SunDestiny | H54: 25 | I54: 7 | J54: 2 | K54: AG
B55: 44984 | C55: 20h10 | D55: Matthew Anello | F55: Aeroporto-Hotel | G55: SunDestiny | H55: 35 | I55: 5 | J55: 2 | K55: CB
B56: 44985 | C56: 03h00 | D56: Clayton Liston | E56: 202 | F56: Hotel-Aeroporto | G56: SunDestiny | H56: 25 | I56: 7 | J56: 1 | K56: CB
B57: 44985 | C57: 06h00 | D57: Thomas Winandy | E57: 416 + 408 | F57: Hotel-Aeroporto | G57: SunDestiny | H57: 35 | I57: 5 | J57: 3 + 1 bebé | K57: AR
H59: =SUM(H6:H57) -> 1630 | I59: =SUM(I6:I57) -> 323.001
S60: =SUM(S58:S58) -> 0 | T60: =SUM(T58:T58) -> 0
B62: ÉPOCA FESTIVA ( 24 e 25 Dezembro ; 31 Dezembro e 1 Janeiro 2022)
B64: - Relembramos que está previsto nas tabelas de preços os serviços a efetuar nestas datas, terão um acréscimo de 50% do valor a cobrar ao cliente;
B66: (Sendo que as V/ vossas comissões serão também beneficiadas nestas datas em mais 25% sobre a comissão já estabelecida)
B68: Exemplos :
B70: Comissão de 5,00€ – passa para 6,25€
B72: Comissão de 7,00€ – passa para 8,75€

Sheet Transfers Março
B1: MSH ROSSIO - TRANSFERS MARÇO 2023
C2: * Por favor conferir comissões de transfers pagos ao hotel e modificar cor para
B3: SUNDESTINY | F3: Rita & Pedro Lobo | G3: 962930401 | H3: 962522529 | M3: 7 Roads | Q3: Carla | R3: 939660691
B5: Data | C5: Horas | D5: Cliente | E5: Quarto | F5: Serviço | G5: Empresa | H5: Valor | I5: Comissão | J5: Nº pax | M5: Data | N5: Horas | O5: Cliente | P5: Quarto | Q5: Serviço | R5: Empresa | S5: Valor | T5: Nº pax
B6: 44986 | C6: 06h30 | D6: Olga Kaye | E6: 403 | F6: Hotel-Aeroporto | G6: SunDestiny | H6: 25 | I6: 7 | J6: 2 | K6: CB | M6: 44993 | N6: 10h20 | O6: Robert Chadwick | Q6: Aeroporto-Hotel | R6: 7 Roads | S6: 39 | T6: 2
B7: 44986 | C7: 08h25 | D7: Thomas Briola | F7: Aeroporto-Hotel | G7: SunDestiny | H7: 35 | I7: 5 | J7: 2 | K7: DO | M7: 44992 | N7: 12h30 | O7: Julia | P7: 411 | Q7: Hotel-Aeroporto | R7: 7 Roads | S7: 22 | T7: 2
B8: 44986 | C8: 10h30 | D8: James Rayner | F8: Aeroporto-Hotel | G8: SunDestiny | H8: 35 | I8: 5 | J8: 2 | K8: AR | M8: 44995 | N8: 09h00 | O8: Gregory Crosland | Q8: Aeroporto-Hotel | R8: 7 Roads | S8: 39 | T8: 2
B9: 44987 | C9: 07h45 | D9: Michael Scrimes | E9: 401 | F9: Hotel-Aeroporto | G9: SunDestiny | H9: 25 | I9: 7 | J9: 2 | K9: DO | M9: 44995 | N9: 08h35 | O9: Robert Chadwick | P9: 401 | Q9: Hotel-Aeroporto | R9: 7 Roads | S9: 22 | T9: 2
B10: 44987 | C10: 17h50 | D10: Dganit Chen Shapira | F10: Aeroporto-Hotel | G10: SunDestiny | H10: 50 | I10: 10 | J10: 4 | K10: AR | M10: 44998 | N10: 21h05 | O10: David Robertson | Q10: Aeroporto-Hotel | R10: 7 Roads | S10: 39 | T10: 2
B11: 44987 | C11: 19h50 | D11: Laura Whittle | F11: Aeroporto-Hotel | G11: SunDestiny | H11: 35 | I11: 5 | J11: 2 | K11: AR | M11: 45004 | N11: 17h50 | O11: Elad Cohen | Q11: Aeroporto-Hotel | R11: 7 Roads | S11: 39 | T11: 1
B12: 44988 | C12: 14h35 | D12: Valérie Geffroy | F12: Aeroporto-Hotel | G12: SunDestiny | H12: 35 | I12: 5 | J12: 2 | K12: AR | M12: 45007 | N12: 08h50 | O12: Sylvia Galbraith | Q12: Aeroporto-Hotel | R12: 7 Roads | S12: 39 | T12: 2
B13: 44988 | C13: 17h15 | D13: Steffie Loots | F13: Aeroporto-Hotel | G13: SunDestiny | H13: 35 | I13: 5 | J13: 2 | K13: CB | M13: 45009 | N13: 12h30 | O13: Elad Cohen | P13: 408 | Q13: Hotel-Aeroporto | R13: 7 Roads | S13: 22 | T13: 1
B14: 44989 | C14: 05h00 | D14: Elena Loureiro | E14: 215 | F14: Hotel-Aeroporto | G14: SunDestiny | H14: 30 | I14: 7.5 | J14: 4 | K14: AR
B15: 44989 | C15: 16h15 | D15: Amy Woolridge | F15: Aeroporto-Hotel | G15: SunDestiny | H15: 35 | I15: 5 | J15: 2 | K15: AR
B16: 44989 | C16: 18h05 | D16: Kay Farinazzo | F16: Aeroporto-Hotel | G16: SunDestiny | H16: 35 | I16: 5 | J16: 2 | K16: DO
B17: 44990 | C17: 08h30 | D17: Sally Mandon | E17: 311 | F17: Hotel-Aeroporto | G17: SunDestiny | H17: 25 | I17: 7 | J17: 2 | K17: CB
B18: 44990 | C18: 17h15 | D18: Laura Whittle | E18: 216 | F18: Hotel-Aeroporto | G18: SunDestiny | H18: 25 | I18: 7 | J18: 2 | K18: AS
B19: 44991 | C19: 16h15 | D19: Dganit Chen Shapira | E19: 303 | F19: Hotel-Aeroporto | G19: SunDestiny | H19: 30 | I19: 7.5 | J19: 4 | K19: AR
B20: 44992 | C20: 19h45 | D20: Heike Kosching-Förste | F20: Aeroporto-Hotel | G20: SunDestiny | H20: 50 | I20: 10 | J20: 4 | K20: AR
B21: 44992 | C21: 07h15 | D21: Carol Anne Dedecker | E21: 409 | F21: Hotel-Aeroporto | G21: SunDestiny | H21: 25 | I21: 7 | J21: 2 | K21: AS
B22: 44992 | C22: 23h15 | D22: Alice Koral Zabari | F22: Aeroporto-Hotel | G22: SunDestiny | H22: 35 | I22: 5 | J22: 2 | K22: AS
B23: 44993 | C23: 05h00 | D23: Liliana | E23: 303 | F23: Hotel-Aeroporto | G23: SunDestiny | H23: 25 | I23: 7 | J23: 2 | K23: AS
B24: 44993 | C24: 12h00 | D24: Brian Boucher | F24: Aeroporto-Hotel | G24: SunDestiny | H24: 35 | I24: 5 | J24: 2 | K24: CB
B25: 44994 | C25: 08h00 | D25: Briola | E25: 415 | F25: Hotel-Aeroporto | G25: SunDestiny | H25: 25 | I25: 7 | J25: 2 | K25: RL
B26: 44994 | C26: 10h05 | D26: Jae Lim | F26: Aeroporto-Hotel | G26: SunDestiny | H26: 35 | I26: 5 | J26: 2 | K26: AS
B27: 44995 | C27: 02h00 | D27: Jeon, Seongmin | E27: 409 | F27: Hotel-Aeroporto | G27: SunDestiny | H27: 25 | I27: 7 | J27: 2 | K27: BM
B28: 44995 | C28: 08h00 | D28: Rachel Selvin | F28: Aeroporto-Hotel | G28: SunDestiny | H28: 35 | I28: 5 | J28: 2 | K28: AR
B29: 44995 | C29: 09h30 | D29: Loriano Tomelleri | F29: Aeroporto-Hotel | G29: SunDestiny | H29: 35 | I29: 5 | J29: 2 | K29: AR
B30: 44996 | C30: 06h30 | D30: Nelson Costa | E30: 208 | F30: Hotel-Aeroporto | G30: SunDestiny | H30: 25 | I30: 7 | J30: 1 | K30: AR
B31: 44996 | C31: 08h30 | D31: Jafchul Lim | E31: 415 | F31: Hotel-Aeroporto | G31: SunDestiny | H31: 25 | I31: 7 | J31: 2 | K31: AR
B32: 44996 | C32: 09h00 | D32: Bruce Sharp | E32: 307+215 | F32: Hotel-Sete Rios | G32: SunDestiny | H32: 30 | I32: 7.5 | J32: 4 | K32: CB
B33: 44997 | C33: 08h50 | D33: Maureen Wallis-Borrelli | F33: Aeroporto-Hotel | G33: SunDestiny | H33: 35 | I33: 5.002 | J33: 2 | K33: AR
B34: 44997 | C34: 16h25 | D34: Jacob Borrelli | F34: Aeroporto-Hotel | G34: SunDestiny | H34: 35 | I34: 5 | J34: 1 | K34: AR
B35: 44998 | C35: 04h00 | D35: Julie Oliver | F35: Hotel-Aeroporto | G35: SunDestiny | H35: 25 | I35: 7 | J35: 2 | K35: AS
B36: 44998 | C36: 09h00 | D36: Jasmin Fuchs | F36: Aeroporto-Hotel | G36: SunDestiny | H36: 35 | I36: 5 | J36: 2 | K36: AR
B37: 44998 | C37: 10h45 | D37: Elina Bakhiieva | F37: Aeroporto-Hotel | G37: SunDestiny | H37: 35 | I37: 5 | J37: 1 | K37: AR
B38: 44998 | C38: 15h20 | D38: Chantale Giguère | F38: Aeroporto-Hotel | G38: SunDestiny | H38: 35 | I38: 5 | J38: 2 | K38: AS
B39: 44998 | C39: 18h55 | D39: Paula Smith | F39: Aeroporto-Hotel | G39: SunDestiny | H39: 35 | I39: 5 | J39: 2 | K39: AR
B40: 44998 | C40: 19h10 | D40: Esmé Wiertz | F40: Aeroporto-Hotel | G40: SunDestiny | H40: 35 | I40: 5 | J40: 2 | K40: CB
B41: 44999 | C41: 11h50 | D41: Kelly Yee | F41: Aeroporto-Hotel | G41: SunDestiny | H41: 35 | I41: 5 | J41: 2 | K41: DO
B42: 44999 | C42: 16h00 | D42: Lynda Berry | E42: 201 | F42: Hotel-Aeroporto | G42: SunDestiny | H42: 25 | I42: 7 | J42: 1 | K42: AR
B43: 45000 | C43: 10h20 | D43: Rebecca Newhouse | F43: Aeroporto-Hotel | G43: SunDestiny | H43: 35 | I43: 5 | J43: 2 | K43: AS
B44: 45001 | C44: 11h30 | D44: Jasmin Fuchs | E44: 316 | F44: Hotel-Aeroporto | G44: SunDestiny | H44: 25 | I44: 7 | J44: 2 | K44: DO
B45: 45001 | C45: 13h20 | D45: Adam Walker | F45: Aeroporto-Hotel | G45: SunDestiny | H45: 35 | I45: 5 | J45: 2 | K45: AR
B46: 45001 | C46: 13h30 | D46: Sandra Sherman | E46: 201 | F46: Hotel-Aeroporto | G46: SunDestiny | H46: 25 | I46: 7 | J46: 2 | K46: DO
B47: 45001 | C47: 20h00 | D47: Paul Hawkins | F47: Aeroporto-Hotel | G47: SunDestiny | H47: 35 | I47: 5 | J47: 2 | K47: AR
B48: 45002 | C48: 02h30 | D48: Kelly Yee | E48: 308 | F48: Hotel-Aeroporto | G48: SunDestiny | H48: 25 | I48: 7 | J48: 2 | K48: DO
B49: 45002 | C49: 07h25 | D49: Jo Ann Pierce | F49: Aeroporto-Hotel | G49: SunDestiny | H49: 35 | I49: 5 | J49: 2 | K49: AS
B50: 45002 | C50: 08h15 | D50: Paula Smith | E50: 302 | F50: Hotel-Aeroporto | G50: SunDestiny | H50: 25 | I50: 7 | J50: 2 | K50: DO
B51: 45002 | C51: 20h15 | D51: Elaine Hood | F51: Aeroporto-Hotel | G51: SunDestiny | H51: 35 | I51: 5 | J51: 2 | K51: AS
B52: 45003 | C52: 09h30 | D52: Giuseppe Spina | E52: 415 | F52: Hotel-Aeroporto | G52: SunDestiny | H52: 25 | I52: 7 | J52: 2 | K52: AR
B53: 45003 | C53: 12h10 | D53: Amy Morton | F53: Aeroporto-Hotel | G53: SunDestiny | H53: 35 | I53: 5 | J53: 2 | K53: CB
B54: 45004 | C54: 09h55 | D54: Simon Judd | F54: Aeroporto-Hotel | G54: SunDestiny | H54: 35 | I54: 5 | J54: 2 | K54: DO
B55: 45004 | C55: 13h00 | D55: Alsaker | E55: 215+201 | F55: Hotel-Aeroporto | G55: SunDestiny | H55: 40 | I55: 10 | J55: 4 | K55: AS
B56: 45004 | C56: 17h00 | D56: Hawkins | E56: 316 | F56: Hotel-Aeroporto | G56: SunDestiny | H56: 25 | I56: 7 | J56: 2 | K56: AS
B57: 45005 | C57: 01h45 | D57: Linda Berberoglu | E57: 316 | F57: Hotel-Aeroporto | G57: SunDestiny | H57: 25 | I57: 7 | J57: 2 | K57: AR
B58: 45005 | C58: 06h00 | D58: Stepan Wilhem | E58: 415 | F58: Hotel-Aeroporto | G58: SunDestiny | H58: 25 | I58: 7 | J58: 2 | K58: DO
B59: 45005 | C59: 12h00 | D59: Kerry Mcaree | E59: 302 | F59: Hotel-Aeroporto | G59: SunDestiny | H59: 25 | I59: 7 | J59: 2 | K59: AR
B60: 45006 | C60: 05h25 | D60: Brian Bartels | F60: Aeroporto-Hotel | G60: SunDestiny | H60: 35 | I60: 5 | J60: 2 | K60: AS
B61: 45006 | C61: 10h10 | D61: Robert Henken | F61: Aeroporto-Hotel | G61: SunDestiny | H61: 35 | I61: 5 | J61: 2 | K61: AS
B62: 45006 | C62: 16h30 | D62: Elad Cohen | E62: 408 | F62: Cacém-Hotel | G62: SunDestiny | H62: 75 | I62: 15 | J62: 1 | K62: AR
B63: 45006 | C63: 17h50 | D63: Iris Rattner | F63: Aeroporto-Hotel | G63: SunDestiny | H63: 35 | I63: 5 | J63: 2 | K63: AR
B64: 45007 | C64: 11h00 | D64: Enzo Tremolada | F64: Aeroporto-Hotel | G64: SunDestiny | H64: 35 | I64: 5 | J64: 2 | K64: AS
B65: 45007 | C65: 15h10 | D65: Ayaka Ban | E65: 216 | F65: Hotel-Aeroporto | G65: SunDestiny | H65: 25 | I65: 7 | J65: 1 | K65: AR
B66: 45008 | C66: 07h20 | D66: Karine Mathy | F66: Aeroporto-Hotel | G66: SunDestiny | H66: 35 | I66: 5 | J66: 2 | K66: AS
B67: 45008 | C67: 08h15 | D67: Cora Mary Morrison | E67: 405 | F67: Hotel-Aeroporto | G67: SunDestiny | H67: 25 | I67: 7 | J67: 2 | K67: AR
B68: 45008 | C68: 10h10 | D68: Alice Costache | F68: Aeroporto-Hotel | G68: SunDestiny | H68: 35 | I68: 5 | J68: 2 | K68: AS
B69: 45008 | C69: 11h45 | D69: Matthew O'Neill | F69: Aeroporto-Hotel | G69: SunDestiny | H69: 35 | I69: 5 | J69: 1 | K69: DO
B70: 45009 | C70: 05h30 | D70: Mahoney | E70: 204 | F70: Hotel-Aeroporto | G70: SunDestiny | H70: 25 | I70: 7 | J70: 2 | K70: DO
B71: 45009 | C71: 07h55 | D71: Gian Luca Casolari | F71: Aeroporto-Hotel | G71: SunDestiny | H71: 35 | I71: 5 | J71: 2 | K71: AR
B72: 45009 | C72: 08h00 | D72: Shannon McElligott. | F72: Aeroporto-Hotel | G72: SunDestiny | H72: 35 | I72: 5 | J72: 2 | K72: CB
B73: 45009 | C73: 10h15 | D73: Judd | E73: 416 | F73: Hotel-Aeroporto | G73: SunDestiny | H73: 25 | I73: 7 | J73: 2 | K73: CB
B74: 45009 | C74: 08h15 | D74: Chiu | E74: 312 | F74: Hotel-Aeroporto | G74: SunDestiny | H74: 25 | I74: 7 | J74: 2 | K74: DO
B75: 45009 | C75: 21h55 | D75: Murray Hendriksen | F75: Aeroporto-Hotel | G75: SunDestiny | H75: 35 | I75: 5 | J75: 2 | K75: DO
B76: 45010 | C76: 07h45 | D76: Shannon McElligott. | E76: 309 | F76: Hotel-Aeroporto | G76: SunDestiny | H76: 25 | I76: 7 | J76: 2 | K76: DO
B77: 45010 | C77: 09h15 | D77: Sylvia Galbraith | E77: 315 | F77: Hotel-Aeroporto | G77: SunDestiny | H77: 25 | I77: 7 | J77: 2 | K77: AS
B78: 45010 | C78: 09h00 | D78: Chantale Giguère | E78: 208 | F78: Hotel-Aeroporto | G78: SunDestiny | H78: 25 | I78: 7 | J78: 2 | K78: AS
B79: 45010 | C79: 10h40 | D79: Ece Demirkir Cakir | F79: Aeroporto-Hotel | G79: SunDestiny | H79: 35 | I79: 5 | J79: 1 | K79: DO
B80: 45010 | C80: 09h00 | D80: Karine Mathy | E80: 209 | F80: Hotel-Aeroporto | G80: SunDestiny | H80: 25 | I80: 7 | J80: 1 | K80: CB
B81: 45011 | C81: 11h00 | D81: Lucile | E81: 308+310+311 | F81: Hotel-Aeroporto | G81: SunDestiny | H81: 40 | I81: 10 | J81: 6 | K81: CB
B82: 45011 | C82: 15h10 | D82: Beverley Hadley | F82: Aeroporto-Hotel | G82: SunDestiny | H82: 35 | I82: 5 | J82: 3 | K82: AR
B83: 45012 | C83: 09h45 | D83: Diet Wolfert | F83: Aeroporto-Hotel | G83: SunDestiny | H83: 35 | I83: 5 | J83: 2 | K83: FP
B84: 45013 | C84: 12h35 | D84: Alessandro di San Lorenzo | F84: Aeroporto-Hotel | G84: SunDestiny | H84: 35 | I84: 5 | J84: 2 | K84: AR
B85: 45013 | C85: 17h00 | D85: Emily Bodin | F85: Aeroporto-Hotel | G85: SunDestiny | H85: 35 | I85: 5 | J85: 1 | K85: AR
B86: 45015 | C86: 09h05 | D86: Erika Bua | F86: Aeroporto-Hotel | G86: SunDestiny | H86: 70 | I86: 10 | J86: 8 | K86: DO
H88: =SUM(H6:H87) -> 2635 | I88: =SUM(I6:I87) -> 507.502

Sheet Transfers Abril
B1: MSH ROSSIO - TRANSFERS ABRIL 2023
C2: * Por favor conferir comissões de transfers pagos ao hotel e modificar cor para
B3: SUNDESTINY | F3: Rita & Pedro Lobo | G3: 962930401 | H3: 962522529 | M3: 7 Roads | Q3: Carla | R3: 939660691
B5: Data | C5: Horas | D5: Cliente | E5: Quarto | F5: Serviço | G5: Empresa | H5: Valor | I5: Comissão | J5: Nº pax | M5: Data | N5: Horas | O5: Cliente | P5: Quarto | Q5: Serviço | R5: Empresa | S5: Valor | T5: Nº pax
B6: 45017 | C6: 19h40 | D6: Michael Arnold | F6: Aeroporto-Hotel | G6: SunDestiny | H6: 35 | I6: 5 | J6: 2 | K6: CB | M6: 45018 | N6: 08h20 | O6: Brigid Grode | Q6: Aeroporto-Hotel | R6: 7 Roads | S6: 39 | T6: 2
B7: 45018 | C7: 08h20 | D7: Shimie Hortig | F7: Aeroporto-Hotel | G7: SunDestiny | H7: 35 | I7: 5 | J7: 3 | K7: AR | M7: 45020 | N7: 07h30 | O7: Kenneth Coffman | Q7: Hotel-Aeroporto | R7: 7 Roads | S7: 22 | T7: 2
B8: 45018 | C8: 09h10 | D8: Liat Hortig | F8: Aeroporto-Hotel | G8: SunDestiny | H8: 35 | I8: 5 | J8: 1 | K8: AR | M8: 45020 | N8: 10h00 | O8: Suzanne Thorniley | Q8: Hotel-Aeroporto | R8: 7 Roads | S8: 22 | T8: 1
B9: 45018 | C9: 10h30 | D9: Sascha Hellbeck | E9: 302 | F9: Hotel-Aeroporto | G9: SunDestiny | H9: 40 | I9: 10 | J9: 4 | K9: CB | M9: 45025 | N9: 08h00 | O9: Michael Holloway | Q9: Hotel-Aeroporto | R9: 7 Roads | S9: 22 | T9: 2
B10: 45018 | C10: 11h00 | D10: Rose Edmands | E10: 303 | F10: Hotel-Aeroporto | G10: SunDestiny | H10: 25 | I10: 7 | J10: 2 | K10: DO | M10: 45031 | N10: 06h30 | O10: Victor Wolff | P10: 202 | Q10: Hotel-Aeroporto | R10: 7 Roads | S10: 22 | T10: 2
B11: 45020 | C11: 09h30 | D11: Stephen Williams | E11: 207 | F11: Hotel-Aeroporto | G11: SunDestiny | H11: 25 | I11: 7 | J11: 2 | K11: AR | M11: 45036 | N11: 03h30 | O11: Sarah Whitmore | P11: 202 | Q11: Hotel-Aeroporto | R11: 7 Roads | S11: 22 | T11: 2
B12: 45020 | C12: 12h20 | D12: David Harrison | F12: Aeroporto-Hotel | G12: SunDestiny | H12: 35 | I12: 5 | J12: 2 | K12: DO | M12: 45037 | N12: 11h15 | O12: David Clay | Q12: Aeroporto-Hotel | R12: 7 Roads | S12: 39 | T12: 2
B13: 45020 | C13: 12h30 | D13: Gruver | F13: Hotel-Aeroporto | G13: SunDestiny | H13: 25 | I13: 7 | J13: 2 | K13: AR | M13: 45037 | N13: 09H05 | O13: John Terrio | Q13: Aeroporto-Hotel | R13: 7 Roads | S13: 39 | T13: 2
B14: 45021 | C14: 15h35 | D14: Diane Amer | F14: Aeroporto-Hotel | G14: SunDestiny | H14: 35 | I14: 5 | J14: 2 | K14: DO | M14: 45041 | N14: 09h45 | O14: Leigh Knight | Q14: Aeroporto-Hotel | R14: 7 Roads | S14: 39 | T14: 2
B15: 45021 | C15: 21h35 | D15: Claire Costello | F15: Aeroporto-Hotel | G15: SunDestiny | H15: 35 | I15: 5 | J15: 2 | K15: DO | M15: 45041 | N15: 15h15 | O15: Cheryl Laney | Q15: Aeroporto-Hotel | R15: 7 Roads | S15: 39 | T15: 2
B16: 45021 | C16: 15h30 | D16: Familia Meneses | F16: Hotel-Aeroporto | G16: SunDestiny | H16: 80 | I16: 20 | J16: 12 | K16: DO | M16: 45042 | N16: 07h00 | O16: Leigh Knight | P16: 415 | Q16: Hotel-Aeroporto | R16: 7 Roads | S16: 22 | T16: 2
B17: 45022 | C17: 06h30 | D17: Gerald Schneider | E17: 316 | F17: Hotel-Aeroporto | G17: SunDestiny | H17: 25 | I17: 7 | J17: 2 | K17: CB | M17: 45043 | N17: 11h10 | O17: Susan Thomson | Q17: Aeroporto-Hotel | R17: 7 Roads | S17: 39 | T17: 2
B18: 45022 | C18: 12h30 | D18: Rachel Reynolds | E18: 403 | F18: Hotel-Aeroporto | G18: SunDestiny | H18: 25 | I18: 7 | J18: 2 | K18: DO | M18: 45044 | N18: 08h15 | O18: Keri Potts | Q18: Aeroporto-Hotel | R18: 7 Roads | S18: 39 | T18: 2
B19: 45022 | C19: 17h25 | D19: Eric Talavet | F19: Aeroporto-Hotel | G19: SunDestiny | H19: 35 | I19: 5 | J19: 2 | K19: AR | M19: 45044 | N19: 08h20 | O19: Susan Graves | Q19: Aeroporto-Hotel | R19: 7 Roads | S19: 39 | T19: 2
B20: 45022 | C20: 15h45 | D20: Elizabeth Bucker | F20: Aeroporto-Hotel | G20: SunDestiny | H20: 35 | I20: 5 | J20: 2 | K20: DO | M20: 45045 | N20: 12h05 | O20: Joan Hillis | Q20: Aeroporto-Hotel | R20: 7 Roads | S20: 39 | T20: 2
B21: 45022 | C21: 21h25 | D21: Maria Gallo | F21: Aeroporto-Hotel | G21: SunDestiny | H21: 35 | I21: 5 | J21: 3 | K21: DO | M21: 45045 | N21: 13h30 | O21: Susan Thomson | P21: 101 | Q21: Hotel-Aeroporto | R21: 7 Roads | S21: 22 | T21: 2 | U21: Pago, mas não usufruiu.
B22: 45023 | C22: 08h20 | D22: Eric Lorenz | F22: Aeroporto-Hotel | G22: SunDestiny | H22: 35 | I22: 5 | J22: 2 | K22: DO | M22: 45046 | N22: 21h15 | O22: Nivethitha Ram Ganapathiram | Q22: Aeroporto-Hotel | R22: 7 Roads | S22: 39 | T22: 2
B23: 45023 | C23: 08h20 | D23: Carol Zimmermann | F23: Aeroporto-Hotel | G23: SunDestiny | H23: 35 | I23: 5 | J23: 2 | K23: DO
B24: 45023 | C24: 14h50 | D24: Gabi Ohlinger | F24: Aeroporto-Hotel | G24: SunDestiny | H24: 35 | I24: 5 | J24: 2 | K24: AR
B25: 45024 | C25: 04h15 | D25: Elizabeth Buckner | E25: 101 | F25: Hotel-Aeroporto | G25: SunDestiny | H25: 25 | I25: 7 | J25: 2 | K25: AR
B26: 45024 | C26: 08h30 | D26: Henriette Fredriksen | E26: 407 | F26: Hotel-Aeroporto | G26: SunDestiny | H26: 25 | I26: 7 | J26: 3 | K26: AR
B27: 45024 | C27: 09h45 | D27: Orit Bem-Sasson | F27: Aeroporto-Hotel | G27: SunDestiny | H27: 35 | I27: 5 | J27: 2 | K27: CB
B28: 45025 | C28: 05h00 | D28: Ann Brandt | E28: 205 | F28: Hotel-Aeroporto | G28: SunDestiny | H28: 25 | I28: 7 | J28: 2 | K28: AR
B29: 45026 | C29: 04h30 | D29: Paloma Coll | E29: 103 | F29: Hotel-Aeroporto | G29: SunDestiny | H29: 25 | I29: 7 | J29: 2 | K29: BM
B30: 45026 | C30: 04h45 | D30: Geir Thomas Eriksen | E30: 304 | F30: Hotel-Aeroporto | G30: SunDestiny | H30: 25 | I30: 7 | J30: 2 | K30: AR
B31: 45026 | C31: 07h30 | D31: Esther Espinosa | E31: 212 | F31: Hotel-Aeroporto | G31: SunDestiny | H31: 25 | I31: 7 | J31: 2 | K31: AR
B32: 45026 | C32: 10h15 | D32: Família Kreuter | E32: 406 + 408 | F32: Hotel-Aeroporto | G32: SunDestiny | H32: 30 | I32: 7.5 | J32: 4 | K32: AR
B33: 45026 | C33: 11h30 | D33: Maria Gallo | E33: 315 | F33: Hotel-Aeroporto | G33: SunDestiny | H33: 25 | I33: 7 | J33: 3 | K33: AS
B34: 45026 | C34: 10h50 | D34: Jason Mancini | F34: Aeroporto-Hotel | G34: SunDestiny | H34: 35 | I34: 5 | J34: 2 | K34: CB
B35: 45027 | C35: 10h30 | D35: Anthony Sorvino | F35: Aeroporto-Hotel | G35: SunDestiny | H35: 35 | I35: 5 | J35: 2 | K35: CB
B36: 45027 | C36: 11h15 | D36: Rolv Slungaard | F36: Aeroporto-Hotel | G36: SunDestiny | H36: 35 | I36: 5.002 | J36: 2 | K36: AR
B37: 45028 | C37: 06h30 | D37: Laura Schuster | F37: Hotel-Aeroporto | G37: SunDestiny | H37: 25 | I37: 7 | J37: 2 | K37: AR
B38: 45028 | C38: 10h00 | D38: Rolv Slungaard | F38: Hotel-Aeroporto | G38: SunDestiny | H38: 25 | I38: 7 | J38: 2 | K38: DO
B39: 45028 | C39: 11h30 | D39: Lawrence Santisteban | E39: 206 + 306 | F39: Hotel-Aeroporto | G39: SunDestiny | H39: 30 | I39: 7.5 | J39: 4 | K39: AR
B40: 45028 | C40: 16h25 | D40: Stan Fiorentino | F40: Aeroporto-Hotel | G40: SunDestiny | H40: 35 | I40: 5 | J40: 2 | K40: DO
B41: 45029 | C41: 08h20 | D41: Chris Larocque | F41: Aeroporto-Hotel | G41: SunDestiny | H41: 50 | I41: 10 | J41: 4 | K41: CL
B42: 45029 | C42: 14h00 | D42: Christophe Boilevin | E42: 415 | F42: Belém-Aeroporto | G42: SunDestiny | H42: 55 | I42: 10 | J42: 2 | K42: AR
B43: 45029 | C43: 15h30 | D43: Karei Paepe | E43: 102 + 104 | F43: Hotel-Aeroporto | G43: SunDestiny | H43: 30 | I43: 7.5 | J43: 4 | K43: AR/TS
B44: 45030 | C44: 09h20 | D44: Elizabeth Buckner | F44: Aeroporto-Hotel | G44: SunDestiny | H44: 35 | I44: 5 | J44: 2 | K44: TS
B45: 45030 | C45: 07h00 | D45: Denise Britt | E45: 207 + 208 | F45: Hotel-Aeroporto | G45: SunDestiny | H45: 40 | I45: 10 | J45: 4 | K45: CB
B46: 45030 | C46: 19h00 | D46: María Jose fernandez | F46: Aeroporto-Hotel | G46: SunDestiny | H46: 35 | I46: 5 | J46: 2 | K46: AS
B47: 45031 | C47: 08h30 | D47: Elizabeth Buckner | E47: 312 | F47: Hotel-Aeroporto | G47: SunDestiny | H47: 25 | I47: 7 | J47: 2 | K47: AS
B48: 45031 | C48: 09h00 | D48: Christian Larocque | E48: 415 + 216 | F48: Hotel-Aeroporto | G48: SunDestiny | H48: 40 | I48: 10 | J48: 4 | K48: DO
B49: 45034 | C49: 09h20 | D49: Valerie Barclay | F49: Aeroporto-Hotel | G49: SunDestiny | H49: 35 | I49: 5 | J49: 2 | K49: AR
B50: 45034 | C50: 11h10 | D50: Barbara Nadon | F50: Aeroporto-Hotel | G50: SunDestiny | H50: 35 | I50: 5 | J50: 2 | K50: DO
B51: 45035 | C51: 07h05 | D51: Elisa Ferrer | E51: 310 | F51: Hotel-Aeroporto | G51: SunDestiny | H51: 35 | I51: 5 | J51: 2 | K51: AS
B52: 45036 | C52: 07h00 | D52: William King | E52: 312 | F52: Hotel-Aeroporto | G52: SunDestiny | H52: 30 | I52: 7.5 | J52: 4 | K52: TS
B53: 45036 | C53: 07h00 | D53: Carol Ann Morrison | E53: 304 | F53: Hotel-Aeroporto | G53: SunDestiny | H53: 25 | I53: 7 | J53: 2 | K53: TS
B54: 45036 | C54: 08h30 | D54: Suzanne Windzio | E54: 211 | F54: Hotel-Aeroporto | G54: SunDestiny | H54: 30 | I54: 7.5 | J54: 2 | K54: AR
B55: 45036 | C55: 15h40 | D55: Andre Glatz | F55: Aeroporto-Hotel | G55: SunDestiny | H55: 35 | I55: 5 | J55: 3 | K55: AR
B56: 45036 | C56: 06h30 | D56: Schneider Claudia | E56: 405 | F56: Hotel-Aeroporto | G56: SunDestiny | H56: 25 | I56: 7 | J56: 2 | K56: TS
B57: 45037 | C57: 08h20 | D57: George Malkames | F57: Aeroporto-Hotel | G57: SunDestiny | H57: 35 | I57: 5 | J57: 2 | K57: AR
B58: 45037 | C58: 10h55 | D58: Hudson Smith (George Malkames) | F58: Aeroporto-Hotel | G58: SunDestiny | H58: 35 | I58: 5 | J58: 2 | K58: AR
B59: 45037 | C59: 19h00 | D59: Chong | E59: 401 + 315 | F59: Hotel-Aeroporto | G59: SunDestiny | H59: 40 | I59: 10 | J59: 4 | K59: DO
B60: 45037 | C60: 23h10 | D60: Lea James | F60: Aeroporto-Hotel | G60: SunDestiny | H60: 35 | I60: 5 | J60: 3 | K60: AS
B61: 45037 | C61: 23h10 | D61: Lea James | F61: Aeroporto-Hotel | G61: SunDestiny | H61: 70 | I61: 10 | J61: 7 | K61: AS
B62: 45038 | C62: 06h30 | D62: Wendy | E62: 416 | F62: Hotel-Aeroporto | G62: SunDestiny | H62: 25 | I62: 7 | J62: 2 | K62: AS
B63: 45038 | C63: 08h20 | D63: Anita Bluestone | F63: Aeroporto-Hotel | G63: SunDestiny | H63: 35 | I63: 5 | J63: 2 | K63: AS
B64: 45038 | C64: 11h25 | D64: Ma Katrina Gozo | F64: Aeroporto-Hotel | G64: SunDestiny | H64: 50 | I64: 10 | J64: 2 | K64: AR
B65: 45038 | C65: 12h05 | D65: Amy Herzog | F65: Aeroporto-Hotel | G65: SunDestiny | H65: 35 | I65: 5 | J65: 2 | K65: AR
B66: 45039 | C66: 11h10 | D66: Charles Scott | F66: Aeroporto-Hotel | G66: SunDestiny | H66: 35 | I66: 5 | J66: 2 | K66: AR
B67: 45039 | C67: 16h29 | D67: Lea James | F67: Hotel-Aeroporto | G67: SunDestiny | H67: 40 | I67: 10 | J67: 7 | K67: CB
B68: 45039 | C68: 16h30 | D68: Lea James | F68: Hotel-Aeroporto | G68: SunDestiny | H68: 25 | I68: 7 | J68: 3 | K68: CB
B69: 45039 | C69: 11h35 | D69: Thomas Hunziker | F69: Aeroporto-Hotel | G69: SunDestiny | H69: 35 | I69: 5 | J69: 2 | K69: AS
B70: 45040 | C70: 05h30 | D70: Koehler | E70: 211 + 408 | F70: Hotel-Aeroporto | G70: SunDestiny | H70: 40 | I70: 10 | J70: 4 | K70: AS
B71: 45040 | C71: 07h15 | D71: Christian Larocque | E71: 404 | F71: Hotel-Aeroporto | G71: SunDestiny | H71: 25 | I71: 7 | J71: 2 | K71: AS
B72: 45040 | C72: 09h00 | D72: Cedric De Trey | E72: 101 | F72: Hotel-Aeroporto | G72: SunDestiny | H72: 25 | I72: 7 | J72: 2 | K72: AS
B73: 45040 | C73: 10h50 | D73: Rebecca Bagin | F73: Aeroporto-Hotel | G73: SunDestiny | H73: 35 | I73: 5 | J73: 2 | K73: AR
B74: 45040 | C74: 16h20 | D74: Nicholas Ioannou | F74: Aeroporto-Hotel | G74: SunDestiny | H74: 35 | I74: 5 | J74: 1 | K74: AR
B75: 45040 | C75: 16h30 | D75: Amy Herzog | F75: Hotel-Aeroporto | G75: SunDestiny | H75: 25 | I75: 7 | J75: 2 | K75: AR
B76: 45040 | C76: 10h50 | D76: Martin Bergman | F76: Aeroporto-Hotel | G76: SunDestiny | H76: 35 | I76: 5 | J76: 2 | K76: AR
B77: 45041 | C77: 06h45 | D77: Francesca Angrisani | E77: 404 | F77: Hotel-Aeroporto | G77: SunDestiny | H77: 25 | I77: 7 | J77: 1 | K77: AR
B78: 45041 | C78: 07h00 | D78: Pedro Silva | E78: 403 | F78: Hotel-Aeroporto | G78: SunDestiny | H78: 25 | I78: 7 | J78: 2 | K78: AR
B79: 45041 | C79: 08h30 | D79: Ma Katrina Gozo | E79: 407 | F79: Hotel-Aeroporto | G79: SunDestiny | H79: 40 | I79: 10 | J79: 2 | K79: AR
B80: 45042 | C80: 22h55 | D80: Barbara Finzen | F80: Aeroporto-Hotel | G80: SunDestiny | H80: 35 | I80: 5 | J80: 2 | K80: AR
B81: 45043 | C81: 02h30 | D81: Lorraine Silvano | E81: 316 | F81: Hotel-Aeroporto | G81: SunDestiny | H81: 25 | I81: 7 | J81: 2 | K81: AR
B82: 45043 | C82: 05h30 | D82: Adde Bhat | E82: 211 | F82: Hotel-Aeroporto | G82: SunDestiny | H82: 25 | I82: 7 | J82: 2 | K82: AR
B83: 45043 | C83: 09h25 | D83: Michael Deeken (Barbara Finzen) | F83: Aeroporto-Hotel | G83: SunDestiny | H83: 35 | I83: 5 | J83: 2 | K83: AR
B84: 45043 | C84: 12h00 | D84: Thomas Hunziker | E84: 202 | F84: Hotel-Aeroporto | G84: SunDestiny | H84: 25 | I84: 7 | J84: 2 | K84: DO
B85: 45043 | C85: 16h10 | D85: Michael Okies | F85: Aeroporto-Hotel | G85: SunDestiny | H85: 50 | I85: 10 | J85: 4 | K85: AR
B86: 45044 | C86: 10h15 | D86: Elizabeth Schroeder | F86: Aeroporto-Hotel | G86: SunDestiny | H86: 35 | I86: 5 | J86: 2 | K86: AR
B87: 45044 | C87: 14h00 | D87: Joanna | E87: 408 + 407 | F87: Hotel-Aeroporto | G87: SunDestiny | H87: 25 | I87: 7 | J87: 2 | K87: CB
B88: 45045 | C88: 07h45 | D88: Carole Chatelard | F88: Aeroporto-Hotel | G88: SunDestiny | H88: 35 | I88: 5 | J88: 2 | K88: TS
B89: 45045 | C89: 12h50 | D89: Giorgio Fioravanti | F89: Aeroporto-Hotel | G89: SunDestiny | H89: 35 | I89: 5 | J89: 2 | K89: AS
B90: 45046 | C90: 07h30 | D90: Kathy Bradley | F90: Hotel-Aeroporto | G90: SunDestiny | H90: 25 | I90: 7 | J90: 2 | K90: CB
B91: 45046 | C91: 08h00 | D91: Tracy Irwin | E91: 205 + 207 | F91: Hotel-Aeroporto | G91: SunDestiny | H91: 30 | I91: 7.5 | J91: 4 | K91: AR
B92: 45046 | C92: 13h35 | D92: Annelies Eeckhout | F92: Aeroporto-Hotel | G92: SunDestiny | H92: 35 | I92: 5 | J92: 2 | K92: AR
H94: =SUM(H6:H92) -> 2905 | I94: =SUM(I6:I92) -> 583.002

Sheet Transfers Maio
B1: MSH ROSSIO - TRANSFERS MAIO 2023
C2: * Por favor conferir comissões de transfers pagos ao hotel e modificar cor para
B3: SUNDESTINY | F3: Rita & Pedro Lobo | G3: 962930401 | H3: 962522529 | M3: 7 Roads | Q3: Carla | R3: 939660691
B5: Data | C5: Horas | D5: Cliente | E5: Quarto | F5: Serviço | G5: Empresa | H5: Valor | I5: Comissão | J5: Nº pax | M5: Data | N5: Horas | O5: Cliente | P5: Quarto | Q5: Serviço | R5: Empresa | S5: Valor | T5: Nº pax
B6: 45047 | C6: 20h25 | D6: Tuli Gavriel | F6: Aeroporto-Hotel | G6: SunDestiny | H6: 35 | I6: 5 | J6: 1 | K6: CB | M6: 45048 | N6: 08h20 | O6: Ronald Secrist | Q6: Aeroporto-Hotel | R6: 7 Roads | S6: 39 | T6: 2
B7: 45047 | C7: 04h00 | D7: Malanie | E7: 104 | F7: Hotel-Aeroporto | G7: SunDestiny | H7: 25 | I7: 7 | J7: 2 | K7: CB | M7: 45048 | N7: 17h55 | O7: Gary Olmeim | Q7: Aeroporto-Hotel | R7: 7 Roads | S7: 39 | T7: 2
B9: 45047 | C9: 03h30 | D9: Arlene Aitkins | E9: 303 | F9: Hotel-Aeroporto | G9: SunDestiny | H9: 25 | I9: 7 | J9: 2 | K9: AR | M9: 45049 | N9: 07h00 | O9: Joan Hills | P9: 302 | Q9: Hotel-Aeroporto | R9: 7 Roads | S9: 22 | T9: 2
B10: 45048 | C10: 06h45 | D10: Mark Sebastian | E10: 205 | F10: Hotel-Aeroporto | G10: SunDestiny | H10: 30 | I10: 7.5 | J10: 2 | K10: AR | M10: 45053 | N10: 06h30 | O10: Scott Sherer | Q10: Aeroporto-Hotel | R10: 7 Roads | S10: 39 | T10: 2
B11: 45048 | C11: 11h15 | D11: Susan Graves | F11: Aeroporto-Hotel | G11: SunDestiny | H11: 35 | I11: 5 | J11: 2 | K11: AR | M11: 45054 | N11: 09h20 | O11: Gary Oman | Q11: Aeroporto-Hotel | R11: 7 Roads | S11: 39 | T11: 2
B12: 45049 | C12: 05h15 | D12: Ginette Paquin | E12: 316 | F12: Hotel-Aeroporto | G12: SunDestiny | H12: 25 | I12: 7 | J12: 2 | K12: DO | M12: 45056 | N12: 05h00 | O12: Scott Sherer | Q12: Hotel-Aeroporto | R12: 7 Roads | S12: 22 | T12: 2
B13: 45049 | C13: 06h30 | D13: Cheryl Gutierrez | E13: 204 | F13: Hotel-Aeroporto | G13: SunDestiny | H13: 25 | I13: 7 | J13: 2 | K13: AR | M13: 45056 | N13: 05h00 | O13: Ronald Brown | Q13: Hotel-Aeroporto | R13: 7 Roads | S13: 22 | T13: 2
B14: 45049 | C14: 11h00 | D14: Chin Chang | E14: 405 | F14: Hotel-Aeroporto | G14: SunDestiny | H14: 25 | I14: 7 | J14: 2 | K14: DO | M14: 45056 | N14: 10h00 | O14: Roger Brazill | Q14: Hotel-Aeroporto | R14: 7 Roads | S14: 22 | T14: 2
B15: 45049 | C15: 16h25 | D15: Stacy Fagan | E15: 210 + 212 | F15: Sete Rios - Hotel | G15: SunDestiny | H15: 50 | I15: 10 | J15: 3 | K15: DO | M15: 45060 | N15: 21h10 | O15: Joseph Eastwood | Q15: Aeroporto-Hotel | R15: 7 Roads | S15: 39 | T15: 2
B16: 45050 | C16: 06h30 | D16: Paula zindler | E16: 303 | F16: Hotel-Aeroporto | G16: SunDestiny | H16: 25 | I16: 7 | J16: 2 | K16: AS | M16: 45061 | N16: 10h35 | O16: Daniel Sullivan | Q16: Aeroporto-Hotel | R16: 7 Roads | S16: 39 | T16: 2
B17: 45050 | C17: 11h00 | D17: Annelise | E17: 211 | F17: Hotel-Aeroporto | G17: SunDestiny | H17: 25 | I17: 7 | J17: 2 | K17: AS | M17: 45063 | N17: 04h30 | O17: Atherine Rothacker | P17: 104 | Q17: Hotel-Aeroporto | R17: 7 Roads | S17: 22 | T17: 1
B18: 45050 | C18: 19h30 | D18: Nivethitha Ram Ganapathiram | E18: 402 | F18: Hotel-Aeroporto | G18: SunDestiny | H18: 25 | I18: 7 | J18: 2 | K18: AR | M18: 45063 | N18: 06h30 | O18: Hani Karout | Q18: Aeroporto-Hotel | R18: 7 Roads | S18: 39 | T18: 2
B19: 45050 | C19: 11h10 | D19: Gilles Blanchet | F19: Aeroporto-Hotel | G19: SunDestiny | H19: 35 | I19: 5 | J19: 2 | K19: AR | M19: 45064 | N19: 06h30 | O19: Catherine Wissing | P19: 301 | Q19: Hotel-Aeroporto | R19: 7 Roads | S19: 22 | T19: 2
B20: 45051 | C20: 23H15 | D20: Florence | F20: Aeroporto-Hotel | G20: SunDestiny | H20: 35 | I20: 5 | J20: 2 | K20: CB | M20: 45065 | N20: 07h30 | O20: Hannah Bucchin | P20: 201 | Q20: Hotel-Aeroporto | R20: 7 Roads | S20: 22 | T20: 2
B21: 45052 | C21: 12h05 | D21: Michael Suerth | F21: Aeroporto-Hotel | G21: SunDestiny | H21: 50 | I21: 10 | J21: 3 | K21: AR | M21: 45069 | N21: 21h35 | O21: Ryan Fansler | Q21: Aeroporto-Hotel | R21: 7 Roads | S21: 39 | T21: 2
B22: 45052 | C22: 10h00 | D22: Paula Loeb | F22: Aeroporto-Hotel | G22: SunDestiny | H22: 35 | I22: 5 | J22: 2 | K22: AS | M22: 45071 | N22: 09h20 | O22: Emilie Niquette | Q22: Aeroporto-Hotel | R22: 7 Roads | S22: 39 | T22: 2
B23: 45053 | C23: 06h10 | D23: Catherine Smith | F23: Aeroporto-Hotel | G23: SunDestiny | H23: 35 | I23: 5 | J23: 2 | K23: FP | M23: 45074 | N23: 14h35 | O23: Harriet Cook | Q23: Aeroporto-Hotel | R23: 7 Roads | S23: 39 | T23: 2
B24: 45053 | C24: 12h25 | D24: Tashri Mahabir | F24: Aeroporto-Hotel | G24: SunDestiny | H24: 35 | I24: 5 | J24: 2 | K24: AS | M24: 45075 | N24: 10h40 | O24: Jay Bower | Q24: Aeroporto-Hotel | R24: 7 Roads | S24: 39 | T24: 2
B25: 45054 | C25: 13h00 | D25: Annick | E25: 312 + 408 | F25: Hotel-Aeroporto | G25: SunDestiny | H25: 25 | I25: 7 | J25: 3 | K25: AS | M25: 45075 | N25: 11h25 | O25: Zachary Pirkl | Q25: Aeroporto-Hotel | R25: 7 Roads | S25: 39 | T25: 2
B26: 45054 | C26: 15h10 | D26: Diana Seruga Sagadin | F26: Aeroporto-Hotel | G26: SunDestiny | H26: 35 | I26: 5 | J26: 1 | K26: AR | M26: 45076 | N26: 06h30 | O26: Daiane Silva | P26: 410 | Q26: Hotel-Aeroporto | R26: 7 Roads | S26: 39 | T26: 2
B27: 45055 | C27: 08h15 | D27: Iohn Henry Niehaus | E27: 407 | F27: Hotel-Aeroporto | G27: SunDestiny | H27: 25 | I27: 7 | J27: 2 | K27: AR | M27: 45076 | N27: 10h50 | O27: Dennis Majerski | Q27: Aeroporto-Hotel | R27: 7 Roads | S27: 39 | T27: 2
B28: 45055 | C28: 23h00 | D28: Nicole Cuttat | F28: Aeroporto-Hotel | G28: SunDestiny | H28: 35 | I28: 5 | J28: 2 | K28: DO | M28: 45077 | N28: 01h00 | O28: Anat scheffer | Q28: Aeroporto-Hotel | R28: 7 Roads | S28: 39 | T28: 2
B29: 45056 | C29: 10h00 | D29: Kristen Ranaldo | F29: Aeroporto-Hotel | G29: SunDestiny | H29: 50 | I29: 10 | J29: 4 | K29: AR
B30: 45056 | C30: 14h20 | D30: Rajeshkumar Mistry | F30: Aeroporto-Hotel | G30: SunDestiny | H30: 35 | I30: 5 | J30: 1 | K30: DO
B31: 45056 | C31: 14h00 | D31: Mahabir Tashri Sandy | E31: 301 | F31: Hotel-Aeroporto | G31: SunDestiny | H31: 25 | I31: 7 | J31: 1 | K31: TS
B32: 45057 | C32: 05h15 | D32: Serena Di Cecilia | E32: 212 | F32: Hotel-Aeroporto | G32: SunDestiny | H32: 25 | I32: 7 | J32: 1 | K32: AR
B33: 45057 | C33: 11h15 | D33: Joohan Soo | F33: Aeroporto-Hotel | G33: SunDestiny | H33: 35 | I33: 5 | J33: 1 | K33: FP
B34: 45057 | C34: 11h30 | D34: Diana Seruga Sagadin | E34: 410 | F34: Hotel-Aeroporto | G34: SunDestiny | H34: 25 | I34: 7 | J34: 2 | K34: AS
B35: 45058 | C35: 05h10 | D35: Gerson | E35: 402 | F35: Hotel-Aeroporto | G35: SunDestiny | H35: 25 | I35: 7 | J35: 2 | K35: GB
B36: 45058 | C36: 14h00 | D36: Rajeshkumar Mistry | E36: 303 | F36: Hotel-Aeroporto | G36: SunDestiny | H36: 25 | I36: 7 | J36: 2 | K36: AS
B37: 45058 | C37: 13h34 | D37: Caroline O'Brien | F37: Aeroporto-Hotel | G37: SunDestiny | H37: 35 | I37: 5 | J37: 2 | K37: AR
B38: 45059 | C38: 08h20 | D38: Steve Taylor | F38: Aeroporto-Hotel | G38: SunDestiny | H38: 35 | I38: 5 | J38: 2 | K38: AS
B39: 45059 | C39: 05h30 | D39: Gbrmazur Nataliia | E39: 407 | F39: Hotel-Aeroporto | G39: SunDestiny | H39: 25 | I39: 7 | J39: 1 | K39: DT/TS
B40: 45059 | C40: 11h00 | D40: Peter Worley | F40: Aeroporto-Hotel | G40: SunDestiny | H40: 35 | I40: 5 | J40: 2 | K40: DT/TS
B41: 45059 | C41: 08h20 | D41: Theresa Oberle | F41: Aeroporto-Hotel | G41: SunDestiny | H41: 50 | I41: 10 | J41: 4 | K41: AR
B42: 45060 | C42: 09h25 | D42: Sarah Kirk | F42: Aeroporto-Hotel | G42: SunDestiny | H42: 35 | I42: 5 | J42: 2 | K42: AR
B43: 45060 | C43: 09h55 | D43: Matt Brown | F43: Aeroporto-Hotel | G43: SunDestiny | H43: 35 | I43: 5 | J43: 2 | K43: FP
B44: 45060 | C44: 21h30 | D44: Bone Tomer Haim | E44: 408 | F44: Hotel-Aeroporto | G44: SunDestiny | H44: 40 | I44: 10 | J44: 4 | K44: TS/DT
B45: 45060 | C45: 10h30 | D45: Brian Fyock | F45: Aeroporto-Hotel | G45: SunDestiny | H45: 50 | I45: 10 | J45: 3 | K45: GB
B46: 45060 | C46: 16h20 | D46: Päivi Siekkinen | F46: Aeroporto-Hotel | G46: SunDestiny | H46: 35 | I46: 5 | J46: 2 | K46: GB
B47: 45061 | C47: 05h30 | D47: Paul Kehoe | F47: Aeroporto-Hotel | G47: SunDestiny | H47: 35 | I47: 5 | J47: 2 | K47: DO
B48: 45061 | C48: 08h00 | D48: Gary Olmeim | F48: Hotel-Aeroporto | G48: SunDestiny | H48: 25 | I48: 7 | J48: 2 | K48: AR
B49: 45061 | C49: 04h30 | D49: Pena Macher Helga Estefania | E49: 316 | F49: Hotel-Aeroporto | G49: SunDestiny | H49: 25 | I49: 7 | J49: 1 | K49: TS
B50: 45061 | C50: 17h55 | D50: Steve Hoefer | F50: Aeroporto-Hotel | G50: SunDestiny | H50: 35 | I50: 5 | J50: 2 | K50: GB
B51: 45061 | C51: 15h00 | D51: Terry Bennet | F51: Aeroporto-Hotel | G51: SunDestiny | H51: 35 | I51: 5 | J51: 2 | K51: AS
B52: 45061 | C52: 20h20 | D52: Sveinn | F52: Aeroporto-Hotel | G52: SunDestiny | H52: 70 | I52: 10 | J52: 6 | K52: AS
B53: 45061 | C53: 15h00 | D53: Brian O'Brien | F53: Hotel-Aeroporto | G53: SunDestiny | H53: 25 | I53: 7 | J53: 2 | K53: AR
B54: 45063 | C54: 05h30 | D54: Raymond Hoagland | E54: 203 | F54: Hotel-Aeroporto | G54: SunDestiny | H54: 25 | I54: 7 | J54: 1 | K54: AR
B55: 45063 | C55: 07h30 | D55: Lan Zheng | E55: 301 | F55: Hotel-Aeroporto | G55: SunDestiny | H55: 25 | I55: 7 | J55: 1 | K55: AR
B56: 45063 | C56: 08h00 | D56: Janet Reiss | E56: 309 | F56: Hotel-Aeroporto | G56: SunDestiny | H56: 25 | I56: 7 | J56: 2 | K56: AR
B57: 45064 | C57: 07h30 | D57: Robert Wellins | E57: 207 | F57: Hotel-Aeroporto | G57: SunDestiny | H57: 25 | I57: 7 | J57: 2 | K57: AR
B58: 45064 | C58: 07h40 | D58: Valérie Siffert Belmejdoub | F58: Aeroporto-Hotel | G58: SunDestiny | H58: 35 | I58: 5 | J58: 2 | K58: AR
B59: 45064 | C59: 08h30 | D59: Jonsson | E59: 210+211 | F59: Hotel-Aeroporto | G59: SunDestiny | H59: 30 | I59: 7.5 | J59: 4 | K59: DO
B60: 45065 | C60: 07h00 | D60: Sveinn Kristinn Oegmundsson | E60: 401 | F60: Hotel-Aeroporto | G60: SunDestiny | H60: 40 | I60: 10 | J60: 6 | K60: DT
B61: 45065 | C61: 08h00 | D61: Kathryn Demby | F61: Aeroporto-Hotel | G61: SunDestiny | H61: 35 | I61: 5 | J61: 2 | K61: GB
B62: 45065 | C62: 11h50 | D62: Rick Donalson | F62: Aeroporto-Hotel | G62: SunDestiny | H62: 35 | I62: 5 | J62: 2 | K62: AR
B63: 45066 | C63: 06h00 | D63: Rute Silva | E63: 401 | F63: Hotel-Aeroporto | G63: SunDestiny | H63: 25 | I63: 7 | J63: 2 | K63: AS
B64: 45066 | C64: 09h30 | D64: Steven Hoefer | E64: 302 | F64: Hotel-Aeroporto | G64: SunDestiny | H64: 25 | I64: 7 | J64: 2 | K64: AS/TS
B65: 45066 | C65: 13h40 | D65: Serafina Guanci | F65: Aeroporto-Hotel | G65: SunDestiny | H65: 35 | I65: 5 | J65: 2 | K65: DT/TS
B66: 40683 | C66: 11h00 | D66: Lisa South | F66: Aeroporto-Hotel | G66: SunDestiny | H66: 35 | I66: 5 | J66: 2 | K66: DT/TS
B67: 45066 | C67: 16h00 | D67: Karine Claudine Jacqueline | E67: 212 | F67: Hotel-Aeroporto | G67: SunDestiny | H67: 25 | I67: 7 | J67: 2 | K67: DT
B68: 45066 | C68: 22h25 | D68: Valerie Doherty | F68: Aeroporto-Hotel | G68: SunDestiny | H68: 35 | I68: 5 | J68: 2 | K68: AR
B69: 45067 | C69: 04h45 | D69: Beata Sabina Podgorska | E69: 206 | F69: Hotel-Aeroporto | G69: SunDestiny | H69: 25 | I69: 7 | J69: 1 | K69: TS
B70: 45067 | C70: 05h00 | D70: juan marcelo | E70: 406 | F70: Hotel-Aeroporto | G70: SunDestiny | H70: 25 | I70: 7 | J70: 2 | K70: DT
B71: 40684 | C71: 08h20 | D71: Michael Benning | F71: Aeroporto-Hotel | G71: SunDestiny | H71: 35 | I71: 5 | J71: 3 | K71: DT/TS
B72: 45067 | C72: 09h00 | D72: elise cullis | E72: 208 | F72: Hotel-Aeroporto | G72: SunDestiny | H72: 25 | I72: 7 | J72: 2 | K72: DT
B73: 45067 | C73: 17h55 | D73: Nicolle Thomas | F73: Aeroporto-Hotel | G73: SunDestiny | H73: 35 | I73: 5 | J73: 2 | K73: FP
B74: 45067 | C74: 18h00 | D74: Janet Hanpeter | F74: Aeroporto-Hotel | G74: SunDestiny | H74: 35 | I74: 5 | J74: 1 | K74: TS
B75: 45067 | C75: 11h00 | D75: Valerie Siffert | E75: 202 | F75: Hotel-Aeroporto | G75: SunDestiny | H75: 25 | I75: 7 | J75: 2 | K75: DT
B76: 45068 | C76: 12h00 | D76: linda everett | E76: 304 | F76: Hotel-Cruise | G76: SunDestiny | H76: 40 | I76: 10 | J76: 6 | K76: CB
B77: 45068 | C77: 12h15 | D77: Elaine | E77: 412+309 | F77: Hotel-Oriente | G77: SunDestiny | H77: 30 | I77: 7.5 | J77: 4 | K77: CB
B78: 45069 | C78: 06h15 | D78: Yolanda Ribeiro | E78: 308 | F78: Hotel-Aeroporto | G78: SunDestiny | H78: 40 | I78: 10 | J78: 3 | K78: DT
B79: 45070 | C79: 11h15 | D79: Marilyn Cowe | F79: Aeroporto-Hotel | G79: SunDestiny | H79: 35 | I79: 5 | J79: 1 | K79: FP
B80: 45070 | C80: 15h35 | D80: Kim Henzi | F80: Aeroporto-Hotel | G80: SunDestiny | H80: 35 | I80: 5.002 | J80: 2 | K80: AR
B81: 45070 | C81: 21h40 | D81: Valerie Walter | F81: Aeroporto-Hotel | G81: SunDestiny | H81: 35 | I81: 5 | J81: 2 | K81: AR
B82: 45071 | C82: 08h00 | D82: Kimberlee Henzi | E82: 316 | F82: Hotel-Santa Apolónia | G82: SunDestiny | H82: 25 | I82: 7 | J82: 2 | K82: AR
B83: 45071 | C83: 21h00 | D83: Wael Altaher | F83: Aeroporto-Hotel | G83: SunDestiny | H83: 35 | I83: 5 | J83: 2 | K83: FP
B84: 45072 | C84: 03h00 | D84: Mark Irvine | E84: 303 | F84: Hotel-Aeroporto | G84: SunDestiny | H84: 25 | I84: 7 | J84: 2 | K84: AR
B85: 45072 | C85: 08h00 | D85: David Sells | E85: 402 | F85: Hotel-Aeroporto | G85: SunDestiny | H85: 25 | I85: 7 | J85: 2 | K85: AS
B86: 45072 | C86: 09h10 | D86: Talia Yerushalmy | F86: Aeroporto-Hotel | G86: SunDestiny | H86: 35 | I86: 5 | J86: 2 | K86: CB
B87: 45073 | C87: 08h00 | D87: Melissa Scott | F87: Aeroporto-Hotel | G87: SunDestiny | H87: 35 | I87: 5 | J87: 2 | K87: DT
B88: 45073 | C88: 13h30 | D88: Carin Anderson | F88: Aeroporto-Hotel | G88: SunDestiny | H88: 50 | I88: 10 | J88: 4 | K88: AR
B89: 45073 | C89: 14h50 | D89: Carin Anderson | F89: Aeroporto-Hotel | G89: SunDestiny | H89: 35 | I89: 5 | J89: 2 | K89: AR
B90: 45074 | C90: 04h00 | D90: António Figueiredo | E90: 206 | F90: Hotel-Aeroporto | G90: SunDestiny | H90: 40 | I90: 10 | J90: 6 | K90: CB
B91: 45074 | C91: 08h20 | D91: Elizabeth Dutro | F91: Aeroporto-Hotel | G91: SunDestiny | H91: 35 | I91: 5 | J91: 2 | K91: DT
B92: 45074 | C92: 08h00 | D92: Wael Altaher | E92: 304 | F92: Hotel-Aeroporto | G92: SunDestiny | H92: 25 | I92: 7 | J92: 2 | K92: AS
B93: 45074 | C93: 13h00 | D93: Carin Anderson | F93: Hotel-Aeroporto | G93: SunDestiny | H93: 40 | I93: 10 | J93: 6 | K93: AS
B94: 45075 | C94: 08h00 | D94: Sarah Schiff | F94: Aeroporto-Hotel | G94: SunDestiny | H94: 50 | I94: 10 | J94: 4 | K94: AR
B95: 45075 | C95: 10h20 | D95: Richard Loerch | F95: Aeroporto-Hotel | G95: SunDestiny | H95: 35 | I95: 5 | J95: 2 | K95: CB
B96: 45076 | C96: 08h15 | D96: Kimberlee Henzi | E96: 215 | F96: Hotel-Aeroporto | G96: SunDestiny | H96: 25 | I96: 7 | J96: 2 | K96: CB
B97: 45076 | C97: 09h20 | D97: Tara Morrow | F97: Aeroporto-Hotel | G97: SunDestiny | H97: 35 | I97: 5 | J97: 2 | K97: CB
B98: 45076 | C98: 10h20 | D98: Lyons | E98: 205 | F98: Hotel-Aeroporto | G98: SunDestiny | H98: 25 | I98: 7 | J98: 2 | K98: DO
B99: 45076 | C99: 10h30 | D99: Melissa Scott | E99: 204 | F99: Hotel-Car Rental Aero | G99: SunDestiny | H99: 25 | I99: 7 | J99: 2 | K99: AR
B100: 45077 | C100: 16h25 | D100: Shelly Bidvia | F100: Aeroporto-Hotel | G100: SunDestiny | H100: 35 | I100: 5 | J100: 2 | K100: AR
B101: 45077 | C101: 06h15 | D101: Michela Falcon | E101: 408 | F101: Hotel-Aeroporto | G101: SunDestiny | H101: 25 | I101: 7 | J101: 2 | K101: TS
B102: 45077 | C102: 05h20 | D102: Nancy Bowerman | E102: 201 | F102: Hotel-Aeroporto | G102: SunDestiny | H102: 30 | I102: 7.5 | J102: 4 | K102: DO
...

Sheet Toursss
B2: Data | C2: Horas | D2: Cliente | E2: Quarto | F2: Serviço | G2: Empresa | H2: Valor | I2: Comissão | J2: Nº pax
B3: 44930 | C3: 08h10 | D3: Christelle Vacilotto | E3: 410 | F3: Tour Sintra | G3: Where To | H3: 130 | I3: 39 | J3: 2 | K3: AR
B4: 44931 | C4: 08h00 | D4: José Luis Fraile | E4: 201 + 205 | F4: Tour Sintra | G4: Where To | H4: 260 | I4: 78 | J4: 4 | K4: Ana
B5: 44944 | C5: 08h15 | D5: John Fanner | E5: 302 | F5: Tour Fatima | G5: Where To | H5: 158 | I5: =+H5*0.3 -> 47.4 | J5: 2 | K5: DO
B6: 44948 | C6: 08h15 | D6: Corina | E6: 208 + 216 | F6: Tour Sintra | G6: Celina | H6: 300 | I6: 75 | J6: 4 | K6: AS
B7: 44986 | C7: 08h00 | D7: Sally Sommonds | E7: 311 | F7: Tour Sintra | G7: Where To | H7: 130 | I7: 39 | J7: 2 | K7: CB/AR
B8: 44988 | C8: 08h20 | D8: Thomas Briola | E8: 415 | F8: Tour Fátima | G8: Where To | H8: 158 | I8: 47.4 | J8: 2 | K8: AR
B9: 45006 | C9: 08h15 | D9: Chantal Guiguere | E9: 208 + 210 | F9: Tour Sintra | G9: Where To | H9: 130 | I9: 39 | J9: 2 | K9: AS
B10: 45008 | C10: 08h15 | D10: Elad Cohen | E10: 408 | F10: Tour Sintra | G10: Where To | H10: 65 | I10: 19.5 | J10: 1 | K10: AS
B11: 45010 | C11: 08h30/09h | D11: Gian Luca Casolari | E11: 407 | F11: Tour Sintra | G11: Yellow Cab | H11: 118 | I11: 33 | J11: 2 | K11: AR
B12: 45011 | C12: 08h30/09h | D12: Ece Demirkir Cakir | E12: 412 | F12: Tour Sintra | G12: Yellow Cab | H12: 59 | I12: 16.5 | J12: 1 | K12: AR
B13: 45014 | C13: 08h15 | D13: Silvia Licini | E13: 215 | F13: Tour Sintra | G13: Where To | H13: 130 | I13: 39 | J13: 2 | K13: DO
B14: 45020 | C14: 08h30/09h | D14: Ali Paydas | E14: 216 | F14: Tour Sintra | G14: Yellow Cab | H14: 118 | I14: 33 | J14: 2 | K14: AR
B15: 45021 | C15: 08h30/09h | D15: Gerald Schneider | E15: 316 | F15: Tour Sintra | G15: Yellow Cab | H15: 118 | I15: 33 | J15: 2 | K15: DO | M15: COMISSÃO VOX CITY: 20% (TOURS, TUK, BOATS, ESCAPE HUNT, ETC..)
B16: 45029 | C16: 08h30/09h | D16: Aasne Bjornsen | E16: 304 | F16: Tour Sintra | G16: Yellow Cab | H16: 118 | I16: 33 | J16: 2 | K16: TS
B17: 45034 | C17: 08h30/09h | D17: Eliana Marques | E17: 208 | F17: Tour Fátima | G17: Yellow Cab | H17: 148 | I17: 35 | J17: 2 | K17: AR | M17: COMISSÃO CELINA TOURS: 25%
B18: 45036 | C18: 08h30/09h | D18: Eliana Marques | E18: 208 | F18: Tour Sintra | G18: Yellow Cab | H18: 118 | I18: 33 | J18: 2 | K18: AR
B19: 45039 | C19: 08h30/09h | D19: Zhiyong He | E19: 402 | F19: Tour Sintra | G19: Yellow Cab | H19: 118 | I19: 33 | J19: 2 | K19: AS | M19: COMISSÃO WHERE TO: 30%
B20: 45047 | C20: 08h00 | D20: Carmen | E20: 203 | F20: Tour Sintra | G20: Where To | H20: 130 | I20: 39 | J20: 2 | K20: CB
B21: 45055 | C21: 08h00 | D21: Sherer | E21: 316 + 415 | F21: Tour Sintra | G21: Where To | H21: 236 | I21: =+H21*0.3 -> 70.8 | J21: 4 | K21: AS | M21: COMISSÃO YELLOW CAB:
B22: 45063 | C22: 08h30/09h | D22: Marcia Lacerda | E22: 409 | F22: Tour Sintra | G22: Yellow Cab | H22: 118 | I22: 33 | J22: 2 | K22: DO
B23: 45067 | C23: 08h30/09h | D23: Serafina Guanci | E23: 403 | F23: Tour Sintra | G23: Yellow Cab | H23: 118 | I23: 33 | J23: 2 | K23: TS/CB
B24: 45070 | C24: 08h30/09h | D24: Alejandro Lara | E24: 211 | F24: Tour Fátima | G24: Yellow Cab | H24: 148 | I24: 35 | J24: 2 | K24: AR
B25: 45072 | C25: 08h00 | D25: Shaw | E25: 409 + 412 | F25: Tour Sintra | G25: Where To | H25: 236 | I25: 70.8 | J25: 4 | K25: CB
B26: 45082 | C26: 08h30/09h | D26: Jean Rosemarie Maver | E26: 209 | F26: Tour Sintra | G26: Yellow Cab | H26: 118 | I26: 33 | J26: 2 | K26: TS
B27: 45092 | C27: 08h30/09h | D27: Elizabeth De Amorim Bueno Vieira | E27: 411 | F27: Tour Fátima | G27: Yellow Cab | H27: 148 | I27: 35 | J27: 2 | K27: TS
B28: 45106 | C28: 08h30/09h | D28: Julia Krottenhart | E28: 410 | F28: Tour Sintra | G28: Yellow Cab | H28: 118 | I28: 33 | J28: 2 | K28: TS
B29: 45117 | C29: 08h30/09h | E29: 315 | F29: Tour Sintra | G29: Yellow Cab | H29: 127.5 | I29: 49.5 | J29: 3 | K29: CB
B30: 45131 | C30: 08h30/09h | D30: Renad Alowayyid | E30: 302 | F30: Tour Sintra | G30: Yellow Cab | H30: 118 | I30: 33 | J30: 2 | K30: AR
B31: 45136 | C31: 08h15 | D31: Penelope White / Thomas White | E31: 408 | F31: Tour Sintra | G31: Where To | H31: 130 | I31: 39 | J31: 2 | K31: TS/IC
B32: 45138 | C32: 08h15 | D32: Cláudia Valredo | E32: 208 + 210 | F32: Tour Sintra | G32: Where To | H32: 236 | I32: 70.8 | J32: 4 | K32: AR/TS
B33: 45139 | C33: 08h15 | D33: Cláudia Valredo | E33: 208 + 210 | F33: Tour Fatima | G33: Where To | H33: 300 | I33: =H33*30% -> 90 | J33: 4 | K33: AR/TS
B34: 45147 | C34: 08h30 | D34: Deborah Kane | E34: 412 | F34: Tour Sintra | G34: Yellow Cab | H34: 59 | I34: 16.5 | J34: 1 | K34: TS/JG
B35: 45154 | C35: 08h30h/09h | D35: Daniel Brickman | E35: 409 | F35: Tour Sintra | G35: Yellow Cab | H35: 118 | I35: 33 | J35: 2 | K35: AR
B36: 45156 | C36: 08h30 | D36: Rene | E36: 206 | F36: Tour Sintra | G36: Yellow Cab | H36: 118 | I36: 33 | J36: 2 | K36: AS/IC
B37: 45160 | C37: 08h15 | D37: Jean Pimlett | E37: 302 | F37: Tour Sintra | G37: Where To | H37: 130 | I37: 39 | J37: 2 | K37: DO
B38: 45170 | C38: 08h10 | D38: Sarrasin Justin | E38: 406 | F38: Tour Sintra | G38: Where To | H38: 130 | I38: 39 | J38: 2 | K38: JG
B39: 45174 | C39: 08h20 | D39: Linqa Jfan Yomng | E39: 207 | F39: Tour Fátima | G39: Yellow Cab | H39: 148 | I39: 35 | J39: 2 | K39: JG
B40: 45174 | C40: 08h30/09h | D40: Philip Lewis | E40: 311 | F40: Tour Sintra | G40: Yellow Cab | H40: 118 | I40: 33 | J40: 2 | K40: AR
B41: 45175 | C41: 08h20 | D41: Mohamed Bouchlain | E41: 303 | F41: Tour Sintra | G41: Where To | H41: 130 | I41: 39 | J41: 2 | K41: DO
B42: 45178 | C42: 08h20 | D42: Jodianne Carter | E42: 207 | F42: Tour Sintra | G42: Where To | H42: 295 | I42: 88.5 | J42: 5 | K42: JG
B43: 45183 | C43: 08h30/09h | D43: Vikki Lynn McLawhorn | E43: 304 | F43: Tour Sintra | G43: Yellow Cab | H43: 118 | I43: 33 | J43: 2 | K43: AR
B44: 45184 | C44: 08h10 | D44: Lisa Grimaudo | E44: 416 | F44: Tour Sintra | G44: Where To | H44: 130 | I44: 39 | J44: 2 | K44: JG
B45: 45185 | C45: 08h00 | D45: Albert Ramage | E45: 204 | F45: Tour Sintra | G45: Where To | H45: 130 | I45: 39 | J45: 2 | K45: JG
... B49: 45204 | C49: 08h30/09h | D49: Ross Robert Bayus | E49: 315 | F49: Tour Sintra | G49: Yellow Cab | H49: 118 | I49: 33 | J49: 2 | K49: TS/CB
B50: 45205 | C50: 08h30h/09h | D50: Janie Lanteigne | E50: 408 + 410 | F50: Tour Sintra | G50: Yellow Cab | H50: 236 | I50: 66 | J50: 2 | K50: AS/AR
B51: 45223 | C51: 08h30/09h | D51: Froilan Mujica | E51: 411 | F51: Tour Sintra | G51: Yellow Cab | H51: 59 | I51: 16.5 | J51: 1 | K51: CB/AR
B52: 45228 | C52: 09h00 | E52: 202+302+316 | F52: Tour Sintra | G52: Yellow Cab | H52: 390 | I52: 70 | J52: 6 | K52: IC/AS
B53: 45230 | C53: 08h00 | D53: David Chua | E53: 403 + 411 + 416 | F53: Tour Sintra | G53: Where To | H53: 236 | I53: 70.8 | J53: 4 | K53: AS
B54: 45231 | C54: 08h00 | D54: David Chua | E54: 403 + 411 + 416 | F54: Tour Fátima | G54: Where To | H54: 300 | I54: 90 | J54: 4 | K54: AS
B55: 45231 | C55: 08h15 | D55: Richard Simchik | E55: 201 | F55: Tour Fátima | G55: Celina Tours | H55: 178 | I55: 44.5 | J55: 2 | K55: AR
B56: 45232 | C56: 08h30 | E56: 401 | F56: Tour Fátima | G56: Yellow Cab | H56: =74+74 -> 148 | I56: =17.5+17.5 -> 35 | J56: 2 | K56: CB
B57: 45236 | C57: 08h00 | D57: Wu Ming | E57: 309 | F57: Tour Sintra | G57: Where To | H57: 130 | I57: 39 | J57: 2 | K57: IC
B58: 45238 | C58: 08h00 | D58: Winstay Lewis | E58: 216 + 307 | F58: Tour Fátima | G58: Where To | H58: 300 | I58: 90 | J58: 4 | K58: IC
B59: 45243 | C59: 08h00 | D59: Eshtela Estrada | E59: 401 | F59: Tour Fátima | G59: Where To | H59: 158 | I59: 47.4 | J59: 2 | K59: AS
B60: 45248 | C60: 08h15 | D60: Giacomo Fideli | E60: 210 | F60: Tour Sintra | G60: Where To | H60: 130 | I60: 39 | J60: 2 | K60: IC
B61: 45248 | C61: 08h15 | D61: Josefa Ribas | E61: 316 | F61: Tour Sintra | G61: Where To | H61: 130 | I61: 39 | J61: 2 | K61: IC
B62: 45250 | D62: 206+306+209 | F62: Tour Fatima | G62: Where To | H62: 450 | I62: =H62*0.3 -> 135 | J62: 6 | K62: IC
B63: 45253 | C63: 08h15 | D63: Ioana Tamas | E63: 408 | F63: Tour Sintra | G63: Where To | H63: 130 | I63: 39 | J63: 2 | K63: IC
B64: 45256 | C64: 08h00 | D64: Wassim Bekhit | E64: 311 | F64: Tour Sintra | G64: Where To | H64: 65 | I64: 19.5 | J64: 1 | K64: IC/AS
B65: 45264 | C65: 08h15 | D65: Vivian Caldeirin | E65: 211 | F65: Tour Sintra | G65: Where To | H65: 130 | I65: 39 | J65: 2 | K65: IC
B66: 45267 | C66: 08h30 | D66: Diego e Ana Barbara | E66: passantes | F66: Tour Fatima | G66: Yellow Cab | H66: 148 | I66: 35 | J66: 2 | K66: CB
B67: 45288 | C67: 08h00 | D67: Kheith Otoole | E67: 206 | F67: Tour Sintra | G67: Where To | H67: 130 | I67: 39 | J67: 2 | K67: IC
B68: 45293 | C68: 08h10 | D68: leung | E68: 208+212 | F68: Tour Sintra | G68: Where To | H68: 300 | I68: 90 | J68: 4 | K68: CB
B69: 45297 | C69: 08h15 | D69: Amy Alderman | E69: 401 | F69: Tour Sintra | G69: Where To | H69: 65 | I69: 19.5 | J69: 1 | K69: TS
B70: 45338 | C70: 09h00 | D70: Nora Bauland | E70: 415 | F70: Tour Sintra | G70: Yellow Cab | H70: 210 | I70: 40 | J70: 2 | K70: IC
B71: 45340 | C71: 08h15 | D71: Stephanie Lapidus | E71: 207 + 307 | F71: Tour Sintra | G71: Where To | H71: 130 | I71: 39 | J71: 2 | K71: TS
B72: 45342 | C72: 08h30 | E72: 211 | F72: Tour Sintra | G72: Yellow Cab | H72: 118 | I72: 33 | J72: 2 | K72: AS
B73: 45344 | C73: 08h10 | D73: Mohamad Samer Basheer | E73: 204 | F73: Tour Sintra | G73: Where To | H73: 98 | I73: 42 | J73: 1 | K73: IC
B74: 45345 | C74: 08h00 | F74: Tour Fátima
B75: 45345 | C75: 08h00 | E75: 209+212 | F75: Tour Sintra | G75: Where To | H75: 123.9 | I75: 53.1 | J75: 3 | K75: IC
B76: 45354 | C76: 08h15 | D76: Jan Bastiaan | E76: 201 | F76: Tour Sintra | G76: Where To | H76: 130 | I76: 39 | J76: 2 | K76: TS
B77: 45361 | C77: 08h30 | D77: Anastasiia Tochenaia | E77: 101 | F77: Tour Sintra | G77: Yellow Cab | H77: 130 | I77: =19+19 -> 38 | J77: 2 | K77: CB
B78: 45362 | C78: 08h00 | E78: 406 | F78: Tour Sintra | G78: Where To | H78: 65 | I78: 19.5 | J78: 1 | K78: CB
B79: 45362 | C79: 08h00 | D79: Octavio Perez | E79: 404 | F79: Tour Fátima | G79: Where To | H79: 158 | I79: 47.4 | J79: 2 | K79: IC
B80: 45370 | C80: 08h30 | D80: Orso Vincenzo | E80: 406 | F80: Tour Sintra | G80: Yellow Cab | H80: 130 | I80: =19+19 -> 38 | J80: 2 | K80: TS
H90: =SUM(H4:H88) -> 11741.4 | I90: =SUM(I4:I88) -> 3355.9

Sheet Gratificações
A1: JANEIRO | E1: FEVEREIRO | I1: MARÇO | M1: ABRIL | Q1: MAIO | U1: JUNHO | Y1: JULHO | AC1: AGOSTO | AG1: SETEMBRO | AK1: OUTUBRO | AO1: NOVEMBRO | AS1: DEZEMBRO | AW1: Janeiro | BA1: Fevereiro | BE1: Março | BI1: Abril | BM1: Maio | BQ1: Junho | BU1: Julho | BY1: Agosto | CC1: Setembro | CG1: Outubro | CK1: Novembro | CO1: Dezembro | CS1: Janeiro 2025 | CW1: Fevereiro 2025 | DA1: Março 2025 | DE1: 16 Setembro 25 A 15 Outubro 25 | DJ1: 15 Outubro 25 A 15 Novembro 25 | DT1: 16 Setembro 25 A 15 Outubro 25
A2: Data | B2: Designação | C2: Valor | D2: Recepcionista | E2: Data | F2: Designação | G2: Valor | H2: Recepcionista | I2: Data | J2: Designação | K2: Valor | L2: Recepcionista | M2: Data | N2: Designação | O2: Valor | P2: Recepcionista | Q2: Data | R2: Designação | S2: Valor | T2: Recepcionista | U2: Data | V2: Designação | W2: Valor | X2: Recepcionista | Y2: Data | Z2: Designação | AA2: Valor | AB2: Recepcionista | AC2: Data | AD2: Designação | AE2: Valor | AG2: Data | AH2: Designação | AI2: Valor | AJ2: Recepcionista | AK2: Data | AL2: Designação | AM2: Valor | AN2: Recepcionista | AO2: Data | AP2: Designação | AQ2: Valor | AR2: Recepcionista | AS2: Data | AT2: Designação | AU2: Valor | AV2: Recepcionista | AW2: Data | AX2: Designação | AY2: Valor | AZ2: Recepcionista | BA2: Data | BB2: Designação | BC2: Valor | BD2: Recepcionista | BE2: Data | BF2: Designação | BG2: Valor | BH2: Recepcionista | BI2: Data | BJ2: Designação | BK2: Valor | BL2: Recepcionista | BM2: Data | BN2: Designação | BO2: Valor | BP2: Recepcionista | BQ2: Data | BR2: Designação | BS2: Valor | BT2: Recepcionista | BU2: Data | BV2: Designação | BW2: Valor | BX2: Recepcionista | BY2: Data | BZ2: Designação | CA2: Valor | CB2: Recepcionista | CC2: Data | CD2: Designação | CE2: Valor | CF2: Recepcionista | CG2: Data | CH2: Designação | CI2: Valor | CJ2: Recepcionista | CK2: Data | CL2: Designação | CM2: Valor | CN2: Recepcionista | CO2: Data | CP2: Designação | CQ2: Valor | CR2: Recepcionista | CS2: Data | CT2: Designação | CU2: Valor | CV2: Recepcionista | CW2: Data | CX2: Designação | CY2: Valor | CZ2: Recepcionista | DA2: Data | DB2: Designação | DC2: Valor | DD2: Recepcionista | DE2: data | DF2: Designação | DG2: Valor | DH2: Recepcionista | DJ2: Recepcionista | DK2: Data | DL2: Designação | DM2: Valor | DN2: Recepcionista | DO2: Data | DP2: Designação | DQ2: Valor | DR2: Recepcionista | DT2: data | DU2: Designação | DV2: Valor | DW2: Recepcionista | DX2: Total comissão | DY2: =+DQ47+DY7+DY8+DY9+DY10+DY6+EB2+DY11 -> 55.31 | EA2: Sobras Tips | EB2: 121.79
A3: 44928 | B3: Where To Comissão | C3: 39 | D3: Andreia | E3: 44958 | F3: Saldo Janeiro | G3: =+C72-C103 -> 1.85 | H3: Daniela | I3: 44986 | J3: Saldo Fevereiro | K3: 0.72 | L3: Daniela | M3: 44986 | N3: Saldo Março | O3: 0.95 | P3: Daniela | Q3: 44986 | R3: Saldo Março | S3: =1171.13-1168 -> 3.13 | T3: Daniela | U3: 45078 | V3: Saldo Maio | W3: 3.67 | X3: Daniela | Y3: 45118 | Z3: Saldo Julho | AA3: 10.67 | AB3: Afonso/Andreia | AC3: 45144 | AD3: Comissão DSCAR | AE3: 18 | AF3: Afonso/Andreia | AG3: 45170 | AH3: TIP 212 | AI3: 10 | AJ3: Afonso | AK3: 45200 | AL3: TIP 316 | AM3: 4 | AN3: Inês | AO3: 45231 | AP3: Celina tours comissão | AQ3: 44.5 | AR3: Cristiana | AS3: 45263 | AT3: TIP Passante | AU3: 5 | AV3: Afonso | AW3: 45293 | AX3: TIP 101 | AY3: 2 | AZ3: Tomás | BA3: 45324 | BB3: Comissão Cooptáxis | BC3: 2.02 | BD3: Andreia/Inês | BE3: 45354 | BF3: Comissão Where To | BG3: 39 | BH3: Afonso/Tomás | BI3: 45385 | BJ3: Comissão Monte Mar | BK3: 10 | BL3: Andreia | BM3: 45413 | BN3: tip 216 | BO3: 5 | BP3: Cris | BQ3: 45444 | BR3: Sofá | BS3: 1.5 | BT3: Renato | BU3: 45474 | BV3: Comissão YellowCab | BW3: 38 | BX3: Tomás | BY3: 45505 | BZ3: Comissão YellowCab | CA3: 40 | CB3: Afonso | CC3: 45537 | CD3: Comissao Yellow Cab | CE3: 40 | CF3: Inês | CG3: 45566 | CH3: WC | CI3: 0.5 | CJ3: Cris | CK3: 45597 | CL3: TIP 416 | CM3: 10 | CN3: Afonso | CO3: 45630 | CP3: TIP 316 | CQ3: 4 | CR3: Inês | CS3: 45659 | CT3: TIP SOFÁ | CU3: 2 | CV3: Afonso | CW3: 45694 | CX3: TIP 307 | CY3: 10 | CZ3: Afonso | DA3: 45720 | DB3: TIP | DC3: 10 | DD3: Inês | DE3: 45916 | DF3: Sobra o mês passado | DG3: 5.5 | DH3: Pedro | DO3: 45992 | DP3: A mais | DQ3: 108.5 | DR3: Erica | DX3: Número de recepcionistas | DY3: 10 | EA3: Falta repor | EB3: 738.8
A4: 44930 | B4: Tip 405 | C4: 1 | D4: Daniela | E4: 44958 | F4: TIP 306 | G4: 1.5 | H4: Daniela | I4: 44986 | J4: Comissão Where To | K4: 39 | L4: Daniela | M4: 45017 | N4: tip 205 | O4: 10.1 | P4: Cristiana | Q4: 45048 | R4: TIP #201 | S4: 3 | T4: Andreia | U4: 45078 | V4: TIP 315 | W4: 5 | X4: Cristiana | Y4: 45110 | Z4: TIP 203 | AA4: 5 | AB4: Afonso/Andreia | AC4: 45145 | AD4: TIP 307 | AE4: 5 | AF4: Tomás/Joana/Andreia | AG4: 45171 | AH4: TIP 415 | AI4: 5 | AJ4: Afonso | AK4: 45201 | AL4: TIP 308 | AM4: 5 | AN4: Inês | AO4: 45231 | AP4: Yellow Cab Fatima | AQ4: 35 | AR4: Cristiana | AS4: 45264 | AT4: Comissao Where to | AU4: 39 | AV4: Inês | AW4: 45292 | AX4: TIP 104 | AY4: 10 | AZ4: Cris | BA4: 45327 | BB4: Comissão Where To | BC4: 19.5 | BD4: Tomás | BE4: 45354 | BF4: Valor de sobra do mês passado | BG4: 8 | BH4: Afonso | BI4: 45385 | BJ4: TIP 202 | BK4: 2 | BL4: Andreia | BM4: 45413 | BN4: tip 103 | BO4: 2 | BP4: Cris | BQ4: 45446 | BR4: Sofá | BS4: 2 | BT4: Andreia | BU4: 45475 | BV4: TIP 316 | BW4: 100 | BX4: Afonso | BY4: 45505 | BZ4: TIP 404 | CA4: 3 | CB4: Cris/Andreia | CC4: 45538 | CD4: TIP 404 | CE4: 2 | CF4: Afonso | CG4: 45566 | CH4: HOSPEDE | CI4: 1.5 | CJ4: Cris | CK4: 45597 | CL4: TIP | CM4: 2 | CN4: Inês | CO4: 45632 | CP4: Impressora | CQ4: 1.5 | CR4: Cris | CS4: 45660 | CT4: TIP Casa de Banho | CU4: 1 | CV4: Afonso | CW4: 45695 | CX4: TIP 315 | CY4: 3 | CZ4: Ivan | DA4: 45720 | DB4: Tour Sintra #206+#209 | DC4: 38 | DD4: Inês/Afonso | DO4: 45993 | DP4: A menos (CitySightSeeing) | DQ4: -27 | DR4: Erica | DX4: Tips p/ pessoa | DY4: =+DY2/DY3 -> 5.531
A5: 44931 | B5: Where To Comissão | C5: 78 | D5: Daniela | E5: 44963 | F5: Falta caixa | G5: -1.13 | H5: Daniela | I5: 44986 | J5: Sobra caixa | K5: 6.12 | L5: Daniela | M5: 45018 | N5: TIP 416 | O5: 11 | P5: Cristiana/Tomás | Q5: 45025 | R5: Falta caixa | S5: -1 | T5: Daniela | U5: 45078 | V5: Fado in Chiado | W5: 6 | X5: Cristiana | Y5: 45110 | Z5: TIP 307 | AA5: 5 | AB5: Afonso/Andreia | AC5: 45146 | AD5: Saldo Julho | AE5: 1.48 | AF5: Daniela | AG5: 45171 | AH5: TIP 104+103 | AI5: 20 | AJ5: Afonso | AK5: 45201 | AL5: Comissão Where To | AM5: 39 | AN5: Afonso/Andreia | AO5: 45233 | AP5: TIP 204 | AQ5: 5 | AR5: Inês | AS5: 45265 | AT5: TIP 302 | AU5: 10 | AV5: Tomás | AW5: 45292 | AX5: Comissão where to | AY5: 90 | AZ5: Cris | BA5: 45329 | BB5: Comissão Trovas Antigas | BC5: 10 | BD5: Cris | BE5: 45354 | BF5: TIP 102 | BG5: 2 | BH5: Cris | BI5: 45385 | BJ5: Tip 316 - assistencia ao # | BK5: 5 | BL5: Cris | BM5: 45413 | BN5: Comissão tour 03/05 | BO5: 41.4 | BP5: Cris | BQ5: 45453 | BR5: TIP 306 | BS5: 30 | BT5: Afonso | BU5: 45476 | BV5: TIP 202 | BW5: 10 | BX5: Inês | BY5: 45506 | BZ5: TIP 315 | CA5: 8 | CB5: Afonso | CC5: 45538 | CD5: TIP 205 | CE5: 4 | CF5: Afonso | CG5: 45567 | CH5: TIP #303 | CI5: 20 | CJ5: Afonso | CK5: 45598 | CL5: Comissão Trovas Antigas | CM5: 35 | CN5: Andreia | CO5: 45633 | CP5: TIP 401 | CQ5: 5.12 | CR5: Afonso | CS5: 45661 | CT5: Comissão tuktuk | CU5: 20 | CV5: Andreia | CW5: 45696 | CX5: A Severa | CY5: 5 | CZ5: Andreia | DA5: 45721 | DB5: TIP 303 | DC5: 2 | DD5: Afonso | DO5: 45994 | DP5: A menos | DQ5: -1.4 | DR5: Helder
A6: 44931 | B6: Tip 312 | C6: 1 | D6: Daniela | E6: 44964 | F6: Comissão A Severa | G6: 20 | H6: Daniela | I6: 44987 | J6: Comissao Where To | K6: 47.4 | L6: Afonso | M6: 45019 | N6: Comissão Yellow Cab | O6: 33 | P6: Daniela/Tomás | Q6: 45051 | R6: TIP #403 | S6: 5.24 | T6: Daniela | U6: 45078 | V6: TIP 316 | W6: 5 | X6: Tomás | Y6: 45110 | Z6: TIP 305 | AA6: 10 | AB6: Afonso/Andreia | AC6: 45146 | AD6: TIP | AE6: 1.7 | AF6: Daniela | AG6: 45172 | AH6: TIP 305 | AI6: 5 | AJ6: Tomás/Andreia | AK6: 45202 | AL6: Comissão Yellow Cab | AM6: 33 | AN6: Tomás/Cristiana | AO6: 45233 | AP6: TIP 405 | AQ6: 5 | AR6: Afonso | AS6: 45265 | AT6: TIP 202 | AU6: 10 | AV6: Afonso | AW6: 45293 | AX6: TIP passante | AY6: =3.3+1.22 -> 4.52 | AZ6: Afonso | BA6: 45329 | BB6: TIP 403 | BC6: 5 | BD6: Cris | BE6: 45356 | BF6: tip 410 | BG6: 3 | BH6: Tomás | BI6: 45386 | BJ6: Tip 316 - assistencia ao # | BK6: 5 | BL6: Cris | BM6: 45414 | BN6: TIP 402 | BO6: 10 | BP6: Andreia | BQ6: 45453 | BR6: Valor dado o mês passado | BS6: -12.88 | BT6: Afonso | BU6: 45476 | BV6: TIP 411 | BW6: 5 | BX6: Inês | BY6: 45507 | BZ6: TIP 405 | CA6: 5 | CB6: Eduardo | CC6: 45540 | CD6: TIP405 | CE6: 10 | CF6: Afonso | CG6: 45569 | CH6: Comissão Where to | CI6: 41.4 | CJ6: Inês | CK6: 45600 | CL6: Tip #303 | CM6: 2 | CN6: Ivan | CO6: 45635 | CP6: VALOR EM SOBRA OUTUBRO | CQ6: 1.48 | CR6: Afonso | CS6: 45663 | CT6: TIP 203 | CU6: 10 | CV6: Afonso | CW6: 45699 | CX6: TIP 315 | CY6: 10 | CZ6: Cris | DA6: 45724 | DB6: Tip 208 | DC6: 2 | DD6: Ivan | DO6: 45994 | DP6: A menos (decorações de natal - A repor) | DQ6: -97.92 | DR6: Erica | DX6: Comissão LS | DY6: =SUMIFS('LS Dez'!J2:J117, 'LS Dez'!C2:C117, "*LS*", 'LS Dez'!L2:L117, "Sim ") -> 118
A7: 44932 | B7: TIP 406 | C7: 2.5 | D7: Afonso | E7: 44971 | F7: TIP 312 | G7: 4 | H7: Cristiana | I7: 44988 | J7: Taxas 201 não lançadas ao c-in | K7: -6 | L7: Cristiana | M7: 45020 | N7: TIP #101 + #104 | O7: 5 | P7: Afonso | Q7: 45052 | R7: TIP #405 | S7: 20 | T7: Afonso | U7: 45078 | V7: Tip 215 | W7: 6 | X7: Tomás | Y7: 45111 | Z7: TIP 316 | AA7: 5 | AB7: Tomás | AC7: 45146 | AD7: Comissão Mar ao Carmo | AE7: 42 | AF7: Tomás | AG7: 45172 | AH7: TIP 405 | AI7: 20 | AJ7: Tomás/Afonso | AK7: 45203 | AL7: Comissão Yellow Cab | AM7: 66 | AN7: Afonso/Andreia | AO7: 45233 | AP7: TIP 208 | AQ7: 20 | AR7: Afonso | AS7: 45265 | AT7: Saldo Novembro | AU7: 7.86 | AV7: Afonso | AW7: 45294 | AX7: TIP 103 | AY7: 10 | AZ7: Tomás | BA7: 45330 | BB7: TIP 215 | BC7: 2 | BD7: Tomás | BE7: 45358 | BF7: TIP 410 | BG7: 5 | BH7: Inês | BI7: 45387 | BJ7: Tip 204 | BK7: 5 | BL7: Cris | BM7: 45415 | BN7: A mais na caixa | BO7: 4 | BP7: Inês | BQ7: 45455 | BR7: Nota perdida | BS7: 20 | BT7: Tomás | BU7: 45477 | BV7: comissão Monte Mar | BW7: 10 | BX7: Inês | BY7: 45508 | BZ7: City Tax | CA7: -4 | CB7: Inês | CC7: 45540 | CD7: Comissão YellowCab | CE7: 45 | CF7: Andreia | CG7: 45569 | CH7: Tip OUT 202+215 | CI7: 15 | CJ7: Inês | CK7: 45604 | CL7: TIP 316 | CM7: 10 | CN7: Inês | CO7: 45635 | CP7: Tip 204 | CQ7: 15 | CR7: Afonso | CS7: 45663 | CT7: Comissão dada o mês passado | CU7: -12.81 | CV7: Afonso | CW7: 45700 | CX7: Comissão Fado in Chiado | CY7: 15 | CZ7: Inês | DA7: 45724 | DB7: Tip 207 | DC7: 5 | DD7: João | DO7: 45995 | DP7: A mais | DQ7: 3 | DR7: Helder | DX7: Comissão 7Roads | DY7: =SUMIFS('7 Roads Dez'!J2:J117, '7 Roads Dez'!C2:C117, "*7Roads*", '7 Roads Dez'!L2:L117, "Sim ") -> 247
A8: 44933 | B8: Dinheiro a mais | C8: =0.15+0.25 -> 0.4 | D8: Andreia | E8: 44983 | F8: TIP 404 | G8: 4 | H8: Cristiana | I8: 44989 | J8: Sobra caixa | K8: 5 | L8: Daniela | M8: 45020 | N8: Comissão Yellow Cab | O8: 33 | P8: Cristiana | Q8: 45054 | R8: TIP 315 | S8: 5 | T8: Afonso | U8: 45079 | V8: TIP 315 | W8: 5 | X8: Tomás | Y8: 45115 | Z8: TIP 410 | AA8: 1 | AB8: Afonso | AC8: 45146 | AD8: Comiissão Yellow Cab | AE8: 16.5 | AF8: Tomás/Joana | AG8: 45173 | AH8: Saldo Agosto | AI8: 2.63 | AJ8: Daniela | AK8: 45203 | AL8: TIP 415 | AM8: 10 | AN8: Afonso/Andreia | AO8: 45233 | AP8: Ajuste de contas | AQ8: -0.21 | AR8: Tomás | AS8: 45266 | AT8: Valor dado o mês passado | AU8: =-44 -> -44 | AV8: Afonso | AW8: 45297 | AX8: TIP 306 + 309 | AY8: 10 | AZ8: Andreia | BA8: 45332 | BB8: TIP 312 | BC8: 4 | BD8: Cris | BE8: 45358 | BF8: TIP | BG8: 1.4 | BH8: Inês | BI8: 45387 | BJ8: TIP 316 | BK8: 10 | BL8: Cris | BM8: 45415 | BN8: Conversão Dólar-Euro | BO8: 6.09 | BP8: Afonso | BQ8: 45457 | BR8: TIP 404 | BS8: 20 | BT8: Afonso | BU8: 45478 | BV8: Dinheiro a mais | BW8: 0.48 | BX8: Andreia | BY8: 45509 | BZ8: Whero to fatima | CA8: 25.2 | CB8: Cris | CC8: 45541 | CD8: TIP 205 | CE8: 10 | CF8: Afonso | CG8: 45568 | CH8: Tip 203 | CI8: 30 | CJ8: Renato/Ivan | CK8: 45604 | CL8: VALOR EM SOBRA OUTUBRO | CM8: 4.68 | CN8: Afonso | CO8: 45636 | CP8: TIP 404 | CQ8: 20 | CR8: Afonso | CS8: 45664 | CT8: Comissão where TO | CU8: 38.4 | CV8: Afonso | CW8: 45700 | CX8: Tip 416 | CY8: 2 | CZ8: Ivan | DA8: 45724 | DB8: Comissão dada o mês passado | DC8: -4.75 | DD8: Afonso | DO8: 45998 | DP8: A mais | DQ8: 6.2 | DR8: Helder | DX8: Comissão CitySightSeeing | DY8: =SUM(CitySightSeeing!E3:E37) -> 33
A9: 44933 | B9: TIP 303 | C9: 5 | D9: Afonso | E9: 44985 | F9: Comissões Lisboa em Fado | G9: 8 | H9: Andreia | I9: 44990 | J9: TIP 103 | K9: 5 | L9: Afonso | M9: 45020 | N9: Tip 208 | O9: 5 | P9: Cristiana | Q9: 45054 | R9: TIP | S9: 1.35 | T9: Andreia | U9: 45079 | V9: Tip passante | W9: 5 | X9: Tomás | Y9: 45116 | Z9: TIP 415+404 | AA9: 20 | AB9: Afonso/Tomás | AC9: 45147 | AD9: Hóspede 412 | AE9: -15 | AF9: Afonso | AG9: 45173 | AH9: Comissão Where To | AI9: 39 | AJ9: Daniela | AK9: 45204 | AL9: TIP 216 | AM9: 3 | AN9: Inês | AO9: 45235 | AP9: TIP 203 | AQ9: 2.5 | AR9: Waleed | AS9: 45267 | AT9: Comissao Where to | AU9: 35 | AV9: Cristiana | AW9: 45297 | AX9: TIP 316 | AY9: 10 | AZ9: Andreia | BA9: 45333 | BB9: Ajuste caixa | BC9: 0.5 | BD9: Renato | BE9: 45358 | BF9: TIP 415 | BG9: 20 | BH9: Afonso | BI9: 45387 | BJ9: TIP 316 | BK9: 5 | BL9: Andreia | BM9: 45415 | BN9: TIP 101 | BO9: 5 | BP9: Afonso | BQ9: 45457 | BR9: TIP 203 | BS9: 2.5 | BT9: Ines | BU9: 45481 | BV9: Dinheiro no chão | BW9: 2 | BX9: Tomás | BY9: 45510 | BZ9: TIP 210 | CA9: 8 | CB9: Cris | CC9: 45450 | CD9: TIP 402+303 | CE9: 10 | CF9: Cris | CG9: 45570 | CH9: Tip 210 | CI9: 4 | CJ9: Ivan | CK9: 45604 | CL9: Troca Dollar-Euro | CM9: 13.2 | CN9: Afonso | CO9: 45636 | CP9: Comissão Yellow Cab | CQ9: 40 | CR9: Afonso | CS9: 45666 | CT9: Tip 407 | CU9: 5 | CV9: Ivan | CW9: 45701 | CX9: TIP 309 + 312 | CY9: 2.5 | CZ9: Andreia | DA9: 45726 | DB9: TIP SOFÁ | DC9: 2.95 | DD9: Renato | DJ9: Pedro | DK9: 45821 | DL9: Sobra o mês passado | DM9: 15.7 | DN9: Pedro | DO9: 46000 | DP9: A mais | DQ9: 10 | DR9: Erica | DX9: Comissão Where To | DY9: =SUM(Tours!H5:H25) -> 329.5
A10: 44934 | B10: TIP 207 | C10: 10 | D10: Flávio | E10: 44990 | F10: Sundestiny | G10: 327.5 | H10: Cristiana | I10: 44991 | J10: TIP 306 /303 | K10: 15.11 | L10: Afonso | M10: 45021 | N10: TIP passante | O10: 20 | P10: Tomás | Q10: 45054 | R10: Comissão Where To | S10: 70.8 | T10: Daniela | U10: 45080 | V10: Tip 416 | W10: 4 | X10: Tomás | Y10: 45117 | Z10: TIP 210 | AA10: 5 | AB10: Tomás | AC10: 45149 | AD10: TIP 408 | AE10: 1.5 | AF10: Joana/Tomás | AG10: 45173 | AH10: Comissão YellowCab | AI10: 33 | AJ10: Tomás/Joana | AK10: 45206 | AL10: Comissão CitySightSeeing | AM10: 182.5 | AN10: Tomás | AO10: 45235 | AP10: TIP 309 | AQ10: 4.5 | AR10: Inês | AS10: 45267 | AT10: Comissão Restaurantes (mar ao carmo, sacramento…) | AU10: 92 | AV10: Tomás | AW10: 45298 | AX10: Valor dado o mês passado | AY10: -0.34 | AZ10: Afonso | BA10: 45334 | BB10: Comissão Tour (direto) | BC10: 15 | BD10: Cris | BE10: 45358 | BF10: TIP 207 | BG10: 1 | BH10: Afonso | BI10: 45388 | BJ10: tip 209 | BK10: 7 | BL10: Tomás | BM10: 45416 | BN10: TIP Hóspede | BO10: 2 | BP10: Andreia | BQ10: 45457 | BR10: TROVAS | BS10: 20 | BT10: INES | BU10: 45481 | BV10: Comissão Where To | BW10: 71.1 | BX10: Afonso | BY10: 45510 | BZ10: Troca Dollar-Euro | CA10: 9.6 | CB10: Afonso | CC10: 45543 | CD10: TIP 410 + 415 | CE10: 20 | CF10: Cris | CG10: 45571 | CH10: Tip 305 | CI10: 10 | CJ10: Ivan | CK10: 45606 | CL10: TIP Grupo | CM10: 0.5 | CN10: Afonso | CO10: 45637 | CP10: tip #211 | CQ10: 2 | CR10: Ivan | CS10: 45303 | CT10: a + na caixa | CU10: 1 | CV10: Inês | CW10: 45702 | CX10: Comissões Mar ao Carmo | CY10: 130 | CZ10: Andreia | DA10: 45726 | DB10: TIP 304 | DC10: 10 | DD10: João | DO10: 46001 | DP10: A mais | DQ10: 54 | DR10: Erica | DX10: Comissão TukTuk | DY10: =SUM(Tours!I30:I49) -> 0
A11: 44940 | B11: TIP 415 | C11: 3.2 | D11: AS/CB | I11: 44992 | J11: TIP 303 | K11: 5.6 | L11: Afonso | M11: 45022 | N11: TIP 212 | O11: 5 | P11: Cristiana | Q11: 45057 | R11: Comissão Trovas Antigas | S11: 10 | T11: Daniela | U11: 45080 | V11: Tip 415 | W11: 3 | X11: Tomás | Y11: 45118 | Z11: Comissão Fado In Chiado | AA11: 15 | AB11: Tomás | AC11: 45150 | AD11: TIP 301 | AE11: 5 | AF11: Tomás | AG11: 45173 | AH11: Comissão YellowCab | AI11: 35 | AJ11: Joana | AK11: 45206 | AL11: TIP 401 | AM11: 2 | AN11: Tomás/Inês | AO11: 45235 | AP11: Comissão Where To | AQ11: 39 | AR11: Inês | AS11: 45268 | AT11: Acerto caixa | AU11: -2 | AV11: Fábio | AW11: 45299 | AX11: TIP 312 | AY11: 10 | AZ11: Cris | BA11: 45336 | BB11: TIP 302 | BC11: 6.9 | BD11: Inês | BE11: 45359 | BF11: Taxas Turisticas não pagas | BG11: -8 | BH11: Afonso | BI11: 45298 | BJ11: tip 316 | BK11: 5 | BL11: Tomás | BM11: 45419 | BN11: TIP 202 + 212 | BO11: 5 | BP11: Andreia | BQ11: 45457 | BR11: ajuda ao hospede | BS11: 5 | BT11: ines | BU11: 45482 | BV11: Valor dado o mês passado | BW11: -2.54 | BX11: Afonso | BY11: 45510 | BZ11: Renato (Autorizado-Afonso) | CA11: -8 | CB11: Afonso | CC11: 45543 | CD11: TIP C-OUT | CE11: 4 | CF11: Renato | CG11: 45572 | CH11: Comissão YellowCab | CI11: 57 | CJ11: Inês | CK11: 45608 | CL11: Comissão Where To | CM11: 84 | CN11: Ivan/Andreia | CO11: 45640 | CP11: Comissão Fado in Chiado | CQ11: 6 | CR11: Afonso | CS11: 45672 | CT11: Comissão YellowCab | CU11: 38 | CV11: Ivan | CW11: 45703 | CX11: Ivan | CY11: -60 | CZ11: Ivan | DA11: 45729 | DB11: Tour Sintra Where To #416 | DC11: 38.4 | DD11: Afonso/Renato | DO11: 46003 | DP11: Coop Táxis | DQ11: 32.8 | DR11: Erica | DX11: Comissão Discover | DY11: =SUM(Tours!Q30:Q50) -> 50.4
A12: 44942 | B12: TIP 416 | C12: 3 | D12: Daniela | I12: 44993 | J12: TIP 215 | K12: 5 | L12: Afonso | M12: 45023 | N12: Comissão A Severa | O12: 10 | P12: Andreia | Q12: 45058 | R12: TIP #315 | S12: 5 | T12: Tomás | U12: 45081 | V12: Comissão Yellow Cab | W12: 33 | X12: Daniela | Y12: 45119 | Z12: Comissão YellowCab | AA12: 50 | AB12: Afonso | AC12: 45151 | AD12: TIP 212 | AE12: 3.8 | AF12: Tomás | AG12: 45174 | AH12: TIP 215 | AI12: 3 | AJ12: Joana/Andreia | AK12: 45207 | AL12: TIP 408 | AM12: 10 | AN12: Afonso | AO12: 45236 | AP12: Comissão Where To | AQ12: 90 | AR12: Inês | AS12: 45268 | AT12: Acerto Tips | AU12: 2 | AV12: Tomás | AW12: 45303 | AX12: TIP 416 | AY12: 3 | AZ12: Afonso | BA12: 45337 | BB12: TIP 208 | BC12: 2 | BD12: Andreia | BE12: 45359 | BF12: Comissão Carla | BG12: 18 | BH12: Afonso/Tomás | BI12: 45389 | BJ12: Valor dado o mês passado | BK12: -12.44 | BL12: Afonso | BM12: 45421 | BN12: Sobra mês passado | BO12: 30.73 | BP12: Afonso | BQ12: 45457 | BR12: TIP 302 | BS12: 30 | BT12: Afonso | BU12: 45483 | BV12: Comissão Where To | BW12: 20.7 | BX12: Inês | BY12: 45512 | BZ12: TIP 204 | CA12: 4 | CB12: Cris | CC12: 45543 | CD12: Tip 410 | CE12: 20$ | CF12: Inês | CG12: 45572 | CH12: Tip 211 | CI12: 0.1 | CJ12: Inês | CK12: 45609 | CL12: TIP #203 | CM12: 10 | CN12: Andreia | CO12: 45641 | CP12: TIP 203 | CQ12: 10 | CR12: Andreia | CS12: 45673 | CT12: Comissão YellowCab | CU12: 38 | CV12: Ivan | CW12: 45704 | CX12: Tip 406 | CY12: 10 | CZ12: Inês/João | DA12: 45729 | DB12: Inês | DC12: -5.5 | DD12: Inês | DO12: 46003 | DP12: A mais | DQ12: 20 | DR12: Erica | DX12: Contagem
A13: 44943 | B13: Where To Comissão | C13: 47.4 | D13: Daniela | I13: 45004 | J13: TIP 405 | K13: 4 | L13: Afonso | M13: 45024 | N13: TIP 302 | O13: 14 | P13: Cristiana | Q13: 45058 | R13: TIP #408 | S13: 6.2 | T13: Tomás | U13: 45085 | V13: Tip passante | W13: 1.5 | X13: Tomás | Y13: 45119 | Z13: Tip 104 | AA13: 50 | AB13: Afonso | AC13: 45153 | AD13: Comiissão Yellow Cab Sintra | AE13: 33 | AF13: Tomás | AG13: 45174 | AH13: Comissão Trovas Antigas | AI13: 20 | AJ13: Joana/Andreia | AK13: 45207 | AL13: TIP 310 | AM13: 2 | AN13: Afonso | AO13: 45240 | AP13: Valor dado no mês passado | AQ13: -13.63 | AR13: Afonso | AS13: 45269 | AT13: TIP 102 | AU13: 2 | AV13: Afonso | AW13: 45306 | AX13: TIP 304 | AY13: 1 | AZ13: Tomás | BA13: 45337 | BB13: Comissão Yellow Cab | BC13: 40 | BD13: Inês | BE13: 45360 | BF13: Comissão Yellow Cab | BG13: 38 | BH13: Cris | BI13: 45391 | BJ13: TIP | BK13: 1.5 | BL13: Cris | BM13: 45423 | BN13: Comissão Fado in Chiado | BO13: 3 | BP13: Inês | BQ13: 45459 | BR13: Suborno wc | BS13: 5 | BT13: Renato | BU13: 45486 | BV13: TIP 406 | BW13: 5 | BX13: Eduardo | BY13: 45513 | BZ13: Valor dado o mês passado | CA13: -9.49 | CB13: Afonso | CC13: 45544 | CD13: Valor em sobra o mês passado | CE13: 5.82 | CF13: Afonso | CG13: 45572 | CH13: TIP 411 | CI13: 3 | CJ13: Afonso | CK13: 45610 | CL13: Comissão Where To | CM13: 41.4 | CN13: Inês | CO13: 45642 | CP13: COMISSÃO SD | CQ13: 35 | CR13: Inês/Andreia | CS13: 45674 | CT13: Comissão Where To | CU13: 38.4 | CV13: Afonso | CW13: 45705 | CX13: Tip 203 | CY13: 1.5 | CZ13: Inês | DA13: 45730 | DB13: City sightseeing | DC13: 115 | DD13: Afonso | DO13: 46005 | DP13: Taberna da Baixa | DQ13: 50 | DR13: Helder | DX13: Notas
B14: Celina Tour | C14: 75 | D14: Afonso | I14: 45005 | J14: Comissão Where To | K14: =19.5+39 -> 58.5 | L14: Afonso | M14: 45025 | N14: Falta caixa | O14: -0.7 | P14: Daniela | Q14: 45059 | R14: TIP #408 | S14: 10 | T14: Afonso | U14: 45086 | V14: TIP 315 | W14: 5 | X14: Tomás | Y14: 45120 | Z14: Tip 208 | AA14: 5 | AB14: Afonso | AC14: 45153 | AD14: Reposição #412 | AE14: 15 | AF14: Afonso | AG14: 45175 | AH14: TIP 208 | AI14: 5 | AJ14: Daniela/Andreia | AK14: 45208 | AL14: TIP | AM14: 10 | AN14: Afonso | AO14: 45240 | AP14: TIP Quartos | AQ14: 8 | AR14: Tomás | AS14: 45271 | AT14: Comissão Yellow Cab (faltava 2€ de outro tour) | AU14: 2 | AV14: Inês | AW14: 45311 | AX14: Comissão Trovas Antigas | AY14: 10 | AZ14: Andreia | BA14: 45337 | BB14: TIP 315 | BC14: 20 | BD14: Inês | BE14: 45360 | BF14: TIP 102+408 | BG14: 10 | BH14: Tomás | BJ14: Comissão Trovas Antigas | BK14: 10 | BL14: Inês | BM14: 45424 | BN14: TIP | BO14: 4 | BP14: Cris | BQ14: 45460 | BR14: Tip passante | BS14: 5 | BT14: Andreia | BU14: 45486 | BV14: TIP 406 | BW14: 2 | BX14: Eduardo | BY14: 45514 | BZ14: TIP #402 | CA14: 20 Dolla | CB14: Renato | CC14: 45544 | CD14: Valor em falta nas tips | CE14: -10.1 | CF14: Afonso | CG14: 45573 | CH14: VALOR EM SOBRA SETEMBRO | CI14: 5.84 | CJ14: Afonso | CM14: -0.8 | CO14: 45642 | CP14: TIP 303 | CQ14: 10 | CR14: Renato | CS14: 45674 | CT14: Ivan | CU14: -65 | CV14: Ivan/Afonso | CW14: 45707 | CX14: TIP 201 | CY14: 5 | CZ14: Afonso | DA14: 45734 | DB14: Andreia | DC14: -31 | DD14: Andreia | DO14: 46006 | DP14: Tips divididas | DQ14: -800 | DR14: Erica | DX14: 500 | DY14: 0 | DZ14: =DX14*DY14 -> 0
A15: 44951 | B15: Dinheiro a mais | C15: 4.5 | D15: Afonso/Flávio | I15: 45006 | J15: Tip 301 | K15: 2.5 | L15: Daniela | M15: 9 a 13 | N15: Tips Quartos | O15: 45 | P15: Daniela | Q15: 45059 | R15: TIP #204 | S15: 10 | T15: Tomás | U15: 45087 | V15: DSCar | W15: 145 | X15: Daniela | Y15: 45122 | Z15: TIP | AA15: 5 | AB15: Daniela | AC15: 45155 | AD15: Comissão Yellow Cab | AE15: 33 | AF15: Afonso/Inês | AG15: 45175 | AH15: TIP Passante | AI15: 10 | AJ15: Tomás | AK15: 45208 | AL15: Saldo Setembro | AM15: 1.11 | AN15: Afonso | AO15: 45240 | AP15: TIP 203 | AQ15: 7.5 | AR15: Afonso | AS15: 45272 | AT15: Comissão CitySightSeeing | AU15: 70 | AV15: Cristiana | AW15: 45327 | AX15: Comissão SD | AY15: 190 | AZ15: Afonso | BA15: 45339 | BB15: Comissão where to | BC15: 39 | BD15: Tomás | BE15: 45361 | BF15: Comissão where to | BG15: 19.5 | BH15: Cris | BI15: 45391 | BJ15: Comissão Where To | BK15: 41.4 | BL15: Cristiana | BM15: 45424 | BN15: TIP 415 | BO15: 2 | BP15: Andreia | BQ15: 45461 | BR15: TIP #206 | BS15: 10 | BT15: Andreia | BU15: 45486 | BV15: TIP 406 | BW15: 5 | BX15: Inês | BY15: 45515 | BZ15: Comissão YellowCab | CA15: 38 | CB15: Afonso | CC15: 45546 | CD15: TIP 410 | CE15: 10 | CF15: Afonso | CG15: 45574 | CH15: TIP 205 | CI15: 5 | CJ15: Andreia | CK15: 45613 | CL15: Sofá | CM15: 0.7 | CN15: Andreia | CO15: 45643 | CP15: Impressora | CQ15: 5 | CR15: Cris/Andreia | CS15: 45309 | CT15: a + na caixa | CU15: 0.2 | CV15: Inês | CW15: 45708 | CX15: TIP | CY15: 3.5 | CZ15: Inês | DA15: 45735 | DB15: PARA SER REPOSTO - IVAN | DC15: -65 | DD15: Ivan | DO15: 46006 | DP15: Devolução a hóspede (taxas cobradas a mais) | DQ15: -8 | DR15: Erica | DX15: 200 | DY15: 0 | DZ15: =DX15*DY15 -> 0
A16: 44952 | B16: Trovas Antigas Comissão | C16: 20 | D16: André | I16: 45006 | J16: \0 | K16: 35 | L16: Daniela | M16: 45028 | N16: Comissão Yellow Cab | O16: 33 | P16: Bárbara/Tomás | Q16: 45060 | R16: TIP #306 | S16: 2 | T16: Tomás | U16: 45086 | V16: tip 315 | W16: 10 | X16: Tomás | Y16: 45124 | Z16: TIP 309 | AA16: 2 | AB16: Afonso | AC16: 45157 | AD16: TIP Passante | AE16: 2.5 | AF16: Tomás | AG16: 45176 | AH16: Comissão CitySightSeeing | AI16: 109.48 | AJ16: Tomás | AK16: 45208 | AL16: TIP 209 | AM16: 1 | AN16: Afonso | AO16: 45241 | AP16: Comissão Where To | AQ16: 47.4 | AR16: Afonso | AS16: 45275 | AT16: Comissão trovas (07/11 - 10/12) | AU16: 120 | AV16: Tomás / Inês | BA16: 45339 | BB16: Ajuste das Tips | BC16: 4 | BD16: Tomás | BE16: 45361 | BF16: Comissão Where To | BG16: 47.5 | BH16: Inês | BI16: 45391 | BJ16: TIP 401 | BK16: 5 | BL16: Inês | BM16: 45424 | BN16: TIP 304 | BO16: 10 | BP16: Cris | BQ16: 45462 | BR16: TIP 410 | BS16: 6 | BT16: Renato | BU16: 45492 | BV16: TIP 316 | BW16: 5 | BX16: Afonso | BY16: 45515 | BZ16: TIP 402 | CA16: 5 | CB16: Afonso | CC16: 45546 | CD16: TIP 401 | CE16: 5 | CF16: Afonso | CG16: 45574 | CH16: Comissão Where to | CI16: 41.4 | CJ16: Inês | CK16: 45613 | CL16: Comissão YellowCab | CM16: 57 | CN16: Inês | CP16: Em falta | CQ16: -3 | CR16: Afonso | CS16: 45309 | CT16: Tour Sintra Where To | CU16: 38.4 | CV16: Inês | CW16: 45708 | CX16: TIP 312 | CY16: 10 | CZ16: Afonso | DA16: 45737 | DB16: TIP 314 | DC16: 3.5 | DD16: Renato /João | DO16: 46009 | DP16: A menos (valor das decorações de natal) | DQ16: -97.94 | DR16: Erica | DX16: 100 | DY16: 0 | DZ16: =DX16*DY16 -> 0
A17: 44953 | B17: Falta na caixa | C17: -20 | D17: Daniela | I17: 45007 | J17: Tip 301 | K17: 15 | L17: Daniela | M17: 45029 | N17: Trovas Antigas | O17: 100 | P17: Daniela | Q17: 45061 | R17: TIP #303 | S17: 5 | T17: Andreia | U17: 45088 | V17: TIP 402 + 304 | W17: 10 | X17: Tomás | Y17: 45124 | Z17: TIP 401 | AA17: 2.5 | AB17: Afonso | AC17: 45157 | AD17: TIP 401+403 | AE17: 5 | AF17: Tomás | AG17: 45176 | AH17: Falta caixa | AI17: -0.89 | AJ17: Daniela | AK17: 45209 | AL17: TIP 310 | AM17: 2 | AN17: Andreia | AO17: 45242 | AP17: TIP 304 | AQ17: 5 | AR17: Andreia | AS17: 45276 | AT17: Valor tirado nas Tips para fazer caixa do dia | AU17: -1.9 | AV17: Fábio | BA17: 45339 | BB17: TIP 415 | BC17: 20 | BD17: Inês | BE17: 45361 | BF17: TIP 305 | BG17: 2 | BH17: Inês | BI17: 45392 | BJ17: tip 401 | BK17: 3.5 | BL17: Cris | BM17: 45425 | BN17: TIP 406 | BO17: 2 | BP17: Afonso | BQ17: 45463 | BR17: TIP 410 | BS17: 10 | BT17: Renato | BU17: 45493 | BV17: TIP PASSANTE | BW17: 5 | BX17: Afonso | BY17: 45516 | BZ17: TIP PASSANTE | CA17: 1.51 | CB17: Renato | CC17: 45546 | CD17: TIP 205 | CE17: 6 | CF17: Cris / Afonso | CG17: 45574 | CH17: TIP OUT | CI17: 2 | CJ17: Cris/Inês | CK17: 45615 | CL17: Comissão Where To | CM17: 41.4 | CN17: Cris | CO17: 45648 | CP17: Comissão Where To | CQ17: 38.4 | CR17: Inês | CS17: 45683 | CT17: TIP | CU17: 0.5 | CV17: Andreia | CW17: 45710 | CX17: A mais | CY17: 4.25 | CZ17: Afonso | DA17: 45738 | DB17: TIP 202 | DC17: 5 | DD17: Afonso | DO17: 46009 | DP17: A mais | DQ17: 2.58 | DR17: Erica | DX17: 50 | DY17: 0 | DZ17: =DX17*DY17 -> 0
A18: 44954 | B18: André | C18: 20 | D18: André | I18: 45009 | J18: TIP 309 (c-in) | K18: 5 | L18: Cristiana | M18: 45031 | N18: TIP 305 | O18: 2 | P18: Afonso | Q18: 45061 | R18: TIP #309 | S18: 2 | T18: Tomás | U18: 45091 | V18: Comissão Yellow Cab | W18: 35 | X18: Tomás | Y18: 45125 | Z18: TIP 401 | AA18: 1.5 | AB18: Flávio | AC18: 45158 | AD18: TIP 416 | AE18: 10 | AF18: Tomás / Dani | AG18: 45176 | AH18: TIP 302 | AI18: 3 | AJ18: Andreia | AK18: 45209 | AL18: Comissão Fado in Chiado | AM18: 12 | AN18: Afonso | AO18: 45244 | AP18: TIP 401 | AQ18: 2 | AR18: Tomás / Cris | AS18: 45276 | AT18: Valor de Tips reposto | AU18: 1.9 | AV18: Inês | BA18: 45339 | BB18: TIP 402 | BC18: 10 | BD18: Tomás | BE18: 45363 | BF18: TIP 302 + 305 | BG18: 5 | BH18: Afonso | BI18: 45392 | BJ18: TIP 401 | BK18: 4 | BL18: Andreia | BM18: 45426 | BN18: TIP 408 | BO18: 2 | BP18: Afonso | BQ18: 45464 | BR18: TIP 206 | BS18: 2 | BT18: Afonso | BU18: 45497 | BV18: TIP Sofá | BW18: 1 | BX18: Afonso/Andreia | BY18: 45518 | BZ18: TIP 307 | CA18: 5 | CB18: Cris | CC18: 45546 | CD18: Tip Passante | CE18: 4 | CF18: Inês | CG18: 45574 | CH18: TIP 411 | CI18: 1 | CJ18: Inês | CK18: 45616 | CL18: Tip #204 | CM18: 5 | CN18: Renato | CO18: 45649 | CP18: Comissão Trovas Antigas | CQ18: 45 | CR18: Inês / Afonso | CS18: 45684 | CT18: TIP 205 | CU18: 5 | CV18: Afonso | CW18: 45711 | CX18: Afonso | CY18: -5 | CZ18: Afonso | DA18: 45740 | DB18: Comissão Where To Sintra #310 | DC18: 57.6 | DD18: Andreia | DO18: 46010 | DP18: Foram retirados 50 euros da 7roads, 2€ gratificações e 2€ LS para acerto de caixa dia 19/12 | DQ18: -54 | DR18: Helder | DX18: 20 | DY18: 2 | DZ18: =DX18*DY18 -> 40
A19: 44954 | B19: Dinheiro a mais | C19: 3.85 | D19: Daniela | I19: 45009 | J19: TIP 408 | K19: 50 | L19: Cristiana | M19: 45031 | N19: TIP | O19: 0.1 | P19: Andreia | Q19: 45062 | R19: Comissão Yellow Cab | S19: 33 | T19: Daniela | U19: 45092 | V19: TIP 215 | W19: 5 | X19: Tomás | Y19: 45125 | Z19: TIP 308 | AA19: 9 | AB19: Afonso | AC19: 45158 | AD19: TIP 102 | AE19: 5 | AF19: Tomás / Cris | AG19: 45176 | AH19: TIP 104 | AI19: 5 | AJ19: Andreia | AK19: 45210 | AL19: TIP Grupo | AM19: 3 | AN19: Cristiana | AO19: 45246 | AP19: TIP 311 | AQ19: 20 | AR19: Tomás | AS19: 45276 | AT19: TIP 315 | AU19: 2 | AV19: Inês | BA19: 45341 | BB19: Comissao yellow cab | BC19: 33 | BD19: Cris | BE19: 45363 | BF19: TROVAS ANTIGAS | BG19: 15 | BH19: Afonso /Cris | BI19: 45392 | BJ19: Transfer Website errado | BK19: -22 | BL19: Afonso | BM19: 45426 | BN19: TIP 204 | BO19: 20 | BP19: Afonso | BQ19: 45467 | BR19: TIP 405 | BS19: 2 | BT19: Tomás | BU19: 45497 | BV19: Tip #404 | BW19: 5 | BX19: Renato | BY19: 45519 | BZ19: TIP 415 | CA19: 6 | CB19: Afonso | CC19: 45547 | CD19: Renato (Autorizado-Afonso) | CE19: -5 | CF19: Afonso | CG19: 45575 | CH19: TIP 405 | CI19: 4 | CJ19: Afonso | CK19: 45616 | CL19: Ivan (autorizado - Afonso) | CM19: -50 | CN19: Ivan/Afonso | CO19: 45650 | CP19: Comissão Odissey Tours | CQ19: 52 | CR19: Inês | CS19: 45684 | CT19: TIP 403 | CU19: 50 | CV19: Afonso | CW19: 45712 | CX19: Comissão Trovas Antigas | CY19: 15 | CZ19: João | DA19: 45740 | DB19: TIP 315 | DC19: 10 | DD19: Afonso | DO19: 46012 | DP19: Where To (marcado diretamente com eles, deram-nos a comissão) | DQ19: 22.5 | DR19: Helder | DX19: 10 | DY19: 1 | DZ19: =DX19*DY19 -> 10
A20: 44960 | B20: Sundestiny | C20: 385 | D20: Daniela | I20: 45009 | J20: Comissão Yellow Cab | K20: 33 | L20: Daniela | M20: 45033 | N20: Comissão Yellow Cab | O20: 35 | P20: Andreia | Q20: 45063 | R20: TIP #308 | S20: 3.5 | T20: Waleed | U20: 45092 | V20: Comissão Trovas Antigas | W20: 60 | X20: Waleed | Y20: 45125 | Z20: TIP 407 | AA20: 10 | AB20: Afonso | AC20: 45158 | AD20: Comissão Where To | AE20: 39 | AF20: Daniela | AG20: 45177 | AH20: TIP 203 | AI20: 2 | AJ20: Tomás | AK20: 45210 | AL20: TIP 103 | AM20: 3.8 | AN20: Tomás | AO20: 45246 | AP20: Dinheiro a + | AQ20: 5.01 | AR20: Tomás | AS20: 45276 | AT20: TIP 303 | AU20: 2 | AV20: Tomás | BA20: 45343 | BB20: Comissão Where To | BC20: 42 | BD20: Inês | BE20: 45365 | BF20: TIP 302+305 | BG20: 5 | BH20: Inês | BI20: 45393 | BJ20: tip 312 | BK20: 10 | BL20: Cris | BM20: 45429 | BN20: TIP Passante | BO20: 10 | BP20: Inês | BQ20: 45469 | BR20: Comissão Yellow Cab | BS20: 20 | BT20: Inês | BU20: 45483 | BV20: TIP | BW20: 10 | BX20: Renato | BY20: 45519 | BZ20: TIP 204 | CA20: 10 Dolla | CB20: Afonso | CC20: 45547 | CD20: TIP 315 | CE20: 5 | CF20: Afonso | CG20: 45575 | CH20: TIP 205 | CI20: 4 | CJ20: Afonso | CK20: 45617 | CL20: Comissão Where To | CM20: 94.8 | CN20: Andreia | CP20: Em falta | CQ20: -0.11 | CR20: Inês | CS20: 45659 | CT20: TIP 210 | CU20: 1.5 | CV20: Afonso | CW20: 45714 | CX20: Andreia | CY20: -10 | CZ20: Andreia | DA20: 45741 | DB20: TIP | DC20: 5 | DD20: Andreia | DO20: 46012 | DP20: Taxas cobradas a mais | DQ20: -2 | DR20: Helder | DX20: 5 | DY20: 1 | DZ20: =DX20*DY20 -> 5
I21: 45011 | J21: Comissão Yellow Cab | K21: 16.5 | L21: Andreia | M21: 45035 | N21: Comissão Yellow Cab | O21: 33 | P21: Andreia | Q21: 45065 | R21: TIP Passante | S21: 5 | T21: Tomas | U21: 45093 | V21: Tip | W21: 4.5 | X21: Daniela | Y21: 45127 | Z21: TIP | AA21: 20 | AB21: Cristiana | AC21: 45159 | AD21: TIP 404 | AE21: 5.45 | AF21: Tomás | AG21: 45177 | AH21: Comissão Where To | AI21: 88.5 | AJ21: Joana/Tomás | AK21: 45210 | AL21: Comissão Trovas Antigas | AM21: 75 | AN21: Andreia | AO21: 45246 | AP21: Comissão Where To | AQ21: 39 | AR21: Inês | AS21: 45278 | AT21: TIP 303 | AU21: 5 | AV21: Afonso | BA21: 45343 | BB21: Comissão Where To | BC21: 53.9 | BD21: Inês | BE21: 45370 | BF21: TIP 301 | BG21: 1 | BH21: Andreia | BI21: 45395 | BJ21: Comissão 7Roads | BK21: 8 | BL21: Inês | BM21: 45429 | BN21: Comissão Yellow Cab | BO21: 70 | BP21: Inês | BQ21: 45470 | BR21: Tip out | BS21: 2.5 | BT21: Cris | BU21: 45503 | BV21: Comissão Tour | BW21: 38 | BX21: Renato | BY21: 45520 | BZ21: Comissao SD | CA21: 35 | CB21: Afonso | CC21: 45547 | CD21: TIP | CE21: 10 | CF21: Prazeres | CG21: 45575 | CH21: TIP 416 | CI21: 5 | CJ21: Inês | CK21: 45617 | CL21: TIP 405 | CM21: 5 | CN21: Afonso | CO21: 45650 | CP21: Renato | CQ21: -10 | CR21: Renato/Inês | CS21: 45693 | CT21: SUN | CU21: 156.5 | CV21: Afonso | CW21: 45715 | CX21: A mais na caixa | CY21: 1 | CZ21: Andreia | DA21: 45744 | DB21: tip | DC21: 1 | DD21: Renato /Andreia | DO21: 46013 | DP21: A menos | DQ21: -94.01 | DR21: Erica | DZ21: =SUM(DZ14:DZ20) -> 55
I22: 45012 | J22: TIP 415 | K22: 2.5 | L22: Andreia | M22: 45036 | N22: Tip 101 | O22: 3 | P22: Tomás | Q22: 45065 | R22: TIP 304 | S22: 5 | T22: Tomas | U22: 45094 | V22: TIP 410 | W22: 10 | X22: Tomás | Y22: 45128 | Z22: TIP | AA22: 11 | AB22: Daniela | AC22: 45161 | AD22: TIP | AE22: 5 | AF22: Andreia | AG22: 45177 | AH22: TIP 203 | AI22: 2 | AJ22: Joana | AK22: 45213 | AL22: TIP 306 | AM22: 3 | AN22: Tomás | AO22: 45247 | AP22: extra de caixa | AQ22: 1.84 | AR22: Waleed | AS22: 45281 | AT22: Fado in chiado | AU22: 9 | AV22: Cristiana | BA22: 45348 | BB22: TIP 204 | BC22: 2 | BD22: Cris | BE22: 45370 | BF22: Comissão Yellow Cab | BG22: 38 | BH22: Tomás | BI22: 45395 | BJ22: TIP 304+404 | BK22: 10 | BL22: Inês | BM22: 45432 | BN22: TIP 204 | BO22: 20 | BP22: Cris | BQ22: 45471 | BR22: Comissão Yellow Cab | BS22: 45 | BT22: Cris | BU22: 45513 | BV22: Comissão SD | BW22: 361.5 | BX22: Afonso | BY22: 45521 | BZ22: TIP #405 | CA22: 20 | CB22: Andreia | CC22: 45548 | CD22: TIP 203 | CE22: 3 | CF22: Afonso | CG22: 45575 | CH22: Comissão Buddy TukTuk | CI22: 165 | CJ22: Inês/Andreia | CK22: 45618 | CL22: Comissão Fado In Chiado | CM22: 12 | CN22: Afonso | CO22: 45654 | CP22: Comissão SD | CQ22: 35 | CR22: Andreia/Inês | CS22: 45693 | CT22: Adiantamento Ivan | CV22: Afonso | CW22: 45724 | CX22: A mais nas TIPS | CY22: 5.5 | CZ22: Afonso | DA22: 45745 | DB22: TIP#309 OUT | DC22: 5 | DD22: João/Andreia | DO22: 46014 | DP22: A mais | DQ22: 63.3 | DR22: Erica
I23: 45013 | J23: Comissão Where To | K23: 39 | L23: Daniela | M23: 45038 | N23: Tip 210 | O23: 2 | P23: Daniela | Q23: 45066 | R23: TIP 402 + 102 | S23: 9 | T23: Tomas | U23: 45094 | V23: Tip passante | W23: 7 | X23: Tomás | Y23: 45135 | Z23: Comissão YellowCab | AA23: 33 | AB23: Tomás/Inês | AC23: 45162 | AD23: Taxas turísticas | AE23: =-12-8 -> -20 | AF23: Daniela | AG23: 45177 | AH23: TIP 402 | AI23: 3 | AJ23: Joana/afonso | AK23: 45222 | AL23: Reposição de caixa (Novo banco) | AM23: -10 | AN23: Tomás/Andreia | AO23: 45247 | AP23: Comissão Where To | AQ23: 39 | AR23: Inês | AS23: 45282 | AT23: TIP 402 | AU23: 5 | AV23: Afonso | BA23: 45351 | BB23: TIP 205 | BC23: 2 | BD23: Renato | BE23: 45373 | BF23: TIP 407 | BG23: 10 | BH23: Tomás/Afonso | BI23: 45398 | BJ23: TIP Hóspedes | BK23: 10 | BL23: Inês | BM23: 45433 | BN23: TIP 308 | BO23: 6 | BP23: Tomás | BQ23: 45471 | BR23: chão | BS23: 5 | BT23: Cris | BY23: 45523 | BZ23: Afonso | CA23: -10 | CB23: Afonso | CC23: 45548 | CD23: TIP 203 | CE23: 3 | CF23: Andreia | CG23: 45577 | CH23: TIP 308 | CI23: 2 | CJ23: Cris | CK23: 45619 | CL23: Comissão Where To | CM23: 50.4 | CN23: Inês | CO23: 45654 | CP23: TIP 315 | CQ23: 5 | CR23: Andreia/Inês | CS23: 45693 | CT23: a mais | CU23: 0.41 | CV23: Afonso | CW23: 45724 | CX23: SUN | CY23: 182 | CZ23: Afonso | DA23: 45746 | DB23: TIP 403 | DC23: 5 | DD23: Afonso | DO23: 46014 | DP23: A menos (vai ser corrigido na caixa de hoje) | DQ23: -16 | DR23: Erica | DX23: 2 | DY23: 0 | DZ23: =DX23*DY23 -> 0
I24: 45015 | J24: TIP 311 (c-in) | K24: 5 | L24: Cristiana | M24: 45038 | N24: passante | O24: 2 | P24: Cristiana | Q24: 45067 | R24: TIP 312 | S24: 1.5 | T24: Tomas | U24: 45095 | V24: TIP 408 | W24: 20 | X24: Afonso/Tomas | Y24: 45135 | Z24: Tour Where to | AA24: 39 | AB24: Tomás/Inês | AC24: 45162 | AD24: TIP 308 | AE24: 5 | AF24: Andreia | AG24: 45177 | AH24: Comissão SD 50€ - Hóspede pagou o Transfer ao Check-In | AI24: 50 | AJ24: Afonso | AK24: 45223 | AL24: Saldo a mais | AM24: 18.55 | AN24: Andreia | AO24: 45248 | AP24: TIP 215+315 | AQ24: 2 | AR24: Tomás | AS24: 45283 | AT24: TIP 210 + 211 | AU24: 30 | AV24: Tomás | BA24: 45351 | BB24: TIP 308 | BC24: 10 | BD24: Afonso | BE24: 45378 | BF24: a mais na caixa | BG24: 0.5 | BH24: Cris | BI24: 45399 | BJ24: TIP Hóspedes | BK24: 3 | BL24: Renato | BM24: 45433 | BN24: TIP 405 416 | BO24: 7 | BP24: Tomás | BQ24: 45471 | BR24: Comissão Where To | BS24: 41.4 | BT24: Cris | BY24: 45524 | BZ24: Comissoes Trovas | CA24: 65 | CB24: Afonso | CC24: 45549 | CD24: TIP 315 | CE24: 3.2 | CF24: Andreia | CG24: 45577 | CH24: tip 201 | CI24: 7 | CJ24: Cris | CK24: 45619 | CL24: TIP #205 | CM24: 5 | CN24: Andreia | CO24: 45654 | CP24: TIP 315 | CQ24: 2 | CR24: Inês | DA24: 45746 | DB24: TIP 415 | DC24: 3 | DD24: João | DO24: 46014 | DP24: A menos | DQ24: -18.99 | DR24: Erica | DX24: 1 | DY24: 0 | DZ24: =DX24*DY24 -> 0
I25: 45020 | J25: Sundestiny | K25: 515 | L25: Daniela | M25: 45039 | N25: Comissão Yellow Cab | O25: 33 | P25: Afonso | Q25: 21/'05/2023 | R25: TIP Passante | S25: 5 | T25: Tomas | U25: 45098 | V25: TIP 201 | W25: 3 | X25: Daniela | Y25: 45136 | Z25: Tip | AA25: 2.51 | AB25: Daniela | AC25: 45163 | AD25: TIP 402 | AE25: 17.7 | AF25: Afonso/Cristiana | AG25: 45178 | AH25: TIP Passante | AI25: 0.5 | AJ25: Andreia | AK25: 45225 | AL25: TIP | AM25: 4 | AN25: Andreia | AO25: 45249 | AP25: TIP 406 | AQ25: 1 | AR25: Andreia | AS25: 45283 | AT25: TIP 411 | AU25: 20 | AV25: Tomás / Afonso | BA25: 45351 | BB25: TIP 205 | BC25: 10 | BD25: Afonso | BE25: 45378 | BF25: City Sighseeing | BG25: 212 | BH25: Afonso | BI25: 45401 | BJ25: TIP 305 | BK25: 20 | BL25: Andreia | BM25: 45434 | BN25: Comissão Where To | BO25: 84 | BP25: Andreia/Inês | BQ25: 45471 | BR25: A mais | BS25: 9.05 | BT25: Afonso | BY25: 45524 | BZ25: Comissão SD | CA25: 25 | CB25: Afonso | CC25: 45550 | CD25: TIP 304 | CE25: 10 | CF25: Afonso | CG25: 45577 | CH25: tip 205 | CI25: 10 | CJ25: afonso | CK25: 45619 | CL25: Comissão Where To | CM25: 38.4 | CN25: Andreia | CO25: 45656 | CP25: Ivan | CQ25: -60 | CR25: Ivan/Afonso | DA25: 45746 | DB25: TIP 315 | DC25: 2 | DD25: Inês | DX25: 0.5 | DY25: 0 | DZ25: =DX25*DY25 -> 0
M26: 45039 | N26: TIP 308 | O26: 10 | P26: Afonso | Q26: 21/'05/2023 | R26: TIP 204 | S26: 5 | T26: Tomas | U26: 45099 | V26: WesternUnion ($ -> €) | W26: 24 | X26: Daniela | Y26: 45137 | Z26: TIP 205 + 302 + 303 | AA26: 15 | AB26: Tomás / Andreia | AC26: 45169 | AD26: Comissão Where To | AE26: 39 | AF26: Joana | AG26: 45178 | AH26: TIP 205 | AI26: 5 | AJ26: Andreia | AK26: 45226 | AL26: TIP 204 | AM26: 10 | AN26: Afonso | AO26: 45249 | AP26: Comissão Where To | AQ26: 135 | AR26: Tomás | AS26: 45283 | AT26: TIP 402 | AU26: 10 | AV26: Afonso | BA26: 45325 | BB26: Comissão SunDestiny | BC26: 480 | BD26: Afonso | BE26: 45378 | BF26: TIP 208 | BG26: 10 | BH26: Afonso | BI26: 45401 | BJ26: TIP 216 | BK26: 5 | BL26: Andreia | BM26: 45434 | BN26: Dinheiro a mais nas TIP's | BO26: 13.05 | BP26: Andreia/Inês | BQ26: 45471 | BR26: Comissão Yellow Cab | BS26: 38 | BT26: Afonso | BY26: 45525 | BZ26: TIP #215 | CA26: 0.5 | CB26: Andreia | CC26: 45550 | CD26: Ivan (Autorizado-Afonso) | CE26: -50 | CF26: Afonso | CG26: 45577 | CH26: Comissão Fado In Chiado | CI26: 6 | CJ26: Afonso/Ivan | CK26: 45619 | CL26: TIP #309 | CM26: 5 | CN26: Andreia | CO26: 45657 | CP26: TIP 403 | CQ26: 20 | CR26: Afonso | DA26: 45747 | DB26: JP | DC26: -1 | DD26: João | DX26: 0.2 | DY26: 0 | DZ26: =DX26*DY26 -> 0
M27: 45041 | N27: TIP #404 | O27: 5 | P27: Waleed | Q27: 21/'05/2023 | R27: TIP 311 | S27: 5 | T27: Tomas | U27: 45102 | V27: TIP 209 | W27: 10 | X27: Afonso | Y27: 45137 | Z27: Comissão Where To | AA27: 70.8 | AB27: Tomás / Andreia | AC27: 45171 | AD27: Comissão SD | AE27: 368 | AF27: Waleed | AG27: 45180 | AH27: TIP 412 | AI27: 3 | AJ27: Andreia | AK27: 45226 | AL27: Comissão Trovas Antigas | AM27: 30 | AN27: Afonso/Andreia | AO27: 45250 | AP27: TIP | AQ27: 3.5 | AR27: Inês | AS27: 45283 | AT27: TIP 307 | AU27: 2 | AV27: Tomás / Afonso | BE27: 45378 | BF27: nem me perguntem, nem eu sei eheh | BG27: 20 | BH27: Cris | BI27: 45401 | BJ27: A mais | BK27: 4.04 | BL27: Afonso | BM27: 45435 | BN27: Comissão CitySight | BO27: 85 | BP27: Tomás | BQ27: 45472 | BR27: TIP 405 | BS27: 3 | BT27: Afonso | BY27: 45525 | BZ27: Deixou o troco | CA27: 2 | CB27: Cris | CC27: 45550 | CD27: Troca Dollar --> Euro | CE27: 60 | CF27: Afonso | CG27: 45578 | CH27: Renato (Autorizado - Afonso) | CI27: -5 | CJ27: Renato | CK27: 45620 | CL27: Ivan (autorizado - Afonso) | CM27: -40 | CN27: Ivan/Afonso | CO27: 45657 | CP27: Andreia - AUT. AFONSO | CQ27: -9.6 | CR27: Andreia | DA27: 45753 | DB27: Comissões SunDestiny | DC27: 434 | DD27: Inês | DX27: 0.1 | DY27: 3 | DZ27: =DX27*DY27 -> 0.3
M28: 45042 | N28: tip 409 | O28: 10 | P28: Daniela | Q28: 45068 | R28: TIP Passante | S28: 20 | T28: Tomas | U28: 45104 | V28: TIP 104 | W28: 10 | X28: Tomas | Y28: 45145 | Z28: Comissão Sun Destiny | AA28: 431.5 | AB28: Waleed | AG28: 45181 | AH28: Tip 308 | AI28: 20 | AJ28: Joana | AK28: 45227 | AL28: Comissão Yellow Cab | AM28: 70 | AN28: Afonso/Inês | AO28: 45251 | AP28: TIP 203 | AQ28: 2 | AR28: Afonso | AS28: 45284 | AT28: TIP 402 | AU28: 5 | AV28: Afonso | BE28: 45379 | BF28: TIP 204 | BG28: 20 | BH28: Afonso/Cris | BI28: 45403 | BJ28: passante | BK28: 5 | BL28: Tomás | BM28: 45437 | BN28: TIP 204 | BO28: 20 | BP28: Afonso | BQ28: 45482 | BR28: Comissão Citysight | BS28: 76.75 | BT28: Tomás | BY28: 45529 | BZ28: Comissão Where To | CA28: 76.8 | CB28: Afonso | CC28: 45551 | CD28: Tip 406 | CE28: 5 | CF28: Renato | CG28: 45579 | CH28: TIP 202 | CI28: 2Dolar | CJ28: Afonso | CK28: 45621 | CL28: Renato (Aut. Andreia) | CM28: -10 | CN28: Renato | CO28: 45663 | CP28: Adiantamento Ivan | CR28: Afonso | DX28: 0.05 | DY28: 0 | DZ28: =DX28*DY28 -> 0
M29: 45043 | N29: Comissão Yellow Cab | O29: 16.5 | P29: Cristiana | Q29: 45068 | R29: TIP 409 | S29: 2 | T29: Tomas | U29: 45104 | V29: TIP 316 | W29: 5 | X29: Tomas | AG29: 45181 | AH29: TIP 208 | AI29: 3 | AJ29: Joana | AK29: 45228 | AL29: #215 c/in deve € á receção | AM29: -35 | AN29: Inês | AO29: 45251 | AP29: TIP 406 | AQ29: 1 | AR29: Afonso | AS29: 45284 | AT29: A mais no envelope | AU29: 4.1 | AV29: Afonso | BE29: 45380 | BF29: TIP 309 | BG29: 5 | BH29: Andreia | BI29: 45405 | BJ29: Tips hóspedes | BK29: 9 | BL29: Cristiana | BM29: 45437 | BN29: Dinheiro a mais nas TIP's | BO29: 1.1 | BP29: Andreia | BQ29: 45482 | BR29: Comissão SD | BS29: 515 | BT29: Afonso | BY29: 45530 | BZ29: TIP 203 | CA29: 1.45 | CB29: Afonso | CC29: 45551 | CD29: TIP 306 | CE29: 2.4 | CF29: Afonso/Prazeres | CG29: 45580 | CH29: TIP 302 | CI29: 10 | CJ29: Andreia/Afonso | CK29: 45622 | CL29: Ivan (autorizado - Afonso) | CM29: -30 | CN29: Ivan/Afonso | CO29: 45663 | CP29: Adiantamento Andreia | CR29: Afonso | DX29: 0.02 | DY29: 0 | DZ29: =DX29*DY29 -> 0
M30: 45043 | N30: Comissao Tuk Tuk | O30: 20 | P30: Waleed | Q30: 45068 | R30: TIP 406 + 408 | S30: 5 | T30: Tomas | U30: 45105 | V30: Comissão Yellow Cab | W30: 35 | X30: Daniela | AG30: 45182 | AH30: TIP 210 | AI30: 1 | AJ30: Andreia | AK30: 45228 | AL30: Comissão Where To | AM30: 160.8 | AN30: Afonso | AO30: 45252 | AP30: Comissão Trovas Antigas | AQ30: 10 | AR30: Andreia | AS30: 45285 | AT30: TIP 402 | AU30: 5 | AV30: Tomás | BE30: 45386 | BF30: SD | BG30: 420 | BH30: tommy | BI30: 45405 | BJ30: TIP 201 | BK30: 5 | BL30: Afonso/Tomás | BM30: 45438 | BN30: tip #204 | BO30: 20 | BP30: Renato | BY30: 45530 | BZ30: TIP 306 | CA30: 4 | CB30: Afonso | CC30: 45551 | CD30: Tip Passante | CE30: 5 | CF30: Prazeres | CG30: 45580 | CH30: TIP 412 | CI30: 4 | CJ30: Cris/Afonso | CK30: 45625 | CL30: Tip 315/204 | CM30: 5 | CN30: Ivan | CO30: 45663 | CP30: Adiantamento Renato | CR30: Afonso | DX30: 0.01 | DY30: 1 | DZ30: =DX30*DY30 -> 0.01
M31: 45043 | N31: TIP 316 | O31: 5 | P31: Waleed | Q31: 45068 | R31: Comissão Yellow Cab | S31: 35 | T31: Andreia | U31: 45106 | V31: Comissão Trovas Antigas | W31: 10 | X31: Tomas | AG31: 45182 | AH31: Comissão Yellow Cab | AI31: 33 | AJ31: Andreia | AK31: 45228 | AL31: TIP 103 | AM31: 5 | AN31: Afonso | AO31: 45256 | AP31: Comissão Where To | AQ31: 19.5 | AR31: Inês | AS31: 45287 | AT31: Comissão Where TO | AU31: 39 | AV31: Inês | BI31: 45405 | BJ31: TIP 411 | BK31: 5 | BL31: Afonso/Tomás | BM31: 45438 | BN31: TIP OUT ? | BO31: 20 | BP31: Afonso | BY31: 45533 | BZ31: Serviço trasnfer SUN PAGO | CA31: 35 | CB31: Afonso | CC31: 45551 | CD31: Tip #? | CE31: 2 | CF31: Cristiana | CG31: 45581 | CH31: Tip 211 | CI31: 5 | CJ31: Ivan | CK31: 45625 | CL31: Tip 403 | CM31: 10 | CN31: Afonso | DZ31: =SUM(DZ23:DZ30) -> 0.31
M32: 45044 | N32: TIP 317 | O32: 10 | P32: Cristiana | Q32: 45069 | R32: TIP 205 | S32: 5 | T32: Tomas | U32: 45106 | V32: TIP 303 | W32: 20 | X32: Tomas | AG32: 45183 | AH32: Comissão Where To | AI32: 39 | AJ32: Joana | AK32: 45228 | AL32: 215 Reposição | AM32: 35 | AN32: Inês | AO32: 45256 | AP32: Tip c-outs | AQ32: 2 | AR32: Cristiana | AS32: 45287 | AT32: TIP 206 | AU32: 5 | AV32: Inês | BI32: 45405 | BJ32: Comssião tour sintra | BK32: 19.5 | BL32: Afonso | BM32: 45439 | BN32: TIP #415 | BO32: 10 | BP32: Afonso | BY32: 45533 | BZ32: Afonso | CA32: 10 | CB32: Afonso | CC32: 45552 | CD32: Comissão Where To | CE32: 41.4 | CF32: Andreia/Afonso | CG32: 45581 | CH32: Comissão Where to | CI32: 41.4 | CJ32: Inês | CK32: 45629 | CL32: Andreia (Autorizdo - Afonso | CM32: -180 | CN32: Afonso | DX32: Total | DZ32: =SUM(DZ21+DZ31) -> 55.31
M33: 28/04/203 | N33: TIP 408 | O33: 5 | P33: Cristiana | Q33: 45069 | R33: TIP 101 + 102 | S33: 5 | T33: Tomas | U33: 45118 | V33: SD | W33: 537.5 | X33: Daniela | AG33: 45183 | AH33: Comissão Where To | AI33: 39 | AJ33: Joana | AK33: 45229 | AL33: TIP 103 | AM33: 3 | AN33: Tomás | AO33: 45257 | AP33: Ajuste de contas | AQ33: -4 | AR33: Afonso | AS33: 45287 | AT33: Para fazer caixa do dia | AU33: -1.5 | AV33: Andreia | BI33: 45406 | BJ33: Valor a mais | BK33: 1 | BL33: Renato | BM33: 45439 | BN33: TIP 406 | BO33: 5 | BP33: Afonso/Tomás | BY33: 45544 | BZ33: comissão SD | CA33: 852.75 | CB33: renato | CC33: 45552 | CD33: Tip Passante | CE33: 4 | CF33: Andreia | CG33: 45582 | CH33: TIP 211 | CI33: 10 | CJ33: Afonso | CK33: 45629 | CL33: Ivan (autorizado - Afonso) | CM33: -60 | CN33: Afonso | DY33: Diferença | DZ33: =DZ32-DY2 -> 0
M34: 45044 | N34: TIP | O34: 10 | P34: Andreia | Q34: 45070 | R34: Comissao Yellow Cab | S34: 33 | T34: Afonso | AG34: 45184 | AH34: TIP | AI34: 20 | AJ34: Inês | AK34: 45230 | AL34: Comissão Where To | AM34: 47.4 | AN34: Inês | AO34: 45260 | AP34: TIP Passante | AQ34: 1 | AR34: Andreia | AS34: 45287 | AT34: Tip 411 | AU34: 5 | AV34: Afonso | BI34: 45408 | BJ34: TIP 315 | BK34: 5 | BL34: Andreia | BM34: 45440 | BN34: TIP passante | BO34: 10 | BP34: Renato | CC34: 45553 | CD34: Tip 415 | CE34: 10 Dolla | CF34: Renato | CG34: 45582 | CH34: TIP 416 | CI34: 5 | CJ34: Afonso | CK34: 45635 | CL34: Adiantamento Andreia | CM34: 180 | CN34: Afonso
M35: 45046 | N35: tip416 | O35: 0.5 | P35: Cristiana | Q35: 45070 | R35: TIP 415 | S35: 2 | T35: Andreia | AG35: 45184 | AH35: TIP 210 | AI35: 1 | AJ35: Joana | AK35: 45230 | AL35: TIP 305 | AM35: 2.41 | AN35: Tomás | AO35: 45265 | AP35: Comissão SunDestiny | AQ35: 536 | AR35: Andreia | AS35: 45287 | AT35: Reposição das tips | AU35: 1.5 | AV35: Afonso | BI35: 45409 | BJ35: TIP 404 | BK35: 10 | BL35: Andreia | BM35: 45442 | BN35: TIP 211 | BO35: 5 | BP35: Tomás | CC35: 45553 | CD35: TIP 302 | CE35: 10 | CF35: Andreia | CG35: 45582 | CH35: A mais na caixa | CI35: 4 | CJ35: Afonso | CK35: 45635 | CL35: Adiantamento Ivan | CM35: 180 | CN35: Afonso
M36: 45046 | N36: Comissão Where To | O36: 39 | P36: Cristiana | Q36: 45070 | R36: TIP 311 | S36: 2 | T36: Andreia | AG36: 45184 | AH36: TIP 202 | AI36: 10 | AJ36: Andreia | AK36: 45231 | AL36: Ajuste de contas | AM36: -13.2 | AN36: Afonso | AQ36: 45.6 | AS36: 45288 | AT36: TIP 216 | AU36: 10 | AV36: Afonso | BI36: 45409 | BJ36: A mais | BK36: 2 | BL36: Afonso | BM36: 45453 | BN36: Comissões SD | BO36: 633 | BP36: Afonso | CC36: 45555 | CD36: Tour não realizado Where To | CE36: -41.4 | CF36: Afonso | CG36: 45583 | CH36: TIP Passante | CI36: 10 | CJ36: Afonso | CK36: 45635 | CL36: Adiantamento Renato | CM36: 10 | CN36: Afonso
M37: 45046 | N37: TIP | O37: 1.18 | P37: Andreia | Q37: 45071 | R37: TIP 205 | S37: 1 | T37: Afonso | AG37: 45186 | AH37: TIP 211 | AI37: 0.5 | AJ37: Waleed | AK37: 45239 | AL37: Comissão SunDestiny | AM37: 866 | AN37: Andreia | AS37: 45288 | AT37: Walk-in 408 | AU37: 6 | AV37: Tomás | BI37: 45409 | BJ37: TIP 404 | BK37: 3 | BL37: Cris | CC37: 45555 | CD37: TIP 416 | CE37: 10 | CF37: Andreia | CG37: 45583 | CH37: Andreia (Autorizado - Afonso) | CI37: -100 | CJ37: Andreia | CK37: 45635 | CL37: Sun | CM37: 525 | CN37: Afonso
M38: 45050 | N38: Comissão SD | O38: 601 | P38: Daniela | Q38: 45071 | R38: TIP 301 | S38: 5 | T38: Afonso | AG38: 45186 | AH38: TIP 404 | AI38: 4 | AJ38: Odair | AS38: 45290 | AT38: TIP 204 | AU38: 3 | AV38: Afonso | BI38: 45412 | BJ38: TIP 116 | BK38: 3 | BL38: Cris | CC38: 45556 | CD38: TIP 215 | CE38: 5 | CF38: Afonso | CG38: 45583 | CH38: Ivan (Autorizado - Afonso) | CI38: -5 | CJ38: Ivan
Q39: 45071 | R39: TIP passante | S39: 2 | T39: Cristiana | AG39: 45188 | AH39: SOBRA CAIXA | AI39: 6 | AJ39: Daniela | AS39: 45291 | AT39: TIP 405 | AU39: 3 | AV39: Cristiana | BI39: 45412 | BJ39: Comissão tour sintra (23/04) | BK39: 19 | BL39: Cris | CC39: 45556 | CD39: Ivan (Autorizado-Afonso) | CE39: -50 | CF39: Afonso | CG39: 45584 | CH39: TIP 102 | CI39: 10 | CJ39: Andreia
Q40: 45072 | R40: TIP 306+309 | S40: 5.14 | T40: Daniela | AG40: 45187 | AH40: TIP 301,302,316 | AI40: 22 | AJ40: Daniela | BI40: 45412 | BJ40: TIP 401 | BK40: 10 | BL40: Afonso | CC40: 45556 | CD40: TIP 303 | CE40: 5 | CF40: Afonso | CG40: 45585 | CH40: Comissão YellowCab | CI40: 38 | CJ40: Cris
Q41: 45072 | R41: Tip 402 | S41: 5 | T41: Afonso | AG41: 45187 | AH41: TIP | AI41: 3 | AJ41: Daniela | BI41: 45415 | BJ41: City Sighseeing | BK41: 50.5 | BL41: Inês | CC41: 45558 | CD41: Tip #104 | CE41: 2 | CF41: Prazeres | CG41: 45586 | CH41: out 406 | CI41: 2.2 | CJ41: Cris
Q42: 45072 | R42: TIP 311 | S42: 5 | T42: Tomas | AG42: 45188 | AH42: TIP Passante | AI42: 1.2 | AJ42: Andreia | BI42: 45419 | BJ42: Comissão Carmo | BK42: 128 | BL42: Tomás | CC42: 45561 | CD42: Comissão Trovas Antigas | CE42: 50 | CF42: Inês | CG42: 45588 | CH42: Ivan (Autorizado - Afonso) | CI42: -10 | CJ42: Ivan
Q43: 45073 | R43: Tip 306 | S43: 10 | T43: Afonso | AG43: 45188 | AH43: Comissão Yellow Cab | AI43: 33 | AJ43: Andreia | BI43: 45421 | BJ43: Comissão Trovas Antigas | BK43: 50 | BL43: Tomás | CC43: 45562 | CD43: Tip 416 | CE43: 0.5 | CF43: Prazeres | CG43: 45590 | CH43: TIP 215 | CI43: 2 | CJ43: Andreia
Q44: 45074 | R44: TIP 304 | S44: 5 | T44: Andreia | AG44: 45192 | AH44: TIP 405 | AI44: 1.1 | AJ44: Tomás/Afonso | CC44: 45562 | CD44: Transfer Website Não marcado | CE44: -22 | CF44: Afonso | CG44: 45591 | CH44: Ivan (Autorizado - Afonso) | CI44: -20 | CJ44: Ivan
Q45: 45076 | R45: TIP 215 | S45: 5 | T45: Tomás | AG45: 45193 | AH45: TIP 209+210 | AI45: 7 | AJ45: Tomás | CC45: 45562 | CD45: A mais | CE45: 1.52 | CF45: Afonso | CG45: 45592 | CH45: Renato (Autorizado - Afonso) | CI45: -4.06 | CJ45: Afonso
Q46: 45077 | R46: TIP | S46: 10 | T46: Afonso | AG46: 45194 | AH46: TIP | AI46: 5 | AJ46: Cristiana | CC46: 45562 | CD46: TIP 204 | CE46: 20 | CF46: Afonso | CG46: 45592 | CH46: TIP OUT 316 | CI46: 5 | CJ46: Cris/ Inês
Q47: 45077 | R47: TIP 416 | S47: 4 | T47: Afonso | AG47: 45194 | AH47: TIP | AI47: 1 | AJ47: Tomás | CC47: 45564 | CD47: TIP 211 | CE47: 0.5 | CF47: Inês | CG47: 45592 | CH47: TIP 416 | CI47: 3 | CJ47: Cris | DO47: Saldo | DQ47: =SUM(DQ3:DQ46) -> -844.38
Q48: 45080 | R48: Comissão SD | S48: 662 | T48: Daniela | AG48: 45198 | AH48: TIP | AI48: 2 | AJ48: Andreia | CC48: 45564 | CD48: TIP 415 | CE48: 2 | CF48: Afonso | CG48: 45593 | CH48: Ivan (Autorizado - Afonso) | CI48: -20 | CJ48: Ivan | DK48: 45853 | DL48: HSK | DM48: -50 | DN48: Pedro
AG49: 45199 | AH49: Saldo a mais | AI49: 34.09 | AJ49: Afonso/Andreia | CC49: 45564 | CD49: TIP 303 | CE49: 10 | CF49: Afonso | CG49: 45594 | CH49: Comissão CitySightSeeing | CI49: 119 | CJ49: Andreia
CC61: 45565 | CD61: Tip 407 | CE61: 3.5 | CF61: Cris | CG61: 45594 | CH61: Comissão Where to | CI61: 41.4 | CJ61: Afonso/Cris
AG62: 45208 | AH62: Comissão SunDestiny | AI62: 664 | AJ62: Andreia | CC62: 45565 | CD62: Tip 403 | CE62: 10 | CF62: Inês | CG62: 45595 | CH62: TIP 208 | CI62: 2 | CJ62: Andreia
CC63: 45573 | CD63: SUN | CE63: 902.5 | CG63: 45596 | CH63: Troco 309 | CI63: 0.5 | CJ63: Andreia
CG64: 45599 | CH64: Ivan (Autorizado - Afonso) | CI64: -20 | CJ64: Ivan
CG65: 45599 | CH65: Andreia (Autorizado - Afonso) | CI65: -50 | CJ65: Andreia
CG66: 45600 | CH66: Ivan (Autorizado - Afonso) | CI66: -50 | CJ66: Ivan
CG67: 45603 | CH67: Ivan (Autorizado - Afonso) | CI67: -30 | CJ67: Ivan
CG68: 45604 | CH68: Sun | CI68: 731.5 | CJ68: Afonso
CD69: adiantamentos | CE69: 105 | CG69: 45604 | CH69: Adiantamentos IVAN | CI69: 155
CD70: adiantamentos | CE70: 105 | CG70: 45604 | CH70: Adiantamentos ANDREIA | CI70: 150
CD71: adiantamentos | CE71: 105 | CG71: 45604 | CH71: Adiantamentos RENATO | CI71: 9
A72: Saldo | C72: =SUM(C3:C62) -> 678.85 | E72: Saldo | G72: =SUM(G3:G62) -> 365.72 | I72: Saldo | K72: =SUM(K3:K62) -> 903.95 | M72: Saldo | O72: =SUM(O3:O62) -> 1167.63 | Q72: Saldo | S72: =SUM(S3:S62) -> 1057.86 | U72: Saldo | W72: =SUM(W3:W62) -> 1043.17 | Y72: Saldo | AA72: =SUM(AA3:AA62) -> 834.48 | AC72: Saldo | AE72: =SUM(AE3:AE62) -> 642.63 | AG72: Saldo | AI72: =SUM(AI3:AI62) -> 1428.11 | AK72: Saldo | AM72: =SUM(AM3:AM62) -> 1661.37 | AO72: Saldo | AQ72: =SUM(AQ3:AQ62) -> 1161.01 | AS72: Saldo | AU72: =SUM(AU3:AU62) -> 518.96 | AW72: Saldo | AY72: =SUM(AY3:AY62) -> 350.18 | BA72: Saldo | BC72: =SUM(BC3:BC62) -> 832.82 | BE72: Saldo | BG72: =SUM(BG3:BG62) -> 967.9 | BI72: Saldo | BK72: =SUM(BK3:BK62) -> 480 | BM72: Saldo | BO72: =SUM(BO3:BO62) -> 1173.37 | BQ72: Saldo | BS72: =SUM(BS3:BS62) -> 913.82 | BU72: Saldo | BW72: =SUM(BW3:BW62) -> 692.24 | BY72: Saldo | CA72: =SUM(CA3:CA62) -> 1254.32 | CC72: Saldo | CE72: =SUM(CE3:CE71) -> 1498.84 | CG72: Saldo | CI72: =SUM(CI3:CI71) -> 1484.68 | CK72: Saldo | CM72: =SUM(CM3:CM71) -> 1066.68 | CO72: Saldo | CQ72: =SUM(CQ3:CQ71) -> 269.79 | CS72: Saldo | CU72: =SUM(CU3:CU71) -> 366.5 | CW72: Saldo | CY72: =SUM(CY3:CY71) -> 340.25 | DA72: Saldo | DC72: =SUM(DC3:DC71) -> 647.2 | DE72: Saldo | DG72: =SUM(DG3:DG71) -> 5.5 | DK72: Saldo | DM72: =SUM(DM3:DM71) -> -34.3 | DT72: Saldo | DV72: =SUM(DV3:DV71) -> 0
DE73: Base de cálculo | DK73: Base de cálculo | DT73: Base de cálculo
A74: Base de cálculo | E74: Base de cálculo | I74: Base de cálculo | M74: Base de cálculo | Q74: Base de cálculo | U74: Base de cálculo | Y74: Base de cálculo | AC74: Base de cálculo | AG74: Base de cálculo | AK74: Base de cálculo | AO74: Base de cálculo | AS74: Base de cálculo | AW74: Base de cálculo | BA74: Base de cálculo | BE74: Base de cálculo | BI74: Base de cálculo | BM74: Base de cálculo | BQ74: Base de cálculo | BU74: Base de cálculo | BY74: Base de cálculo | CC74: Base de cálculo | CG74: Base de cálculo | CK74: Base de cálculo | CO74: Base de cálculo | CS74: Base de cálculo | CW74: Base de cálculo | DA74: Base de cálculo
A75: Total comissão | B75: =+C72 -> 678.85 | E75: Total comissão | F75: =+G72 -> 365.72 | I75: Total comissão | J75: =+K72 -> 903.95 | M75: Total comissão | N75: =+O72 -> 1167.63 | Q75: Total comissão | R75: =+S72 -> 1057.86 | U75: Total comissão | V75: =+W72 -> 1043.17 | Y75: Total comissão | Z75: =+AA72 -> 834.48 | AC75: Total comissão | AD75: =+AE72 -> 642.63 | AG75: Total comissão | AH75: =+AI72 -> 1428.11 | AK75: Total comissão | AL75: =+AM72 -> 1661.37 | AO75: Total comissão | AP75: =+AQ72 -> 1161.01 | AS75: Total comissão | AT75: =+AU72 -> 518.96 | AW75: Total comissão | AX75: =+AY72 -> 350.18 | BA75: Total comissão | BB75: =+BC72 -> 832.82 | BE75: Total comissão | BF75: =+BG72 -> 967.9 | BI75: Total comissão | BJ75: =+BK72 -> 480 | BM75: Total comissão | BN75: =+BO72 -> 1173.37 | BQ75: Total comissão | BR75: =+BS72 -> 913.82 | BU75: Total comissão | BV75: =+BW72 -> 692.24 | BY75: Total comissão | BZ75: =+CA72 -> 1254.32 | CC75: Total comissão | CD75: =+CE72 -> 1498.84 | CG75: Total comissão | CH75: =+CI72 -> 1484.68 | CK75: Total comissão | CL75: =+CM72 -> 1066.68 | CO75: Total comissão | CP75: =+CQ72 -> 269.79 | CS75: Total comissão | CT75: =+CU72 -> 366.5 | CW75: Total comissão | CX75: =+CY72 -> 340.25 | DA75: Total comissão | DB75: =+DC72 -> 647.2 | DE75: Total comissão | DF75: =+DG72 -> 5.5 | DK75: Total comissão | DL75: =+DM72 -> -34.3 | DT75: Total comissão | DU75: =+DV72 -> 0
A76: Dias trabalho padrão | B76: 31 | E76: Dias trabalho padrão | F76: 31 | I76: Dias trabalho padrão | J76: 31 | M76: Dias trabalho padrão | N76: 30 | Q76: Dias trabalho padrão | R76: 31 | U76: Dias trabalho padrão | V76: 30 | Y76: Dias trabalho padrão | Z76: 30 | AC76: Dias trabalho padrão | AD76: 31 | AG76: Dias trabalho padrão | AH76: 30 | AK76: Dias trabalho padrão | AL76: 31 | AO76: Dias trabalho padrão | AP76: 30 | AS76: Dias trabalho padrão | AT76: 31 | AW76: Dias trabalho padrão | AX76: 31 | BA76: Dias trabalho padrão | BB76: 29 | BE76: Dias trabalho padrão | BF76: 31 | BI76: Dias trabalho padrão | BJ76: 30 | BM76: Dias trabalho padrão | BN76: 31 | BQ76: Dias trabalho padrão | BR76: 30 | BU76: Dias trabalho padrão | BV76: 31 | BY76: Dias trabalho padrão | BZ76: 31 | CC76: Dias trabalho padrão | CD76: 30 | CG76: Dias trabalho padrão | CH76: 31 | CK76: Dias trabalho padrão | CL76: 30 | CO76: Dias trabalho padrão | CP76: 31 | CS76: Dias trabalho padrão | CT76: 31 | CW76: Dias trabalho padrão | CX76: 28 | DA76: Dias trabalho padrão | DB76: 31 | DE76: Dias trabalho padrão | DF76: 31 | DK76: Dias trabalho padrão | DL76: 31 | DT76: Dias trabalho padrão | DU76: 31
A77: Ausências | B77: =+SUM(B83:B91) -> 68 | E77: Ausências | F77: =+SUM(F83:F91) -> 66 | I77: Ausências | J77: =+SUM(J83:J91) -> 50 | M77: Ausências | N77: =+SUM(N83:N91) -> 91 | Q77: Ausências | R77: =+SUM(R83:R91) -> 77 | U77: Ausências | V77: =+SUM(V83:V91) -> 75 | Y77: Ausências | Z77: =+SUM(Z83:Z91) -> 89 | AC77: Ausências | AD77: =+SUM(AD83:AD91) -> 69 | AG77: Ausências | AK77: Ausências | AL77: =+SUM(AL83:AL91) -> 0 | AO77: Ausências | AP77: =+SUM(AP83:AP91) -> 0 | AS77: Ausências | AT77: =+SUM(AT83:AT91) -> 0 | AW77: Ausências | AX77: =+SUM(AX83:AX91) -> 0 | BA77: Ausências | BB77: =+SUM(BB83:BB91) -> 0 | BE77: Ausências | BF77: =+SUM(BF83:BF91) -> 0 | BI77: Ausências | BJ77: 0 | BM77: Ausências | BN77: 0 | BQ77: Ausências | BR77: 0 | BU77: Ausências | BV77: 0 | BY77: Ausências | BZ77: 0 | CC77: Ausências | CD77: 0 | CG77: Ausências | CH77: 0 | CK77: Ausências | CL77: 0 | CO77: Ausências | CP77: 0 | CS77: Ausências | CT77: 0 | CW77: Ausências | CX77: 0 | DA77: Ausências | DB77: 0 | DE77: Ausências | DF77: 0 | DK77: Ausências | DL77: 0 | DT77: Ausências | DU77: 0
A78: Numero de recepcionistas | B78: 6 | E78: Numero de recepcionistas | F78: 6 | I78: Numero de recepcionistas | J78: 5 | M78: Numero de recepcionistas | N78: 7 | Q78: Numero de recepcionistas | R78: 7 | U78: Numero de recepcionistas | V78: 7 | Y78: Numero de recepcionistas | Z78: 7 | AC78: Numero de recepcionistas | AD78: 7 | AG78: Numero de recepcionistas | AH78: 8 | AK78: Numero de recepcionistas | AL78: 6 | AO78: Numero de recepcionistas | AP78: 6 | AS78: Numero de recepcionistas | AT78: 5 | AW78: Numero de recepcionistas | AX78: 5 | BA78: Numero de recepcionistas | BB78: 6 | BE78: Numero de recepcionistas | BF78: 6 | BI78: Numero de recepcionistas | BJ78: 6 | BM78: Numero de recepcionistas | BN78: 6 | BQ78: Numero de recepcionistas | BR78: 6 | BU78: Numero de recepcionistas | BV78: 6 | BY78: Numero de recepcionistas | BZ78: 5 | CC78: Numero de recepcionistas | CD78: 6 | CG78: Numero de recepcionistas | CH78: 6 | CK78: Numero de recepcionistas | CL78: 6 | CO78: Numero de recepcionistas | CP78: 6 | CS78: Numero de recepcionistas | CT78: 6 | CW78: Numero de recepcionistas | CX78: 6 | DA78: Numero de recepcionistas | DB78: 6 | DE78: Numero de recepcionistas | DF78: 7 | DK78: Numero de recepcionistas | DL78: 7 | DT78: Numero de recepcionistas | DU78: 7
A79: Total dias trabalhados | B79: =+(B76*B78)-B77 -> 118 | E79: Total dias trabalhados | F79: =+(F76*F78)-F77 -> 120 | I79: Total dias trabalhados | J79: =+(J76*J78)-J77 -> 105 | M79: Total dias trabalhados | N79: =+(N76*N78)-N77 -> 119 | Q79: Total dias trabalhados | R79: =+(R76*R78)-R77 -> 140 | U79: Total dias trabalhados | V79: =+(V76*V78)-V77 -> 135 | Y79: Total dias trabalhados | Z79: =+(Z76*Z78)-Z77 -> 121 | AC79: Total dias trabalhados | AD79: =+(AD76*AD78)-AD77 -> 148 | AG79: Total dias trabalhados | AH79: =+(AH76*AH78)-AH77 -> 240 | AK79: Total dias trabalhados | AL79: =+(AL76*AL78)-AL77 -> 186 | AO79: Total dias trabalhados | AP79: =+(AP76*AP78)-AP77 -> 180 | AS79: Total dias trabalhados | AT79: =+(AT76*AT78)-AT77 -> 155 | AW79: Total dias trabalhados | AX79: =+(AX76*AX78)-AX77 -> 155 | BA79: Total dias trabalhados | BB79: =+(BB76*BB78)-BB77 -> 174 | BE79: Total dias trabalhados | BF79: =+(BF76*BF78)-BF77 -> 186 | BI79: Total dias trabalhados | BJ79: =+(BJ76*BJ78)-BJ77 -> 180 | BM79: Total dias trabalhados | BN79: =+(BN76*BN78)-BN77 -> 186 | BQ79: Total dias trabalhados | BR79: =+(BR76*BR78)-BR77 -> 180 | BU79: Total dias trabalhados | BV79: =+(BV76*BV78)-BV77 -> 186 | BY79: Total dias trabalhados | BZ79: =+(BZ76*BZ78)-BZ77 -> 155 | CC79: Total dias trabalhados | CD79: =+(CD76*CD78)-CD77 -> 180 | CG79: Total dias trabalhados | CH79: =+(CH76*CH78)-CH77 -> 186 | CK79: Total dias trabalhados | CL79: =+(CL76*CL78)-CL77 -> 180 | CO79: Total dias trabalhados | CP79: =+(CP76*CP78)-CP77 -> 186 | CS79: Total dias trabalhados | CT79: =+(CT76*CT78)-CT77 -> 186 | CW79: Total dias trabalhados | CX79: =+(CX76*CX78)-CX77 -> 168 | DA79: Total dias trabalhados | DB79: =+(DB76*DB78)-DB77 -> 186 | DE79: Total dias trabalhados | DF79: =+(DF76*DF78)-DF77 -> 217 | DK79: Total dias trabalhados | DL79: =+(DL76*DL78)-DL77 -> 217 | DT79: Total dias trabalhados | DU79: =+(DU76*DU78)-DU77 -> 217
A80: Valor por dia trabalhado | B80: =+B75/B79 -> 5.7529661 | E80: Valor por dia trabalhado | F80: =+F75/F79 -> 3.0476667 | I80: Valor por dia trabalhado | J80: =+J75/J79 -> 8.6090476 | M80: Valor por dia trabalhado | N80: =+N75/N79 -> 9.8120168 | Q80: Valor por dias trabalhados | R80: =+R75/R79 -> 7.5561429 | U80: Valor por dia trabalhado | V80: =+V75/V79 -> 7.7271852 | Y80: Valor por dias trabalhados | Z80: =+Z75/Z79 -> 6.8965289 | AC80: Valor por dias trabalhados | AD80: =+AD75/AD79 -> 4.3420946 | AG80: Valor por dias trabalhados | AH80: =+AH75/AH79 -> 5.9504583 | AK80: Valor por dias trabalhados | AL80: =+AL75/AL79 -> 8.9320968 | AO80: Valor por dias trabalhados | AP80: =+AP75/AP79 -> 6.4500556 | AS80: Valor por dias trabalhados | AT80: =+AT75/AT79 -> 3.348129 | AW80: Valor por dias trabalhados | AX80: =+AX75/AX79 -> 2.2592258 | BA80: Valor por dias trabalhados | BB80: =+BB75/BB79 -> 4.7863218 | BE80: Valor por dias trabalhados | BF80: =+BF75/BF79 -> 5.2037634 | BI80: Valor por dias trabalhados | BJ80: =+BJ75/BJ79 -> 2.6666667 | BM80: Valor por dias trabalhados | BN80: =+BN75/BN79 -> 6.3084409 | BQ80: Valor por dias trabalhados | BR80: =+BR75/BR79 -> 5.0767778 | BU80: Valor por dias trabalhados | BV80: =+BV75/BV79 -> 3.7217204 | BY80: Valor por dias trabalhados | BZ80: =+BZ75/BZ79 -> 8.0923871 | CC80: Valor por dias trabalhados | CD80: =+CD75/CD79 -> 8.3268889 | CG80: Valor por dias trabalhados | CH80: =+CH75/CH79 -> 7.9821505 | CK80: Valor por dias trabalhados | CL80: =+CL75/CL79 -> 5.926 | CO80: Valor por dias trabalhados | CP80: =+CP75/CP79 -> 1.4504839 | CS80: Valor por dias trabalhados | CT80: =+CT75/CT79 -> 1.9704301 | CW80: Valor por dias trabalhados | CX80: =+CX75/CX79 -> 2.0252976 | DA80: Valor por dias trabalhados | DB80: =+DB75/DB79 -> 3.4795699 | DE80: Valor por dias trabalhados | DF80: =+DF75/DF79 -> 0.025345622 | DK80: Valor por dias trabalhados | DL80: =+DL75/DL79 -> -0.15806452 | DT80: Valor por dias trabalhados | DU80: =+DU75/DU79 -> 0
A82: Nome | B82: Ausências | C82: Dias disponíveis | D82: Total | E82: Nome | F82: Ausências | G82: Dias disponíveis | H82: Total | I82: Nome | J82: Ausências | K82: Dias disponíveis | L82: Total | M82: Nome | N82: Ausências | O82: Dias disponíveis | P82: Total | Q82: Nome | R82: Ausências | S82: Dias disponíveis | T82: Total | U82: Nome | V82: Ausências | W82: Dias disponíveis | X82: Total | Y82: Nome | Z82: Ausências | AA82: Dias disponíveis | AB82: Total | AC82: Nome | AD82: Ausências | AE82: Dias disponíveis | AF82: Total | AG82: Nome | AH82: Ausências | AI82: Dias disponíveis | AJ82: Total | AK82: Nome | AL82: Ausências | AM82: Dias disponíveis | AN82: Total | AO82: Nome | AP82: Ausências | AQ82: Dias disponíveis | AR82: Total | AS82: Nome | AT82: Ausências | AU82: Dias disponíveis | AV82: Total | AW82: Nome | AX82: Ausências | AY82: Dias disponíveis | AZ82: Total | BA82: Nome | BB82: Ausências | BC82: Dias disponíveis | BD82: Total | BE82: Nome | BF82: Ausências | BG82: Dias disponíveis | BH82: Total | BI82: Nome | BJ82: Ausências | BK82: Dias disponíveis | BL82: Total | BM82: Nome | BN82: Ausências | BO82: Dias disponíveis | BP82: Total | BQ82: Nome | BR82: Ausências | BS82: Dias disponíveis | BT82: Total | BU82: Nome | BV82: Ausências | BW82: Dias disponíveis | BX82: Total | BY82: Nome | BZ82: Ausências | CA82: Dias disponíveis | CB82: Total | CC82: Nome | CD82: Ausências | CE82: Dias disponíveis | CF82: Total | CG82: Nome | CH82: Ausências | CI82: Dias disponíveis | CJ82: Total | CK82: Nome | CL82: Ausências | CM82: Dias disponíveis | CN82: Total | CO82: Nome | CP82: Ausências | CQ82: Dias disponíveis | CR82: Total | CS82: Nome | CT82: Ausências | CU82: Dias disponíveis | CV82: Total | CW82: Nome | CX82: Ausências | CY82: Dias disponíveis | CZ82: Total | DA82: Nome | DB82: Ausências | DC82: Dias disponíveis | DD82: Total | DE82: Nome | DF82: Dias disponíveis | DG82: Total | DK82: Nome | DL82: Dias disponíveis | DM82: Total | DT82: Nome | DU82: Dias disponíveis | DV82: Total
A83: Afonso | B83: 11 | C83: =+B76-B83 -> 20 | D83: =+B80*C83 -> 115.05932 | E83: Afonso | F83: 12 | G83: =+F76-F83 -> 19 | H83: =+F80*G83 -> 57.905667 | I83: Afonso | J83: 10 | K83: =+J76-J83 -> 21 | L83: =+J80*K83 -> 180.79 | M83: Afonso | N83: 10 | O83: =+N76-N83 -> 20 | P83: =+N80*O83 -> 196.24034 | Q83: Afonso | R83: 13 | S83: =+R76-R83 -> 18 | T83: =+R80*S83 -> 136.01057 | U83: Afonso | V83: 9 | W83: =+V76-V83 -> 21 | X83: =+V80*W83 -> 162.27089 | Y83: Afonso | Z83: 13 | AA83: =+Z76-Z83 -> 17 | AB83: =+Z80*AA83 -> 117.24099 | AC83: Afonso | AD83: 10 | AE83: =+AD76-AD83 -> 21 | AF83: =+AD80*AE83 -> 91.183986 | AG83: Afonso | AI83: =+AH76-AH83 -> 30 | AJ83: =+AH80*AI83 -> 178.51375 | AK83: Afonso | AM83: =+AL76-AL83 -> 31 | AN83: =+AL80*AM83 -> 276.895 | AO83: Afonso | AQ83: =+AP76-AP83 -> 30 | AR83: =+AP80*AQ83 -> 193.50167 | AS83: Afonso | AU83: =+AT76-AT83 -> 31 | AV83: =+AT80*AU83 -> 103.792 | AW83: Afonso | AY83: =+AX76-AX83 -> 31 | AZ83: =+AX80*AY83 -> 70.036 | BA83: Afonso | BC83: =+BB76-BB83 -> 29 | BD83: 150 | BE83: Afonso | BG83: 31 | BH83: =+BF80*BG83 -> 161.31667 | BI83: Afonso | BK83: 30 | BL83: =+BJ80*BK83 -> 80 | BM83: Afonso | BO83: 31 | BP83: =+BN80*BO83 -> 195.56167 | BQ83: Afonso | BS83: 30 | BT83: =+BR80*BS83 -> 152.30333 | BU83: Afonso | BW83: 31 | BX83: =+BV80*BW83 -> 115.37333 | BY83: Afonso | CA83: 31 | CB83: =+BZ80*CA83 -> 250.864 | CC83: Afonso | CE83: 30 | CF83: =+CD80*CE83 -> 249.80667 | CG83: Afonso | CI83: 31 | CJ83: =+CH80*CI83 -> 247.44667 | CK83: Afonso | CM83: 30 | CN83: =+CL80*CM83 -> 177.78 | CO83: Afonso | CQ83: 31 | CR83: =+CP80*CQ83 -> 44.965 | CS83: Afonso | CU83: 31 | CV83: =+CT80*CU83 -> 61.083333 | CW83: Afonso | CY83: 28 | CZ83: =+CX80*CY83 -> 56.708333 | DA83: Afonso | DC83: 31 | DD83: =+DB80*DC83 -> 107.86667 | DE83: Afonso | DF83: 31 | DG83: =+DF80*DF83 -> 0.78571429 | DK83: Afonso | DL83: 31 | DM83: =+DL80*DL83 -> -4.9 | DT83: Afonso | DU83: 31 | DV83: =+DU80*DU83 -> 0
A84: Andreia | B84: 17 | C84: =+B76-B84 -> 14 | D84: =+B80*C84 -> 80.541525 | E84: Andreia | F84: 8 | G84: =+F76-F84 -> 23 | H84: =+F80*G84 -> 70.096333 | I84: Andreia | J84: 9 | K84: =+J76-J84 -> 22 | L84: =+J80*K84 -> 189.39905 | M84: Andreia | N84: 9 | O84: =+N76-N84 -> 21 | P84: =+N80*O84 -> 206.05235 | Q84: Andreia | R84: 9 | S84: =+R76-R84 -> 22 | T84: =+R80*S84 -> 166.23514 | U84: Andreia | V84: 10 | W84: =+V76-V84 -> 20 | X84: =+V80*W84 -> 154.5437 | Y84: Andreia | Z84: 18 | AA84: =+Z76-Z84 -> 12 | AB84: =+Z80*AA84 -> 82.758347 | AC84: Andreia | AD84: 9 | AE84: =+AD76-AD84 -> 22 | AF84: =+AD80*AE84 -> 95.526081 | AG84: Andreia | AI84: =+AH76-AH84 -> 30 | AJ84: =+AH80*AI84 -> 178.51375 | AK84: Andreia | AM84: =+AL76-AL84 -> 31 | AN84: =+AL80*AM84 -> 276.895 | AO84: Andreia | AQ84: =+AP76-AP84 -> 30 | AR84: =+AP80*AQ84 -> 193.50167 | AS84: Andreia | AU84: =+AT76-AT84 -> 31 | AV84: =+AT80*AU84 -> 103.792 | AW84: Andreia | AY84: =+AX76-AX84 -> 31 | AZ84: =+AX80*AY84 -> 70.036 | BA84: Andreia | BC84: =+BB76-BB84 -> 29 | BD84: 150 | BE84: Andreia | BG84: =+BF76-BF84 -> 31 | BH84: =+BF80*BG84 -> 161.31667 | BI84: Andreia | BK84: =+BJ76-BJ84 -> 30 | BL84: =+BJ80*BK84 -> 80 | BM84: Andreia | BO84: =+BN76-BN84 -> 31 | BP84: =+BN80*BO84 -> 195.56167 | BQ84: Andreia | BS84: 30 | BT84: =+BR80*BS84 -> 152.30333 | BU84: Andreia | BW84: 31 | BX84: =+BV80*BW84 -> 115.37333 | BY84: Andreia | CA84: 31 | CB84: =+BZ80*CA84 -> 250.864 | CC84: Andreia | CE84: 30 | CF84: =+CD80*CE84 -> 249.80667 | CG84: Andreia | CI84: 31 | CJ84: =+CH80*CI84 -> 247.44667 | CK84: Andreia | CM84: 30 | CN84: =+CL80*CM84 -> 177.78 | CO84: Andreia | CQ84: 31 | CR84: =+CP80*CQ84 -> 44.965 | CS84: Andreia | CU84: 31 | CV84: =+CT80*CU84 -> 61.083333 | CW84: Andreia | CY84: 28 | CZ84: =+CX80*CY84 -> 56.708333 | DA84: Andreia | DC84: 31 | DD84: =+DB80*DC84 -> 107.86667 | DE84: Carolina | DF84: 31 | DG84: =+DF80*DF84 -> 0.78571429 | DK84: Carolina | DL84: 31 | DM84: =+DL80*DL84 -> -4.9 | DT84: Carolina | DU84: 31 | DV84: =+DU80*DU84 -> 0
A85: Cristiana | B85: 10 | C85: =+B76-B85 -> 21 | D85: =+B80*C85 -> 120.81229 | E85: Cristiana | F85: 12 | G85: =+F76-F85 -> 19 | H85: =+F80*G85 -> 57.905667 | I85: Cristiana | J85: 9 | K85: =+J76-J85 -> 22 | L85: =+J80*K85 -> 189.39905 | M85: Cristiana | N85: 10 | O85: =+N76-N85 -> 20 | P85: =+N80*O85 -> 196.24034 | Q85: Cristiana | R85: 16 | S85: =+R76-R85 -> 15 | T85: =+R80*S85 -> 113.34214 | U85: Cristiana | V85: 14 | W85: =+V76-V85 -> 16 | X85: =+V80*W85 -> 123.63496 | Y85: Cristiana | Z85: 10 | AA85: =+Z76-Z85 -> 20 | AB85: =+Z80*AA85 -> 137.93058 | AC85: Cristiana | AD85: 13 | AE85: =+AD76-AD85 -> 18 | AF85: =+AD80*AE85 -> 78.157703 | AG85: Cristiana | AI85: =+AH76-AH85 -> 30 | AJ85: =+AH80*AI85 -> 178.51375 | AK85: Cristiana | AM85: =+AL76-AL85 -> 31 | AN85: =+AL80*AM85 -> 276.895 | AO85: Cristiana | AQ85: =+AP76-AP85 -> 30 | AR85: =+AP80*AQ85 -> 193.50167 | AS85: Cristiana | AU85: =+AT76-AT85 -> 31 | AV85: =+AT80*AU85 -> 103.792 | AW85: Cristiana | AY85: =+AX76-AX85 -> 31 | AZ85: =+AX80*AY85 -> 70.036 | BA85: Cristiana | BC85: =+BB76-BB85 -> 29 | BD85: 150 | BE85: Cristiana | BG85: =+BF76-BF85 -> 31 | BH85: =+BF80*BG85 -> 161.31667 | BI85: Cristiana | BK85: =+BJ76-BJ85 -> 30 | BL85: =+BJ80*BK85 -> 80 | BM85: Cristiana | BO85: =+BN76-BN85 -> 31 | BP85: =+BN80*BO85 -> 195.56167 | BQ85: Cristiana | BS85: 30 | BT85: =+BR80*BS85 -> 152.30333 | BU85: Cristiana | BW85: 31 | BX85: =+BV80*BW85 -> 115.37333 | BY85: Cristiana | CA85: 31 | CB85: =+BZ80*CA85 -> 250.864 | CC85: Cristiana | CE85: 30 | CF85: =+CD80*CE85 -> 249.80667 | CG85: Cristiana | CI85: 31 | CJ85: =+CH80*CI85 -> 247.44667 | CK85: Cristiana | CM85: 30 | CN85: =+CL80*CM85 -> 177.78 | CO85: Cristiana | CQ85: 31 | CR85: =+CP80*CQ85 -> 44.965 | CS85: Cristiana | CU85: 31 | CV85: =+CT80*CU85 -> 61.083333 | CW85: Cristiana | CY85: 28 | CZ85: =+CX80*CY85 -> 56.708333 | DA85: João | DC85: 31 | DD85: =+DB80*DC85 -> 107.86667 | DE85: Dina | DF85: 31 | DG85: =+DF80*DF85 -> 0.78571429 | DK85: Dina | DL85: 31 | DM85: =+DL80*DL85 -> -4.9 | DT85: Dina | DU85: 31 | DV85: =+DU80*DU85 -> 0
A86: André Grilo | B86: 10 | C86: =+B76-B86 -> 21 | D86: =+B80*C86 -> 120.81229 | E86: André Grilo | F86: 14 | G86: =+F76-F86 -> 17 | H86: =+F80*G86 -> 51.810333 | L86: =+J80*K86 -> 0 | M86: Tomás | N86: 9 | O86: =+N76-N86 -> 21 | P86: =+N80*O86 -> 206.05235 | Q86: Tomás | R86: 9 | S86: =+R76-R86 -> 22 | T86: =+R80*S86 -> 166.23514 | U86: Tomás | V86: 8 | W86: =+V76-V86 -> 22 | X86: =+V80*W86 -> 169.99807 | Y86: Tomás | Z86: 10 | AA86: =+Z76-Z86 -> 20 | AB86: =+Z80*AA86 -> 137.93058 | AC86: Tomás | AD86: 9 | AE86: =+AD76-AD86 -> 22 | AF86: =+AD80*AE86 -> 95.526081 | AG86: Tomás | AI86: =+AH76-AH86 -> 30 | AJ86: =+AH80*AI86 -> 178.51375 | AK86: Tomás | AM86: =+AL76-AL86 -> 31 | AN86: =+AL80*AM86 -> 276.895 | AO86: Tomás | AQ86: =+AP76-AP86 -> 30 | AR86: =+AP80*AQ86 -> 193.50167 | AS86: Tomás | AU86: =+AT76-AT86 -> 31 | AV86: =+AT80*AU86 -> 103.792 | AW86: Tomás | AY86: =+AX76-AX86 -> 31 | AZ86: =+AX80*AY86 -> 70.036 | BA86: Tomás | BC86: =+BB76-BB86 -> 29 | BD86: 150 | BE86: Tomás | BG86: =+BF76-BF86 -> 31 | BH86: =+BF80*BG86 -> 161.31667 | BI86: Tomás | BK86: =+BJ76-BJ86 -> 30 | BL86: =+BJ80*BK86 -> 80 | BM86: Tomás | BO86: =+BN76-BN86 -> 31 | BP86: =+BN80*BO86 -> 195.56167 | BQ86: Tomás | BS86: 30 | BT86: =+BR80*BS86 -> 152.30333 | BU86: Tomás | BW86: 31 | BX86: =+BV80*BW86 -> 115.37333 | BY86: Eduardo | CB86: 0 | CC86: Ivan | CE86: 30 | CF86: =+CD80*CE86 -> 249.80667 | CG86: Ivan | CI86: 31 | CJ86: =+CH80*CI86 -> 247.44667 | CK86: Ivan | CM86: 30 | CN86: =+CL80*CM86 -> 177.78 | CO86: Ivan | CQ86: 31 | CR86: =+CP80*CQ86 -> 44.965 | CS86: Ivan | CU86: 31 | CV86: =+CT80*CU86 -> 61.083333 | CW86: Ivan | CY86: 28 | CZ86: =+CX80*CY86 -> 56.708333 | DA86: Ivan | DC86: 31 | DD86: =+DB80*DC86 -> 107.86667 | DE86: Flávia | DF86: 31 | DG86: =+DF80*DF86 -> 0.78571429 | DK86: Flávia | DL86: 31 | DM86: =+DL80*DL86 -> -4.9 | DT86: Flávia | DU86: 31 | DV86: =+DU80*DU86 -> 0
A87: Flávio | B87: 9 | C87: =+B76-B87 -> 22 | D87: =+B80*C87 -> 126.56525 | E87: Flávio | F87: 9 | G87: =+F76-F87 -> 22 | H87: =+F80*G87 -> 67.048667 | I87: Flávio | J87: 14 | K87: 17 | L87: =+J80*K87 -> 146.35381 | M87: Flávio | N87: 15 | O87: =+N76-N87 -> 15 | P87: =+N80*O87 -> 147.18025 | Q87: Flávio | R87: 11 | S87: =+R76-R87 -> 20 | T87: =+R80*S87 -> 151.12286 | U87: Flávio | V87: 14 | W87: =+V76-V87 -> 16 | X87: =+V80*W87 -> 123.63496 | Y87: Flávio | Z87: 15 | AA87: =+Z76-Z87 -> 15 | AB87: =+Z80*AA87 -> 103.44793 | AC87: Joana | AD87: 9 | AE87: =+AD76-AD87 -> 22 | AF87: =+AD80*AE87 -> 95.526081 | AG87: Joana | AI87: =+AH76-AH87 -> 30 | AJ87: =+AH80*AI87 -> 178.51375 | AK87: Inês | AM87: =+AL76-AL87 -> 31 | AN87: =+AL80*AM87 -> 276.895 | AO87: Inês | AQ87: =+AP76-AP87 -> 30 | AR87: =+AP80*AQ87 -> 193.50167 | AS87: Inês | AU87: =+AT76-AT87 -> 31 | AV87: =+AT80*AU87 -> 103.792 | AW87: Inês | AY87: =+AX76-AX87 -> 31 | AZ87: =+AX80*AY87 -> 70.036 | BA87: Inês | BC87: 29 | BD87: 150 | BE87: Inês | BG87: 31 | BH87: =+BF80*BG87 -> 161.31667 | BI87: Inês | BK87: 30 | BL87: =+BJ80*BK87 -> 80 | BM87: Inês | BO87: 31 | BP87: =+BN80*BO87 -> 195.56167 | BQ87: Inês | BS87: 30 | BT87: =+BR80*BS87 -> 152.30333 | BU87: Inês | BW87: 31 | BX87: =+BV80*BW87 -> 115.37333 | BY87: Inês | CA87: 31 | CB87: =+BZ80*CA87 -> 250.864 | CC87: Inês | CE87: 30 | CF87: =+CD80*CE87 -> 249.80667 | CG87: Inês | CI87: 31 | CJ87: =+CH80*CI87 -> 247.44667 | CK87: Inês | CM87: 30 | CN87: =+CL80*CM87 -> 177.78 | CO87: Inês | CQ87: 31 | CR87: =+CP80*CQ87 -> 44.965 | CS87: Inês | CU87: 31 | CV87: =+CT80*CU87 -> 61.083333 | CW87: Inês | CY87: 28 | CZ87: =+CX80*CY87 -> 56.708333 | DA87: Inês | DC87: 31 | DD87: =+DB80*DC87 -> 107.86667 | DE87: Maria | DF87: 31 | DG87: =+DF80*DF87 -> 0.78571429 | DK87: Maria | DL87: 31 | DM87: =+DL80*DL87 -> -4.9 | DT87: Maria | DU87: 31 | DV87: =+DU80*DU87 -> 0
M88: Waleed | N88: 25 | O88: =+N76-N88 -> 5 | P88: =+N80*O88 -> 49.060084 | Q88: Waleed | R88: 9 | S88: =+R76-R88 -> 22 | T88: =+R80*S88 -> 166.23514 | U88: Waleed | V88: 10 | W88: 20 | X88: =+V80*W88 -> 154.5437 | Y88: Waleed | Z88: 10 | AA88: 20 | AB88: =+Z80*AA88 -> 137.93058 | AC88: Waleed | AD88: 9 | AE88: 22 | AF88: =+AD80*AE88 -> 95.526081 | AG88: Waleed | AI88: 30 | AJ88: =+AH80*AI88 -> 178.51375 | AK88: Waleed | AM88: =+AL76-AL88 -> 31 | AN88: =+AL80*AM88 -> 276.895 | AO88: Waleed | AQ88: =+AP76-AP88 -> 30 | AR88: =+AP80*AQ88 -> 193.50167 | BA88: Renato | BC88: 29 | BD88: 75 | BE88: Renato | BG88: 31 | BH88: =+BF80*BG88 -> 161.31667 | BI88: Renato | BK88: 30 | BL88: =+BJ80*BK88 -> 80 | BM88: Renato | BO88: 31 | BP88: =+BN80*BO88 -> 195.56167 | BQ88: Renato | BS88: 30 | BT88: =+BR80*BS88 -> 152.30333 | BU88: Renato | BW88: 31 | BX88: =+BV80*BW88 -> 115.37333 | BY88: Renato | CA88: 31 | CB88: =+BZ80*CA88 -> 250.864 | CC88: Renato | CE88: 30 | CF88: =+CD80*CE88 -> 249.80667 | CG88: Renato | CI88: 31 | CJ88: =+CH80*CI88 -> 247.44667 | CK88: Renato | CM88: 30 | CN88: =+CL80*CM88 -> 177.78 | CO88: Renato | CQ88: 31 | CR88: =+CP80*CQ88 -> 44.965 | CS88: Renato | CU88: 31 | CV88: =+CT80*CU88 -> 61.083333 | CW88: Renato | CY88: 28 | CZ88: =+CX80*CY88 -> 56.708333 | DA88: Renato | DC88: 31 | DD88: =+DB80*DC88 -> 107.86667 | DE88: Pedro | DF88: 31 | DG88: =+DF80*DF88 -> 0.78571429 | DK88: Pedro | DL88: 31 | DM88: =+DL80*DL88 -> -4.9 | DT88: Pedro | DU88: 31 | DV88: =+DU80*DU88 -> 0
DE89: Fabio | DF89: 31 | DG89: =+DF80*DF89 -> 0.78571429 | DK89: Fabio | DL89: 31 | DM89: =+DL80*DL89 -> -4.9 | DN89: -20 | DT89: Fabio | DU89: 31 | DV89: =+DU80*DU89 -> 0
AG90: Inês | AI90: =+AH76-AH90 -> 30 | AJ90: =+AH80*AI90 -> 178.51375
A91: Daniela | B91: 11 | C91: =+B76-B91 -> 20 | D91: =+B80*C91 -> 115.05932 | E91: Daniela | F91: 11 | G91: =+F76-F91 -> 20 | H91: =+F80*G91 -> 60.953333 | I91: Daniela | J91: 8 | K91: =+J76-J91 -> 23 | L91: =+J80*K91 -> 198.0081 | M91: Daniela | N91: 13 | O91: =+N76-N91 -> 17 | P91: =+N80*O91 -> 166.80429 | Q91: Daniela | R91: 10 | S91: =+R76-R91 -> 21 | T91: =+R80*S91 -> 158.679 | U91: Daniela | V91: 10 | W91: =+V76-V91 -> 20 | X91: =+V80*W91 -> 154.5437 | Y91: Daniela | Z91: 13 | AA91: =+Z76-Z91 -> 17 | AB91: =+Z80*AA91 -> 117.24099 | AC91: Daniela | AD91: 10 | AE91: =+AD76-AD91 -> 21 | AF91: =+AD80*AE91 -> 91.183986 | AG91: Daniela | AI91: =+AH76-AH91 -> 30 | AJ91: =+AH80*AI91 -> 178.51375 | AN91: =+AL80*AM91 -> 0 | AR91: =+AP80*AQ91 -> 0 | AV91: =+AT80*AU91 -> 0 | AZ91: =+AX80*AY91 -> 0 | BD91: =+BB80*BC91 -> 0 | BH91: =+BF80*BG91 -> 0 | BL91: =+BJ80*BK91 -> 0 | BP91: =+BN80*BO91 -> 0 | BT91: =+BR80*BS91 -> 0 | BX91: =+BV80*BW91 -> 0 | CB91: =+BZ80*CA91 -> 0 | CF91: =+CD80*CE91 -> 0 | CJ91: =+CH80*CI91 -> 0 | CN91: =+CL80*CM91 -> 0 | CR91: =+CP80*CQ91 -> 0 | CV91: =+CT80*CU91 -> 0 | CZ91: =+CX80*CY91 -> 0 | DD91: =+DB80*DC91 -> 0 | DG91: =+DF80*DF91 -> 0 | DM91: =+DL80*DL91 -> 0 | DV91: =+DU80*DU91 -> 0
D92: =SUM(D83:D91) -> 678.85 | H92: =SUM(H83:H91) -> 365.72 | L92: =SUM(L83:L91) -> 903.95 | P92: =SUM(P83:P91) -> 1167.63 | T92: =SUM(T83:T91) -> 1057.86 | X92: =SUM(X83:X91) -> 1043.17 | AB92: =SUM(AB83:AB91) -> 834.48 | AF92: =SUM(AF83:AF91) -> 642.63 | AJ92: =SUM(AJ83:AJ91) -> 1428.11 | AN92: =SUM(AN83:AN91) -> 1661.37 | AR92: =SUM(AR83:AR91) -> 1161.01 | AV92: =SUM(AV83:AV91) -> 518.96 | AZ92: =SUM(AZ83:AZ91) -> 350.18 | BD92: =SUM(BD83:BD91) -> 825 | BH92: =SUM(BH83:BH91) -> 967.9 | BL92: =SUM(BL83:BL91) -> 480 | BP92: =SUM(BP83:BP91) -> 1173.37 | BT92: =SUM(BT83:BT91) -> 913.82 | BX92: =SUM(BX83:BX91) -> 692.24 | CB92: =SUM(CB83:CB91) -> 1254.32 | CF92: =SUM(CF83:CF91) -> 1498.84 | CJ92: =SUM(CJ83:CJ91) -> 1484.68 | CN92: =SUM(CN83:CN91) -> 1066.68 | CR92: =SUM(CR83:CR91) -> 269.79 | CV92: =SUM(CV83:CV91) -> 366.5 | CZ92: =SUM(CZ83:CZ91) -> 340.25 | DD92: =SUM(DD83:DD91) -> 647.2 | DH92: =SUM(DG83:DG91) -> 5.5 | DN92: =SUM(DM83:DM91) -> -34.3 | DW92: =SUM(DV83:DV91) -> 0
A93: Nome | B93: Valor | C93: Valor arredondado | E93: Nome | F93: Valor | G93: Valor arredondado | I93: Nome | J93: Valor | K93: Valor arredondado | M93: Nome | N93: Valor | O93: Valor arredondado | Q93: Nome | R93: Valor | S93: Valor arredondado | U93: Nome | V93: Valor | W93: Valor arredondado | Y93: Nome | Z93: Valor | AA93: Valor arredondado | AC93: Nome | AD93: Valor | AE93: Valor arredondado | AG93: Nome | AH93: Valor | AI93: Valor arredondado | AK93: Nome | AL93: Valor | AM93: Valor arredondado | AO93: Nome | AP93: Valor | AQ93: Valor arredondado | AS93: Nome | AT93: Valor | AU93: Valor arredondado | AW93: Nome | AX93: Valor | AY93: Valor arredondado | BA93: Nome | BB93: Valor | BC93: Valor arredondado | BE93: Nome | BF93: Valor | BG93: Valor arredondado | BI93: Nome | BJ93: Valor | BK93: Valor arredondado | BM93: Nome | BN93: Valor | BO93: Valor arredondado | BQ93: Nome | BR93: Valor | BS93: Valor arredondado | BU93: Nome | BV93: Valor | BW93: Valor arredondado | BY93: Nome | BZ93: Valor | CA93: Valor arredondado | CC93: Nome | CD93: Valor | CE93: Valor arredondado | CG93: Nome | CH93: Valor | CI93: Valor arredondado | CK93: Nome | CL93: Valor | CM93: Valor arredondado | CO93: Nome | CP93: Valor | CQ93: Valor arredondado | CS93: Nome | CT93: Valor | CU93: Valor arredondado | CW93: Nome | CX93: Valor | CY93: Valor arredondado | DA93: Nome | DB93: Valor | DC93: Valor arredondado | DE93: Nome | DF93: Valor | DG93: Valor arredondado | DK93: Nome | DL93: Valor | DM93: Valor arredondado | DT93: Nome | DU93: Valor | DV93: Valor arredondado
A94: Afonso | B94: =+D83 -> 115.05932 | C94: 115 | E94: Afonso | F94: =+H83 -> 57.905667 | G94: 58 | I94: Afonso | J94: =+L83 -> 180.79 | K94: 180 | M94: Afonso | N94: =+P83 -> 196.24034 | O94: 196 | Q94: Afonso | R94: =+T83 -> 136.01057 | S94: 147 | U94: Afonso | V94: =+X83 -> 162.27089 | W94: 165 | Y94: Afonso | Z94: =+AB83 -> 117.24099 | AA94: 130 | AC94: Afonso | AD94: =+AF83 -> 91.183986 | AE94: 91 | AG94: Afonso | AH94: =+AJ83 -> 178.51375 | AI94: 190 | AK94: Afonso | AL94: =+AN83 -> 276.895 | AM94: 280 | AO94: Afonso | AP94: =+AR83 -> 193.50167 | AQ94: 200 | AS94: Afonso | AT94: =+AV83 -> 103.792 | AU94: 165 | AW94: Afonso | AX94: =+AZ83 -> 70.036 | AY94: 70 | BA94: Afonso | BB94: =+BD83 -> 150 | BC94: 150 | BE94: Afonso | BF94: =+BH83 -> 161.31667 | BG94: 165 | BI94: Afonso | BJ94: =+BL83 -> 80 | BK94: 210 | BM94: Afonso | BN94: =+BP83 -> 195.56167 | BO94: 200 | BQ94: Afonso | BR94: =+BT83 -> 152.30333 | BS94: 160 | BU94: Afonso | BV94: =+BX83 -> 115.37333 | BW94: 120 | BY94: Afonso | BZ94: =+CB83 -> 250.864 | CA94: 250 | CC94: Afonso | CD94: =+CF83 -> 249.80667 | CE94: 220 | CG94: Afonso | CH94: =+CJ83 -> 247.44667 | CI94: 255 | CK94: Afonso | CL94: =+CN83 -> 177.78 | CM94: 184 | CO94: Afonso | CP94: =+CR83 -> 44.965 | CQ94: 100 | CS94: Afonso | CT94: =+CV83 -> 61.083333 | CU94: 71.5 | CW94: Afonso | CX94: =+CZ83 -> 56.708333 | CY94: 65 | DA94: Afonso | DB94: =+DD83 -> 107.86667 | DC94: 139 | DE94: Afonso | DF94: =+DG83 -> 0.78571429 | DK94: Afonso | DL94: =+DM83 -> -4.9 | DT94: Afonso | DU94: =+DV83 -> 0
A95: Andreia | B95: =+D84 -> 80.541525 | C95: 81 | E95: Andreia | F95: =+H84 -> 70.096333 | G95: 70 | I95: Andreia | J95: =+L84 -> 189.39905 | K95: 190 | M95: Andreia | N95: =+P84 -> 206.05235 | O95: 206 | Q95: Andreia | R95: =+T84 -> 166.23514 | S95: 179 | U95: Andreia | V95: =+X84 -> 154.5437 | W95: 155 | Y95: Andreia | Z95: =+AB84 -> 82.758347 | AA95: 92 | AC95: Andreia | AD95: =+AF84 -> 95.526081 | AE95: 95 | AG95: Andreia | AH95: =+AJ84 -> 178.51375 | AI95: 190 | AK95: Andreia | AL95: =+AN84 -> 276.895 | AM95: 280 | AO95: Andreia | AP95: =+AR84 -> 193.50167 | AQ95: 200 | AS95: Andreia | AT95: =+AV84 -> 103.792 | AU95: 165 | AW95: Andreia | AX95: =+AZ84 -> 70.036 | AY95: 70 | BA95: Andreia | BB95: =+BD84 -> 150 | BC95: 150 | BE95: Andreia | BF95: =+BH84 -> 161.31667 | BG95: 165 | BI95: Andreia | BJ95: =+BL84 -> 80 | BK95: 210 | BM95: Andreia | BN95: =+BP84 -> 195.56167 | BO95: 200 | BQ95: Andreia | BR95: =+BT84 -> 152.30333 | BS95: 160 | BU95: Andreia | BV95: =+BX84 -> 115.37333 | BW95: 120 | BY95: Andreia | BZ95: =+CB84 -> 250.864 | CA95: 250 | CC95: Andreia | CD95: =+CF84 -> 249.80667 | CE95: 220 | CG95: Andreia | CH95: =+CJ84 -> 247.44667 | CI95: =255-CI70 -> 105 | CK95: Andreia | CL95: =+CN84 -> 177.78 | CM95: 4 | CO95: Andreia | CP95: =+CR84 -> 44.965 | CQ95: 90.4 | CS95: Andreia | CT95: =+CV84 -> 61.083333 | CU95: 72 | CW95: Andreia | CX95: =+CZ84 -> 56.708333 | CY95: 60 | DA95: Andreia | DB95: =+DD84 -> 107.86667 | DC95: 108 | DE95: Carolina | DF95: =+DG84 -> 0.78571429 | DK95: Carolina | DL95: =+DM84 -> -4.9 | DT95: Carolina | DU95: =+DV84 -> 0
A96: Cristiana | B96: =+D85 -> 120.81229 | C96: 120 | E96: Cristiana | F96: =+H85 -> 57.905667 | G96: 58 | I96: Cristiana | J96: =+L85 -> 189.39905 | K96: 190 | M96: Cristiana | N96: =+P85 -> 196.24034 | O96: 196 | Q96: Cristiana | R96: =+T85 -> 113.34214 | S96: 122 | U96: Cristiana | V96: =+X85 -> 123.63496 | W96: 125 | Y96: Cristiana | Z96: =+AB85 -> 137.93058 | AA96: 152 | AC96: Cristiana | AD96: =+AF85 -> 78.157703 | AE96: 78 | AG96: Cristiana | AH96: =+AJ85 -> 178.51375 | AI96: 190 | AK96: Cristiana | AL96: =+AN85 -> 276.895 | AM96: 280 | AO96: Cristiana | AP96: =+AR85 -> 193.50167 | AQ96: 200 | AS96: Cristiana | AT96: =+AV85 -> 103.792 | AU96: 165 | AW96: Cristiana | AX96: =+AZ85 -> 70.036 | AY96: 70 | BA96: Cristiana | BB96: =+BD85 -> 150 | BC96: 150 | BE96: Cristiana | BF96: =+BH85 -> 161.31667 | BG96: 165 | BI96: Cristiana | BJ96: =+BL85 -> 80 | BK96: 210 | BM96: Cristiana | BN96: =+BP85 -> 195.56167 | BO96: 200 | BQ96: Cristiana | BR96: =+BT85 -> 152.30333 | BS96: 160 | BU96: Cristiana | BV96: =+BX85 -> 115.37333 | BW96: 120 | BY96: Cristiana | BZ96: =+CB85 -> 250.864 | CA96: 250 | CC96: Cristiana | CD96: =+CF85 -> 249.80667 | CE96: 220 | CG96: Cristiana | CH96: =+CJ85 -> 247.44667 | CI96: 255 | CK96: Cristiana | CL96: =+CN85 -> 177.78 | CM96: 184 | CO96: Cristiana | CP96: =+CR85 -> 44.965 | CQ96: 100 | CS96: Cristiana | CT96: =+CV85 -> 61.083333 | CU96: 72 | CW96: Cristiana | CX96: =+CZ85 -> 56.708333 | CY96: 70 | DA96: João | DB96: =+DD85 -> 107.86667 | DC96: 138 | DE96: Dina | DF96: =+DG85 -> 0.78571429 | DK96: Dina | DL96: =+DM85 -> -4.9 | DT96: Dina | DU96: =+DV85 -> 0
A97: André Grilo | B97: =+D86 -> 120.81229 | C97: 120 | E97: André Grilo | F97: =+H86 -> 51.810333 | G97: 51 | I97: André Grilo | J97: =+L86 -> 0 | M97: Tomás | N97: =+P86 -> 206.05235 | O97: 206 | Q97: Tomás | R97: =+T86 -> 166.23514 | S97: 179 | U97: Tomás | V97: =+X86 -> 169.99807 | W97: 173 | Y97: Tomás | Z97: =+AB86 -> 137.93058 | AA97: 152 | AC97: Tomás | AD97: =+AF86 -> 95.526081 | AE97: 95 | AG97: Tomás | AH97: =+AJ86 -> 178.51375 | AI97: 190 | AK97: Tomás | AL97: =+AN86 -> 276.895 | AM97: 280 | AO97: Tomás | AP97: =+AR86 -> 193.50167 | AQ97: 200 | AS97: Tomás | AT97: =+AV86 -> 103.792 | AU97: 165 | AW97: Tomás | AX97: =+AZ86 -> 70.036 | AY97: 70 | BA97: Tomás | BB97: =+BD86 -> 150 | BC97: 150 | BE97: Tomás | BF97: =+BH86 -> 161.31667 | BG97: 165 | BI97: Tomás | BJ97: =+BL86 -> 80 | BK97: 210 | BM97: Tomás | BN97: =+BP86 -> 195.56167 | BO97: 200 | BQ97: Tomás | BR97: =+BT86 -> 152.30333 | BS97: 160 | BU97: Tomás | BV97: =+BX86 -> 115.37333 | BW97: 120 | BY97: Ivan | BZ97: =+CB86 -> 0 | CC97: Ivan | CD97: =+CF86 -> 249.80667 | CE97: 120 | CG97: Ivan | CH97: =+CJ86 -> 247.44667 | CI97: 100 | CK97: Ivan | CL97: =+CN86 -> 177.78 | CM97: 4 | CO97: Ivan | CP97: =+CR86 -> 44.965 | CQ97: 40 | CS97: Ivan | CT97: =+CV86 -> 61.083333 | CU97: 7 | CW97: Ivan | CX97: =+CZ86 -> 56.708333 | CY97: 10 | DA97: Ivan | DB97: =+DD86 -> 107.86667 | DC97: 74 | DE97: Flávia | DF97: =+DG86 -> 0.78571429 | DK97: Flávia | DL97: =+DM86 -> -4.9 | DT97: Flávia | DU97: =+DV86 -> 0
A98: Flávio | B98: =+D87 -> 126.56525 | C98: 126 | E98: Flávio | F98: =+H87 -> 67.048667 | G98: 67 | I98: Flávio | J98: =+L87 -> 146.35381 | K98: 146 | M98: Flávio | N98: =+P87 -> 147.18025 | O98: 147 | Q98: Flávio | R98: =+T87 -> 151.12286 | S98: 163 | U98: Flávio | V98: =+X87 -> 123.63496 | W98: 125 | Y98: Flávio | Z98: =+AB87 -> 103.44793 | AA98: 115 | AC98: Joana | AD98: =+AF87 -> 95.526081 | AE98: 95 | AG98: Joana | AH98: =+AJ87 -> 178.51375 | AI98: 190 | AK98: Inês | AL98: =+AN87 -> 276.895 | AM98: 280 | AO98: Inês | AP98: =+AR87 -> 193.50167 | AQ98: 200 | AS98: Inês | AT98: =+AV87 -> 103.792 | AU98: 165 | AW98: Inês | AX98: =+AZ87 -> 70.036 | AY98: 70 | BA98: Inês | BB98: =+BD87 -> 150 | BC98: 150 | BE98: Inês | BF98: =+BH87 -> 161.31667 | BG98: 165 | BI98: Inês | BJ98: =+BL87 -> 80 | BK98: 210 | BM98: Inês | BN98: =+BP87 -> 195.56167 | BO98: 200 | BQ98: Inês | BR98: =+BT87 -> 152.30333 | BS98: 160 | BU98: Inês | BV98: =+BX87 -> 115.37333 | BW98: 120 | BY98: Inês | BZ98: =+CB87 -> 250.864 | CA98: 250 | CC98: Inês | CD98: =+CF87 -> 249.80667 | CE98: 220 | CG98: Inês | CH98: =+CJ87 -> 247.44667 | CI98: 255 | CK98: Inês | CL98: =+CN87 -> 177.78 | CM98: 184 | CO98: Inês | CP98: =+CR87 -> 44.965 | CQ98: 100 | CS98: Inês | CT98: =+CV87 -> 61.083333 | CU98: 72 | CW98: Inês | CX98: =+CZ87 -> 56.708333 | CY98: 70 | DA98: Inês | DB98: =+DD87 -> 107.86667 | DC98: 133.5 | DE98: Maria | DF98: =+DG87 -> 0.78571429 | DK98: Maria | DL98: =+DM87 -> -4.9 | DT98: Maria | DU98: =+DV87 -> 0
M99: Waleed | N99: =+P88 -> 49.060084 | O99: 50 | Q99: Waleed | R99: =+T88 -> 166.23514 | S99: 179 | U99: Waleed | V99: =+X88 -> 154.5437 | W99: 155 | Y99: Waleed | Z99: =+AB88 -> 137.93058 | AA99: 152 | AC99: Waleed | AD99: =+AF88 -> 95.526081 | AE99: 95 | AG99: Waleed | AH99: =+AJ88 -> 178.51375 | AI99: 190 | AK99: Waleed | AL99: =+AN88 -> 276.895 | AM99: 280 | AO99: Waleed | AP99: =+AR88 -> 193.50167 | AQ99: 200 | BA99: Renato | BB99: 70 | BC99: 75 | BE99: Renato | BF99: =BH88 -> 161.31667 | BG99: 165 | BI99: Renato | BJ99: =+BL88 -> 80 | BK99: 210 | BM99: Renato | BN99: =BP88 -> 195.56167 | BO99: 200 | BQ99: Renato | BR99: =BT88 -> 152.30333 | BS99: 160 | BU99: Renato | BV99: =BX88 -> 115.37333 | BW99: 112 | BY99: Renato | BZ99: =CB88 -> 250.864 | CA99: 250 | CC99: Renato | CD99: =CF88 -> 249.80667 | CE99: 215 | CG99: Renato | CH99: =CJ88 -> 247.44667 | CI99: =255-CI71 -> 246 | CK99: Renato | CL99: =CN88 -> 177.78 | CM99: 174 | CO99: Renato | CP99: =CR88 -> 44.965 | CQ99: 90 | CS99: Renato | CT99: =CV88 -> 61.083333 | CU99: 72 | CW99: Renato | CX99: =CZ88 -> 56.708333 | CY99: 70 | DA99: Renato | DB99: =DD88 -> 107.86667 | DC99: 139 | DE99: Pedro | DF99: =+DG88 -> 0.78571429 | DK99: Pedro | DL99: =+DM88 -> -4.9 | DT99: Pedro | DU99: =+DV88 -> 0
DE100: Fabio | DF100: =DG89 -> 0.78571429 | DK100: Fabio | DL100: =DM89 -> -4.9 | DT100: Fabio | DU100: =DV89 -> 0
AG101: Inês | AH101: =+AJ90 -> 178.51375 | AI101: 190
A102: Daniela | B102: =+D91 -> 115.05932 | C102: 115 | E102: Daniela | F102: =+H91 -> 60.953333 | G102: 61 | I102: Daniela | J102: =+L91 -> 198.0081 | K102: 197 | M102: Daniela | N102: =+P91 -> 166.80429 | O102: 167 | Q102: Daniela | R102: =+T91 -> 158.679 | S102: 171 | U102: Daniela | V102: =+X91 -> 154.5437 | W102: 155 | Y102: Daniela | Z102: =+AB91 -> 117.24099 | AA102: 130 | AC102: Daniela | AD102: =+AF91 -> 91.183986 | AE102: 91 | AG102: Daniela | AH102: =+AJ91 -> 178.51375 | AI102: 190
C103: =SUM(C94:D102) -> 677 | G103: =SUM(G94:H102) -> 365 | K103: =SUM(K94:L102) -> 903 | O103: =SUM(O94:P102) -> 1168 | S103: =SUM(S94:S102) -> 1140 | W103: =SUM(W94:X102) -> 1053 | AA103: =SUM(AA94:AA102) -> 923 | AE103: =SUM(AE94:AE102) -> 640 | AI103: =SUM(AI94:AI102) -> 1520 | AM103: =SUM(AM94:AM102) -> 1680 | AQ103: =SUM(AQ94:AQ102) -> 1200 | AU103: =SUM(AU94:AU102) -> 825 | AY103: =SUM(AY94:AY102) -> 350 | BC103: =SUM(BC94:BC102) -> 825 | BG103: =SUM(BG94:BG102) -> 990 | BK103: =SUM(BK94:BK102) -> 1260 | BO103: =SUM(BO94:BO102) -> 1200 | BS103: =SUM(BS94:BS102) -> 960 | BW103: =SUM(BW94:BW102) -> 712 | CA103: =SUM(CA94:CA102) -> 1250 | CE103: =SUM(CE94:CE102) -> 1215 | CI103: =SUM(CI94:CI102) -> 1216 | CM103: =SUM(CM94:CM102) -> 734 | CQ103: =SUM(CQ94:CQ102) -> 520.4 | CU103: =SUM(CU94:CU102) -> 366.5 | CY103: =SUM(CY94:CY102) -> 345 | DC103: =SUM(DC94:DC102) -> 731.5 | DG103: =SUM(DG94:DG102) -> 0 | DM103: =SUM(DM94:DM102) -> 0 | DV103: =SUM(DV94:DV102) -> 0
AN105: =AN92-AM103 -> -18.63

Sheet CitySightSeeing Bus
B2: Data | C2: Voucher | D2: Valor | E2: Comissão | G2: Comissão CitySightSeeing = 25%
B3: 45730 | C3: T-20254609394 | D3: 70 | E3: =D3*25% -> 17.5
B4: 45739 | C4: T-20254609396 | D4: 32 | E4: =D4*25% -> 8 | G4: Contacto: +351 918903816 | I4: João Simões (Departamento Comercial)
B5: 45745 | C5: T-20254609397 | D5: 64 | E5: =D5*25% -> 16
B6: 45750 | C6: T-20254609399 | D6: 66 | E6: =D6*25% -> 16.5 | G6: Valores dos bilhetes (Adultos) | H6: Valores dos bilhetes (Criança 4-12 anos) | I6: Acesso
B7: 45755 | C7: T-202546093910 | D7: 66 | E7: =D7*25% -> 16.5 | G7: 32 | H7: 10 | I7: Linha vermelha, azul e verde
B8: 45755 | C8: T-202546093911 | D8: 72 | E8: =D8*25% -> 18 | G8: Crianças com menos de 4 anos | I8: Grátis todas as linhas
E9: =D9*25% -> 0
E10: =D10*25% -> 0 | G10: Horário Normal | H10: Horário Verão | I10: Início - Fim
E11: =D11*25% -> 0 | G11: 10h30 - 16h30 | H11: 10h30 - 17h30 | I11: Marquês Pombal - Restauradores
E12: =D12*25% -> 0 | G12: 09h30 - 16h30 | H12: 09h30 - 17h30 | I12: Marquês Pombal - Restauradores
E13: =D13*25% -> 0 | G13: 10h00 - 17h00 | H13: 10h00 - 18h00 | I13: Marquês Pombal - Parque Eduardo VII
E14: =D14*25% -> 0
E15: =D15*25% -> 0 | G15: Beneficos do Voucher | H15: 10% desconto na Gulbenkian
E16: =D16*25% -> 0 | H16: O voucher connosco dura 48h (não 24h como referido no papel)
E17: =D17*25% -> 0
E18: =D18*25% -> 0 | G18: Como funcionam as comissões | H18: Vamos ter um envelope na receção onde vamos metendo o dinheiro dos clientes, o João Simões vem normalmente ao final do mês para verificar se as contas estão certas e dá a comissão
E19: =D19*25% -> 0
E20: =D20*25% -> 0
E21: =D21*25% -> 0
E22: =D22*25% -> 0
E23: =D23*25% -> 0 | G23: Significado das cores | H23: Dinheiro no Envelope
E24: =D24*25% -> 0 | H24: Comissões dadas
E25: =D25*25% -> 0
E26: =D26*25% -> 0
E27: =D27*25% -> 0
E28: =D28*25% -> 0
E29: =D29*25% -> 0
E30: =D30*25% -> 0
E31: =D31*25% -> 0
E32: =D32*25% -> 0
E33: =D33*25% -> 0
E34: =D34*25% -> 0
E35: =D35*25% -> 0
E36: =D36*25% -> 0
E37: =D37*25% -> 0
C38: Dinheiro no envelope | D38: =SUM(D3:D37) -> 370 | E38: =SUM(E3:E37) -> 92.5 | F38: Comissão a receber

Sheet Transfers Novembro 2024
B1: MSH ROSSIO - TRANSFERS Novembro 2024 | Y1: {=_xlfn.IFS(X1=25,7,X1=30,7.5,X1=35,5,X1=40,10,X1=50,10,X1=70,15,X1=0,"")}
C2: * Por favor conferir comissões de transfers pagos ao hotel e modificar cor para
B3: SUNDESTINY | F3: Rita & Pedro Lobo | G3: 962930401 | H3: 962522529
B4: Data | C4: Horas | D4: Cliente | E4: Quarto | F4: Serviço | G4: Empresa | H4: Valor | I4: Comissão | J4: Nº pax
B5: 45597 | C5: 05h15 | D5: Lars Bassen | E5: 401 | F5: Hotel-Aeroporto | G5: SunDestiny | H5: 25 | I5: 7 | J5: 1 | K5: AR
B6: 45597 | C6: 08h55 | D6: Lynette Hansen | F6: Aeroporto-Hotel | G6: SunDestiny | H6: 35 | I6: 5 | J6: 1 | K6: RM
B7: 45597 | C7: 09h55 | D7: Holly Clayton | F7: Aeroporto-Hotel | G7: SunDestiny | H7: 35 | I7: 5 | J7: 2 | K7: AR
B8: 45598 | C8: 08h15 | D8: Thekkoote | E8: 311 | F8: Hotel-Aeroporto | G8: SunDestiny | H8: 25 | I8: 7 | J8: 2 | K8: CB
B9: 45599 | C9: 07h00 | D9: Marne Medeiros | E9: 410 + 406 + 407 + 103 + 209 | F9: Hotel-Aeroporto | G9: SunDestiny | H9: 80 | I9: 20 | J9: 7 | K9: IS
B10: 45599 | C10: 10h30 | D10: Diana Childress | E10: 203 + 303 + 316 | F10: Hotel-Penha Longa Resort-Cascais | G10: SunDestiny | H10: 200 | I10: 40 | J10: 6 | K10: AR
B11: 45600 | C11: 04h00 | D11: Shinji Sumi | E11: 304 | F11: Hotel-Aeroporto | G11: SunDestiny | H11: 25 | I11: 7 | J11: 2 | K11: IC
B12: 45602 | C12: 09h00 | D12: Nancy Marquardt | F12: Aeroporto-Hotel | G12: SunDestiny | H12: 35 | I12: 5 | J12: 1 | K12: AR
B13: 45602 | C13: 16h05 | D13: Henry Reeve | F13: Aeroporto-Hotel | G13: SunDestiny | H13: 35 | I13: 5 | J13: 1 | K13: IC
B14: 45602 | C14: 13h45 | D14: Celine Bessi | F14: Aeroporto-Hotel | G14: SunDestiny | H14: 35 | I14: 5 | J14: 1 | K14: AR
B15: 45602 | C15: 16h25 | D15: James Potts | F15: Aeroporto-Hotel | G15: SunDestiny | H15: 35 | I15: 5 | J15: 2 | K15: CB
B16: 45603 | C16: 14h30 | D16: Celine Bessi | E16: 201 | F16: Hotel-Cruzeiros | G16: SunDestiny | H16: 30 | I16: 7.5 | J16: 2 | K16: AS
B17: 45604 | C17: 05h30 | D17: Corinna Startmann | E17: 408 | F17: Hotel-Aeroporto | G17: SunDestiny | H17: 25 | I17: 7 | J17: 2 | K17: AR
B18: 45604 | C18: 07h30 | D18: Eva Saul | E18: 410 | F18: Hotel-Aeroporto | G18: SunDestiny | H18: 25 | I18: 7 | J18: 2 | K18: AS
B19: 45604 | C19: 08h15 | D19: Patrick Dickinson | E19: 101 + 406 | F19: Hotel-Aeroporto | G19: SunDestiny | H19: 40 | I19: 10 | J19: 4 | K19: AS
B20: 45604 | C20: 08h15 | D20: Fay Margaret | E20: 212 | F20: Hotel-Aeroporto | G20: SunDestiny | H20: 25 | I20: 7 | J20: 1 | K20: CB
B21: 45604 | C21: 10h00 | D21: Tom Dippel | F21: Cruise Port-Hotel | G21: SunDestiny | H21: 70 | I21: 15 | J21: 4 | K21: AR | L21: 2 VAN's
B22: 45604 | C22: 10h00 | D22: Tom Dippel | F22: Cruise Port-Hotel | G22: SunDestiny | H22: 70 | I22: 15 | J22: 4 | K22: AR
B23: 45604 | C23: 12h00 | D23: James Potts | E23: 204 | F23: Hotel-Cruzeiros | G23: SunDestiny | H23: 25 | I23: 7 | J23: 2 | K23: AS
B24: 45604 | C24: 19h00 | D24: Armelle Bocquillon | F24: Aeroporto-Hotel | G24: SunDestiny | H24: 35 | I24: 5 | J24: 2 | K24: CB
B25: 45605 | C25: 08h00 | D25: Annette Aalborg | F25: Aeroporto-Art | G25: SunDestiny | H25: 35 | I25: 5 | J25: 1 | K25: RM
B26: 45606 | C26: 02h00 | D26: Pallav Shukla | F26: Hotel-Aeroporto | G26: SunDestiny | H26: 25 | I26: 7 | J26: 1 | K26: IC
B27: 45606 | C27: 02h30 | D27: Kenneth Grossman | E27: 401 | F27: Aeroporto-Hotel | G27: SunDestiny | H27: 25 | I27: 7 | J27: 2 | K27: IC
B28: 45607 | C28: 04h00 | D28: Gabriella De Assis | E28: 215 | F28: Hotel-Aeroporto | G28: SunDestiny | H28: 40 | I28: 10 | J28: 3 | K28: CB
B29: 45608 | C29: 07h30 | D29: Tom Dippel | E29: 202 + 216 + 303 + 311 | F29: Hotel-Aeroporto | G29: SunDestiny | H29: 40 | I29: 10 | J29: 8 | K29: CB
B30: 45608 | C30: 07h30 | D30: Tom Dippel | F30: Hotel-Aeroporto | G30: SunDestiny | H30: 40 | I30: 10 | K30: CB
B31: 45608 | D31: Henry Reeve | F31: Tour Lisboa - 4h | G31: SunDestiny | H31: 220 | I31: =H31*20% -> 44 | J31: 2 | K31: CB | L31: Marcado diretamente com a SD
B32: 45609 | C32: 07h00 | D32: Dr Abdullah Sarwar | F32: Aeroporto-Hotel | G32: Sundestiny | H32: 35 | I32: 5 | J32: 1 | K32: IC
A33: 45611 | B33: 45611 | C33: 09h00 | D33: Suzanne Mernyk | F33: Aeroporto-Hotel | G33: Sundestiny | H33: 35 | I33: 5 | J33: 2 | K33: IS
B34: 45612 | C34: 08h30 | D34: Victoria Troake | E34: 101 | F34: Hotel-Oriente | G34: Sundestiny | H34: 25 | I34: 7 | J34: 2 | K34: IS
B35: 45612 | C35: 11h15 | E35: 303 | F35: Hotel-Cruzeiros | G35: Sundestiny | H35: 40 | I35: 10 | J35: 2 | K35: CB
B36: 45612 | C36: 11h45 | E36: 207 | F36: Hotel-Cruzeiros | G36: Sundestiny | H36: 25 | I36: 7 | J36: 2 | K36: CB
B37: 45612 | C37: 11h30 | D37: Aksana Abbas | F37: Aeroporto-Hotel | G37: SunDestiny | H37: 35 | I37: 5 | J37: 2 | K37: IC
B38: 45582 | C38: 09h00 | D38: Stephen Summers | F38: Aeroporto-Hotel | G38: SunDestiny | H38: 35 | I38: 5 | J38: 2 | K38: AS
B39: 45614 | C39: 09h15 | D39: Stephanie Tuan | E39: 205 | F39: Hotel-Aeroporto | G39: SunDestiny | H39: 25 | I39: 7 | J39: 2 | K39: IC
B40: 45615 | C40: 06h30 | D40: Lisa Rivera | E40: 415 | F40: Hotel-Aeroporto | G40: SunDestiny | H40: 25 | I40: 7 | J40: 2 | K40: IS
B41: 45616 | C41: 09h45 | D41: Chia Lin Cheng | E41: 215 | F41: Hotel-Aeroporto | G41: SunDestiny | H41: 30 | I41: 7.5 | J41: 3 | K41: AR
B42: 45617 | C42: 09h30 | D42: Babs Read | F42: Cruzeiros-Hotel | G42: SunDestiny | H42: 35 | I42: 5 | J42: 2 | K42: AS
B43: 45617 | C43: 10h15 | D43: dana lorene | E43: 404 | F43: Hotel-Aeroporto | G43: SunDestiny | H43: 25 | I43: 7 | J43: 2 | K43: CB
B44: 45617 | C44: 17h30 | E44: 202 | F44: Hotel - Aeroporto | G44: SunDestiny | H44: 25 | I44: 7 | J44: 2 | L44: Não estava anotado
B45: 45618 | C45: 04h45 | D45: Hilario Rodrigues | E45: 307 | F45: Hotel-Aeroporto | G45: SunDestiny | H45: 25 | I45: 7 | J45: 2 | K45: CB
B46: 45618 | C46: 06h25 | D46: Theresa Chan | F46: Aeroporto-Hotel | G46: SunDestiny | H46: 35 | I46: 5 | J46: 1 | K46: IS
B47: 45618 | C47: 14h00 | D47: Grace Chung | E47: 405 + 301 | F47: Hotel-Aeroporto | G47: SunDestiny | H47: 40 | I47: 10 | J47: 5 | K47: AS
B48: 45619 | C48: 07h30 | D48: Lauryn Yoder | E48: 203 | F48: Hotel-Aeroporto | G48: SunDestiny | H48: 25 | I48: 7 | J48: 2 | K48: IC
B49: 45619 | C49: 07h45 | D49: Theresa Chan | E49: 401 | F49: Hotel-Aeroporto | G49: SunDestiny | H49: 25 | I49: 7 | J49: 1 | K49: AS
B50: 45619 | C50: 08h10 | D50: Antonio Faciola | F50: Aeroporto-Hotel | G50: SunDestiny | H50: 35 | I50: 5 | J50: 2 | K50: AR
B51: 45619 | C51: 09h30 | D51: Anthony Calvillo | F51: Aeroporto-Hotel | G51: SunDestiny | H51: 70 | I51: 15 | J51: 5 | K51: IC
B52: 45620 | C52: 06h15 | D52: Benton Wakefield | E52: 205 | F52: Hotel-Aeroporto | G52: SunDestiny | H52: 25 | I52: 7 | J52: 1 | K52: AR
B53: 45620 | C53: 07h00 | D53: Martin Fisher | E53: 301 | F53: Hotel-Aeroporto | G53: SunDestiny | H53: 25 | I53: 7 | J53: 2 | K53: IC
B54: 45621 | C54: 09h00 | D54: Michelle Roach | E54: 205 | F54: Hotel-Aeroporto | G54: SunDestiny | H54: 25 | I54: 7 | J54: 2 | K54: AS
B55: 45621 | C55: 12h55 | D55: Richard Roper | F55: Aeroporto-Hotel | G55: SunDestiny | H55: 35 | I55: 5 | J55: 2 | K55: AS
B56: 45622 | C56: 03h30 | D56: Maria Mora | E56: 307 | F56: Hotel-Aeroporto | G56: SunDestiny | H56: 25 | I56: 7 | J56: 2 | K56: AR
B57: 45622 | C57: 06h30 | D57: Beth Keenan | E57: 310 | F57: Hotel-Aeroporto | G57: SunDestiny | H57: 30 | I57: 7.5 | J57: 4 | K57: AR | L57: cobraram 25€
B58: 45622 | C58: 09h05 | D58: Paul Forness | F58: Aeroporto-Hotel | G58: SunDestiny | H58: 35 | I58: 5 | J58: 2 | K58: AR
B59: 45623 | C59: 05h30 | D59: Susan Sexton | F59: Aeroporto-Hotel | G59: SunDestiny | H59: 35 | I59: 5 | J59: 2 | K59: RM
B60: 45624 | C60: 10h15 | D60: Kirsty Ewing | F60: Aeroporto-Hotel | G60: SunDestiny | H60: 35 | I60: 5 | J60: 2 | K60: AS
B61: 45625 | C61: 05h00 | D61: Nathalie Saccone | E61: 208 | F61: Hotel-Aeroporto | G61: SunDestiny | H61: 25 | I61: 7 | J61: 2 | K61: AS
B62: 45594 | C62: 10h30 | D62: Brenda Colon | E62: 411 | F62: Hotel-Cruzeiros | G62: SunDestiny | H62: 25 | I62: 7 | J62: 2 | K62: AS
B63: 45594 | C63: 10h30 | D63: David Osborne | E63: 212 | F63: Hotel-Cruzeiros | G63: SunDestiny | H63: 25 | I63: 7 | J63: 2 | K63: AS
B64: 45625 | C64: 10h50 | D64: Jennifer Chao | E64: 405 | F64: Hotel-Cruzeiros | G64: SunDestiny | H64: 40 | I64: 10 | J64: 5 | K64: AR
B65: 45625 | C65: 11h30 | D65: Criselda De Leon | E65: 203 | F65: Hotel-Cruzeiros | G65: SunDestiny | H65: 25 | I65: 7 | J65: 2 | K65: AR
B66: 45565 | C66: 04h00 | D66: Susan Richardson | E66: 216 | F66: Hotel - Aeroporto | G66: SunDestiny | H66: 25 | I66: 7 | J66: 2
H68: =SUM(H6:H66) -> 2395 | I68: =SUM(I6:I66) -> 518.5
B71: ÉPOCA FESTIVA ( 24 e 25 Dezembro ; 31 Dezembro e 1 Janeiro 2023)
B73: - Relembramos que está previsto nas tabelas de preços os serviços a efetuar nestas datas, terão um acréscimo de 50% do valor a cobrar ao cliente;
B75: (Sendo que as V/ vossas comissões serão também beneficiadas nestas datas em mais 25% sobre a comissão já estabelecida)
B77: Exemplos :
B79: Comissão de 5,00€ – passa para 10€
B81: Comissão de 10,00€ – passa para 20€

Sheet Transfers Junho
B1: MSH ROSSIO - TRANSFERS JUNHO 2023
C2: * Por favor conferir comissões de transfers pagos ao hotel e modificar cor para
B3: SUNDESTINY | F3: Rita & Pedro Lobo | G3: 962930401 | H3: 962522529 | M3: 7 Roads | Q3: Carla | R3: 939660691
B5: Data | C5: Horas | D5: Cliente | E5: Quarto | F5: Serviço | G5: Empresa | H5: Valor | I5: Comissão | J5: Nº pax | M5: Data | N5: Horas | O5: Cliente | P5: Quarto | Q5: Serviço | R5: Empresa | S5: Valor | T5: Nº pax
B6: 45078 | C6: 10h00 | D6: Steven Forman | F6: Aeroporto-Hotel | G6: SunDestiny | H6: 50 | I6: 10 | J6: 4 | K6: TS | M6: 45078 | N6: 23h45 | O6: Gennaro Piciullo | Q6: Aeroporto-Hotel | R6: 7 Roads | S6: 39 | T6: 2
B7: 45078 | C7: 05h30 | D7: Karin Kronika | E7: 311 | F7: Hotel-Aeroporto | G7: SunDestiny | H7: 25 | I7: 7 | J7: 2 | K7: TS | M7: 45079 | N7: 07h00 | O7: Sandra Pridgeon | P7: 410 | Q7: Hotel-Aeroporto | R7: 7 Roads | S7: 22 | T7: 2
B8: 45078 | C8: 10h50 | D8: Larry Leib | F8: Aeroporto-Hotel | G8: SunDestiny | H8: 35 | I8: 5 | J8: 2 | K8: WM | M8: 45081 | N8: 15h20 | O8: Stefan Spengler | Q8: Aeroporto-Hotel | R8: 7 Roads | S8: 39 | T8: 3
B9: 45079 | C9: 11h30 | D9: Michael Zachary | E9: 216 | F9: Hotel-Aeroporto | G9: SunDestiny | H9: 25 | I9: 7 | J9: 2 | K9: TS | M9: 45081 | N9: 21h15 | O9: Lauren Hatmaker | Q9: Aeroporto-Hotel | R9: 7 Roads | S9: 39 | T9: 2
B10: 45080 | C10: 06h00 | D10: Rute Bueno da Silva | E10: 315 | F10: Hotel-Aeroporto | G10: SunDestiny | H10: 25 | I10: 7 | J10: 2 | K10: TS | M10: 45082 | N10: 14h00 | O10: Lauren Hatmaker | P10: 302 | Q10: Hotel-Aeroporto | R10: 7 Roads | S10: 22 | T10: 2
B11: 45080 | C11: 07h30 | D11: Geertruda | E11: 415 | F11: Hotel-Aeroporto | G11: SunDestiny | H11: 40 | I11: 10 | J11: 5 | K11: CB | M11: 45083 | N11: 10h15 | O11: Kathleen Skinner | Q11: Aeroporto-Hotel | R11: 7 Roads | S11: 39 | T11: 2
B12: 45080 | C12: 10h45 | D12: Dennis Michael | E12: 308 | F12: Hotel-Santa Apolonia | G12: SunDestiny | H12: 25 | I12: 7 | J12: 2 | K12: CB | M12: 45083 | N12: 10h35 | O12: Bernadette Rowan | Q12: Aeroporto-Hotel | R12: 7 Roads | S12: 39 | T12: 2
B13: 45080 | C13: 17h35 | D13: Andrew Whisnant | F13: Aeroporto-Hotel | G13: SunDestiny | H13: 35 | I13: 5 | J13: 2 | K13: FP | M13: 45085 | N13: 12h05 | O13: Timothy Lynch | Q13: Aeroporto-Hotel | R13: 7 Roads | S13: 39 | T13: 2
B14: 45081 | C14: 05h00 | D14: Patricia Barbosa | E14: 401 | F14: Hotel-Aeroporto | G14: SunDestiny | H14: 25 | I14: 7 | J14: 2 | K14: TS | M14: 45085 | N14: 11h20 | O14: Paul McCan | Q14: Aeroporto-Hotel | R14: 7 Roads | S14: 39 | T14: 2
B15: 45081 | C15: 05h30 | D15: Charlene Ngige | F15: Aeroporto-Hotel | G15: SunDestiny | H15: 35 | I15: 5 | J15: 1 | K15: AR | M15: 45087 | N15: 04h00 | O15: Vissarion Michas | P15: 416 | Q15: Hotel-Aeroporto | R15: 7 Roads | S15: 22 | T15: 2
B16: 45081 | C16: 06h45 | D16: Larry Leib | E16: 404 | F16: Hotel-Aeroporto | G16: SunDestiny | H16: 25 | I16: 7 | J16: 2 | K16: CB | M16: 45088 | N16: 07h00 | O16: Michael Bowen | P16: 416 + 201 + 309 | Q16: Hotel-Aeroporto | R16: 7 Roads | S16: 44 | T16: 2
B17: 45081 | C17: 07h15 | D17: Stephen Forman | E17: 310 | F17: Hotel-Entre Campos | G17: SunDestiny | H17: 30 | I17: 7.5 | J17: 4 | K17: TS | M17: 45089 | N17: 06h40 | O17: Elizabeth Vieira | Q17: Aeroporto-Hotel | R17: 7 Roads | S17: 39 | T17: 2
B18: 45081 | C18: 10h30 | D18: Darla Humphreys | F18: Aeroporto-Hotel | G18: SunDestiny | H18: 35 | I18: 5 | J18: 1 | K18: AR | M18: 45089 | N18: 08h00 | O18: Steven Exposito | P18: 415 | Q18: Hotel-Aeroporto | R18: 7 Roads | S18: 22 | T18: 2
B19: 45082 | C19: 10h00 | D19: Judith Brady | E19: 303 | F19: Hotel-Aeroporto | G19: SunDestiny | H19: 25 | I19: 7 | J19: 2 | K19: AR | M19: 45092 | N19: 10h45 | O19: Sharon Salloway | P19: 308 | Q19: Hotel-Aeroporto | R19: 7 Roads | S19: 22 | T19: 2
B20: 45082 | C20: 12h05 | D20: Lauren Vinsick. | F20: Aeroporto-Hotel | G20: SunDestiny | H20: 35 | I20: 5 | J20: 2 | K20: TS | M20: 45095 | N20: 07h15 | O20: Sridhar Iyer | P20: 408 | Q20: Hotel-Aeroporto | R20: 7 Roads | S20: 22 | T20: 2
B21: 45082 | C21: 11h00 | D21: Alan Balsam | F21: Aeroporto-Hotel | G21: SunDestiny | H21: 35 | I21: 5 | J21: 1 | K21: TS | M21: 45096 | N21: 08h30 | O21: Gloria Jean Rasmussen | P21: 209 | Q21: Hotel-Aeroporto | R21: 7 Roads | S21: 22 | T21: 1
B22: 45083 | C22: 07h00 | D22: Andrew Whisnant | E22: 206 | F22: Hotel-Aeroporto | G22: SunDestiny | H22: 25 | I22: 7 | J22: 2 | K22: CB | M22: 45096 | N22: 11h30 | O22: Rebeca | P22: 206 | Q22: Hotel-Aeroporto | R22: 7 Roads | S22: 22 | T22: 2
B23: 45084 | C23: 08h00 | D23: Elaine | E23: 412 + 311 | F23: Hotel-Aeroporto | G23: SunDestiny | H23: 30 | I23: 7.5 | J23: 4 | K23: CB | M23: 45097 | N23: 09h05 | O23: Sidra McCarthy | Q23: Aeroporto-Hotel | R23: 7 Roads | S23: 39 | T23: 2
B24: 45084 | C24: 09h00 | D24: Diane Lynn | E24: 203 | F24: Hotel-Aeroporto | G24: SunDestiny | H24: 40 | I24: 10 | J24: 2 | K24: DO | M24: 45097 | N24: 16h30 | O24: Elizabeth Vieira | P24: 411 | Q24: Hotel-Aeroporto | R24: 7 Roads | S24: 22 | T24: 2
B25: 45084 | C25: 18h45 | D25: Malcolm Lundy | F25: Aeroporto-Hotel | G25: SunDestiny | H25: 35 | I25: 5 | J25: 2 | K25: CB | M25: 45100 | N25: 8h30 | O25: Stephan Kornfeld | P25: 302 | Q25: Hotel-Aeroporto | R25: 7 Roads | S25: 22 | T25: 2
B26: 45085 | C26: 06h10 | D26: Virginia Stengel | F26: Aeroporto-Hotel | G26: SunDestiny | H26: 35 | I26: 5 | J26: 2 | K26: AR | M26: 45100 | N26: 14h45 | O26: Alliyha Taylor-Whetstone | Q26: Aeroporto-Hotel | R26: 7 Roads | S26: 39 | T26: 3
B27: 45085 | C27: 08h00 | D27: Anne Frey | F27: Aeroporto-Hotel | G27: SunDestiny | H27: 35 | I27: 5 | J27: 2 | K27: AR | M27: 45101 | N27: 09h00 | O27: Kathleen Skinner | Q27: Hotel-Aeroporto | R27: 7 Roads | S27: 22 | T27: 2
B28: 45085 | C28: 09h00 | D28: Debbi, Efraim | E28: 310 | F28: Hotel-Aeroporto | G28: SunDestiny | H28: 40 | I28: 10 | J28: 6 | K28: DT | M28: 45101 | N28: 05h20 | O28: Amber Woolfenden | Q28: Aeroporto-Hotel | R28: 7 Roads | S28: 39 | T28: 3
B29: 45086 | C29: 17h10 | D29: Chikako Stewart | F29: Aeroporto-Hotel | G29: SunDestiny | H29: 35 | I29: 5 | J29: 1 | K29: AR | M29: 45103 | N29: 11h30 | O29: Amber Woolfenden | P29: 207 | Q29: Hotel-Aeroporto | R29: 7 Roads | S29: 22 | T29: 3
B30: 45087 | C30: 04h30 | D30: Virginia Stengel | E30: 205 | F30: Hotel-Aeroporto | G30: SunDestiny | H30: 25 | I30: 7 | J30: 2 | K30: AS | M30: 45106 | N30: 7h30 | O30: Fallis Wayne | P30: 306 | Q30: Hotel-Aeroporto | R30: 7 Roads | S30: 22 | T30: 1
B31: 45087 | C31: 19h15 | D31: Michael Kremzow | F31: Aeroporto-Hotel | G31: SunDestiny | H31: 35 | I31: 5 | J31: 2 | K31: NT | M31: 45107 | N31: 04h30 | O31: Lee Sunmin | P31: 401 | Q31: Hotel-Aeroporto | R31: 7 Roads | S31: 22 | T31: 2
B32: 45088 | C32: 04h00 | D32: Anne Frey | E32: 210+208 | F32: Hotel-Aeroporto | G32: SunDestiny | H32: 25 | I32: 7 | J32: 2 | K32: AS
B33: 45088 | C33: 07h45 | D33: Lauren Sick | E33: 403 | F33: Hotel-Aeroporto | G33: SunDestiny | H33: 25 | I33: 7 | J33: 1 | K33: TS
B34: 45088 | C34: 04h45 | D34: Mark Oxley | E34: 215 | F34: Hotel-Aeroporto | G34: SunDestiny | H34: 25 | I34: 7 | J34: 2 | K34: DO
B35: 45088 | C35: 09h15 | D35: Heidrun Wieling | E35: 312 | F35: Hotel-Aeroporto | G35: SunDestiny | H35: 40 | I35: 10 | J35: 7 | K35: AR
B36: 45088 | C36: 09h15 | D36: Heidrun Wieling | E36: 312 | F36: Hotel-Aeroporto | G36: SunDestiny | H36: 25 | I36: 7 | J36: 2 | K36: AR
B37: 45088 | C37: 13h30 | D37: Lauren Sick | E37: 403 | F37: Hotel-Aeroporto | G37: SunDestiny | H37: 25 | I37: 7 | J37: 1 | K37: TS
B38: 45089 | C38: 09h30 | D38: Mireille Gilet | E38: 409 + 410 | F38: Hotel-Aeroporto | G38: SunDestiny | H38: 25 | I38: 7 | J38: 3 | K38: DT
B39: 45090 | C39: 18h40 | D39: Jackie Christensen | F39: Aeroporto-Hotel | G39: SunDestiny | H39: 35 | I39: 5 | J39: 2 | K39: CB
B40: 45090 | C40: 07h15 | D40: Marcelo Lopes | F40: Aeroporto-Hotel | G40: SunDestiny | H40: 35 | I40: 5 | J40: 2 | K40: AR
B41: 45090 | C41: 21h00 | D41: Boaz Hadashi | F41: Aeroporto-Hotel | G41: SunDestiny | H41: 35 | I41: 5 | J41: 2 | K41: CB
B42: 45091 | C42: 05h45 | D42: Miguel Gaitan | F42: Aeroporto-Hotel | G42: SunDestiny | H42: 35 | I42: 5 | J42: 2 | K42: GB
B43: 45091 | C43: 09h20 | D43: Bernard Clement | F43: Aeroporto-Hotel | G43: SunDestiny | H43: 50 | I43: 10 | J43: 4 | K43: CA
B44: 45092 | C44: 10h15 | D44: Martha Newman | F44: Aeroporto-Hotel | G44: SunDestiny | H44: 35 | I44: 5 | J44: 2 | K44: AS
B45: 45092 | C45: 12h35 | D45: Bruce Nelson | F45: Aeroporto-Hotel | G45: SunDestiny | H45: 35 | I45: 5 | J45: 2 | K45: AS
B46: 45092 | C46: 15h30 | D46: Jacquelyn Sue Christensen | E46: 205 | F46: Hotel-Cruise Ship Port | G46: SunDestiny | H46: 25 | I46: 7 | J46: 2 | K46: AR
B47: 167 | C47: 16h05 | D47: Steve Ranney | F47: Aeroporto-Hotel | G47: SunDestiny | H47: 35 | I47: 5 | J47: 2 | K47: WM
B48: 45092 | C48: 21h00 | D48: Inbal Shurek | F48: Aeroporto-Hotel | G48: SunDestiny | H48: 50 | I48: 10 | J48: 4 | K48: AR
B49: 45092 | C49: 22h35 | D49: Juliana Valerio | F49: Aeroporto-Hotel | G49: SunDestiny | H49: 35 | I49: 5 | J49: 2 | K49: TS
B50: 45092 | C50: 18h40 | D50: Kate Agel | F50: Aeroporto-Hotel | G50: SunDestiny | H50: 35 | I50: 5 | J50: 2 | K50: FP
B51: 45092 | C51: 17h55 | D51: Dave Kimberling | F51: Aeroporto-Hotel | G51: SunDestiny | H51: 35 | I51: 5 | J51: 2 | K51: FP
B52: 45094 | C52: 05h15 | D52: Gabriel | E52: 101 | F52: Hotel-Aeroporto | G52: SunDestiny | H52: 25 | I52: 7 | J52: 2 | K52: CB
B53: 45094 | C53: 06h00 | D53: Guy Stanley Toczek | E53: 407 | F53: Hotel-Aeroporto | G53: SunDestiny | H53: 25 | I53: 7 | J53: 2 | K53: DT
B54: 45094 | C54: 08h00 | D54: Thomas Anthony Ciesla | E54: 410 | F54: Hotel-Aeroporto | G54: SunDestiny | H54: 25 | I54: 7 | J54: 2 | K54: DT
B55: 45094 | C55: 09h00 | D55: Shurek Noam | E55: 208 | F55: Hotel-Aeroporto | G55: SunDestiny | H55: 30 | I55: 7.5 | J55: 4 | K55: TS
B56: 45094 | C56: 09h20 | D56: Michael Kremzow | E56: 211 | F56: Hotel-Aeroporto | G56: SunDestiny | H56: 25 | I56: 7 | J56: 2 | K56: DO
B57: 45094 | C57: 09h45 | D57: Bruno Hofer | E57: 212 | F57: Hotel-Aeroporto | G57: SunDestiny | H57: 30 | I57: 7.5 | J57: 4 | K57: TS
B58: 45094 | C58: 10h15 | D58: Paul Joseph Baker | E58: 207 | F58: Hotel-Aeroporto | G58: SunDestiny | H58: 25 | I58: 7 | J58: 2 | K58: TS
B59: 45095 | C59: 09h05 | D59: Andrew Wagner | F59: Aeroporto-Hotel | G59: SunDestiny | H59: 50 | I59: 10 | J59: 4 | K59: AR
B60: 45095 | C60: 08h30 | D60: Bruce Nelson | E60: 304+404 | F60: Hotel-Santa Apolonia | G60: SunDestiny | H60: 40 | I60: 10 | J60: 4 | K60: CB
B61: 45095 | C61: 08h45 | D61: Anna Matushenko | E61: 309 | F61: Hotel-Aeroporto | G61: SunDestiny | H61: 25 | I61: 7 | J61: 2 | K61: CB
B62: 45096 | C62: 05h00 | D62: Juliana Valerio | E62: 306 | F62: Hotel-Aeroporto | G62: SunDestiny | H62: 25 | I62: 7 | J62: 2 | K62: AS
B63: 45096 | C63: 15h20 | D63: Cristina Nita-Rotaru | F63: Aeroporto-Hotel | G63: SunDestiny | H63: 35 | I63: 5 | J63: 2 | K63: TS
B64: 45097 | C64: 15h00 | D64: Lidia Superchi | E64: 407 | F64: Hotel-Aeroporto | G64: SunDestiny | H64: 25 | I64: 7 | J64: 2 | K64: TS
B65: 45097 | C65: 16h20 | D65: Delmine da Costa | F65: Aeroporto-Hotel | G65: SunDestiny | H65: 35 | I65: 5 | J65: 2 | K65: GB
B66: 45097 | C66: 11h00 | D66: Dov Brem | E66: 307 | F66: Hotel-Aeroporto | G66: SunDestiny | H66: 25 | I66: 7 | J66: 2 | K66: FP
B67: 45097 | C67: 11h00 | D67: Martha Newman | E67: 305 | F67: Hotel-Aeroporto | G67: SunDestiny | H67: 25 | I67: 7 | J67: 2 | K67: DO
B68: 45097 | C68: 13h30 | D68: Belinda Mclennan | E68: 302 | F68: Hotel-Aeroporto | G68: SunDestiny | H68: 25 | I68: 7 | J68: 2 | K68: DO
B69: 45098 | C69: 03h30 | D69: Francesca Musso | E69: 211 | F69: Hotel-Aeroporto | G69: SunDestiny | H69: 25 | I69: 7 | J69: 2 | K69: FP
B70: 45098 | C70: 14h00 | D70: Antonia Blyth | F70: Aeroporto-Hotel | G70: SunDestiny | H70: 35 | I70: 5 | J70: 2 | K70: AR
B71: 45100 | C71: 07h30 | D71: Cristina | E71: 101 | F71: Hotel-Santa Apolonia | G71: SunDestiny | H71: 25 | I71: 7 | J71: 2 | K71: AS
B72: 45100 | C72: 21h40 | D72: Antje Weisser | F72: Aeroporto-Hotel | G72: SunDestiny | H72: 35 | I72: 5 | J72: 1 | K72: FP
B73: 45101 | C73: 05h15 | D73: Jacek Kajetan | E73: 208 | F73: Hotel-Aeroporto | G73: SunDestiny | H73: 25 | I73: 7 | J73: 1 | K73: TS
B74: 45101 | C74: 08h50 | D74: Alexandre Hartmann | F74: Aeroporto-Hotel | G74: SunDestiny | H74: 35 | I74: 5 | J74: 1 | K74: DO
B75: 45101 | C75: 13h25 | D75: April Callahan | F75: Aeroporto-Hotel | G75: SunDestiny | H75: 50 | I75: 10 | J75: 4 | K75: AR | S75: =SUM(S41:S72) -> 0
B76: 45103 | C76: 12h30 | D76: Betsy Rock | F76: Aeroporto-Hotel | G76: SunDestiny | H76: 35 | I76: 5 | J76: 2 | K76: WM
B77: 45104 | C77: 05h30 | D77: Wendy Page | E77: 303 | F77: Hotel-Aeroporto | G77: SunDestiny | H77: 25 | I77: 7 | J77: 2 | K77: AS
B78: 45104 | C78: 06h30 | D78: Rieflin | E78: 402+403 | F78: Hotel-Aeroporto | G78: SunDestiny | H78: 30 | I78: 7.5 | J78: 3 | K78: AS
B79: 45104 | C79: 12h30 | D79: Sheridan | E79: 302 | F79: Hotel-Aeroporto | G79: SunDestiny | H79: 25 | I79: 7 | J79: 2 | K79: DO
B80: 45105 | C80: 04h45 | D80: Hogue | E80: 402 | F80: Hotel-Aeroporto | G80: SunDestiny | H80: 25 | I80: 7 | J80: 2 | K80: TS
B81: 45105 | C81: 09h15 | D81: Petra Ghadamsi | F81: Aeroporto-Hotel | G81: SunDestiny | H81: 35 | I81: 5 | J81: 2 | K81: FP
B82: 45105 | C82: 10h30 | D82: Kamm Prongay | F82: Aeroporto-Hotel | G82: SunDestiny | H82: 35 | I82: 5 | J82: 2 | K82: AS
B83: 45105 | C83: 08h30 | D83: Kingston Patricia | E83: 203 | F83: Hotel-Aeroporto | G83: SunDestiny | H83: 25 | I83: 7 | J83: 2 | K83: WM
B84: 45106 | C84: 09h00 | D84: Eduardo Reininger | E84: 204 | F84: Hotel-Aeroporto | G84: SunDestiny | H84: 25 | I84: 7 | J84: 2 | K84: TS
B85: 45107 | C85: 06h45 | D85: Luis Karem | E85: 303 + 302 | F85: Hotel-Aeroporto | G85: SunDestiny | H85: 40 | I85: 10 | J85: 2 | K85: TS
H87: =SUM(H6:H85) -> 2530 | I87: =SUM(I6:I85) -> 537.5
B90: ÉPOCA FESTIVA ( 24 e 25 Dezembro ; 31 Dezembro e 1 Janeiro 2022)
B92: - Relembramos que está previsto nas tabelas de preços os serviços a efetuar nestas datas, terão um acréscimo de 50% do valor a cobrar ao cliente;
B94: (Sendo que as V/ vossas comissões serão também beneficiadas nestas datas em mais 25% sobre a comissão já estabelecida)
B96: Exemplos :
B98: Comissão de 5,00€ – passa para 6,25€
B100: Comissão de 7,00€ – passa para 8,75€

Sheet Transfers Julho
B1: MSH ROSSIO - TRANSFERS JULHO 2023
C2: * Por favor conferir comissões de transfers pagos ao hotel e modificar cor para
B3: SUNDESTINY | F3: Rita & Pedro Lobo | G3: 962930401 | H3: 962522529 | M3: 7 Roads | Q3: Carla | R3: 939660691
B5: Data | C5: Horas | D5: Cliente | E5: Quarto | F5: Serviço | G5: Empresa | H5: Valor | I5: Comissão | J5: Nº pax | M5: Data | N5: Horas | O5: Cliente | P5: Quarto | Q5: Serviço | R5: Empresa | S5: Valor | T5: Nº pax
B6: 45108 | C6: 11h05 | D6: Christopher Wozniak | F6: Aeroporto-Hotel | G6: SunDestiny | H6: 35 | I6: 5 | J6: 2 | K6: AR | M6: 45108 | N6: 11h15 | O6: Steve Riddle | Q6: Aeroporto-Hotel | R6: 7 Roads | S6: 39 | T6: 2
B7: 45108 | C7: 10h30 | D7: Tania MacDonnell | E7: 309 + 310 + 311 | F7: Hotel-Aeroporto | G7: SunDestiny | H7: 30 | I7: 7.5 | J7: 4 | K7: TS | M7: 45109 | N7: 09h00 | O7: Dominique Scheidecker | Q7: Aeroporto-Hotel | R7: 7 Roads | S7: 39 | T7: 2
B8: 45109 | C8: 10h45 | D8: Tanya Ho-Shue | F8: Aeroporto-Hotel | G8: SunDestiny | H8: 35 | I8: 5 | J8: 2 | K8: FP | M8: 45109 | N8: 08h30 | O8: Anthony Vandygrift | P8: 215 | Q8: Hotel-Aeroporto | R8: 7 Roads | S8: 22 | T8: 3
B9: 45109 | C9: 18h00 | D9: Giorgia Manzoni | E9: 301 | F9: Hotel-Aeroporto | G9: SunDestiny | H9: 25 | I9: 7 | J9: 2 | K9: CB | M9: 45110 | N9: 06h45 | O9: Agripina Martins | P9: 101 | Q9: Hotel-Aeroporto | R9: 7 Roads | S9: 22 | T9: 1
B10: 45110 | C10: 05h15 | D10: Myriam Brvnelle | E10: 411 | F10: Hotel-Aeroporto | G10: SunDestiny | H10: 25 | I10: 7 | J10: 1 | K10: CB | M10: 45112 | N10: 08h30 | O10: Maribeth Crissie Shank | P10: 206 | Q10: Hotel-Aeroporto | R10: 7 Roads | S10: 22 | T10: 2
B11: 45110 | C11: 06h30 | D11: Kieran Yao | E11: 102 | F11: Hotel-Aeroporto | G11: SunDestiny | H11: 25 | I11: 7 | J11: 2 | K11: AR | M11: 45113 | N11: 04h30 | O11: Tyan, Sean Lee | P11: 311 | Q11: Hotel-Aeroporto | R11: 7 Roads | S11: 22 | T11: 2
B12: 45110 | C12: 08h15 | D12: Le Ann Robic | E12: 412 | F12: Hotel-Aeroporto | G12: SunDestiny | H12: 25 | I12: 7 | J12: 1 | K12: CB | M12: 45113 | N12: 19h50 | O12: Austin Amelse | Q12: Aeroporto-Hotel | R12: 7 Roads | S12: 39 | T12: 2
B13: 45110 | C13: 12h45 | D13: Jessica da Silva | F13: Aeroporto-Hotel | G13: SunDestiny | H13: 35 | I13: 5 | J13: 2 | K13: AR | M13: 45115 | N13: 23h10 | O13: Clementine Briand | Q13: Aeroporto-Hotel | R13: 7 Roads | S13: 39 | T13: 2
B14: 45111 | C14: 04h30 | D14: Wilson Aguilar | E14: 402 | F14: Hotel-Aeroporto | G14: SunDestiny | H14: 25 | I14: 7 | J14: 2 | K14: TS | M14: 45117 | N14: 9h30 | O14: Judith | P14: 215 | Q14: Hotel-Aeroporto | R14: 7 Roads | S14: 39 | T14: 2
B15: 45111 | C15: 06h30 | D15: Erin Eigh Weliver | E15: 102 | F15: Hotel-Aeroporto | G15: SunDestiny | H15: 25 | I15: 7 | J15: 2 | K15: TS | M15: 45117 | N15: 08h20 | O15: Paul Shappirio | Q15: Aeroporto-Hotel | R15: 7 Roads | S15: 39 | T15: 2
B16: 45111 | C16: 06h55 | D16: Meagan Sprout | F16: Aeroporto-Hotel | G16: SunDestiny | H16: 35 | I16: 5 | J16: 2 | K16: AR | M16: 45118 | N16: 15h00 | O16: Shoval Chen | Q16: Aeroporto-Hotel | R16: 7 Roads | S16: 39 | T16: 2
B17: 45111 | C17: 07h30 | D17: Rachel Landau | E17: 309 | F17: Hotel-Aeroporto | G17: SunDestiny | H17: 25 | I17: 7 | J17: 2 | K17: TS | M17: 45118 | N17: 15h00 | O17: Eduardo Brymer | Q17: Aeroporto-Hotel | R17: 7 Roads | S17: 39 | T17: 2
B18: 45111 | C18: 08h30 | D18: Stacey Ann Norris | E18: 403 | F18: Hotel-Aeroporto | G18: SunDestiny | H18: 25 | I18: 7 | J18: 2 | K18: DT | M18: 45119 | N18: 10h30 | O18: Erin Baigis | Q18: Aeroporto-Hotel | R18: 7 Roads | S18: 39 | T18: 2
B19: 45111 | C19: 10h00 | D19: Chris Sae Hau | E19: 304 + 415 | F19: Hotel-Aeroporto | G19: SunDestiny | H19: 40 | I19: 10 | J19: 5 | K19: AR | M19: 45122 | N19: 09h30 | O19: Katherine Sophia | P19: 201 | Q19: Hotel-Aeroporto | R19: 6 Roads | S19: 22 | T19: 2
B20: 45111 | C20: 16h30 | D20: Bruce Fuhrmann | E20: 404 | F20: Santa Apolonia-Hotel | G20: SunDestiny | H20: 50 | I20: 7.5 | J20: 4 | K20: AS | M20: 45122 | N20: 10h00 | O20: Lazar | P20: 315 | Q20: Hotel-Aeroporto | R20: 7 Roads | S20: 22 | T20: 2
B21: 45112 | C21: 13h00 | D21: Vanlys, Dominique | E21: 411 | F21: Hotel-Aeroporto | G21: SunDestiny | H21: 25 | I21: 7 | J21: 2 | K21: FR | M21: 45124 | N21: 04h30 | O21: Liam | P21: 102 | Q21: Hotel-Aeroporto | R21: 7 Roads | S21: 22 | T21: 2
B22: 45112 | C22: 05h20 | D22: Glenn Shaffer | F22: Aeroporto-Hotel | G22: SunDestiny | H22: 35 | I22: 5 | J22: 2 | K22: TS | M22: 209 | N22: 15h45 | O22: Jacob Herscovitz | Q22: Aeroporto-Hotel | R22: 7 Roads | S22: 39 | T22: 2
B23: 45113 | C23: 05h45 | D23: Ilson Gomes | E23: 310 | F23: Hotel-Aeroporto | G23: SunDestiny | H23: 25 | I23: 7 | J23: 2 | K23: DO | M23: 45135 | N23: 06h30 | O23: Frederick Long | P23: 401 | Q23: Hotel-Aeroporto | R23: 7 Roads | S23: 22 | T23: 1
B24: 45113 | C24: 09h20 | D24: Jason Yeast | F24: Aeroporto-Hotel | G24: SunDestiny | H24: 35 | I24: 5 | J24: 2 | K24: CB
B25: 45113 | C25: 07h00 | D25: Rutecki, Josedh | E25: 305 + 308 | F25: Hotel-Aeroporto | G25: SunDestiny | H25: 30 | I25: 7.5 | J25: 4 | K25: WM
B26: 45113 | C26: 15h45 | D26: Lyndsey McLain | F26: Aeroporto-Hotel | G26: SunDestiny | H26: 35 | I26: 5 | J26: 2 | K26: WM
B27: 45115 | C27: 04h30 | D27: Bruce Fuhrmann | E27: 404 | F27: Hotel-Aeroporto | G27: SunDestiny | H27: 25 | I27: 7 | J27: 2 | K27: DO
B28: 45115 | C28: 10h20 | D28: Laura Rost | F28: Aeroporto-Hotel | G28: SunDestiny | H28: 35 | I28: 5 | J28: 3 | K28: AR
B29: 45115 | C29: 13h30 | D29: Lars | F29: Aeroporto-Hotel | G29: SunDestiny | H29: 35 | I29: 5 | J29: 2 | K29: AS
B30: 45115 | C30: 15h45 | D30: Lesley Speer | F30: Aeroporto-Hotel | G30: SunDestiny | H30: 35 | I30: 5 | J30: 1 | K30: FP
B31: 45116 | C31: 08h30 | D31: Glenn Shaffer | F31: Hotel-Oriente | G31: SunDestiny | H31: 25 | I31: 7 | J31: 2 | K31: AS
B32: 45116 | C32: 09h20 | D32: Pam Brown | F32: Hotel-Aeroporto | G32: SunDestiny | H32: 25 | I32: 7 | J32: 2 | K32: FP
B33: 45116 | C33: 21h35 | D33: Alannah Michael | F33: Aeroporto-Hotel | G33: SunDestiny | H33: 35 | I33: 5 | J33: 2 | K33: AS
B34: 45117 | C34: 07h45 | D34: Gregg Jennings | F34: Aeroporto-Hotel | G34: SunDestiny | H34: 35 | I34: 5 | J34: 2 | K34: AS
B35: 45117 | C35: 12h00 | D35: Mark Palevsky | F35: Aeroporto-Hotel | G35: SunDestiny | H35: 35 | I35: 5 | J35: 2 | K35: AS
B36: 45117 | C36: 21h00 | D36: Hagar Kachlon | F36: Aeroporto-Hotel | G36: SunDestiny | H36: 35 | I36: 5 | J36: 2 | K36: DT
B37: 45118 | C37: 04h00 | D37: Markus Erharter Mbq | E37: 215 | F37: hotel-aeroporto | G37: SunDestiny | H37: 25 | I37: 7 | J37: 2 | K37: DT
B38: 45118 | C38: 08h30 | D38: Mark Palevsky | E38: 209 | F38: Hotel-Aeroporto | G38: SunDestiny | H38: 25 | I38: 7 | J38: 2 | K38: AS
B39: 45118 | C39: 09h50 | D39: Gladson Mota | F39: Aeroporto-Hotel | G39: SunDestiny | H39: 50 | I39: 7.5 | J39: 4 | K39: TS
B40: 45119 | C40: 04h30 | D40: Julien Arena | E40: 212 | F40: Hotel-Aeroporto | G40: SunDestiny | H40: 25 | I40: 7 | J40: 2 | K40: DT
B41: 45120 | C41: 07h30 | D41: Andrew Heaton | E41: 301+316 | F41: Hotel-Entrecampos | G41: SunDestiny | H41: 25 | I41: 7 | J41: 2 | K41: AS
B42: 45121 | C42: 04h30 | D42: Joao Cotta | E42: 407 | F42: Hotel-Aeroporto | G42: SunDestiny | H42: 25 | I42: 7 | J42: 2 | K42: AS
B43: 45121 | C43: 10h00 | D43: Rahimim Atis | E43: 305+307 | F43: Hotel-Aeroporto | G43: SunDestiny | H43: 40 | I43: 10 | J43: 4 | K43: AS
B44: 45121 | C44: 14h40 | D44: Claudia Guntli | F44: Aeroporto-Hotel | G44: SunDestiny | H44: 35 | I44: 5 | J44: 2 | K44: TS
B45: 45122 | C45: 05h30 | D45: Veronica Barba | E45: 405 | F45: Hotel-Aeroporto | G45: SunDestiny | H45: 25 | I45: 7 | J45: 2 | K45: AS
B46: 45125 | C46: 06h30 | D46: William | E46: 401 | F46: Hotel-Aeroporto | G46: SunDestiny | H46: 25 | I46: 7 | J46: 2 | K46: AS
B47: 45125 | C47: 16h30 | D47: Michal | E47: 405 | F47: Hotel-Aeroporto | G47: SunDestiny | H47: 25 | I47: 7 | J47: 2 | K47: AS
B48: 45126 | C48: 07h00 | D48: Elia Esteves | F48: Aeroporto-Hotel | G48: SunDestiny | H48: 70 | I48: 15 | J48: 4 | K48: CB
